Workbook

Sheet Posicion Inicial Gallo
A1: tipo_especie | B1: Ticker | C1: especie | D1: Codigo especie | E1: Codigo Especie Origen | F1: comentario especies | G1: detalle | H1: custodia | I1: cantidad | J1: precio Tenencia Inicial Pesos | K1: precio Tenencia Inicial USD | L1: Precio de PreciosIniciales | M1: precio costo(en proceso) | N1: Origen precio costo | O1: comentarios precio costo | P1: Precio a Utilizar | Q1: importe_pesos | R1: porc_cartera_pesos | S1: importe_dolares | T1: porc_cartera_dolares | U1: Tipo Instrumento | V1: Precio Nominal
A2: RENTA FIJA EN DOLARES | B2: BPOA7 | C2: BOPREAL S. 1 A VTO31/10/27 U$S CG | D2: 9234 | E2: PreciosInicialesEspecies | H2: CAJA VALORES | I2: 613798 | J2: 112460 | K2: 0.96300281 | L2: 112100 | N2: PrecioTenenciasIniciales | P2: 1001.513 | Q2: 6.9027723e+08 | R2: 515.16 | S2: 591089.2 | T2: 515.16 | U2: Títulos Públicos | V2: 1001.513
A3: RENTA FIJA EN DOLARES | B3: FUTUROS | D3: 56996 | E3: EspeciesGallo | J3: 0 | K3: 0 | L3: 0 | N3: PreciosInicialesEspecies | P3: 0 | U3: Obligaciones Negociables | V3: 0
A4: RENTA FIJA EN DOLARES | B4: DLR012025 | C4: DLR012025 | E4: NoEncontrado | H4: CAJA VALORES | I4: -200 | J4: 0 | K4: 0 | L4: 0 | N4: PreciosInicialesEspecies | P4: 0 | V4: 0
A5: CASH | B5: PESOS | C5: PESOS | G5: Cuenta Corriente | I5: -1125781.2 | J5: 1 | K5: 0.00085630314 | L5: 1 | N5: PreciosInicialesEspecies | P5: 1 | Q5: -1125781.2 | R5: -0.84 | S5: -964.01 | T5: -0.84 | V5: 1
A6: CASH | B6: DOLARES | C6: DOLARES | G6: Cuenta Corriente | I6: -475386.47 | J6: 1167.8055 | K6: 1 | L6: 1167.806 | N6: PreciosInicialesEspecies | P6: 1167.806 | Q6: -5.5515894e+08 | R6: -414.32 | S6: -475386.47 | T6: -414.32 | V6: 1167.806

Sheet Posicion Final Gallo
A1: tipo_especie | B1: Ticker | C1: especie | D1: Codigo especie | E1: Codigo Especie Origen | F1: comentario especies | G1: detalle | H1: custodia | I1: cantidad | J1: precio Tenencia Final Pesos | K1: precio Tenencia Final USD | L1: Precio Tenencia Inicial | M1: precio costo(en proceso) | N1: Origen precio costo | O1: comentarios precio costo | P1: Precio a Utilizar | Q1: importe_pesos | R1: porc_cartera_pesos | S1: importe_dolares | T1: porc_cartera_dolares | U1: Tipo Instrumento | V1: Precio Nominal
A2: RENTA FIJA EN PESOS | B2: TZV/25 | C2: BONO TESORO NACIONAL 30/06/25 U$S CG | D2: 9245 | E2: EspeciesGallo | H2: CAJA VALORES | I2: 200000 | J2: 1172.5 | K2: 0.9825732 | L2: 0 | N2: PreciosInicialesEspecies | P2: 0 | Q2: 234500000 | R2: 51.61 | S2: 196514.64 | T2: 51.61 | U2: Títulos Públicos | V2: 0
A3: RENTA FIJA EN DOLARES | B3: BPOB7 | C3: BOPREAL S. 1 B VTO31/10/27 U$S CG | D3: 9235 | E3: PreciosInicialesEspecies | H3: CAJA VALORES | I3: 205824 | J3: 1155.1 | K3: 0.96799173 | L3: 105910 | N3: PreciosInicialesEspecies | P3: 105910 | Q3: 2.377473e+08 | R3: 52.33 | S3: 199235.93 | T3: 52.33 | U3: Títulos Públicos | V3: 1059.1
A4: RENTA FIJA EN DOLARES | B4: FUTUROS | D4: 56996 | E4: EspeciesGallo | J4: 0 | K4: 0 | L4: 0 | N4: PreciosInicialesEspecies | P4: 0 | U4: Obligaciones Negociables | V4: 0
A5: RENTA FIJA EN DOLARES | B5: DLR062025 | C5: DLR062025 | E5: NoEncontrado | H5: CAJA VALORES | I5: -200 | J5: 0 | K5: 0 | L5: 0 | N5: PreciosInicialesEspecies | P5: 0 | V5: 0
A6: CASH | B6: PESOS | C6: PESOS | G6: Cuenta Corriente | I6: -2.3696646e+08 | J6: 0 | K6: 0 | L6: 1 | N6: PreciosInicialesEspecies | P6: 1 | V6: 1
A7: CASH | B7: DOLARES | C7: DOLARES | G7: Cuenta Corriente | I7: -14984.4 | J7: 1193.2953 | K7: 1 | L7: 1167.806 | N7: PreciosInicialesEspecies | P7: 1167.806 | Q7: -17880814 | R7: -3.94 | S7: -14984.4 | T7: -3.94 | V7: 1167.806

Sheet Boletos
A1: Tipo de Instrumento | B1: Concertación | C1: Liquidación | D1: Nro. Boleto | E1: Moneda | F1: Tipo Operación | G1: Cod.Instrum | H1: Instrumento Crudo | I1: InstrumentoConMoneda | J1: Cantidad | K1: Precio | L1: Tipo Cambio | M1: Bruto | N1: Interés | O1: Gastos | P1: Neto Calculado | Q1: Origen | R1: moneda emision | S1: Auditoría | T1: Precio Nominal
A2: Títulos Públicos | B2: 45733 | D2: 30874 | E2: Pesos | F2: COMPRA | G2: 9256 | H2: LT REP ARGENTINA CAP $ V31/03/25 | I2: LT REP ARGENTINA CAP $ V31/03/25 - Pesos | J2: 16000000 | K2: 156 | L2: 1 | M2: 24960000 | N2: 0 | O2: 0 | P2: 24960000 | Q2: gallo-Renta Fija Pesos | R2: Pesos | S2: Origen: Gallo-Renta Fija Pesos | Fecha: 17/03/25 | Cod: 09256 | Op: COMPRA | T2: 1.56
A3: Títulos Públicos | B3: 45734 | D3: 31254 | E3: Pesos | F3: VENTA | G3: 9256 | H3: LT REP ARGENTINA CAP $ V31/03/25 | I3: LT REP ARGENTINA CAP $ V31/03/25 - Pesos | J3: -16000000 | K3: 136.031 | L3: 1 | M3: -21764960 | N3: 0 | O3: 0 | P3: -21764960 | Q3: gallo-Renta Fija Pesos | R3: Pesos | S3: Origen: Gallo-Renta Fija Pesos | Fecha: 18/03/25 | Cod: 09256 | Op: VENTA | T3: 1.36031
A4: Títulos Públicos | B4: 45768 | D4: 44452 | E4: Dolar MEP | F4: COMPRA | G4: 5921 | H4: BONO USD 2030 LA | I4: BONO REP. ARGENTINA USD STEP UP 2030 - Dolar MEP (local) | J4: 150056 | K4: 64.692 | L4: 1122.08 | M4: 97074.228 | N4: 0 | O4: 0 | P4: 97074.228 | Q4: gallo-Renta Fija Dolares | R4: Dolar MEP (local) | S4: Origen: Gallo-Renta Fija Dolares | Fecha: 21/04/25 | Cod: 05921 | Op: COMPRA | T4: 0.64692
A5: Títulos Públicos | B5: 45768 | D5: 44453 | E5: Dolar MEP | F5: VENTA USD | G5: 5921 | H5: BONO USD 2030 LA | I5: BONO REP. ARGENTINA USD STEP UP 2030 - Dolar MEP (local) | J5: -150056 | K5: 66.479 | L5: 1122.08 | M5: -99755.728 | N5: 0 | O5: 0 | P5: -99755.728 | Q5: gallo-Renta Fija Dolares | R5: Dolar MEP (local) | S5: Origen: Gallo-Renta Fija Dolares | Fecha: 21/04/25 | Cod: 05921 | Op: VENTA USD | T5: 0.66479
A6: Títulos Públicos | B6: 45769 | D6: 44402 | E6: Dolar MEP | F6: VENTA USD | G6: 9234 | H6: BOPREAL S. 1 A VTO31/10/27 U$S CG | I6: BOPREAL S. 1 A VTO31/10/27 U$S CG - Dolar MEP (local) | J6: -200000 | K6: 100 | L6: 1140.38 | M6: -200000 | N6: 0 | O6: 0 | P6: -200000 | Q6: gallo-Renta Fija Dolares | R6: Dolar MEP (local) | S6: Origen: Gallo-Renta Fija Dolares | Fecha: 22/04/25 | Cod: 09234 | Op: VENTA USD | T6: 1
A7: Títulos Públicos | B7: 45769 | D7: 44405 | E7: Dolar MEP | F7: VENTA | G7: 9234 | H7: BOPREAL S. 1 A VTO31/10/27 U$S CG | I7: BOPREAL S. 1 A VTO31/10/27 U$S CG - Dolar MEP (local) | J7: -100000 | K7: 95.799 | L7: 1140.38 | M7: -95799 | N7: 0 | O7: 0 | P7: -95799 | Q7: gallo-Renta Fija Dolares | R7: Dolar MEP (local) | S7: Origen: Gallo-Renta Fija Dolares | Fecha: 22/04/25 | Cod: 09234 | Op: VENTA | T7: 0.95799
A8: Títulos Públicos | B8: 45770 | D8: 44957 | E8: Dolar MEP | F8: VENTA USD | G8: 9234 | H8: BOPREAL S. 1 A VTO31/10/27 U$S CG | I8: BOPREAL S. 1 A VTO31/10/27 U$S CG - Dolar MEP (local) | J8: -16458 | K8: 100 | L8: 1168 | M8: -16458 | N8: 0 | O8: 0 | P8: -16458 | Q8: gallo-Renta Fija Dolares | R8: Dolar MEP (local) | S8: Origen: Gallo-Renta Fija Dolares | Fecha: 23/04/25 | Cod: 09234 | Op: VENTA USD | T8: 1
A9: Títulos Públicos | B9: 45771 | D9: 45873 | E9: Dolar MEP | F9: VENTA USD | G9: 9234 | H9: BOPREAL S. 1 A VTO31/10/27 U$S CG | I9: BOPREAL S. 1 A VTO31/10/27 U$S CG - Dolar MEP (local) | J9: -85547 | K9: 100.012 | L9: 1186.53 | M9: -85557.266 | N9: 0 | O9: 0 | P9: -85557.266 | Q9: gallo-Renta Fija Dolares | R9: Dolar MEP (local) | S9: Origen: Gallo-Renta Fija Dolares | Fecha: 24/04/25 | Cod: 09234 | Op: VENTA USD | T9: 1.00012
A10: Títulos Públicos | B10: 45772 | D10: 46252 | E10: Dolar MEP | F10: VENTA USD | G10: 9234 | H10: BOPREAL S. 1 A VTO31/10/27 U$S CG | I10: BOPREAL S. 1 A VTO31/10/27 U$S CG - Dolar MEP (local) | J10: -211793 | K10: 100.25 | L10: 1184.24 | M10: -212322.48 | N10: 0 | O10: 0 | P10: -212322.48 | Q10: gallo-Renta Fija Dolares | R10: Dolar MEP (local) | S10: Origen: Gallo-Renta Fija Dolares | Fecha: 25/04/25 | Cod: 09234 | Op: VENTA USD | T10: 1.0025
A11: Títulos Públicos | B11: 45784 | D11: 50504 | E11: Pesos | F11: COMPRA | G11: 9311 | H11: BONO TESORO NACION AJ CER V30/5/25 $ CG | I11: BONO TESORO NACION AJ CER V30/5/25 $ CG - Pesos | J11: 90867961 | K11: 122.982 | L11: 1 | M11: 1.1175124e+08 | N11: 0 | O11: 0 | P11: 1.1175124e+08 | Q11: gallo-Renta Fija Pesos | R11: Pesos | S11: Origen: Gallo-Renta Fija Pesos | Fecha: 07/05/25 | Cod: 09311 | Op: COMPRA | T11: 1.22982
A12: Títulos Públicos | B12: 45784 | D12: 50489 | E12: Pesos | F12: VENTA | G12: 9311 | H12: BONO TESORO NACION AJ CER V30/5/25 $ CG | I12: BONO TESORO NACION AJ CER V30/5/25 $ CG - Pesos | J12: -90867961 | K12: 118.244 | L12: 1 | M12: -1.0744591e+08 | N12: 0 | O12: 0 | P12: -1.0744591e+08 | Q12: gallo-Renta Fija Pesos | R12: Pesos | S12: Origen: Gallo-Renta Fija Pesos | Fecha: 07/05/25 | Cod: 09311 | Op: VENTA | T12: 1.18244
A13: Títulos Públicos | B13: 45796 | D13: 55534 | E13: Dolar MEP | F13: COMPRA | G13: 5921 | H13: BONO USD 2030 LA | I13: BONO REP. ARGENTINA USD STEP UP 2030 - Dolar MEP (local) | J13: 140242 | K13: 67.74 | L13: 1148.77 | M13: 94999.931 | N13: 0 | O13: 0 | P13: 94999.931 | Q13: gallo-Renta Fija Dolares | R13: Dolar MEP (local) | S13: Origen: Gallo-Renta Fija Dolares | Fecha: 19/05/25 | Cod: 05921 | Op: COMPRA | T13: 0.6774
... A16: Títulos Públicos | B16: 45799 | D16: 57372 | E16: Dolar MEP | F16: VENTA | G16: 5921 | H16: BONO USD 2030 LA | I16: BONO REP. ARGENTINA USD STEP UP 2030 - Dolar MEP (local) | J16: -144117 | K16: 67.854 | L16: 1143.49 | M16: -97789.149 | N16: 0 | O16: 0 | P16: -97789.149 | Q16: gallo-Renta Fija Dolares | R16: Dolar MEP (local) | S16: Origen: Gallo-Renta Fija Dolares | Fecha: 22/05/25 | Cod: 05921 | Op: VENTA | T16: 0.67854
A17: Títulos Públicos | B17: 45807 | C17: 2/6/2025 | D17: 23030 | E17: Pesos | F17: Compra Contado Continuo | G17: 9245 | H17: BONO TESORO NA | I17: BONO TESORO NACIONAL 30/06/25 U$S CG - Dolar MEP (local) | J17: 200000 | K17: 1184 | L17: 1 | M17: 236800000 | N17: 0 | O17: 0 | P17: 236800000 | Q17: Visual | R17: Dolar MEP (local) | S17: Origen: Visual | Fecha: 30/5/2025 | Cod: 9245 | Op: Compra Contado Continuo | T17: 1184
A18: Futuros | B18: 45811 | C18: 3/6/2025 | D18: 62414 | E18: Pesos | F18: Futuro Venta | H18: DLR062025 | J18: -200 | K18: 1204.5 | L18: 1 | M18: 0 | N18: 0 | O18: -349786.8 | P18: -349786.8 | Q18: Visual | R18: =IF(ISERROR(VLOOKUP(G18,EspeciesVisual!C:Q,5,FALSE)),"",VLOOKUP(G18,EspeciesVisual!C:Q,5,FALSE)) | S18: Origen: Visual | Fecha: 3/6/2025 | Cod: None | Op: Futuro Venta | T18: 1204.5
A19: Títulos Públicos | B19: 45811 | C19: 4/6/2025 | D19: 62413 | E19: Pesos | F19: Compra Contado Continuo | G19: 9245 | H19: BONO TESORO NA | I19: BONO TESORO NACIONAL 30/06/25 U$S CG - Dolar MEP (local) | J19: 200000 | K19: 1170 | L19: 1 | M19: 234000000 | N19: 0 | O19: 0 | P19: 234000000 | Q19: Visual | R19: Dolar MEP (local) | S19: Origen: Visual | Fecha: 3/6/2025 | Cod: 9245 | Op: Compra Contado Continuo | T19: 1170
A20: Títulos Públicos | B20: 45826 | C20: 18/6/2025 | D20: 68915 | E20: Pesos | F20: Venta Contado Continuo No | G20: 5921 | H20: BONO REP. ARGE | I20: BONO REP. ARGENTINA USD STEP UP 2030 - Dolar MEP (local) | J20: -146753 | K20: 781.1868 | L20: 1 | M20: -1.1464151e+08 | N20: 0 | O20: 0 | P20: -1.1464151e+08 | Q20: Visual | R20: Dolar MEP (local) | S20: Origen: Visual | Fecha: 18/6/2025 | Cod: 5921 | Op: Venta Contado Continuo No | T20: 781.1868
A21: Títulos Públicos | B21: 45826 | C21: 18/6/2025 | D21: 68914 | E21: Dolar ME | F21: Compra Contado Continuo | G21: 5921 | H21: BONO REP. ARGE | I21: BONO REP. ARGENTINA USD STEP UP 2030 - Dolar MEP (local) | J21: 146753 | K21: 0.6746 | L21: 1185 | M21: 98999.57 | N21: 0 | O21: 0 | P21: 98999.57 | Q21: Visual | R21: Dolar MEP (local) | S21: Origen: Visual | Fecha: 18/6/2025 | Cod: 5921 | Op: Compra Contado Continuo | T21: 0.6746
A22: Títulos Públicos | B22: 45827 | C22: 19/6/2025 | D22: 69553 | E22: Pesos | F22: Venta Contado Continuo No | G22: 5921 | H22: BONO REP. ARGE | I22: BONO REP. ARGENTINA USD STEP UP 2030 - Dolar MEP (local) | J22: -104790 | K22: 779.222 | L22: 1 | M22: -81654673 | N22: 0 | O22: 0 | P22: -81654673 | Q22: Visual | R22: Dolar MEP (local) | S22: Origen: Visual | Fecha: 19/6/2025 | Cod: 5921 | Op: Venta Contado Continuo No | T22: 779.222
A23: Títulos Públicos | B23: 45827 | C23: 19/6/2025 | D23: 69552 | E23: Dolar ME | F23: Compra Contado Continuo | G23: 5921 | H23: BONO REP. ARGE | I23: BONO REP. ARGENTINA USD STEP UP 2030 - Dolar MEP (local) | J23: 104790 | K23: 0.668 | L23: 1160 | M23: 69999.72 | N23: 0 | O23: 0 | P23: 69999.72 | Q23: Visual | R23: Dolar MEP (local) | S23: Origen: Visual | Fecha: 19/6/2025 | Cod: 5921 | Op: Compra Contado Continuo | T23: 0.668
A24: Futuros | B24: 45833 | C24: 25/6/2025 | D24: 72322 | E24: Pesos | F24: Futuro Compra | H24: DLR062025 | J24: 400 | K24: 1194.5 | L24: 1 | M24: 0 | N24: 0 | O24: 115627.6 | P24: 115627.6 | Q24: Visual | R24: =IF(ISERROR(VLOOKUP(G24,EspeciesVisual!C:Q,5,FALSE)),"",VLOOKUP(G24,EspeciesVisual!C:Q,5,FALSE)) | S24: Origen: Visual | Fecha: 25/6/2025 | Cod: None | Op: Futuro Compra | T24: 1194.5
A25: Títulos Públicos | B25: 45833 | C25: 26/6/2025 | D25: 72321 | E25: Pesos | F25: Venta Contado | G25: 9245 | H25: BONO TESORO NA | I25: BONO TESORO NACIONAL 30/06/25 U$S CG - Dolar MEP (local) | J25: -400000 | K25: 1171.4 | L25: 1 | M25: -4.6856e+08 | N25: 0 | O25: 0 | P25: -4.6856e+08 | Q25: Visual | R25: Dolar MEP (local) | S25: Origen: Visual | Fecha: 25/6/2025 | Cod: 9245 | Op: Venta Contado | T25: 1171.4
A26: Letras del Tesoro nac | B26: 45833 | C26: 25/6/2025 | D26: 71646 | E26: Pesos | F26: Venta Contado Continuo No | G26: 9336 | H26: LT REP ARG CAP | I26: LT REP ARG CAP V.10/07/25 $ CG - Pesos | J26: -117198824 | K26: 1.0043 | L26: 1 | M26: -1.1770278e+08 | N26: 0 | O26: 0 | P26: -1.1770278e+08 | Q26: Visual | R26: Pesos | S26: Origen: Visual | Fecha: 25/6/2025 | Cod: 9336 | Op: Venta Contado Continuo No | T26: 1.0043
A27: Letras del Tesoro nac | B27: 45833 | C27: 25/6/2025 | D27: 71645 | E27: Dolar ME | F27: Compra Contado Continuo | G27: 9336 | H27: LT REP ARG CAP | I27: LT REP ARG CAP V.10/07/25 $ CG - Pesos | J27: 117198824 | K27: 0.0009 | L27: 1195 | M27: 99619 | N27: 0 | O27: 0 | P27: 99619 | Q27: Visual | R27: Pesos | S27: Origen: Visual | Fecha: 25/6/2025 | Cod: 9336 | Op: Compra Contado Continuo | T27: 0.00085
A28: Títulos Públicos | B28: 45834 | C28: 27/6/2025 | D28: 72765 | E28: Pesos | F28: Venta Contado | G28: 5921 | H28: BONO REP. ARGE | I28: BONO REP. ARGENTINA USD STEP UP 2030 - Dolar MEP (local) | J28: -6480 | K28: 825.7 | L28: 1 | M28: -5350536 | N28: 0 | O28: -5885.59 | P28: -5344650.4 | Q28: Visual | R28: Dolar MEP (local) | S28: Origen: Visual | Fecha: 26/6/2025 | Cod: 5921 | Op: Venta Contado | T28: 825.7
A29: Títulos Públicos | B29: 45834 | C29: 27/6/2025 | D29: 72764 | E29: Dolar ME | F29: Compra Contado | G29: 5921 | H29: BONO REP. ARGE | I29: BONO REP. ARGENTINA USD STEP UP 2030 - Dolar MEP (local) | J29: 6480 | K29: 0.6915 | L29: 1205 | M29: 4480.92 | N29: 0 | O29: 0 | P29: 4481.37 | Q29: Visual | R29: Dolar MEP (local) | S29: Origen: Visual | Fecha: 26/6/2025 | Cod: 5921 | Op: Compra Contado | T29: 0.6915
A30: Títulos Públicos | B30: 45834 | C30: 27/6/2025 | D30: 72767 | E30: Dolar ME | F30: Venta Contado | G30: 9235 | H30: BOPREAL S. 1 B V | I30: BOPREAL S. 1 B VTO31/10/27 U$S CG - Dolar MEP (local) | J30: -224031 | K30: 0.984 | L30: 1205 | M30: -220446.5 | N30: 0 | O30: 0 | P30: -220204.01 | Q30: Visual | R30: Dolar MEP (local) | S30: Origen: Visual | Fecha: 26/6/2025 | Cod: 9235 | Op: Venta Contado | T30: 0.984
A31: Títulos Públicos | B31: 45834 | C31: 27/6/2025 | D31: 72766 | E31: Dolar ME | F31: Compra Contado | G31: 9235 | H31: BOPREAL S. 1 B V | I31: BOPREAL S. 1 B VTO31/10/27 U$S CG - Dolar MEP (local) | J31: 18207 | K31: 0.986 | L31: 1205 | M31: 17952.1 | N31: 0 | O31: 0 | P31: 17953.9 | Q31: Visual | R31: Dolar MEP (local) | S31: Origen: Visual | Fecha: 26/6/2025 | Cod: 9235 | Op: Compra Contado | T31: 0.986
A32: Letras del Tesoro nac | B32: 45838 | C32: 30/6/2025 | D32: 74097 | E32: Pesos | F32: Venta Contado Continuo No | G32: 9336 | H32: LT REP ARG CAP | I32: LT REP ARG CAP V.10/07/25 $ CG - Pesos | J32: -234899991 | K32: 1.0149 | L32: 1 | M32: -2.384e+08 | N32: 0 | O32: 0 | P32: -2.384e+08 | Q32: Visual | R32: Pesos | S32: Origen: Visual | Fecha: 30/6/2025 | Cod: 9336 | Op: Venta Contado Continuo No | T32: 1.0149
A33: Letras del Tesoro nac | B33: 45838 | C33: 30/6/2025 | D33: 74096 | E33: Dolar ME | F33: Compra Contado Continuo | G33: 9336 | H33: LT REP ARG CAP | I33: LT REP ARG CAP V.10/07/25 $ CG - Pesos | J33: 234899991 | K33: 0.0009 | L33: 1205 | M33: 199664.99 | N33: 0 | O33: 0 | P33: 199664.99 | Q33: Visual | R33: Pesos | S33: Origen: Visual | Fecha: 30/6/2025 | Cod: 9336 | Op: Compra Contado Continuo | T33: 0.00084999999
A34: Letras del Tesoro nac | B34: 45839 | C34: 1/7/2025 | D34: 75056 | E34: Pesos | F34: Venta Contado Continuo No | G34: 9336 | H34: LT REP ARG CAP | I34: LT REP ARG CAP V.10/07/25 $ CG - Pesos | J34: -297126301 | K34: 1.0147 | L34: 1 | M34: -3.0149406e+08 | N34: 0 | O34: 0 | P34: -3.0149406e+08 | Q34: Visual | R34: Pesos | S34: Origen: Visual | Fecha: 1/7/2025 | Cod: 9336 | Op: Venta Contado Continuo No | T34: 1.0147
A35: Letras del Tesoro nac | B35: 45839 | C35: 1/7/2025 | D35: 75055 | E35: Dolar ME | F35: Compra Contado Continuo | G35: 9336 | H35: LT REP ARG CAP | I35: LT REP ARG CAP V.10/07/25 $ CG - Pesos | J35: 297126301 | K35: 0.0008 | L35: 1215 | M35: 249586.09 | N35: 0 | O35: 0 | P35: 249586.09 | Q35: Visual | R35: Pesos | S35: Origen: Visual | Fecha: 1/7/2025 | Cod: 9336 | Op: Compra Contado Continuo | T35: 0.00083999999
A36: Letras del Tesoro nac | B36: 45840 | C36: 2/7/2025 | D36: 75897 | E36: Pesos | F36: Venta Contado Continuo No | G36: 9336 | H36: LT REP ARG CAP | I36: LT REP ARG CAP V.10/07/25 $ CG - Pesos | J36: -296896672 | K36: 1.0382 | L36: 1 | M36: -3.0823812e+08 | N36: 0 | O36: 0 | P36: -3.0823812e+08 | Q36: Visual | R36: Pesos | S36: Origen: Visual | Fecha: 2/7/2025 | Cod: 9336 | Op: Venta Contado Continuo No | T36: 1.0382
... A79: Títulos Públicos | B79: 45978 | C79: 18/11/2025 | D79: 154211 | E79: Dolar ME | F79: Venta Contado | G79: 5922 | H79: BONO REP. ARGE | I79: BONO REP. ARGENTINA USD STEP UP 2035 - Dolar MEP (local) | J79: -336800 | K79: 0.7487 | L79: 1425 | M79: -252162.33 | N79: 0 | O79: 0 | P79: -251758.87 | Q79: Visual | R79: Dolar MEP (local) | S79: Origen: Visual | Fecha: 17/11/2025 | Cod: 5922 | Op: Venta Contado | T79: 0.7487

Sheet Cauciones Tomadoras
A1: Concertación | B1: Plazo | C1: Liquidación | D1: Operación | E1: Boleto | F1: Contado | G1: Futuro | H1: Tipo de Cambio | I1: Tasa (%) | J1: Interés Bruto | K1: Interés Devengado | L1: Aranceles | M1: Derechos | N1: Costo Financiero | O1: Moneda | P1: Origen | Q1: Auditoría
A2: 45656 | B2: 3 | C2: 45659 | D2: TOM CAU TER | E2: 136043 | F2: -475346.98 | G2: -475377.84 | H2: 1167.806 | J2: -30.86 | K2: -30.86 | L2: -8.63 | M2: 0 | N2: -39.49 | O2: Dolar MEP | P2: Gallo-Cauciones Dolares | Q2: Origen: Gallo-Cauciones Dolares
A3: 45659 | B3: 1 | C3: 45660 | D3: TOM CAU TER | E3: 511 | F3: -475386.47 | G3: -475392.98 | H3: 1167.806 | J3: -6.51 | K3: -6.51 | L3: -2.88 | M3: 0 | N3: -9.39 | O3: Dolar MEP | P3: Gallo-Cauciones Dolares | Q3: Origen: Gallo-Cauciones Dolares
A4: 45660 | B4: 3 | C4: 45663 | D4: TOM CAU TER | E4: 1095 | F4: -475395.86 | G4: -475415.01 | H4: 1167.806 | J4: -19.15 | K4: -19.15 | L4: -8.63 | M4: 0 | N4: -27.78 | O4: Dolar MEP | P4: Gallo-Cauciones Dolares | Q4: Origen: Gallo-Cauciones Dolares
A5: 45663 | B5: 1 | C5: 45664 | D5: TOM CAU TER | E5: 1645 | F5: -475423.64 | G5: -475429.37 | H5: 1167.806 | J5: -5.73 | K5: -5.73 | L5: -2.88 | M5: 0 | N5: -8.61 | O5: Dolar MEP | P5: Gallo-Cauciones Dolares | Q5: Origen: Gallo-Cauciones Dolares
A6: 45664 | B6: 1 | C6: 45665 | D6: TOM CAU TER | E6: 2205 | F6: -475432.25 | G6: -475437.33 | H6: 1167.806 | J6: -5.08 | K6: -5.08 | L6: -2.88 | M6: 0 | N6: -7.96 | O6: Dolar MEP | P6: Gallo-Cauciones Dolares | Q6: Origen: Gallo-Cauciones Dolares
A7: 45665 | B7: 143 | C7: 45808 | D7: TOM CAU TER | E7: 2807 | F7: -475440.21 | G7: -475444.12 | H7: 1167.806 | J7: -3.91 | K7: -3.91 | L7: -2.88 | M7: 0 | N7: -6.79 | O7: Dolar MEP | P7: Gallo-Cauciones Dolares | Q7: Origen: Gallo-Cauciones Dolares
A8: 45666 | B8: 1 | C8: 45667 | D8: TOM CAU TER | E8: 3344 | F8: -475447 | G8: -475451.95 | H8: 1167.806 | J8: -4.95 | K8: -4.95 | L8: -2.88 | M8: 0 | N8: -7.83 | O8: Dolar MEP | P8: Gallo-Cauciones Dolares | Q8: Origen: Gallo-Cauciones Dolares
A9: 45667 | B9: 3 | C9: 45670 | D9: TOM CAU TER | E9: 4024 | F9: -475454.83 | G9: -475462.26 | H9: 1167.806 | J9: -7.43 | K9: -7.43 | L9: -200.4 | M9: 0 | N9: -207.83 | O9: Dolar MEP | P9: Gallo-Cauciones Dolares | Q9: Origen: Gallo-Cauciones Dolares
A10: 45670 | B10: 1 | C10: 45671 | D10: TOM CAU TER | E10: 4696 | F10: -475662.66 | G10: -475667.09 | H10: 1167.806 | J10: -4.43 | K10: -4.43 | L10: -66.83 | M10: 0 | N10: -71.26 | O10: Dolar MEP | P10: Gallo-Cauciones Dolares | Q10: Origen: Gallo-Cauciones Dolares
A11: 45671 | B11: 1 | C11: 45672 | D11: TOM CAU TER | E11: 5480 | F11: -475733.92 | G11: -475738.61 | H11: 1167.806 | J11: -4.69 | K11: -4.69 | L11: -66.84 | M11: 0 | N11: -71.53 | O11: Dolar MEP | P11: Gallo-Cauciones Dolares | Q11: Origen: Gallo-Cauciones Dolares
A12: 45672 | B12: 1 | C12: 45673 | D12: TOM CAU TER | E12: 6212 | F12: -475805.45 | G12: -475811.19 | H12: 1167.806 | J12: -5.74 | K12: -5.74 | L12: -66.85 | M12: 0 | N12: -72.59 | O12: Dolar MEP | P12: Gallo-Cauciones Dolares | Q12: Origen: Gallo-Cauciones Dolares
A13: 45673 | B13: 1 | C13: 45674 | D13: TOM CAU TER | E13: 6786 | F13: -475878 | G13: -475882.57 | H13: 1167.806 | J13: -4.57 | K13: -4.57 | L13: -66.86 | M13: 0 | N13: -71.43 | O13: Dolar MEP | P13: Gallo-Cauciones Dolares | Q13: Origen: Gallo-Cauciones Dolares
... A74: 45771 | B74: 1 | C74: 45772 | D74: TOM CAU TER | E74: 46609 | F74: -60055.74 | G74: -60059.67 | H74: 1167.806 | J74: -3.93 | K74: -3.93 | L74: -30.6 | M74: 0 | N74: -34.53 | O74: Dolar MEP | P74: Gallo-Cauciones Dolares | Q74: Origen: Gallo-Cauciones Dolares
A75: 45810 | B75: 1 | C75: 45811 | D75: Apertura Tomador Cauci | E75: 62888 | F75: 3300000 | G75: 3302133.7 | H75: 1 | I75: 23.6 | J75: -2133.7 | K75: -2133.7 | L75: -218.94 | M75: -19.98 | N75: -2372.62 | O75: Pesos | P75: Visual-Cauciones Tomadoras | Q75: Origen: Visual-Cauciones Tomadoras
A76: 45810 | B76: 1 | C76: 45811 | D76: Apertura Tomador Cauci | E76: 62888 | F76: 1088000 | G76: 1088703.5 | H76: 1 | I76: 23.6 | J76: -703.47 | K76: -703.47 | L76: -72.18 | M76: -6.59 | N76: -782.24 | O76: Pesos | P76: Visual-Cauciones Tomadoras | Q76: Origen: Visual-Cauciones Tomadoras
A77: 45810 | B77: 1 | C77: 45811 | D77: Apertura Tomador Cauci | E77: 62888 | F77: 72549.35 | G77: 72596.26 | H77: 1 | I77: 23.6 | J77: -46.91 | K77: -46.91 | L77: -4.81 | M77: -0.44 | N77: -52.16 | O77: Pesos | P77: Visual-Cauciones Tomadoras | Q77: Origen: Visual-Cauciones Tomadoras
A78: 45810 | B78: 1 | C78: 45811 | D78: Apertura Tomador Cauci | E78: 62888 | F78: 68000 | G78: 68043.97 | H78: 1 | I78: 23.6 | J78: -43.97 | K78: -43.97 | L78: -4.51 | M78: -0.41 | N78: -48.89 | O78: Pesos | P78: Visual-Cauciones Tomadoras | Q78: Origen: Visual-Cauciones Tomadoras
A79: 45810 | B79: 1 | C79: 45811 | D79: Apertura Tomador Cauci | E79: 62888 | F79: 23016.96 | G79: 23031.84 | H79: 1 | I79: 23.6 | J79: -14.88 | K79: -14.88 | L79: -1.53 | M79: -0.14 | N79: -16.55 | O79: Pesos | P79: Visual-Cauciones Tomadoras | Q79: Origen: Visual-Cauciones Tomadoras
A80: 45810 | B80: 1 | C80: 45811 | D80: Apertura Tomador Cauci | E80: 62888 | F80: 500000 | G80: 500323.29 | H80: 1 | I80: 23.6 | J80: -323.29 | K80: -323.29 | L80: -33.17 | M80: -3.03 | N80: -359.49 | O80: Pesos | P80: Visual-Cauciones Tomadoras | Q80: Origen: Visual-Cauciones Tomadoras
A81: 45810 | B81: 1 | C81: 45811 | D81: Apertura Tomador Cauci | E81: 62888 | F81: 23478585 | G81: 23493766 | H81: 1 | I81: 23.6 | J81: -15180.67 | K81: -15180.67 | L81: -1557.67 | M81: -142.14 | N81: -16880.48 | O81: Pesos | P81: Visual-Cauciones Tomadoras | Q81: Origen: Visual-Cauciones Tomadoras
A82: 45810 | B82: 1 | C82: 45811 | D82: Apertura Tomador Cauci | E82: 62888 | F82: 5000000 | G82: 5003232.9 | H82: 1 | I82: 23.6 | J82: -3232.88 | K82: -3232.88 | L82: -331.72 | M82: -30.27 | N82: -3594.87 | O82: Pesos | P82: Visual-Cauciones Tomadoras | Q82: Origen: Visual-Cauciones Tomadoras
A83: 45810 | B83: 1 | C83: 45811 | D83: Apertura Tomador Cauci | E83: 62888 | F83: 1.3238925e+08 | G83: 1.3247485e+08 | H83: 1 | I83: 23.6 | J83: -85599.63 | K83: -85599.63 | L83: -8783.26 | M83: -801.47 | N83: -95184.36 | O83: Pesos | P83: Visual-Cauciones Tomadoras | Q83: Origen: Visual-Cauciones Tomadoras
A84: 45810 | B84: 1 | C84: 45811 | D84: Apertura Tomador Cauci | E84: 62888 | F84: 60292775 | G84: 60331759 | H84: 1 | I84: 23.6 | J84: -38983.82 | K84: -38983.82 | L84: -4000.08 | M84: -365.01 | N84: -43348.91 | O84: Pesos | P84: Visual-Cauciones Tomadoras | Q84: Origen: Visual-Cauciones Tomadoras
A85: 45810 | B85: 1 | C85: 45811 | D85: Apertura Tomador Cauci | E85: 62888 | F85: 1007026.4 | G85: 1007677.5 | H85: 1 | I85: 23.6 | J85: -651.12 | K85: -651.12 | L85: -66.81 | M85: -6.1 | N85: -724.03 | O85: Pesos | P85: Visual-Cauciones Tomadoras | Q85: Origen: Visual-Cauciones Tomadoras
A86: 45810 | B86: 1 | C86: 45811 | D86: Apertura Tomador Cauci | E86: 62888 | F86: 3488772.7 | G86: 3491028.5 | H86: 1 | I86: 23.6 | J86: -2255.75 | K86: -2255.75 | L86: -231.46 | M86: -21.12 | N86: -2508.33 | O86: Pesos | P86: Visual-Cauciones Tomadoras | Q86: Origen: Visual-Cauciones Tomadoras
... A195: 45834 | B195: 1 | C195: 45835 | D195: Apertura Tomador Cauci | E195: 72990 | F195: 28.48 | G195: -3753.56 | H195: 1 | I195: 0 | J195: 0 | K195: 0 | L195: 0 | M195: 0 | N195: 0 | O195: Pesos | P195: Visual-Cauciones Tomadoras | Q195: Origen: Visual-Cauciones Tomadoras

Sheet Cauciones Colocadoras
A1: Concertación | B1: Plazo | C1: Liquidación | D1: Operación | E1: Boleto | F1: Contado | G1: Futuro | H1: Tipo de Cambio | I1: Tasa (%) | J1: Interés Bruto | K1: Interés Devengado | L1: Aranceles | M1: Derechos | N1: Costo Financiero | O1: Moneda | P1: Origen | Q1: Auditoría

Sheet Rentas y Dividendos Gallo
A1: Tipo de Instrumento | B1: Concertación | C1: Liquidación | D1: Nro. Boleto | E1: Moneda | F1: Tipo Operación | G1: Cod.Instrum | H1: Instrumento Crudo | I1: InstrumentoConMoneda | J1: Cantidad | K1: Precio | L1: Tipo Cambio | M1: Bruto | N1: Interés | O1: Gastos | P1: Costo | Q1: Neto Calculado | R1: Origen | S1: moneda emision | T1: Auditoría

Sheet Resultado Ventas ARS
A1: Origen | B1: Tipo de Instrumento | C1: Instrumento | D1: Cod.Instrum | E1: Concertación | F1: Liquidación | G1: Moneda | H1: Tipo Operación | I1: Cantidad | J1: Precio | K1: Bruto | L1: Interés | M1: Tipo de Cambio | N1: Gastos | O1: IVA | P1: Resultado | Q1: Cantidad Stock Inicial | R1: Precio Stock Inicial | S1: Costo por venta(gallo) | T1: Neto Calculado(visual) | U1: Resultado Calculado(final) | V1: Cantidad de Stock Final | W1: Precio Stock Final | X1: Explicación Q | Y1: Explicación R-U | Z1: chequeado | AA1: Precio Nominal
A2: gallo-Renta Fija Pesos | B2: Títulos Públicos | C2: LT REP ARGENTINA CAP $ V31/03/25 - Pesos | D2: 9256 | E2: 45733 | G2: Pesos | H2: COMPRA | I2: 16000000 | J2: 156 | K2: 24960000 | L2: 0 | M2: 1 | N2: 0 | O2: 0 | Q2: 0 | R2: 0 | S2: 0 | T2: 24960000 | U2: 0 | V2: 16000000 | W2: 1.56 | X2: BUSCARV(D2→Posicion Inicial Gallo col V=Precio Nominal, fallback PrecioTenenciasIniciales/PreciosInicialesEspecies) | Y2: R=Precio stock previo | S=16000000*R2=16000000*[stock price] | T=K2+L2=2496000000.0+0 | U=|T2|-|S2| | Z2: Origen: gallo-Renta Fija Pesos | Cod: 9256 | AA2: 1.56
A3: gallo-Renta Fija Pesos | B3: Títulos Públicos | C3: LT REP ARGENTINA CAP $ V31/03/25 - Pesos | D3: 9256 | E3: 45734 | G3: Pesos | H3: VENTA | I3: -16000000 | J3: 136.031 | K3: -21764960 | L3: 0 | M3: 1 | N3: 0 | O3: 0 | Q3: 16000000 | R3: 1.56 | S3: -24960000 | T3: -21764960 | U3: -3195040 | V3: 0 | W3: 0 | X3: SI D3=D2: W2, SINO: BUSCARV(D3→Posicion Inicial Gallo col V=Precio Nominal, fallback PrecioTenenciasIniciales/PreciosInicialesEspecies) | Y3: R=Precio stock previo | S=-16000000*R3=-16000000*[stock price] | T=K3+L3=-2176496000.0+0 | U=|T3|-|S3| | Z3: Origen: gallo-Renta Fija Pesos | Cod: 9256 | AA3: 1.36031
A4: gallo-Renta Fija Pesos | B4: Títulos Públicos | C4: BONO TESORO NACION AJ CER V30/5/25 $ CG - Pesos | D4: 9311 | E4: 45784 | G4: Pesos | H4: COMPRA | I4: 90867961 | J4: 122.982 | K4: 1.1175124e+08 | L4: 0 | M4: 1 | N4: 0 | O4: 0 | Q4: 0 | R4: 0 | S4: 0 | T4: 1.1175124e+08 | U4: 0 | V4: 90867961 | W4: 1.22982 | X4: SI D4=D3: W3, SINO: BUSCARV(D4→Posicion Inicial Gallo col V=Precio Nominal, fallback PrecioTenenciasIniciales/PreciosInicialesEspecies) | Y4: R=Precio stock previo | S=90867961*R4=90867961*[stock price] | T=K4+L4=11175123579.702+0 | U=|T4|-|S4| | Z4: Origen: gallo-Renta Fija Pesos | Cod: 9311 | AA4: 1.22982
A5: gallo-Renta Fija Pesos | B5: Títulos Públicos | C5: BONO TESORO NACION AJ CER V30/5/25 $ CG - Pesos | D5: 9311 | E5: 45784 | G5: Pesos | H5: VENTA | I5: -90867961 | J5: 118.244 | K5: -1.0744591e+08 | L5: 0 | M5: 1 | N5: 0 | O5: 0 | Q5: 90867961 | R5: 1.22982 | S5: -1.1175124e+08 | T5: -1.0744591e+08 | U5: -4305324 | V5: 0 | W5: 0 | X5: SI D5=D4: W4, SINO: BUSCARV(D5→Posicion Inicial Gallo col V=Precio Nominal, fallback PrecioTenenciasIniciales/PreciosInicialesEspecies) | Y5: R=Precio stock previo | S=-90867961*R5=-90867961*[stock price] | T=K5+L5=-10744591180.484+0 | U=|T5|-|S5| | Z5: Origen: gallo-Renta Fija Pesos | Cod: 9311 | AA5: 1.18244

Sheet Resultado Ventas USD
A1: Origen | B1: Tipo de Instrumento | C1: Instrumento | D1: Cod.Instrum | E1: Concertación | F1: Liquidación | G1: Moneda | H1: Tipo Operación | I1: Cantidad | J1: Precio | K1: Precio Standarizado | L1: Precio Standarizado en USD | M1: Bruto en USD | N1: Interés | O1: Tipo de Cambio | P1: Valor USD Dia | Q1: Gastos USD | R1: IVA USD | S1: Resultado | T1: Cantidad Stock Inicial | U1: Precio Stock USD | V1: Costo por venta(gallo) | W1: Neto Calculado(visual) | X1: Resultado Calculado(final) | Y1: Cantidad de Stock Final | Z1: Precio Stock Final | AA1: Explicación T-Z | AB1: Auditoría | AC1: Precio Nominal
A2: gallo-Renta Fija Dolares | B2: Títulos Públicos | C2: BONO REP. ARGENTINA USD STEP UP 2030 - Dolar MEP (local) | D2: 5921 | E2: 45768 | G2: Dolar MEP | H2: COMPRA | I2: 150056 | J2: 64.692 | K2: 64.692 | L2: 64.692 | M2: 97074.228 | N2: 0 | O2: 1 | P2: 1122.08 | Q2: 0 | R2: 0 | T2: 0 | U2: 0.76005775 | V2: 0 | W2: 97074.228 | X2: 0 | Y2: 150056 | Z2: 0.64692 | AA2: T=BUSCARV(D2→Posicion Inicial Gallo col V=Precio Nominal, fallback PrecioTenenciasIniciales/PreciosInicialesEspecies) | U=PrecioPos/P2 | V=150056*U si venta | Q=GastosUSD | W=M +/- Q segun signo | X=|W|-|V| | Y=I+T | Z=Promedio | AB2: Origen: gallo-Renta Fija Dolares | Cod: 5921 | K(PrecioStd)=raw | L=K*O | GastosFuente=0 | AC2: 0.64692
A3: gallo-Renta Fija Dolares | B3: Títulos Públicos | C3: BONO REP. ARGENTINA USD STEP UP 2030 - Dolar MEP (local) | D3: 5921 | E3: 45768 | G3: Dolar MEP | H3: VENTA USD | I3: -150056 | J3: 66.479 | K3: 66.479 | L3: 66.479 | M3: -99755.728 | N3: 0 | O3: 1 | P3: 1122.08 | Q3: 0 | R3: 0 | T3: 150056 | U3: 0.64692 | V3: -97074.228 | W3: -99755.728 | X3: 2681.5007 | Y3: 0 | Z3: 0 | AA3: SI D3=D2: Z2, SINO: BUSCARV(col V=Precio Nominal (Posicion Inicial Gallo), fallback PrecioTenenciasIniciales/PreciosInicialesEspecies) | U=PrecioPos/P3 | V=-150056*U si venta | Q=GastosUSD | W=M +/- Q segun signo | X=|W|-|V| | Y=I+T | Z=Promedio | AB3: Origen: gallo-Renta Fija Dolares | Cod: 5921 | K(PrecioStd)=raw | L=K*O | GastosFuente=0 | AC3: 0.66479
A4: gallo-Renta Fija Dolares | B4: Títulos Públicos | C4: BONO REP. ARGENTINA USD STEP UP 2030 - Dolar MEP (local) | D4: 5921 | E4: 45796 | G4: Dolar MEP | H4: COMPRA | I4: 140242 | J4: 67.74 | K4: 67.74 | L4: 67.74 | M4: 94999.931 | N4: 0 | O4: 1 | P4: 1148.77 | Q4: 0 | R4: 0 | T4: 0 | U4: 0.64692 | V4: 0 | W4: 94999.931 | X4: 0 | Y4: 140242 | Z4: 0.6774 | AA4: SI D4=D3: Z3, SINO: BUSCARV(col V=Precio Nominal (Posicion Inicial Gallo), fallback PrecioTenenciasIniciales/PreciosInicialesEspecies) | U=PrecioPos/P4 | V=140242*U si venta | Q=GastosUSD | W=M +/- Q segun signo | X=|W|-|V| | Y=I+T | Z=Promedio | AB4: Origen: gallo-Renta Fija Dolares | Cod: 5921 | K(PrecioStd)=raw | L=K*O | GastosFuente=0 | AC4: 0.6774
A5: gallo-Renta Fija Dolares | B5: Títulos Públicos | C5: BONO REP. ARGENTINA USD STEP UP 2030 - Dolar MEP (local) | D5: 5921 | E5: 45796 | G5: Dolar MEP | H5: VENTA | I5: -140242 | J5: 66.727 | K5: 66.727 | L5: 66.727 | M5: -93579.279 | N5: 0 | O5: 1 | P5: 1148.77 | Q5: 0 | R5: 0 | T5: 140242 | U5: 0.6774 | V5: -94999.931 | W5: -93579.279 | X5: -1420.6515 | Y5: 0 | Z5: 0 | AA5: SI D5=D4: Z4, SINO: BUSCARV(col V=Precio Nominal (Posicion Inicial Gallo), fallback PrecioTenenciasIniciales/PreciosInicialesEspecies) | U=PrecioPos/P5 | V=-140242*U si venta | Q=GastosUSD | W=M +/- Q segun signo | X=|W|-|V| | Y=I+T | Z=Promedio | AB5: Origen: gallo-Renta Fija Dolares | Cod: 5921 | K(PrecioStd)=raw | L=K*O | GastosFuente=0 | AC5: 0.66727
A6: gallo-Renta Fija Dolares | B6: Títulos Públicos | C6: BONO REP. ARGENTINA USD STEP UP 2030 - Dolar MEP (local) | D6: 5921 | E6: 45799 | G6: Dolar MEP | H6: COMPRA | I6: 144117 | J6: 68 | K6: 68 | L6: 68 | M6: 97999.56 | N6: 0 | O6: 1 | P6: 1143.49 | Q6: 0 | R6: 0 | T6: 0 | U6: 0.6774 | V6: 0 | W6: 97999.56 | X6: 0 | Y6: 144117 | Z6: 0.68 | AA6: SI D6=D5: Z5, SINO: BUSCARV(col V=Precio Nominal (Posicion Inicial Gallo), fallback PrecioTenenciasIniciales/PreciosInicialesEspecies) | U=PrecioPos/P6 | V=144117*U si venta | Q=GastosUSD | W=M +/- Q segun signo | X=|W|-|V| | Y=I+T | Z=Promedio | AB6: Origen: gallo-Renta Fija Dolares | Cod: 5921 | K(PrecioStd)=raw | L=K*O | GastosFuente=0 | AC6: 0.68
A7: gallo-Renta Fija Dolares | B7: Títulos Públicos | C7: BONO REP. ARGENTINA USD STEP UP 2030 - Dolar MEP (local) | D7: 5921 | E7: 45799 | G7: Dolar MEP | H7: VENTA | I7: -144117 | J7: 67.854 | K7: 67.854 | L7: 67.854 | M7: -97789.149 | N7: 0 | O7: 1 | P7: 1143.49 | Q7: 0 | R7: 0 | T7: 144117 | U7: 0.68 | V7: -97999.56 | W7: -97789.149 | X7: -210.41082 | Y7: 0 | Z7: 0 | AA7: SI D7=D6: Z6, SINO: BUSCARV(col V=Precio Nominal (Posicion Inicial Gallo), fallback PrecioTenenciasIniciales/PreciosInicialesEspecies) | U=PrecioPos/P7 | V=-144117*U si venta | Q=GastosUSD | W=M +/- Q segun signo | X=|W|-|V| | Y=I+T | Z=Promedio | AB7: Origen: gallo-Renta Fija Dolares | Cod: 5921 | K(PrecioStd)=raw | L=K*O | GastosFuente=0 | AC7: 0.67854
A8: Visual | B8: Títulos Públicos | C8: BONO REP. ARGENTINA USD STEP UP 2030 - Dolar MEP (local) | D8: 5921 | E8: 45826 | F8: 18/6/2025 | G8: Dolar ME | H8: Compra Contado Continuo | I8: 146753 | J8: 0.6746 | K8: 67.46 | L8: 67.46 | M8: 98999.574 | N8: 0 | O8: 1 | P8: 1185 | Q8: 0 | R8: 0 | T8: 0 | U8: 0.68 | V8: 0 | W8: 98999.574 | X8: 0 | Y8: 146753 | Z8: 0.6746 | AA8: SI D8=D7: Z7, SINO: BUSCARV(col V=Precio Nominal (Posicion Inicial Gallo), fallback PrecioTenenciasIniciales/PreciosInicialesEspecies) | U=PrecioPos/P8 | V=146753*U si venta | Q=GastosUSD | W=M +/- Q segun signo | X=|W|-|V| | Y=I+T | Z=Promedio | AB8: Origen: Visual | Cod: 5921 | K(PrecioStd)=x100 | L=K*O | GastosFuente=0 | AC8: 0.6746
A9: Visual | B9: Títulos Públicos | C9: BONO REP. ARGENTINA USD STEP UP 2030 - Dolar MEP (local) | D9: 5921 | E9: 45826 | F9: 18/6/2025 | G9: Pesos | H9: Venta Contado Continuo No | I9: -146753 | J9: 781.1868 | K9: 78118.68 | L9: 65.922937 | M9: -96743.887 | N9: 0 | O9: 0.00084388186 | P9: 1185 | Q9: 0 | R9: 0 | T9: 146753 | U9: 0.6746 | V9: -98999.574 | W9: -96743.887 | X9: -2255.6865 | Y9: 0 | Z9: 0 | AA9: SI D9=D8: Z8, SINO: BUSCARV(col V=Precio Nominal (Posicion Inicial Gallo), fallback PrecioTenenciasIniciales/PreciosInicialesEspecies) | U=PrecioPos/P9 | V=-146753*U si venta | Q=GastosUSD | W=M +/- Q segun signo | X=|W|-|V| | Y=I+T | Z=Promedio | AB9: Origen: Visual | Cod: 5921 | K(PrecioStd)=x100 | L=K*O | GastosFuente=0 | AC9: 0.65922937
A10: Visual | B10: Títulos Públicos | C10: BONO REP. ARGENTINA USD STEP UP 2030 - Dolar MEP (local) | D10: 5921 | E10: 45827 | F10: 19/6/2025 | G10: Dolar ME | H10: Compra Contado Continuo | I10: 104790 | J10: 0.668 | K10: 66.8 | L10: 66.8 | M10: 69999.72 | N10: 0 | O10: 1 | P10: 1160 | Q10: 0 | R10: 0 | T10: 0 | U10: 0.6746 | V10: 0 | W10: 69999.72 | X10: 0 | Y10: 104790 | Z10: 0.668 | AA10: SI D10=D9: Z9, SINO: BUSCARV(col V=Precio Nominal (Posicion Inicial Gallo), fallback PrecioTenenciasIniciales/PreciosInicialesEspecies) | U=PrecioPos/P10 | V=104790*U si venta | Q=GastosUSD | W=M +/- Q segun signo | X=|W|-|V| | Y=I+T | Z=Promedio | AB10: Origen: Visual | Cod: 5921 | K(PrecioStd)=x100 | L=K*O | GastosFuente=0 | AC10: 0.668
A11: Visual | B11: Títulos Públicos | C11: BONO REP. ARGENTINA USD STEP UP 2030 - Dolar MEP (local) | D11: 5921 | E11: 45827 | F11: 19/6/2025 | G11: Pesos | H11: Venta Contado Continuo No | I11: -104790 | J11: 779.222 | K11: 77922.2 | L11: 67.17431 | M11: -70391.96 | N11: 0 | O11: 0.00086206897 | P11: 1160 | Q11: 0 | R11: 0 | T11: 104790 | U11: 0.668 | V11: -69999.72 | W11: -70391.96 | X11: 392.23981 | Y11: 0 | Z11: 0 | AA11: SI D11=D10: Z10, SINO: BUSCARV(col V=Precio Nominal (Posicion Inicial Gallo), fallback PrecioTenenciasIniciales/PreciosInicialesEspecies) | U=PrecioPos/P11 | V=-104790*U si venta | Q=GastosUSD | W=M +/- Q segun signo | X=|W|-|V| | Y=I+T | Z=Promedio | AB11: Origen: Visual | Cod: 5921 | K(PrecioStd)=x100 | L=K*O | GastosFuente=0 | AC11: 0.6717431
A12: Visual | B12: Títulos Públicos | C12: BONO REP. ARGENTINA USD STEP UP 2030 - Dolar MEP (local) | D12: 5921 | E12: 45834 | F12: 27/6/2025 | G12: Dolar ME | H12: Compra Contado | I12: 6480 | J12: 0.6915 | K12: 69.15 | L12: 69.15 | M12: 4480.92 | N12: 0 | O12: 1 | P12: 1205 | Q12: 0 | R12: 0 | T12: 0 | U12: 0.668 | V12: 0 | W12: 4480.92 | X12: 0 | Y12: 6480 | Z12: 0.6915 | AA12: SI D12=D11: Z11, SINO: BUSCARV(col V=Precio Nominal (Posicion Inicial Gallo), fallback PrecioTenenciasIniciales/PreciosInicialesEspecies) | U=PrecioPos/P12 | V=6480*U si venta | Q=GastosUSD | W=M +/- Q segun signo | X=|W|-|V| | Y=I+T | Z=Promedio | AB12: Origen: Visual | Cod: 5921 | K(PrecioStd)=x100 | L=K*O | GastosFuente=0 | AC12: 0.6915
A13: Visual | B13: Títulos Públicos | C13: BONO REP. ARGENTINA USD STEP UP 2030 - Dolar MEP (local) | D13: 5921 | E13: 45834 | F13: 27/6/2025 | G13: Pesos | H13: Venta Contado | I13: -6480 | J13: 825.7 | K13: 82570 | L13: 68.522822 | M13: -4440.2788 | N13: 0 | O13: 0.00082987552 | P13: 1205 | Q13: 0 | R13: 0 | T13: 6480 | U13: 0.6915 | V13: -4480.92 | W13: -4440.2788 | X13: -40.641162 | Y13: 0 | Z13: 0 | AA13: SI D13=D12: Z12, SINO: BUSCARV(col V=Precio Nominal (Posicion Inicial Gallo), fallback PrecioTenenciasIniciales/PreciosInicialesEspecies) | U=PrecioPos/P13 | V=-6480*U si venta | Q=GastosUSD | W=M +/- Q segun signo | X=|W|-|V| | Y=I+T | Z=Promedio | AB13: Origen: Visual | Cod: 5921 | K(PrecioStd)=x100 | L=K*O | GastosFuente=-5885.59 | AC13: 0.68522822
A14: Visual | B14: Títulos Públicos | C14: BONO REP. ARGENTINA USD STEP UP 2030 - Dolar MEP (local) | D14: 5921 | E14: 45849 | F14: 11/7/2025 | G14: Dolar ME | H14: Compra Contado | I14: 938 | J14: 0.5998 | K14: 59.98 | L14: 59.98 | M14: 562.6124 | N14: 0 | O14: 1 | P14: 1275 | Q14: 0 | R14: 0 | T14: 0 | U14: 0.6915 | V14: 0 | W14: 562.6124 | X14: 0 | Y14: 938 | Z14: 0.5998 | AA14: SI D14=D13: Z13, SINO: BUSCARV(col V=Precio Nominal (Posicion Inicial Gallo), fallback PrecioTenenciasIniciales/PreciosInicialesEspecies) | U=PrecioPos/P14 | V=938*U si venta | Q=GastosUSD | W=M +/- Q segun signo | X=|W|-|V| | Y=I+T | Z=Promedio | AB14: Origen: Visual | Cod: 5921 | K(PrecioStd)=x100 | L=K*O | GastosFuente=0 | AC14: 0.5998
A15: Visual | B15: Títulos Públicos | C15: BONO REP. ARGENTINA USD STEP UP 2030 - Dolar MEP (local) | D15: 5921 | E15: 45849 | F15: 11/7/2025 | G15: Pesos | H15: Venta Contado | I15: -938 | J15: 760.2 | K15: 76020 | L15: 59.623529 | M15: -559.26871 | N15: 0 | O15: 0.00078431373 | P15: 1275 | Q15: 0 | R15: 0 | T15: 938 | U15: 0.5998 | V15: -562.6124 | W15: -559.26871 | X15: -3.3436941 | Y15: 0 | Z15: 0 | AA15: SI D15=D14: Z14, SINO: BUSCARV(col V=Precio Nominal (Posicion Inicial Gallo), fallback PrecioTenenciasIniciales/PreciosInicialesEspecies) | U=PrecioPos/P15 | V=-938*U si venta | Q=GastosUSD | W=M +/- Q segun signo | X=|W|-|V| | Y=I+T | Z=Promedio | AB15: Origen: Visual | Cod: 5921 | K(PrecioStd)=x100 | L=K*O | GastosFuente=-784.38 | AC15: 0.59623529
A16: Visual | B16: Títulos Públicos | C16: BONO REP. ARGENTINA USD STEP UP 2030 - Dolar MEP (local) | D16: 5921 | E16: 45854 | F16: 16/7/2025 | G16: Dolar ME | H16: Compra Contado Continuo | I16: 333979 | J16: 0.5967 | K16: 59.67 | L16: 59.67 | M16: 199285.27 | N16: 0 | O16: 1 | P16: 1280 | Q16: 0 | R16: 0 | T16: 0 | U16: 0.5998 | V16: 0 | W16: 199285.27 | X16: 0 | Y16: 333979 | Z16: 0.5967 | AA16: SI D16=D15: Z15, SINO: BUSCARV(col V=Precio Nominal (Posicion Inicial Gallo), fallback PrecioTenenciasIniciales/PreciosInicialesEspecies) | U=PrecioPos/P16 | V=333979*U si venta | Q=GastosUSD | W=M +/- Q segun signo | X=|W|-|V| | Y=I+T | Z=Promedio | AB16: Origen: Visual | Cod: 5921 | K(PrecioStd)=x100 | L=K*O | GastosFuente=0 | AC16: 0.5967
A17: Visual | B17: Títulos Públicos | C17: BONO REP. ARGENTINA USD STEP UP 2030 - Dolar MEP (local) | D17: 5921 | E17: 45854 | F17: 16/7/2025 | G17: Pesos | H17: Venta Contado Continuo No | I17: -333979 | J17: 751.2453 | K17: 75124.53 | L17: 58.691039 | M17: -196015.75 | N17: 0 | O17: 0.00078125 | P17: 1280 | Q17: 0 | R17: 0 | T17: 333979 | U17: 0.5967 | V17: -199285.27 | W17: -196015.75 | X17: -3269.5239 | Y17: 0 | Z17: 0 | AA17: SI D17=D16: Z16, SINO: BUSCARV(col V=Precio Nominal (Posicion Inicial Gallo), fallback PrecioTenenciasIniciales/PreciosInicialesEspecies) | U=PrecioPos/P17 | V=-333979*U si venta | Q=GastosUSD | W=M +/- Q segun signo | X=|W|-|V| | Y=I+T | Z=Promedio | AB17: Origen: Visual | Cod: 5921 | K(PrecioStd)=x100 | L=K*O | GastosFuente=0 | AC17: 0.58691039
A18: Visual | B18: Títulos Públicos | C18: BONO REP. ARGENTINA USD STEP UP 2030 - Dolar MEP (local) | D18: 5921 | E18: 45898 | F18: 29/8/2025 | G18: Dolar ME | H18: Compra Contado Continuo | I18: 506230 | J18: 0.5912 | K18: 59.12 | L18: 59.12 | M18: 299283.18 | N18: 0 | O18: 1 | P18: 1345 | Q18: 0 | R18: 0 | T18: 0 | U18: 0.5967 | V18: 0 | W18: 299283.18 | X18: 0 | Y18: 506230 | Z18: 0.5912 | AA18: SI D18=D17: Z17, SINO: BUSCARV(col V=Precio Nominal (Posicion Inicial Gallo), fallback PrecioTenenciasIniciales/PreciosInicialesEspecies) | U=PrecioPos/P18 | V=506230*U si venta | Q=GastosUSD | W=M +/- Q segun signo | X=|W|-|V| | Y=I+T | Z=Promedio | AB18: Origen: Visual | Cod: 5921 | K(PrecioStd)=x100 | L=K*O | GastosFuente=0 | AC18: 0.5912
A19: Visual | B19: Títulos Públicos | C19: BONO REP. ARGENTINA USD STEP UP 2030 - Dolar MEP (local) | D19: 5921 | E19: 45898 | F19: 29/8/2025 | G19: Pesos | H19: Venta Contado Continuo No | I19: -506230 | J19: 788.003 | K19: 78800.3 | L19: 58.587584 | M19: -296587.92 | N19: 0 | O19: 0.00074349442 | P19: 1345 | Q19: 0 | R19: 0 | T19: 506230 | U19: 0.5912 | V19: -299283.18 | W19: -296587.92 | X19: -2695.2513 | Y19: 0 | Z19: 0 | AA19: SI D19=D18: Z18, SINO: BUSCARV(col V=Precio Nominal (Posicion Inicial Gallo), fallback PrecioTenenciasIniciales/PreciosInicialesEspecies) | U=PrecioPos/P19 | V=-506230*U si venta | Q=GastosUSD | W=M +/- Q segun signo | X=|W|-|V| | Y=I+T | Z=Promedio | AB19: Origen: Visual | Cod: 5921 | K(PrecioStd)=x100 | L=K*O | GastosFuente=0 | AC19: 0.58587584
... A30: Visual | B30: Títulos Públicos | C30: BONOS REP. ARG. U$S STEP UP V.09/07/35 - Dolar Cable (exterior) | D30: 81088 | E30: 45908 | F30: 8/9/2025 | G30: Pesos | H30: Venta Contado Continuo No | I30: -523368 | J30: 813.96 | K30: 81396 | L30: 58.982609 | M30: -308696.1 | N30: 0 | O30: 0.00072463768 | P30: 1380 | Q30: 0 | R30: 0 | T30: 523368 | U30: 0.57 | V30: -298319.76 | W30: -308696.1 | X30: 10376.339 | Y30: 0 | Z30: 0 | AA30: SI D30=D29: Z29, SINO: BUSCARV(col V=Precio Nominal (Posicion Inicial Gallo), fallback PrecioTenenciasIniciales/PreciosInicialesEspecies) | U=PrecioPos/P30 | V=-523368*U si venta | Q=GastosUSD | W=M +/- Q segun signo | X=|W|-|V| | Y=I+T | Z=Promedio | AB30: Origen: Visual | Cod: 81088 | K(PrecioStd)=x100 | L=K*O | GastosFuente=0 | AC30: 0.58982609
A31: gallo-Renta Fija Dolares | B31: Títulos Públicos | C31: BOPREAL S. 1 A VTO31/10/27 U$S CG - Dolar MEP (local) | D31: 9234 | E31: 45769 | G31: Dolar MEP | H31: VENTA USD | I31: -200000 | J31: 100 | K31: 100 | L31: 100 | M31: -200000 | N31: 0 | O31: 1 | P31: 1140.38 | Q31: 0 | R31: 0 | T31: 613798 | U31: 0.87822747 | V31: -175645.49 | W31: -200000 | X31: 24354.505 | Y31: 413798 | Z31: 0.87822747 | AA31: SI D31=D30: Z30, SINO: BUSCARV(col V=Precio Nominal (Posicion Inicial Gallo), fallback PrecioTenenciasIniciales/PreciosInicialesEspecies) | U=PrecioPos/P31 | V=-200000*U si venta | Q=GastosUSD | W=M +/- Q segun signo | X=|W|-|V| | Y=I+T | Z=Promedio | AB31: Origen: gallo-Renta Fija Dolares | Cod: 9234 | K(PrecioStd)=raw | L=K*O | GastosFuente=0 | AC31: 1
A32: gallo-Renta Fija Dolares | B32: Títulos Públicos | C32: BOPREAL S. 1 A VTO31/10/27 U$S CG - Dolar MEP (local) | D32: 9234 | E32: 45769 | G32: Dolar MEP | H32: VENTA | I32: -100000 | J32: 95.799 | K32: 95.799 | L32: 95.799 | M32: -95799 | N32: 0 | O32: 1 | P32: 1140.38 | Q32: 0 | R32: 0 | T32: 413798 | U32: 0.87822747 | V32: -87822.747 | W32: -95799 | X32: 7976.2525 | Y32: 313798 | Z32: 0.87822747 | AA32: SI D32=D31: Z31, SINO: BUSCARV(col V=Precio Nominal (Posicion Inicial Gallo), fallback PrecioTenenciasIniciales/PreciosInicialesEspecies) | U=PrecioPos/P32 | V=-100000*U si venta | Q=GastosUSD | W=M +/- Q segun signo | X=|W|-|V| | Y=I+T | Z=Promedio | AB32: Origen: gallo-Renta Fija Dolares | Cod: 9234 | K(PrecioStd)=raw | L=K*O | GastosFuente=0 | AC32: 0.95799
A33: gallo-Renta Fija Dolares | B33: Títulos Públicos | C33: BOPREAL S. 1 A VTO31/10/27 U$S CG - Dolar MEP (local) | D33: 9234 | E33: 45770 | G33: Dolar MEP | H33: VENTA USD | I33: -16458 | J33: 100 | K33: 100 | L33: 100 | M33: -16458 | N33: 0 | O33: 1 | P33: 1168 | Q33: 0 | R33: 0 | T33: 313798 | U33: 0.87822747 | V33: -14453.868 | W33: -16458 | X33: 2004.1322 | Y33: 297340 | Z33: 0.87822747 | AA33: SI D33=D32: Z32, SINO: BUSCARV(col V=Precio Nominal (Posicion Inicial Gallo), fallback PrecioTenenciasIniciales/PreciosInicialesEspecies) | U=PrecioPos/P33 | V=-16458*U si venta | Q=GastosUSD | W=M +/- Q segun signo | X=|W|-|V| | Y=I+T | Z=Promedio | AB33: Origen: gallo-Renta Fija Dolares | Cod: 9234 | K(PrecioStd)=raw | L=K*O | GastosFuente=0 | AC33: 1
A34: gallo-Renta Fija Dolares | B34: Títulos Públicos | C34: BOPREAL S. 1 A VTO31/10/27 U$S CG - Dolar MEP (local) | D34: 9234 | E34: 45771 | G34: Dolar MEP | H34: VENTA USD | I34: -85547 | J34: 100.012 | K34: 100.012 | L34: 100.012 | M34: -85557.266 | N34: 0 | O34: 1 | P34: 1186.53 | Q34: 0 | R34: 0 | T34: 297340 | U34: 0.87822747 | V34: -75129.726 | W34: -85557.266 | X34: 10427.54 | Y34: 211793 | Z34: 0.87822747 | AA34: SI D34=D33: Z33, SINO: BUSCARV(col V=Precio Nominal (Posicion Inicial Gallo), fallback PrecioTenenciasIniciales/PreciosInicialesEspecies) | U=PrecioPos/P34 | V=-85547*U si venta | Q=GastosUSD | W=M +/- Q segun signo | X=|W|-|V| | Y=I+T | Z=Promedio | AB34: Origen: gallo-Renta Fija Dolares | Cod: 9234 | K(PrecioStd)=raw | L=K*O | GastosFuente=0 | AC34: 1.00012
A35: gallo-Renta Fija Dolares | B35: Títulos Públicos | C35: BOPREAL S. 1 A VTO31/10/27 U$S CG - Dolar MEP (local) | D35: 9234 | E35: 45772 | G35: Dolar MEP | H35: VENTA USD | I35: -211793 | J35: 100.25 | K35: 100.25 | L35: 100.25 | M35: -212322.48 | N35: 0 | O35: 1 | P35: 1184.24 | Q35: 0 | R35: 0 | T35: 211793 | U35: 0.87822747 | V35: -186002.43 | W35: -212322.48 | X35: 26320.051 | Y35: 0 | Z35: 0 | AA35: SI D35=D34: Z34, SINO: BUSCARV(col V=Precio Nominal (Posicion Inicial Gallo), fallback PrecioTenenciasIniciales/PreciosInicialesEspecies) | U=PrecioPos/P35 | V=-211793*U si venta | Q=GastosUSD | W=M +/- Q segun signo | X=|W|-|V| | Y=I+T | Z=Promedio | AB35: Origen: gallo-Renta Fija Dolares | Cod: 9234 | K(PrecioStd)=raw | L=K*O | GastosFuente=0 | AC35: 1.0025
A36: Visual | B36: Títulos Públicos | C36: BOPREAL S. 1 B VTO31/10/27 U$S CG - Dolar MEP (local) | D36: 9235 | E36: 45834 | F36: 27/6/2025 | G36: Dolar ME | H36: Compra Contado | I36: 18207 | J36: 0.986 | K36: 98.6 | L36: 98.6 | M36: 17952.102 | N36: 0 | O36: 1 | P36: 1205 | Q36: 0 | R36: 0 | T36: 0 | U36: 0.90691433 | V36: 0 | W36: 17952.102 | X36: 0 | Y36: 18207 | Z36: 0.986 | AA36: SI D36=D35: Z35, SINO: BUSCARV(col V=Precio Nominal (Posicion Inicial Gallo), fallback PrecioTenenciasIniciales/PreciosInicialesEspecies) | U=PrecioPos/P36 | V=18207*U si venta | Q=GastosUSD | W=M +/- Q segun signo | X=|W|-|V| | Y=I+T | Z=Promedio | AB36: Origen: Visual | Cod: 9235 | K(PrecioStd)=x100 | L=K*O | GastosFuente=0 | AC36: 0.986
A37: Visual | B37: Títulos Públicos | C37: BOPREAL S. 1 B VTO31/10/27 U$S CG - Dolar MEP (local) | D37: 9235 | E37: 45834 | F37: 27/6/2025 | G37: Dolar ME | H37: Venta Contado | I37: -224031 | J37: 0.984 | K37: 98.4 | L37: 98.4 | M37: -220446.5 | N37: 0 | O37: 1 | P37: 1205 | Q37: 0 | R37: 0 | T37: 18207 | U37: 0.986 | V37: -220894.57 | W37: -220446.5 | X37: -448.062 | Y37: -205824 | Z37: 0.986 | AA37: SI D37=D36: Z36, SINO: BUSCARV(col V=Precio Nominal (Posicion Inicial Gallo), fallback PrecioTenenciasIniciales/PreciosInicialesEspecies) | U=PrecioPos/P37 | V=-224031*U si venta | Q=GastosUSD | W=M +/- Q segun signo | X=|W|-|V| | Y=I+T | Z=Promedio | AB37: Origen: Visual | Cod: 9235 | K(PrecioStd)=x100 | L=K*O | GastosFuente=0 | AC37: 0.984
A38: Visual | B38: Títulos Públicos | C38: BONO TESORO NACIONAL 30/06/25 U$S CG - Dolar MEP (local) | D38: 9245 | E38: 45807 | F38: 2/6/2025 | G38: Pesos | H38: Compra Contado Continuo | I38: 200000 | J38: 1184 | K38: 118400 | L38: 99.352197 | M38: 198704.39 | N38: 0 | O38: 0.00083912328 | P38: 1191.72 | Q38: 0 | R38: 0 | T38: 0 | U38: 0.88798996 | V38: 0 | W38: 198704.39 | X38: 0 | Y38: 200000 | Z38: 0.99352197 | AA38: SI D38=D37: Z37, SINO: BUSCARV(col V=Precio Nominal (Posicion Inicial Gallo), fallback PrecioTenenciasIniciales/PreciosInicialesEspecies) | U=PrecioPos/P38 | V=200000*U si venta | Q=GastosUSD | W=M +/- Q segun signo | X=|W|-|V| | Y=I+T | Z=Promedio | AB38: Origen: Visual | Cod: 9245 | K(PrecioStd)=x100 | L=K*O | GastosFuente=0 | AC38: 0.99352197
A39: Visual | B39: Títulos Públicos | C39: BONO TESORO NACIONAL 30/06/25 U$S CG - Dolar MEP (local) | D39: 9245 | E39: 45811 | F39: 4/6/2025 | G39: Pesos | H39: Compra Contado Continuo | I39: 200000 | J39: 1170 | K39: 117000 | L39: 98.3466 | M39: 196693.2 | N39: 0 | O39: 0.00084056923 | P39: 1189.67 | Q39: 0 | R39: 0 | T39: 200000 | U39: 0.99352197 | V39: 0 | W39: 196693.2 | X39: 0 | Y39: 400000 | Z39: 0.98849399 | AA39: SI D39=D38: Z38, SINO: BUSCARV(col V=Precio Nominal (Posicion Inicial Gallo), fallback PrecioTenenciasIniciales/PreciosInicialesEspecies) | U=PrecioPos/P39 | V=200000*U si venta | Q=GastosUSD | W=M +/- Q segun signo | X=|W|-|V| | Y=I+T | Z=Promedio | AB39: Origen: Visual | Cod: 9245 | K(PrecioStd)=x100 | L=K*O | GastosFuente=0 | AC39: 0.983466
A40: Visual | B40: Títulos Públicos | C40: BONO TESORO NACIONAL 30/06/25 U$S CG - Dolar MEP (local) | D40: 9245 | E40: 45833 | F40: 26/6/2025 | G40: Pesos | H40: Venta Contado | I40: -400000 | J40: 1171.4 | K40: 117140 | L40: 97.907943 | M40: -391631.77 | N40: 0 | O40: 0.0008358199 | P40: 1196.43 | Q40: 0 | R40: 0 | T40: 400000 | U40: 0.98849399 | V40: -395397.59 | W40: -391631.77 | X40: -3765.8231 | Y40: 0 | Z40: 0 | AA40: SI D40=D39: Z39, SINO: BUSCARV(col V=Precio Nominal (Posicion Inicial Gallo), fallback PrecioTenenciasIniciales/PreciosInicialesEspecies) | U=PrecioPos/P40 | V=-400000*U si venta | Q=GastosUSD | W=M +/- Q segun signo | X=|W|-|V| | Y=I+T | Z=Promedio | AB40: Origen: Visual | Cod: 9245 | K(PrecioStd)=x100 | L=K*O | GastosFuente=0 | AC40: 0.97907943
A41: Visual | B41: Títulos Públicos | C41: BONTES $ A DESC AJ CER V15/12/27 - Pesos | D41: 9250 | E41: 45909 | F41: 9/9/2025 | G41: Dolar ME | H41: Compra Contado Continuo | I41: 274408787 | J41: 0.0011 | K41: 0.0011 | L41: 0.0011 | M41: 301849.67 | N41: 0 | O41: 1 | P41: 1425 | Q41: 0 | R41: 0 | T41: 0 | U41: 0.0012330815 | V41: 0 | W41: 301849.67 | X41: 0 | Y41: 274408787 | Z41: 0.0011 | AA41: SI D41=D40: Z40, SINO: BUSCARV(col V=Precio Nominal (Posicion Inicial Gallo), fallback PrecioTenenciasIniciales/PreciosInicialesEspecies) | U=PrecioPos/P41 | V=274408787*U si venta | Q=GastosUSD | W=M +/- Q segun signo | X=|W|-|V| | Y=I+T | Z=Promedio | AB41: Origen: Visual | Cod: 9250 | K(PrecioStd)=raw | L=K*O | GastosFuente=0 | AC41: 0.0011
A42: Visual | B42: Títulos Públicos | C42: BONTES $ A DESC AJ CER V15/12/27 - Pesos | D42: 9250 | E42: 45909 | F42: 9/9/2025 | G42: Pesos | H42: Venta Contado Continuo No | I42: -274408787 | J42: 1.5538 | K42: 1.5538 | L42: 0.001090386 | M42: -299211.49 | N42: 0 | O42: 0.00070175439 | P42: 1425 | Q42: 0 | R42: 0 | T42: 274408787 | U42: 0.0011 | V42: -301849.67 | W42: -299211.49 | X42: -2638.1757 | Y42: 0 | Z42: 0 | AA42: SI D42=D41: Z41, SINO: BUSCARV(col V=Precio Nominal (Posicion Inicial Gallo), fallback PrecioTenenciasIniciales/PreciosInicialesEspecies) | U=PrecioPos/P42 | V=-274408787*U si venta | Q=GastosUSD | W=M +/- Q segun signo | X=|W|-|V| | Y=I+T | Z=Promedio | AB42: Origen: Visual | Cod: 9250 | K(PrecioStd)=raw | L=K*O | GastosFuente=0 | AC42: 0.001090386
A43: Visual | B43: Letras del Tesoro nac | C43: LETRAS DEL TESORO CAP $ V31/07/25 - Pesos | D43: 9305 | E43: 45848 | F43: 10/7/2025 | G43: Dolar ME | H43: Compra Contado Continuo | I43: 218804409 | J43: 0.0011 | K43: 0.0011 | L43: 0.0011 | M43: 249437.03 | N43: 0 | O43: 1 | P43: 1275 | Q43: 0 | R43: 0 | T43: 0 | U43: 0.0010838701 | V43: 0 | W43: 249437.03 | X43: 0 | Y43: 218804409 | Z43: 0.00114 | AA43: SI D43=D42: Z42, SINO: BUSCARV(col V=Precio Nominal (Posicion Inicial Gallo), fallback PrecioTenenciasIniciales/PreciosInicialesEspecies) | U=PrecioPos/P43 | V=218804409*U si venta | Q=GastosUSD | W=M +/- Q segun signo | X=|W|-|V| | Y=I+T | Z=Promedio | AB43: Origen: Visual | Cod: 9305 | K(PrecioStd)=raw | L=K*O | GastosFuente=0 | AC43: 0.0011
A44: Visual | B44: Letras del Tesoro nac | C44: LETRAS DEL TESORO CAP $ V31/07/25 - Pesos | D44: 9305 | E44: 45848 | F44: 10/7/2025 | G44: Pesos | H44: Venta Contado Continuo No | I44: -218804409 | J44: 1.4428 | K44: 1.4428 | L44: 0.0011316078 | M44: -247600.79 | N44: 0 | O44: 0.00078431373 | P44: 1275 | Q44: 0 | R44: 0 | T44: 218804409 | U44: 0.00114 | V44: -249437.03 | W44: -247600.79 | X44: -1836.2447 | Y44: 0 | Z44: 0 | AA44: SI D44=D43: Z43, SINO: BUSCARV(col V=Precio Nominal (Posicion Inicial Gallo), fallback PrecioTenenciasIniciales/PreciosInicialesEspecies) | U=PrecioPos/P44 | V=-218804409*U si venta | Q=GastosUSD | W=M +/- Q segun signo | X=|W|-|V| | Y=I+T | Z=Promedio | AB44: Origen: Visual | Cod: 9305 | K(PrecioStd)=raw | L=K*O | GastosFuente=0 | AC44: 0.0011316078
A45: Visual | B45: Letras del Tesoro nac | C45: LETRAS DEL TESORO CAP $ V31/07/25 - Pesos | D45: 9305 | E45: 45849 | F45: 11/7/2025 | G45: Dolar ME | H45: Compra Contado Continuo | I45: 216790302 | J45: 0.0012 | K45: 0.0012 | L45: 0.0012 | M45: 249308.85 | N45: 0 | O45: 1 | P45: 1275 | Q45: 0 | R45: 0 | T45: 0 | U45: 0.00114 | V45: 0 | W45: 249308.85 | X45: 0 | Y45: 216790302 | Z45: 0.00115 | AA45: SI D45=D44: Z44, SINO: BUSCARV(col V=Precio Nominal (Posicion Inicial Gallo), fallback PrecioTenenciasIniciales/PreciosInicialesEspecies) | U=PrecioPos/P45 | V=216790302*U si venta | Q=GastosUSD | W=M +/- Q segun signo | X=|W|-|V| | Y=I+T | Z=Promedio | AB45: Origen: Visual | Cod: 9305 | K(PrecioStd)=raw | L=K*O | GastosFuente=0 | AC45: 0.0012
A46: Visual | B46: Letras del Tesoro nac | C46: LETRAS DEL TESORO CAP $ V31/07/25 - Pesos | D46: 9305 | E46: 45849 | F46: 11/7/2025 | G46: Pesos | H46: Venta Contado Continuo No | I46: -216790302 | J46: 1.4559 | K46: 1.4559 | L46: 0.0011418824 | M46: -247549.02 | N46: 0 | O46: 0.00078431373 | P46: 1275 | Q46: 0 | R46: 0 | T46: 216790302 | U46: 0.00115 | V46: -249308.85 | W46: -247549.02 | X46: -1759.8299 | Y46: 0 | Z46: 0 | AA46: SI D46=D45: Z45, SINO: BUSCARV(col V=Precio Nominal (Posicion Inicial Gallo), fallback PrecioTenenciasIniciales/PreciosInicialesEspecies) | U=PrecioPos/P46 | V=-216790302*U si venta | Q=GastosUSD | W=M +/- Q segun signo | X=|W|-|V| | Y=I+T | Z=Promedio | AB46: Origen: Visual | Cod: 9305 | K(PrecioStd)=raw | L=K*O | GastosFuente=0 | AC46: 0.0011418824
A47: Visual | B47: Letras del Tesoro nac | C47: LETRAS DEL TESORO CAP $ V31/07/25 - Pesos | D47: 9305 | E47: 45852 | F47: 14/7/2025 | G47: Dolar ME | H47: Compra Contado Continuo | I47: 216766273 | J47: 0.0012 | K47: 0.0012 | L47: 0.0012 | M47: 249281.21 | N47: 0 | O47: 1 | P47: 1275 | Q47: 0 | R47: 0 | T47: 0 | U47: 0.00115 | V47: 0 | W47: 249281.21 | X47: 0 | Y47: 216766273 | Z47: 0.00115 | AA47: SI D47=D46: Z46, SINO: BUSCARV(col V=Precio Nominal (Posicion Inicial Gallo), fallback PrecioTenenciasIniciales/PreciosInicialesEspecies) | U=PrecioPos/P47 | V=216766273*U si venta | Q=GastosUSD | W=M +/- Q segun signo | X=|W|-|V| | Y=I+T | Z=Promedio | AB47: Origen: Visual | Cod: 9305 | K(PrecioStd)=raw | L=K*O | GastosFuente=0 | AC47: 0.0012
... A73: Visual | B73: Títulos Públicos | C73: BOPREAL 4B VTO31/10/28 U$S CG - Dolar MEP (local) | D73: 9350 | E73: 45973 | F73: 13/11/2025 | G73: Dolar ME | H73: Compra Contado | I73: 307000 | J73: 0.815 | K73: 81.5 | L73: 81.5 | M73: 250205 | N73: 0 | O73: 1 | P73: 1440 | Q73: 0 | R73: 0 | T73: 0 | U73: 0 | V73: 0 | W73: 250205 | X73: 0 | Y73: 307000 | Z73: 0.815 | AA73: SI D73=D72: Z72, SINO: BUSCARV(col V=Precio Nominal (Posicion Inicial Gallo), fallback PrecioTenenciasIniciales/PreciosInicialesEspecies) | U=PrecioPos/P73 | V=307000*U si venta | Q=GastosUSD | W=M +/- Q segun signo | X=|W|-|V| | Y=I+T | Z=Promedio | AB73: Origen: Visual | Cod: 9350 | K(PrecioStd)=x100 | L=K*O | GastosFuente=0 | AC73: 0.815

Sheet Rentas Dividendos ARS
A1: Instrumento | B1: Cod.Instrum | C1: Categoría | D1: tipo_instrumento | E1: Concertación | F1: Liquidación | G1: Nro. NDC | H1: Tipo Operación | I1: Cantidad | J1: Moneda | K1: Tipo de Cambio | L1: Gastos | M1: Importe | N1: Origen | O1: Importe Original

Sheet Rentas Dividendos USD
A1: Instrumento | B1: Cod.Instrum | C1: Categoría | D1: tipo_instrumento | E1: Concertación | F1: Liquidación | G1: Nro. NDC | H1: Tipo Operación | I1: Cantidad | J1: Moneda | K1: Tipo de Cambio | L1: Gastos | M1: Importe | N1: Origen | O1: Importe Original

Sheet FCI
A1: Concertación | B1: Liquidación | C1: Moneda | D1: Tipo Operación | E1: Cantidad | F1: Tipo de Cambio | G1: Precio | H1: Bruto | I1: Gastos | J1: IVA | K1: Resultado

Sheet Opciones
A1: Instrumento | B1: Concertación | C1: Liquidación | D1: Moneda | E1: Tipo Operación | F1: Cantidad | G1: Tipo de Cambio | H1: Precio | I1: Bruto | J1: Gastos | K1: IVA | L1: Resultado

Sheet Futuros
A1: Moneda | B1: Instrumento | C1: Tipo de Liquidación | D1: Total
A2: ARS | B2: DLR062025 - Pesos | C2: MTM - Diferencia | D2: -1900000
A3: ARS | B3: DLR062025 - Pesos | C3: Resultado - Cancelación | D3: 6600000

Sheet Pagare_CPD
A1: Instrumento | B1: Concertación | C1: Liquidación | D1: Vencimiento | E1: Tipo Operación | F1: Abreviatura | G1: Moneda | H1: Tipo Cambio | I1: Valor Nominal | J1: Tasa | K1: Valor Final | L1: Gastos | M1: Neto | N1: Origen

Sheet Resumen
A1: Moneda | B1: Ventas | C1: FCI | D1: Opciones | E1: Rentas | F1: Dividendos | G1: Pagare/CPD | H1: Futuros | I1: Cau (Tom) | J1: Cau (Col) | K1: Total
A2: ARS | B2: -7500364 | C2: 0 | D2: 0 | E2: 0 | F2: 0 | G2: 0 | H2: 4700000 | I2: -8540413.2 | J2: 0 | K2: -11340777
A3: USD | B3: 40519.464 | C3: 0 | D3: 0 | E3: 0 | F3: 0 | G3: 0 | H3: 0 | I3: -6715.46 | J3: 0 | K3: 33804.004

Sheet Posicion Titulos
A1: Instrumento | B1: Código | C1: Ticker | D1: Cantidad | E1: Importe | F1: Moneda | G1: Origen
A2: Es Disponible Sí | D2: 0 | E2: 0 | G2: Visual-Posicion Titulos
A3: BOPREAL 4B VTO31/10/28 U$S CG | B3: 9350 | C3: BPOB8 | D3: 307000 | E3: 394464300 | F3: Pesos | G3: Visual-Posicion Titulos

Sheet EspeciesVisual
A1: Descripción | B1: Tipo de Especie | C1: Código | D1: Fecha de Emisión | E1: Fecha de Vencimiento | F1: Mercado | G1: Moneda de Emisión | H1: Abreviatura | I1: Lámina Mínima | J1: Moneda (Reuters / Bloomberg) | K1: Código SISCEN | L1: ISIN Code | M1: Moneda (Reuters / Bloomberg) | N1: Moneda de Emisión | O1: Tipo de Instrumento | Q1: InstrumentoConMoneda | R1: Tipo de Especie
G2: Descripción | J2: Símbolo | M2: Descripción | N2: Símbolo
A3: *MAV160601050 | B3: Cheques Diferidos | D3: 31/5/2025 | E3: 31/5/2025 | F3: MAV | G3: Pesos | H3: *MAV160601050 | N3: $ | O3: Especie (CPD/Pagaré/FCE) | Q3: *MAV160601050 - Pesos | R3: Cheques Diferidos
A4: *MAV250700791 | B4: Cheques Diferidos | D4: 31/5/2025 | E4: 31/5/2025 | F4: MAV | G4: Pesos | H4: *MAV250700791 | N4: $ | O4: Especie (CPD/Pagaré/FCE) | Q4: *MAV250700791 - Pesos | R4: Cheques Diferidos
A5: *MAV010800659 | B5: Cheques Diferidos | D5: 31/5/2025 | E5: 31/5/2025 | F5: MAV | G5: Pesos | H5: *MAV010800659 | N5: $ | O5: Especie (CPD/Pagaré/FCE) | Q5: *MAV010800659 - Pesos | R5: Cheques Diferidos
A6: *MAV100700897 | B6: Cheques Diferidos | D6: 31/5/2025 | E6: 31/5/2025 | F6: MAV | G6: Pesos | H6: *MAV100700897 | N6: $ | O6: Especie (CPD/Pagaré/FCE) | Q6: *MAV100700897 - Pesos | R6: Cheques Diferidos
A7: *MAV300700682 | B7: Cheques Diferidos | D7: 31/5/2025 | E7: 31/5/2025 | F7: MAV | G7: Pesos | H7: *MAV300700682 | N7: $ | O7: Especie (CPD/Pagaré/FCE) | Q7: *MAV300700682 - Pesos | R7: Cheques Diferidos
A8: *MAV190600710 | B8: Cheques Diferidos | D8: 31/5/2025 | E8: 31/5/2025 | F8: MAV | G8: Pesos | H8: *MAV190600710 | N8: $ | O8: Especie (CPD/Pagaré/FCE) | Q8: *MAV190600710 - Pesos | R8: Cheques Diferidos
A9: *MAV270600865 | B9: Cheques Diferidos | D9: 31/5/2025 | E9: 31/5/2025 | F9: MAV | G9: Pesos | H9: *MAV270600865 | N9: $ | O9: Especie (CPD/Pagaré/FCE) | Q9: *MAV270600865 - Pesos | R9: Cheques Diferidos
A10: *MAV060700589 | B10: Cheques Diferidos | D10: 31/5/2025 | E10: 31/5/2025 | F10: MAV | G10: Pesos | H10: *MAV060700589 | N10: $ | O10: Especie (CPD/Pagaré/FCE) | Q10: *MAV060700589 - Pesos | R10: Cheques Diferidos
A11: *MAV280600941 | B11: Cheques Diferidos | D11: 31/5/2025 | E11: 31/5/2025 | F11: MAV | G11: Pesos | H11: *MAV280600941 | N11: $ | O11: Especie (CPD/Pagaré/FCE) | Q11: *MAV280600941 - Pesos | R11: Cheques Diferidos
A12: *MAV020700566 | B12: Cheques Diferidos | D12: 31/5/2025 | E12: 31/5/2025 | F12: MAV | G12: Pesos | H12: *MAV020700566 | N12: $ | O12: Especie (CPD/Pagaré/FCE) | Q12: *MAV020700566 - Pesos | R12: Cheques Diferidos
A13: *MAV300601372 | B13: Cheques Diferidos | D13: 31/5/2025 | E13: 31/5/2025 | F13: MAV | G13: Pesos | H13: *MAV300601372 | N13: $ | O13: Especie (CPD/Pagaré/FCE) | Q13: *MAV300601372 - Pesos | R13: Cheques Diferidos
A14: *MAV040600605 | B14: Cheques Diferidos | D14: 31/5/2025 | E14: 31/5/2025 | F14: MAV | G14: Pesos | H14: *MAV040600605 | N14: $ | O14: Especie (CPD/Pagaré/FCE) | Q14: *MAV040600605 - Pesos | R14: Cheques Diferidos
... A224: *MAV170600903 | B224: Cheques Diferidos | D224: 31/5/2025 | E224: 31/5/2025 | F224: MAV | G224: Pesos | H224: *MAV170600903 | N224: $ | O224: Especie (CPD/Pagaré/FCE) | Q224: *MAV170600903 - Pesos | R224: Cheques Diferidos
A225: *MAV200600888 | B225: ECHEQ | D225: 5/6/2025 | E225: 20/6/2025 | F225: BYMA | G225: Pesos | H225: *MAV200600888 | I225: 0.01 | N225: $ | O225: Especie (CPD/Pagaré/FCE) | Q225: *MAV200600888 - Pesos | R225: ECHEQ
A226: *MAV200600883 | B226: ECHEQ | D226: 5/6/2025 | E226: 20/6/2025 | F226: BYMA | G226: Pesos | H226: *MAV200600883 | I226: 0.01 | N226: $ | O226: Especie (CPD/Pagaré/FCE) | Q226: *MAV200600883 - Pesos | R226: ECHEQ
A227: *MAV190600778 | B227: ECHEQ | D227: 5/6/2025 | E227: 19/6/2025 | F227: BYMA | G227: Pesos | H227: *MAV190600778 | I227: 0.01 | N227: $ | O227: Especie (CPD/Pagaré/FCE) | Q227: *MAV190600778 - Pesos | R227: ECHEQ
A228: *MAV230601175 | B228: ECHEQ | D228: 5/6/2025 | E228: 23/6/2025 | F228: BYMA | G228: Pesos | H228: *MAV230601175 | I228: 0.01 | N228: $ | O228: Especie (CPD/Pagaré/FCE) | Q228: *MAV230601175 - Pesos | R228: ECHEQ
A229: *MAV220600711 | B229: ECHEQ | D229: 5/6/2025 | E229: 22/6/2025 | F229: BYMA | G229: Pesos | H229: *MAV220600711 | I229: 0.01 | N229: $ | O229: Especie (CPD/Pagaré/FCE) | Q229: *MAV220600711 - Pesos | R229: ECHEQ
A230: *MAV200600886 | B230: ECHEQ | D230: 5/6/2025 | E230: 20/6/2025 | F230: BYMA | G230: Pesos | H230: *MAV200600886 | I230: 0.01 | N230: $ | O230: Especie (CPD/Pagaré/FCE) | Q230: *MAV200600886 - Pesos | R230: ECHEQ
A231: *MAV200600882 | B231: ECHEQ | D231: 5/6/2025 | E231: 20/6/2025 | F231: BYMA | G231: Pesos | H231: *MAV200600882 | I231: 0.01 | N231: $ | O231: Especie (CPD/Pagaré/FCE) | Q231: *MAV200600882 - Pesos | R231: ECHEQ
A232: *MAV300601575 | B232: ECHEQ | D232: 5/6/2025 | E232: 30/6/2025 | F232: BYMA | G232: Pesos | H232: *MAV300601575 | I232: 0.01 | N232: $ | O232: Especie (CPD/Pagaré/FCE) | Q232: *MAV300601575 - Pesos | R232: ECHEQ
A233: *MAV290600631 | B233: ECHEQ | D233: 5/6/2025 | E233: 29/6/2025 | F233: BYMA | G233: Pesos | H233: *MAV290600631 | I233: 0.01 | N233: $ | O233: Especie (CPD/Pagaré/FCE) | Q233: *MAV290600631 - Pesos | R233: ECHEQ
A234: *MAV240601016 | B234: ECHEQ | D234: 5/6/2025 | E234: 24/6/2025 | F234: BYMA | G234: Pesos | H234: *MAV240601016 | I234: 0.01 | N234: $ | O234: Especie (CPD/Pagaré/FCE) | Q234: *MAV240601016 - Pesos | R234: ECHEQ
A235: *MAV230601173 | B235: ECHEQ | D235: 5/6/2025 | E235: 23/6/2025 | F235: BYMA | G235: Pesos | H235: *MAV230601173 | I235: 0.01 | N235: $ | O235: Especie (CPD/Pagaré/FCE) | Q235: *MAV230601173 - Pesos | R235: ECHEQ
A236: *MAV071001056 | B236: ECHEQ | D236: 16/9/2025 | E236: 9/10/2025 | F236: MAV | G236: Pesos | H236: *MAV071001056 | I236: 0.01 | N236: $ | O236: Especie (CPD/Pagaré/FCE) | Q236: *MAV071001056 - Pesos | R236: ECHEQ
... A914: *BIS301100204 | B914: ECHEQ | D914: 20/8/2025 | E914: 3/12/2025 | F914: MAV | G914: Pesos | H914: *BIS301100204 | I914: 0.01 | N914: $ | O914: Especie (CPD/Pagaré/FCE) | Q914: *BIS301100204 - Pesos | R914: ECHEQ
A915: #UTD190860001 | B915: Pagaré Hard Dolar | E915: 19/8/2026 | F915: BYMA | G915: Dolar MEP (local) | H915: #UTD190860001 | I915: 0.01 | N915: U$D | O915: Especie (CPD/Pagaré/FCE) | Q915: #UTD190860001 - Dolar MEP (local) | R915: Pagaré Hard Dolar
A916: #UTD010860001 | B916: Pagaré Hard Dolar | E916: 1/8/2026 | F916: BYMA | G916: Dolar MEP (local) | H916: #UTD010860001 | I916: 0.01 | N916: U$D | O916: Especie (CPD/Pagaré/FCE) | Q916: #UTD010860001 - Dolar MEP (local) | R916: Pagaré Hard Dolar
A917: *BIN231000052 | B917: ECHEQ | D917: 21/8/2025 | E917: 23/10/2025 | F917: BYMA | G917: Pesos | H917: *BIN231000052 | I917: 0.01 | N917: $ | O917: Especie (CPD/Pagaré/FCE) | Q917: *BIN231000052 - Pesos | R917: ECHEQ
A918: *BIN200900061 | B918: ECHEQ | D918: 21/8/2025 | E918: 20/9/2025 | F918: BYMA | G918: Pesos | H918: *BIN200900061 | I918: 0.01 | N918: $ | O918: Especie (CPD/Pagaré/FCE) | Q918: *BIN200900061 - Pesos | R918: ECHEQ
A919: *MAV300100998 | B919: ECHEQ | D919: 18/11/2025 | E919: 3/2/2026 | F919: MAV | G919: Pesos | H919: *MAV300100998 | I919: 0.01 | N919: $ | O919: Especie (CPD/Pagaré/FCE) | Q919: *MAV300100998 - Pesos | R919: ECHEQ
A920: *MAV300100999 | B920: ECHEQ | D920: 18/11/2025 | E920: 3/2/2026 | F920: MAV | G920: Pesos | H920: *MAV300100999 | I920: 0.01 | N920: $ | O920: Especie (CPD/Pagaré/FCE) | Q920: *MAV300100999 - Pesos | R920: ECHEQ
A921: *MAV300101003 | B921: ECHEQ | D921: 18/11/2025 | E921: 3/2/2026 | F921: MAV | G921: Pesos | H921: *MAV300101003 | I921: 0.01 | N921: $ | O921: Especie (CPD/Pagaré/FCE) | Q921: *MAV300101003 - Pesos | R921: ECHEQ
A922: *MAV300101004 | B922: ECHEQ | D922: 18/11/2025 | E922: 3/2/2026 | F922: MAV | G922: Pesos | H922: *MAV300101004 | I922: 0.01 | N922: $ | O922: Especie (CPD/Pagaré/FCE) | Q922: *MAV300101004 - Pesos | R922: ECHEQ
A923: *MAV020100874 | B923: ECHEQ | D923: 18/11/2025 | E923: 6/1/2026 | F923: MAV | G923: Pesos | H923: *MAV020100874 | I923: 0.01 | N923: $ | O923: Especie (CPD/Pagaré/FCE) | Q923: *MAV020100874 - Pesos | R923: ECHEQ
A924: *MAV020100876 | B924: ECHEQ | D924: 18/11/2025 | E924: 6/1/2026 | F924: MAV | G924: Pesos | H924: *MAV020100876 | I924: 0.01 | N924: $ | O924: Especie (CPD/Pagaré/FCE) | Q924: *MAV020100876 - Pesos | R924: ECHEQ
A925: *MAV230100935 | B925: ECHEQ | D925: 18/11/2025 | E925: 27/1/2026 | F925: MAV | G925: Pesos | H925: *MAV230100935 | I925: 0.01 | N925: $ | O925: Especie (CPD/Pagaré/FCE) | Q925: *MAV230100935 - Pesos | R925: ECHEQ
A926: *MAV301101593 | B926: ECHEQ | D926: 20/11/2025 | E926: 30/11/2025 | F926: BYMA | G926: Pesos | H926: *MAV301101593 | I926: 0.01 | N926: $ | O926: Especie (CPD/Pagaré/FCE) | Q926: *MAV301101593 - Pesos | R926: ECHEQ
A927: *MAV041200881 | B927: ECHEQ | D927: 20/11/2025 | E927: 4/12/2025 | F927: BYMA | G927: Pesos | H927: *MAV041200881 | I927: 0.01 | N927: $ | O927: Especie (CPD/Pagaré/FCE) | Q927: *MAV041200881 - Pesos | R927: ECHEQ
A928: *MAV031200894 | B928: ECHEQ | D928: 20/11/2025 | E928: 3/12/2025 | F928: BYMA | G928: Pesos | H928: *MAV031200894 | I928: 0.01 | N928: $ | O928: Especie (CPD/Pagaré/FCE) | Q928: *MAV031200894 - Pesos | R928: ECHEQ
... A4351: *MOV051100049 | B4351: ECHEQ | D4351: 29/7/2025 | E4351: 10/11/2025 | F4351: MAV | G4351: Pesos | H4351: *MOV051100049 | I4351: 0.01 | N4351: $ | O4351: Especie (CPD/Pagaré/FCE) | Q4351: *MOV051100049 - Pesos | R4351: ECHEQ
A4352: #UMV031150049 | B4352: Pagaré Hard Dolar | E4352: 3/11/2025 | F4352: BYMA | G4352: Dolar MEP (local) | H4352: #UMV031150049 | I4352: 0.01 | N4352: U$D | O4352: Especie (CPD/Pagaré/FCE) | Q4352: #UMV031150049 - Dolar MEP (local) | R4352: Pagaré Hard Dolar
A4353: *BIN010100026 | B4353: ECHEQ | D4353: 11/11/2025 | E4353: 6/1/2026 | F4353: MAV | G4353: Pesos | H4353: *BIN010100026 | I4353: 0.01 | N4353: $ | O4353: Especie (CPD/Pagaré/FCE) | Q4353: *BIN010100026 - Pesos | R4353: ECHEQ
A4354: #MAV111250055 | B4354: Pagare | D4354: 11/11/2025 | E4354: 12/12/2025 | F4354: MAV | G4354: Pesos | H4354: #MAV111250055 | I4354: 0.01 | N4354: $ | O4354: Especie (CPD/Pagaré/FCE) | Q4354: #MAV111250055 - Pesos | R4354: Pagare
A4355: *BIN160100061 | B4355: ECHEQ | D4355: 11/11/2025 | E4355: 16/1/2026 | F4355: BYMA | G4355: Pesos | H4355: *BIN160100061 | I4355: 0.01 | N4355: $ | O4355: Especie (CPD/Pagaré/FCE) | Q4355: *BIN160100061 - Pesos | R4355: ECHEQ
A4356: *TRD121200040 | B4356: ECHEQ | D4356: 12/11/2025 | E4356: 12/12/2025 | F4356: BYMA | G4356: Pesos | H4356: *TRD121200040 | I4356: 0.01 | N4356: $ | O4356: Especie (CPD/Pagaré/FCE) | Q4356: *TRD121200040 - Pesos | R4356: ECHEQ
A4357: *BIN270200037 | B4357: ECHEQ | D4357: 12/11/2025 | E4357: 27/2/2026 | F4357: BYMA | G4357: Pesos | H4357: *BIN270200037 | I4357: 0.01 | N4357: $ | O4357: Especie (CPD/Pagaré/FCE) | Q4357: *BIN270200037 - Pesos | R4357: ECHEQ
A4358: *BIN240200049 | B4358: ECHEQ | D4358: 12/11/2025 | E4358: 24/2/2026 | F4358: BYMA | G4358: Pesos | H4358: *BIN240200049 | I4358: 0.01 | N4358: $ | O4358: Especie (CPD/Pagaré/FCE) | Q4358: *BIN240200049 - Pesos | R4358: ECHEQ
A4359: *MAV130101028 | B4359: ECHEQ | D4359: 12/11/2025 | E4359: 13/1/2026 | F4359: BYMA | G4359: Pesos | H4359: *MAV130101028 | I4359: 0.01 | N4359: $ | O4359: Especie (CPD/Pagaré/FCE) | Q4359: *MAV130101028 - Pesos | R4359: ECHEQ
A4360: *MAV130101027 | B4360: ECHEQ | D4360: 12/11/2025 | E4360: 13/1/2026 | F4360: BYMA | G4360: Pesos | H4360: *MAV130101027 | I4360: 0.01 | N4360: $ | O4360: Especie (CPD/Pagaré/FCE) | Q4360: *MAV130101027 - Pesos | R4360: ECHEQ
A4361: *BIN130200044 | B4361: ECHEQ | D4361: 12/11/2025 | E4361: 13/2/2026 | F4361: BYMA | G4361: Pesos | H4361: *BIN130200044 | I4361: 0.01 | N4361: $ | O4361: Especie (CPD/Pagaré/FCE) | Q4361: *BIN130200044 - Pesos | R4361: ECHEQ
A4362: #UMV231250021 | B4362: Pagare | D4362: 13/11/2025 | E4362: 23/12/2025 | F4362: BYMA | G4362: Dolar MEP (local) | H4362: #UMV231250021 | I4362: 0.01 | N4362: U$D | O4362: Especie (CPD/Pagaré/FCE) | Q4362: #UMV231250021 - Dolar MEP (local) | R4362: Pagare
A4363: *BIN151200149 | B4363: ECHEQ | D4363: 13/11/2025 | E4363: 15/12/2025 | F4363: BYMA | G4363: Pesos | H4363: *BIN151200149 | I4363: 0.01 | N4363: $ | O4363: Especie (CPD/Pagaré/FCE) | Q4363: *BIN151200149 - Pesos | R4363: ECHEQ
A4364: *MAV060200804 | B4364: ECHEQ | D4364: 13/11/2025 | E4364: 10/2/2026 | F4364: MAV | G4364: Pesos | H4364: *MAV060200804 | I4364: 0.01 | N4364: $ | O4364: Especie (CPD/Pagaré/FCE) | Q4364: *MAV060200804 - Pesos | R4364: ECHEQ
... A5042: *BIS301200121 | B5042: ECHEQ | D5042: 9/9/2025 | E5042: 5/1/2026 | F5042: MAV | G5042: Pesos | H5042: *BIS301200121 | I5042: 0.01 | N5042: $ | O5042: Especie (CPD/Pagaré/FCE) | Q5042: *BIS301200121 - Pesos | R5042: ECHEQ
A5043: TRND300900009 | B5043: Cheques Diferidos | E5043: 30/9/2025 | F5043: BYMA | G5043: Pesos | H5043: TRND300900009 | I5043: 0.01 | N5043: $ | O5043: Especie (CPD/Pagaré/FCE) | Q5043: TRND300900009 - Pesos | R5043: Cheques Diferidos
A5044: *MAV200901262 | B5044: ECHEQ | D5044: 10/9/2025 | E5044: 20/9/2025 | F5044: BYMA | G5044: Pesos | H5044: *MAV200901262 | I5044: 0.01 | N5044: $ | O5044: Especie (CPD/Pagaré/FCE) | Q5044: *MAV200901262 - Pesos | R5044: ECHEQ
A5045: *MAV180900981 | B5045: ECHEQ | D5045: 10/9/2025 | E5045: 18/9/2025 | F5045: BYMA | G5045: Pesos | H5045: *MAV180900981 | I5045: 0.01 | N5045: $ | O5045: Especie (CPD/Pagaré/FCE) | Q5045: *MAV180900981 - Pesos | R5045: ECHEQ
A5046: *MAV170900989 | B5046: ECHEQ | D5046: 10/9/2025 | E5046: 17/9/2025 | F5046: BYMA | G5046: Pesos | H5046: *MAV170900989 | I5046: 0.01 | N5046: $ | O5046: Especie (CPD/Pagaré/FCE) | Q5046: *MAV170900989 - Pesos | R5046: ECHEQ
A5047: *CRE151100189 | B5047: ECHEQ | D5047: 10/9/2025 | E5047: 15/11/2025 | F5047: BYMA | G5047: Pesos | H5047: *CRE151100189 | I5047: 0.01 | N5047: $ | O5047: Especie (CPD/Pagaré/FCE) | Q5047: *CRE151100189 - Pesos | R5047: ECHEQ
A5048: *CRE151100188 | B5048: ECHEQ | D5048: 10/9/2025 | E5048: 15/11/2025 | F5048: BYMA | G5048: Pesos | H5048: *CRE151100188 | I5048: 0.01 | N5048: $ | O5048: Especie (CPD/Pagaré/FCE) | Q5048: *CRE151100188 - Pesos | R5048: ECHEQ
A5049: *CRE141100111 | B5049: ECHEQ | D5049: 10/9/2025 | E5049: 14/11/2025 | F5049: BYMA | G5049: Pesos | H5049: *CRE141100111 | I5049: 0.01 | N5049: $ | O5049: Especie (CPD/Pagaré/FCE) | Q5049: *CRE141100111 - Pesos | R5049: ECHEQ
A5050: *CRE141100110 | B5050: ECHEQ | D5050: 10/9/2025 | E5050: 14/11/2025 | F5050: BYMA | G5050: Pesos | H5050: *CRE141100110 | I5050: 0.01 | N5050: $ | O5050: Especie (CPD/Pagaré/FCE) | Q5050: *CRE141100110 - Pesos | R5050: ECHEQ
A5051: *CRE141100108 | B5051: ECHEQ | D5051: 10/9/2025 | E5051: 14/11/2025 | F5051: BYMA | G5051: Pesos | H5051: *CRE141100108 | I5051: 0.01 | N5051: $ | O5051: Especie (CPD/Pagaré/FCE) | Q5051: *CRE141100108 - Pesos | R5051: ECHEQ
A5052: *BIS030200106 | B5052: ECHEQ | D5052: 15/12/2025 | E5052: 3/2/2026 | F5052: MAV | G5052: Pesos | H5052: *BIS030200106 | I5052: 0.01 | N5052: $ | O5052: Especie (CPD/Pagaré/FCE) | Q5052: *BIS030200106 - Pesos | R5052: ECHEQ
A5053: *BIS110400065 | B5053: ECHEQ | D5053: 15/12/2025 | E5053: 11/4/2026 | F5053: MAV | G5053: Pesos | H5053: *BIS110400065 | I5053: 0.01 | N5053: $ | O5053: Especie (CPD/Pagaré/FCE) | Q5053: *BIS110400065 - Pesos | R5053: ECHEQ
A5054: *BIS130200164 | B5054: ECHEQ | D5054: 15/12/2025 | E5054: 13/2/2026 | F5054: MAV | G5054: Pesos | H5054: *BIS130200164 | I5054: 0.01 | N5054: $ | O5054: Especie (CPD/Pagaré/FCE) | Q5054: *BIS130200164 - Pesos | R5054: ECHEQ
A5055: *BIS020300085 | B5055: ECHEQ | D5055: 15/12/2025 | E5055: 2/3/2026 | F5055: MAV | G5055: Pesos | H5055: *BIS020300085 | I5055: 0.01 | N5055: $ | O5055: Especie (CPD/Pagaré/FCE) | Q5055: *BIS020300085 - Pesos | R5055: ECHEQ
... A5449: *MAV101001357 | B5449: ECHEQ | D5449: 3/10/2025 | E5449: 10/10/2025 | F5449: BYMA | G5449: Pesos | H5449: *MAV101001357 | I5449: 0.01 | N5449: $ | O5449: Especie (CPD/Pagaré/FCE) | Q5449: *MAV101001357 - Pesos | R5449: ECHEQ
A5450: TRND091100003 | B5450: Cheques Diferidos | E5450: 9/11/2025 | F5450: MAV | G5450: Pesos | H5450: TRND091100003 | I5450: 0.01 | N5450: $ | O5450: Especie (CPD/Pagaré/FCE) | Q5450: TRND091100003 - Pesos | R5450: Cheques Diferidos
A5451: TRND091200001 | B5451: Cheques Diferidos | E5451: 9/12/2025 | F5451: MAV | G5451: Pesos | H5451: TRND091200001 | I5451: 0.01 | N5451: $ | O5451: Especie (CPD/Pagaré/FCE) | Q5451: TRND091200001 - Pesos | R5451: Cheques Diferidos
A5452: *BIS010300093 | B5452: ECHEQ | D5452: 12/12/2025 | E5452: 1/3/2026 | F5452: MAV | G5452: Pesos | H5452: *BIS010300093 | I5452: 0.01 | N5452: $ | O5452: Especie (CPD/Pagaré/FCE) | Q5452: *BIS010300093 - Pesos | R5452: ECHEQ
A5453: *BIS100100248 | B5453: ECHEQ | D5453: 12/12/2025 | E5453: 10/1/2026 | F5453: MAV | G5453: Pesos | H5453: *BIS100100248 | I5453: 0.01 | N5453: $ | O5453: Especie (CPD/Pagaré/FCE) | Q5453: *BIS100100248 - Pesos | R5453: ECHEQ
A5454: *BIS250100145 | B5454: ECHEQ | D5454: 12/12/2025 | E5454: 25/1/2026 | F5454: MAV | G5454: Pesos | H5454: *BIS250100145 | I5454: 0.01 | N5454: $ | O5454: Especie (CPD/Pagaré/FCE) | Q5454: *BIS250100145 - Pesos | R5454: ECHEQ
A5455: *BIS250200106 | B5455: ECHEQ | D5455: 12/12/2025 | E5455: 25/2/2026 | F5455: MAV | G5455: Pesos | H5455: *BIS250200106 | I5455: 0.01 | N5455: $ | O5455: Especie (CPD/Pagaré/FCE) | Q5455: *BIS250200106 - Pesos | R5455: ECHEQ
A5456: *BIS280200340 | B5456: ECHEQ | D5456: 12/12/2025 | E5456: 28/2/2026 | F5456: MAV | G5456: Pesos | H5456: *BIS280200340 | I5456: 0.01 | N5456: $ | O5456: Especie (CPD/Pagaré/FCE) | Q5456: *BIS280200340 - Pesos | R5456: ECHEQ
A5457: *BIS090200100 | B5457: ECHEQ | D5457: 12/12/2025 | E5457: 9/2/2026 | F5457: MAV | G5457: Pesos | H5457: *BIS090200100 | I5457: 0.01 | N5457: $ | O5457: Especie (CPD/Pagaré/FCE) | Q5457: *BIS090200100 - Pesos | R5457: ECHEQ
A5458: *MAV231201202 | B5458: ECHEQ | D5458: 4/12/2025 | E5458: 23/12/2025 | F5458: MAV | G5458: Pesos | H5458: *MAV231201202 | I5458: 0.01 | N5458: $ | O5458: Especie (CPD/Pagaré/FCE) | Q5458: *MAV231201202 - Pesos | R5458: ECHEQ
A5459: *TRD230400011 | B5459: ECHEQ | D5459: 4/12/2025 | E5459: 23/4/2026 | F5459: MAV | G5459: Pesos | H5459: *TRD230400011 | I5459: 0.01 | N5459: $ | O5459: Especie (CPD/Pagaré/FCE) | Q5459: *TRD230400011 - Pesos | R5459: ECHEQ
A5460: *TRD260400024 | B5460: ECHEQ | D5460: 4/12/2025 | E5460: 26/4/2026 | F5460: MAV | G5460: Pesos | H5460: *TRD260400024 | I5460: 0.01 | N5460: $ | O5460: Especie (CPD/Pagaré/FCE) | Q5460: *TRD260400024 - Pesos | R5460: ECHEQ
A5461: *BIN110300052 | B5461: ECHEQ | D5461: 5/12/2025 | E5461: 11/3/2026 | F5461: BYMA | G5461: Pesos | H5461: *BIN110300052 | I5461: 0.01 | N5461: $ | O5461: Especie (CPD/Pagaré/FCE) | Q5461: *BIN110300052 - Pesos | R5461: ECHEQ
A5462: *MAV151201708 | B5462: ECHEQ | D5462: 5/12/2025 | E5462: 15/12/2025 | F5462: BYMA | G5462: Pesos | H5462: *MAV151201708 | I5462: 0.01 | N5462: $ | O5462: Especie (CPD/Pagaré/FCE) | Q5462: *MAV151201708 - Pesos | R5462: ECHEQ
A5463: *MAV131201162 | B5463: ECHEQ | D5463: 5/12/2025 | E5463: 13/12/2025 | F5463: BYMA | G5463: Pesos | H5463: *MAV131201162 | I5463: 0.01 | N5463: $ | O5463: Especie (CPD/Pagaré/FCE) | Q5463: *MAV131201162 - Pesos | R5463: ECHEQ
... A5602: *AVR111200015 | B5602: ECHEQ | D5602: 4/9/2025 | E5602: 15/12/2025 | F5602: MAV | G5602: Pesos | H5602: *AVR111200015 | I5602: 0.01 | N5602: $ | O5602: Especie (CPD/Pagaré/FCE) | Q5602: *AVR111200015 - Pesos | R5602: ECHEQ
A5603: #UTD200860001 | B5603: Pagaré Hard Dolar | E5603: 20/8/2026 | F5603: BYMA | G5603: Dolar MEP (local) | H5603: #UTD200860001 | I5603: 0.01 | N5603: U$D | O5603: Especie (CPD/Pagaré/FCE) | Q5603: #UTD200860001 - Dolar MEP (local) | R5603: Pagaré Hard Dolar
A5604: *GAR011200287 | B5604: ECHEQ | D5604: 5/9/2025 | E5604: 1/12/2025 | F5604: BYMA | G5604: Pesos | H5604: *GAR011200287 | I5604: 0.01 | N5604: $ | O5604: Especie (CPD/Pagaré/FCE) | Q5604: *GAR011200287 - Pesos | R5604: ECHEQ
A5605: *MAV220901197 | B5605: ECHEQ | D5605: 5/9/2025 | E5605: 22/9/2025 | F5605: BYMA | G5605: Pesos | H5605: *MAV220901197 | I5605: 0.01 | N5605: $ | O5605: Especie (CPD/Pagaré/FCE) | Q5605: *MAV220901197 - Pesos | R5605: ECHEQ
A5606: *MAV210900735 | B5606: ECHEQ | D5606: 5/9/2025 | E5606: 21/9/2025 | F5606: BYMA | G5606: Pesos | H5606: *MAV210900735 | I5606: 0.01 | N5606: $ | O5606: Especie (CPD/Pagaré/FCE) | Q5606: *MAV210900735 - Pesos | R5606: ECHEQ
A5607: *MAV200901234 | B5607: ECHEQ | D5607: 5/9/2025 | E5607: 20/9/2025 | F5607: BYMA | G5607: Pesos | H5607: *MAV200901234 | I5607: 0.01 | N5607: $ | O5607: Especie (CPD/Pagaré/FCE) | Q5607: *MAV200901234 - Pesos | R5607: ECHEQ
A5608: *MAV240900920 | B5608: ECHEQ | D5608: 5/9/2025 | E5608: 24/9/2025 | F5608: BYMA | G5608: Pesos | H5608: *MAV240900920 | I5608: 0.01 | N5608: $ | O5608: Especie (CPD/Pagaré/FCE) | Q5608: *MAV240900920 - Pesos | R5608: ECHEQ
A5609: *MAV230901093 | B5609: ECHEQ | D5609: 5/9/2025 | E5609: 23/9/2025 | F5609: BYMA | G5609: Pesos | H5609: *MAV230901093 | I5609: 0.01 | N5609: $ | O5609: Especie (CPD/Pagaré/FCE) | Q5609: *MAV230901093 - Pesos | R5609: ECHEQ
A5610: *BIN291100072 | B5610: ECHEQ | D5610: 8/9/2025 | E5610: 29/11/2025 | F5610: BYMA | G5610: Pesos | H5610: *BIN291100072 | I5610: 0.01 | N5610: $ | O5610: Especie (CPD/Pagaré/FCE) | Q5610: *BIN291100072 - Pesos | R5610: ECHEQ
A5611: *BIN240900040 | B5611: ECHEQ | D5611: 8/9/2025 | E5611: 24/9/2025 | F5611: BYMA | G5611: Pesos | H5611: *BIN240900040 | I5611: 0.01 | N5611: $ | O5611: Especie (CPD/Pagaré/FCE) | Q5611: *BIN240900040 - Pesos | R5611: ECHEQ
A5612: *MAV161000875 | B5612: ECHEQ | D5612: 12/9/2025 | E5612: 20/10/2025 | F5612: MAV | G5612: Pesos | H5612: *MAV161000875 | I5612: 0.01 | N5612: $ | O5612: Especie (CPD/Pagaré/FCE) | Q5612: *MAV161000875 - Pesos | R5612: ECHEQ
A5613: *MAV141001109 | B5613: ECHEQ | D5613: 12/9/2025 | E5613: 16/10/2025 | F5613: MAV | G5613: Pesos | H5613: *MAV141001109 | I5613: 0.01 | N5613: $ | O5613: Especie (CPD/Pagaré/FCE) | Q5613: *MAV141001109 - Pesos | R5613: ECHEQ
A5614: *MAV061001107 | B5614: ECHEQ | D5614: 12/9/2025 | E5614: 8/10/2025 | F5614: MAV | G5614: Pesos | H5614: *MAV061001107 | I5614: 0.01 | N5614: $ | O5614: Especie (CPD/Pagaré/FCE) | Q5614: *MAV061001107 - Pesos | R5614: ECHEQ
A5615: *MAV201001178 | B5615: ECHEQ | D5615: 12/9/2025 | E5615: 22/10/2025 | F5615: MAV | G5615: Pesos | H5615: *MAV201001178 | I5615: 0.01 | N5615: $ | O5615: Especie (CPD/Pagaré/FCE) | Q5615: *MAV201001178 - Pesos | R5615: ECHEQ
... A7601: *BIS050700049 | B7601: ECHEQ | D7601: 28/5/2025 | E7601: 10/7/2025 | F7601: MAV | G7601: Pesos | H7601: *BIS050700049 | I7601: 1 | N7601: $ | O7601: Especie (CPD/Pagaré/FCE) | Q7601: *BIS050700049 - Pesos | R7601: ECHEQ
...

Sheet EspeciesGallo
A1: 'Codigo' | B1: 'Nombre de la Especie' | C1: 'Tipo' | D1: 'Clase' | E1: 'Precio' | F1: 'Ls' | G1: 'Lam.Min.' | H1: 'V.Res.' | I1: 'Gr' | J1: 'Norm.' | K1: 'Parid' | L1: 'Cable' | M1: 'Block' | N1: 'Mda.' | O1: 'Merc' | P1: 'Vencim' | Q1: 'Isin Code' | R1: 'Emisor' | S1: 'Tipo de Activo' | T1: 'LPA' | U1: 'LOP' | V1: 'LPR' | W1: 'CANT.X LOTE' | X1: 'CUSIP' | Y1: 'OBSERVACIONES' | Z1: 'RIESGO'
A2: 05203 | B2: LETRAS DEL TESORO 182D USD 17/07/2017 | C2: Letr | E2: Porc. | F2: 0 | G2: 0.00 | I2: 0 | J2: L2DL7 | K2: L2L7D | L2: L2L7C | N2: U$S | P2: 17/07/17 | Q2: ARARGE5203E7 | T2: 0 | U2: 0 | V2: 0 | W2: 0 | Y2: L2DL7 | Z2: Sin Calificar
A3: 05227 | B3: LETRAS DEL TESORO U$S VTO.09/02/2018 | C3: Letr | E3: Porc. | F3: 0 | G3: 0.00 | I3: 0 | J3: LTDF8 | K3: LTF8D | L3: LTF8C | N3: U$S | P3: 09/02/18 | Q3: ARARGE5204O4 | T3: 0 | U3: 0 | V3: 0 | W3: 0 | Z3: Sin Calificar
A4: 05228 | B4: LETRAS DEL TESORO U$S VTO.29/06/2018 | C4: Letr | E4: Porc. | F4: 0 | G4: 0.00 | I4: 0 | J4: L2DJ8 | K4: L2J8D | L4: L2J8C | N4: U$S | P4: 29/06/18 | Q4: ARARGE5204P1 | T4: 0 | U4: 0 | V4: 0 | W4: 0 | Z4: Sin Calificar
A5: 05229 | B5: LETRAS DEL TESORO U$S VTO.14/12/2018 | C5: Letr | E5: Porc. | F5: 0 | G5: 0.00 | I5: 0 | J5: LTDD8 | K5: LDD8D | L5: LDD8C | N5: U$S | P5: 14/12/18 | Q5: ARARGE5204Q9 | T5: 0 | U5: 0 | V5: 0 | W5: 0 | Z5: Sin Calificar
A6: 05230 | B6: LETRAS DEL TESORO U$S VTO.13/04/18 | C6: Letr | E6: Porc. | F6: 0 | G6: 0.00 | I6: 0 | J6: L4DA8 | K6: L4D8D | N6: U$S | P6: 13/04/18 | Q6: ARARGE5204S5 | T6: 0 | U6: 0 | V6: 0 | W6: 0 | Z6: Sin Calificar
A7: 53124 | B7: ON.BCO.PCIA.CORDOBA S2 V.18/12/20 | C7: O/N | E7: Porc. | F7: 0 | G7: 0.00 | H7: 100 | I7: 0 | J7: COS2O | Q7: ARBNCO560016 | T7: 0 | U7: 0 | V7: 0 | W7: 0 | Z7: Sin Calificar
A8: 80543 | B8: O.N. CRESUD CL.25 V.11/07/21 U$S CG | C8: O/N | E8: Porc. | F8: 0 | G8: 0.00 | I8: 0 | J8: CSFQO-US | K8: CSFQD | L8: CSFQC | Q8: ARCRES560080 | T8: 0 | U8: 0 | V8: 0 | W8: 0 | Z8: Sin Calificar
A9: 53018 | B9: CPFF CREDICUOTAS CONSUMO 4 $ CG | C9: Fdo. | E9: Porc. | F9: 0 | G9: 0.00 | H9: 100 | I9: 0 | J9: DR04Q | Q9: AREQUI490GX5 | T9: 0 | U9: 0 | V9: 0 | W9: 0 | Z9: Sin Calificar
A10: 31024 | B10: INV.JURAMENTO CLASE B DER.SUSCRIPCION | C10: Priv | E10: Normal | F10: 0 | G10: 0.00 | I10: 0 | J10: INVJX | Q10: ARINJU020043 | T10: 0 | U10: 0 | V10: 0 | W10: 0 | X10: 88031M109 | Z10: Sin Calificar
A11: 96712 | B11: HEPION PHARMACEUTICALS INC. | C11: Priv | E11: Normal | F11: 0 | G11: 0.00 | I11: 0 | J11: HEPA-US | N11: DOLAR | O11: Ext. | Q11: US4268973025 | T11: 0 | U11: 0 | V11: 0 | W11: 0 | X11: 426897302 | Z11: Sin Calificar
A12: 83133 | B12: US TREASURY BILL ZCP V.14/12/23 | C12: Publ | E12: Porc. | F12: 0 | G12: 0.00 | I12: 0 | J12: TB14122023 | N12: DOLAR | O12: Ext. | Q12: US912797FU69 | T12: 0 | U12: 0 | V12: 0 | W12: 0 | Z12: Sin Calificar
A13: 40786 | B13: BONOS C/DESCUENTO EUROS STEP UP V.2033 | C13: Publ | E13: Porc. | F13: 0 | G13: 0.00 | I13: 0 | J13: DICE | K13: DICED | L13: DICEC | Q13: XS0205545840 | T13: 0 | U13: 0 | V13: 0 | W13: 0 | Z13: Sin Calificar
A14: 91598 | B14: BONO PCIA BS AS 09-06-2021 9.95% | C14: Publ | E14: Porc. | F14: 0 | G14: 0.00 | H14: 100 | I14: 0 | J14: PBJ21 | K14: PB21D | L14: PB21C | N14: U$S | Q14: XS1244682487 | T14: 0 | U14: 0 | V14: 0 | W14: 0 | Z14: Sin Calificar
A15: 80554 | B15: NOTA SOCIETE GENERALE 1,253% V.06/07/21 | C15: Priv | E15: Porc. | F15: 0 | G15: 0.00 | I15: 0 | J15: NOSG | N15: U$S | O15: Ext. | Q15: XS1816490467 | T15: 0 | U15: 0 | V15: 0 | W15: 0 | Z15: Sin Calificar
A16: 82808 | B16: ON AGUA Y SANEA 7.9% V.01/05/26 U$S | C16: O/N | E16: Porc. | F16: 0 | G16: 1.00 | I16: 0 | J16: ONAYSA26 | N16: U$S | O16: Usd | Q16: XS2571927768 | T16: 0 | U16: 0 | V16: 0 | W16: 0 | Z16: Sin Calificar
A17: 00795 | B17: PATRICIOS | C17: Priv | D17: ORDS | E17: Normal | F17: 0 | G17: 0.00 | H17: 100 | I17: 0 | Q17: 594918104 | T17: 0 | U17: 0 | V17: 0 | W17: 0 | X17: 594918104 | Z17: Sin Calificar
A18: 06375 | B18: O.N. BANCO HIPOTECARIO | C18: O/N | D18: . | E18: Porc. | F18: 0 | G18: 0.00 | H18: 100 | I18: 0 | J18: OBHX1 | K18: PBHX1 | Q18: 594918104 | T18: 0 | U18: 0 | V18: 0 | W18: 0 | X18: 594918104 | Z18: Sin Calificar
A19: 06376 | B19: 06376 | C19: Priv | D19: . | E19: Normal | F19: 0 | G19: 0.00 | I19: 0 | Q19: 594918104 | T19: 0 | U19: 0 | V19: 0 | W19: 0 | X19: 594918104 | Z19: Sin Calificar
A20: 06383 | B20: 06383 | C20: Priv | D20: . | E20: Normal | F20: 0 | G20: 0.00 | I20: 0 | Q20: 594918104 | T20: 0 | U20: 0 | V20: 0 | W20: 0 | X20: 594918104 | Z20: Sin Calificar
A21: 00762 | B21: NOEL | C21: Priv | D21: ORDS | E21: Normal | F21: 0 | G21: 0.00 | I21: 0 | Q21: 68389X105 | T21: 0 | U21: 0 | V21: 0 | W21: 0 | X21: 68389X105 | Z21: Sin Calificar
A22: 47732 | B22: PROSHARES QQQ TRUST SERIES I | C22: Priv | E22: Normal | F22: 0 | G22: 0.00 | H22: 100 | I22: 0 | J22: QQQ-USA | N22: DOLAR | O22: Ext. | Q22: 73935A104 | T22: 0 | U22: 0 | V22: 0 | W22: 0 | Z22: Sin Calificar
A23: 07719 | B23: SAFE TECHNOLOGIES INTER. INC. | C23: Priv | E23: Normal | F23: 0 | G23: 0.00 | H23: 100 | I23: 0 | J23: SFAD | Q23: 786416107 | T23: 0 | U23: 0 | V23: 0 | W23: 0 | X23: 786416107 | Z23: Sin Calificar
A24: 48877 | B24: SAFE TECHNOLOGIES INC NEW | C24: Priv | E24: Normal | F24: 0 | G24: 0.00 | H24: 100 | I24: 0 | J24: SAFE-US | N24: U$S | O24: Ext. | Q24: 786416107 | T24: 0 | U24: 0 | V24: 0 | W24: 0 | X24: 786416107 | Z24: Sin Calificar
A25: 08570 | B25: CEDEAR ADIDAS AG | C25: Priv | E25: Normal | F25: 0 | G25: 0.00 | I25: 0 | J25: ADS | K25: ADSD | L25: ADSC | N25: DOLAR | Q25: ADSD | T25: 0 | U25: 0 | V25: 0 | W25: 0 | Z25: Sin Calificar
A26: 30015 | B26: BANCO PATAGONIA ACCS. CLASE B | C26: Priv | E26: Normal | F26: 0 | G26: 0.00 | H26: 100 | I26: 0 | J26: BPAT | M26: BPATB | Q26: AMERI013163 | T26: 0 | U26: 0 | V26: 0 | W26: 100 | Z26: Sin Calificar
A27: 57533 | B27: ON PYME CNV ZAFRA SER 1 CL. A V 29/12/25 | C27: O/N | E27: Normal | F27: 0 | G27: 0.00 | I27: 0 | Q27: AR000002607 | T27: 0 | U27: 0 | V27: 0 | W27: 0 | Z27: Moderado
A28: 08648 | B28: CEDEAR DANAHER CORP | C28: Priv | E28: Normal | F28: 0 | G28: 0.00 | I28: 0 | J28: DHR | Q28: AR0002457668 | T28: 0 | U28: 0 | V28: 0 | W28: 0 | X28: AR0002457668 | Z28: Sin Calificar
A29: 57658 | B29: ON MSU ENERGY CL.10 V12/03/26 U$S CG | C29: O/N | E29: Porc. | F29: 0 | G29: 0.00 | I29: 0 | J29: RUCA | K29: RUCAD | Q29: AR0006306242 | T29: 0 | U29: 0 | V29: 0 | W29: 0 | Z29: Sin Calificar
A30: 09260 | B30: LT REP ARGENTINA CAP $ V01/07/24 | C30: Letr | E30: Porc. | F30: 0 | G30: 0.00 | I30: 0 | J30: S01L4 | P30: 01/07/24 | Q30: AR0006731399 | T30: 0 | U30: 0 | V30: 0 | W30: 0 | Z30: Sin Calificar
A31: 58427 | B31: ON BANCO COMAFI CL.9 V30/07/25 U$S CG | C31: O/N | E31: Porc. | F31: 0 | G31: 0.00 | I31: 0 | J31: AFC9O | K31: AFC9D | N31: U$S | Q31: AR0014222183 | T31: 0 | U31: 0 | V31: 0 | W31: 0 | Y31: AFC9O | Z31: Sin Calificar
A32: 09266 | B32: LT REP ARGENTINA CAP V16/08/24 $ CG | C32: Letr | E32: Porc. | F32: 0 | G32: 0.00 | I32: 0 | J32: S16G4 | K32: S2G4D | P32: 16/08/24 | Q32: AR0015187120 | T32: 0 | U32: 0 | V32: 0 | W32: 0 | Y32: S16G4 | Z32: Sin Calificar
A33: 58123 | B33: ON CIA GEN.COMB. CL.36 V10/10/27 U$S CG | C33: O/N | E33: Porc. | F33: 0 | G33: 0.00 | I33: 0 | K33: CP36D | Q33: AR0015464982 | T33: 0 | U33: 0 | V33: 0 | W33: 0 | Z33: Sin Calificar
A34: 58245 | B34: ON YPF ENER.ELEC. C.19 V.22/11/26 U$S CG | C34: O/N | E34: Porc. | F34: 0 | G34: 1.00 | I34: 0 | J34: YFCKO | K34: YFCKO | L34: YFCKO | M34: YFCKO | N34: U$S | Q34: AR0015491712 | R34: YPF ENERGIA ELECTRICA S.A. | T34: 0 | U34: 0 | V34: 0 | W34: 0 | Y34: YFCKO | Z34: Sin Calificar
A35: 58624 | B35: ON ARCOR CL.26 V09/05/27 U$S CG | C35: O/N | E35: Porc. | F35: 0 | G35: 0.00 | I35: 0 | K35: RCCRD | Q35: AR0016944933 | T35: 0 | U35: 0 | V35: 0 | W35: 0 | Z35: Sin Calificar
A36: 09323 | B36: BONO NACION TASA DUAL15/12/26 $ CG | C36: Publ | E36: Porc. | F36: 0 | G36: 0.00 | I36: 0 | J36: TTD26 | Q36: AR0021930364 | T36: 0 | U36: 0 | V36: 0 | W36: 0 | Y36: TTD26 | Z36: Sin Calificar
A37: 57609 | B37: ON P CNV G DEMAGRO S1CB V28/02/26 U$S CG | C37: O/N | E37: Porc. | F37: 0 | G37: 0.00 | I37: 0 | J37: DM1BP | Q37: AR0031436766 | T37: 0 | U37: 0 | V37: 0 | W37: 0 | Z37: Sin Calificar
A38: 08661 | B38: CEDEAR ISHARES TRUST FTSE | C38: Priv | E38: Normal | F38: 0 | G38: 0.00 | I38: 0 | J38: FXI | Q38: AR0033445195 | T38: 0 | U38: 0 | V38: 0 | W38: 0 | Z38: Sin Calificar
A39: 58415 | B39: ON.PLUSPETROL S.A CLASE 1 | C39: O/N | E39: Porc. | F39: 0 | G39: 0.00 | I39: 0 | J39: PLC1O | K39: PLC1O | L39: PLC1O | N39: U$S | Q39: AR0036431960 | T39: 0 | U39: 0 | V39: 0 | W39: 0 | Y39: PLC1O | Z39: Sin Calificar
A40: 58416 | B40: ON.PLUSPETROL S.A CLASE 2 | C40: O/N | E40: Porc. | F40: 0 | G40: 0.00 | I40: 0 | J40: PLC2O | K40: PLC2D | L40: PLC2C | Q40: AR0036431960 | T40: 0 | U40: 0 | V40: 0 | W40: 0 | Y40: PLC2O | Z40: Sin Calificar
A41: 57484 | B41: ON TELECOM CL. 18 V17/11/27 UVA CG | C41: O/N | E41: Porc. | F41: 0 | G41: 0.00 | I41: 0 | J41: TLCJO | Q41: AR0041103448 | T41: 0 | U41: 0 | V41: 0 | W41: 0 | Z41: Sin Calificar
A42: 09281 | B42: LT REP ARGENTINA CAP V13/12/24 $ CG | C42: Letr | E42: Porc. | F42: 0 | G42: 0.00 | I42: 0 | J42: S13D4 | K42: S13DD | L42: S13DC | P42: 13/12/24 | Q42: AR0041901791 | T42: 0 | U42: 0 | V42: 0 | W42: 0 | Y42: S13D4 | Z42: Sin Calificar
A43: 09310 | B43: BONO TESORO NACIONAL V15/12/25 $ CG | C43: Publ | E43: Porc. | F43: 0 | G43: 0.00 | I43: 0 | J43: T15D5 | Q43: AR0057122373 | T43: 0 | U43: 0 | V43: 0 | W43: 0 | Y43: T15D5 | Z43: Sin Calificar
A44: 09311 | B44: BONO TESORO NACION AJ CER V30/5/25 $ CG | C44: Publ | E44: Porc. | F44: 0 | G44: 0.00 | I44: 0 | J44: TZXY5 | M44: TXY5X | Q44: AR0058584431 | T44: 0 | U44: 0 | V44: 0 | W44: 0 | Y44: TZXY5 | Z44: Sin Calificar
A45: 58186 | B45: ON PYME CNV CAIMAN S.2 C.A $ V.30/10/26 | C45: O/N | E45: Porc. | F45: 0 | G45: 0.00 | I45: 0 | N45: U$S | Q45: AR0066632412 | T45: 0 | U45: 0 | V45: 0 | W45: 0 | Z45: Sin Calificar
A46: 57858 | B46: ON RIZOBACTER 9 CL.B U$S V 28/06/26 CG | C46: O/N | E46: Porc. | F46: 0 | G46: 1.00 | I46: 0 | J46: RZ9BO | N46: U$S | Q46: AR0069851811 | T46: 0 | U46: 0 | V46: 0 | W46: 0 | Y46: RZ9BO | Z46: Sin Calificar
A47: 09318 | B47: BONCAP $ 2,15% 30/06/26 | C47: Publ | E47: Porc. | F47: 0 | G47: 0.00 | I47: 0 | J47: T30J6 | Q47: AR0071678673 | T47: 0 | U47: 0 | V47: 0 | W47: 0 | Y47: T30J6 | Z47: Sin Calificar
A48: 58649 | B48: ON CNH IND. CL.9 V.21/05/27 U$S C.G. | C48: O/N | E48: Porc. | F48: 0 | G48: 0.00 | I48: 0 | J48: CIC9O | Q48: AR0073116151 | T48: 0 | U48: 0 | V48: 0 | W48: 0 | Z48: Sin Calificar
A49: 58130 | B49: ON YPF CLASE 33 U$S VTO 10/10/28 C.G | C49: O/N | E49: Porc. | F49: 0 | G49: 0.00 | I49: 0 | J49: YMCZO | K49: YMCZD | L49: YMCZC | Q49: AR0079616063 | T49: 0 | U49: 0 | V49: 0 | W49: 0 | Y49: YMCZO | Z49: Sin Calificar
A50: 58426 | B50: ON LEDESMA CL.15 VTO.04/10/27 U$S CG | C50: O/N | E50: Porc. | F50: 0 | G50: 0.00 | I50: 0 | J50: LDCGO | Q50: AR007977559 | T50: 0 | U50: 0 | V50: 0 | W50: 0 | Y50: LDCGO | Z50: Sin Calificar
A51: 08658 | B51: CEDEAR ETF SPDR GOLD TRUST | C51: Priv | E51: Normal | F51: 0 | G51: 0.00 | I51: 0 | J51: GLD | K51: GLDD | L51: GLDC | Q51: AR0082060689 | T51: 0 | U51: 0 | V51: 0 | W51: 0 | Z51: Sin Calificar
A52: 58338 | B52: ON BANCO HIPOTECARIO CL.8 V20/12/25 $ CG | C52: O/N | E52: Porc. | F52: 0 | G52: 0.00 | I52: 0 | J52: HBC8O | Q52: AR0083266764 | T52: 0 | U52: 0 | V52: 0 | W52: 0 | Z52: Sin Calificar
A53: 58150 | B53: ON IRSA INVYREP C23 V23/10/29 | C53: O/N | E53: Porc. | F53: 0 | G53: 0.00 | I53: 0 | J53: IRCOO | K53: IRCOD | L53: IRCOC | M53: IRCOO | N53: U$S | Q53: AR0084572384 | T53: 0 | U53: 0 | V53: 0 | W53: 0 | Y53: IRCOO | Z53: Sin Calificar
A54: 30061 | B54: DISTRIBUIDORA GAS DEL CENTRO | C54: Priv | E54: Normal | F54: 0 | G54: 0.00 | I54: 0 | J54: DGCE | Q54: AR0097356114 | T54: 0 | U54: 0 | V54: 0 | W54: 0 | Z54: Sin Calificar
A55: 58230 | B55: ON PAN AMERICAN ENER 37 V13/11/28 U$S CG | C55: O/N | E55: Porc. | F55: 0 | G55: 0.00 | I55: 0 | J55: PN37O | K55: PN37D | L55: PN37C | M55: PN37O | Q55: AR0098578880 | T55: 0 | U55: 0 | V55: 0 | W55: 0 | Y55: PN37O | Z55: Sin Calificar
A56: 09251 | B56: LT REP ARGENTINA CAP $ V31/01/25 | C56: Letr | E56: Porc. | F56: 0 | G56: 0.00 | I56: 0 | J56: S31E5 | M56: SE5X | P56: 31/01/25 | Q56: AR0104841496 | T56: 0 | U56: 0 | V56: 0 | W56: 0 | X56: AR0104841496 | Y56: S31E5 | Z56: Sin Calificar
A57: 09305 | B57: LETRAS DEL TESORO CAP $ V31/07/25 | C57: Letr | E57: Porc. | F57: 0 | G57: 0.00 | I57: 0 | J57: S31L5 | M57: SL5X | P57: 31/07/25 | Q57: AR0112750168 | T57: 0 | U57: 0 | V57: 0 | W57: 0 | Y57: S31L5 | Z57: Sin Calificar
A58: 09239 | B58: LT REP ARG AJ CER A DESC V20/05/24 $ CG | C58: Letr | E58: Porc. | F58: 0 | G58: 0.00 | I58: 0 | J58: X20Y4 | P58: 20/05/24 | Q58: AR0125910452 | T58: 0 | U58: 0 | V58: 0 | W58: 0 | Y58: X20Y4 | Z58: Sin Calificar
A59: 57828 | B59: ON YPF ENER.ELEC. C.16 V.13/12/25 U$S CG | C59: O/N | E59: Porc. | F59: 0 | G59: 0.00 | I59: 0 | J59: YFCHO | Q59: AR0128636096 | T59: 0 | U59: 0 | V59: 0 | W59: 0 | Y59: YFCHO | Z59: Sin Calificar
A60: 57855 | B60: ON YPF CLASE 30 U$S VTO 01/07/26 C.G | C60: O/N | E60: Porc. | F60: 0 | G60: 0.00 | I60: 0 | J60: YMCWO | Q60: AR0132676112 | T60: 0 | U60: 0 | V60: 0 | W60: 0 | X60: AR0132676112 | Y60: YMCWO | Z60: Sin Calificar
A61: 08598 | B61: CEDEAR PALANTIR TECHNOLOGIES INC | C61: Priv | E61: Normal | F61: 0 | G61: 0.00 | I61: 0 | J61: PLTR | Q61: AR0132889822 | T61: 0 | U61: 0 | V61: 0 | W61: 0 | Y61: PLTR | Z61: Sin Calificar
A62: 09248 | B62: BONTES $ A DESC AJ CER V15/12/25 | C62: Publ | E62: Porc. | F62: 0 | G62: 0.00 | I62: 0 | J62: TZXD5 | Q62: AR0137939010 | T62: 0 | U62: 0 | V62: 0 | W62: 0 | X62: AR0137939010 | Y62: TZXD5 | Z62: Sin Calificar
A63: 58133 | B63: ON VISTA ENERGY CL.26 V10/10/31 U$S CG | C63: O/N | E63: Porc. | F63: 0 | G63: 0.00 | I63: 0 | J63: VSCRO | K63: VSCRD | L63: VSCRC | N63: DOLAR | Q63: AR0138120560 | T63: 0 | U63: 0 | V63: 0 | W63: 0 | Z63: Sin Calificar
A64: 57646 | B64: ON EDENOR CL.3 V.22/11/26 U$S CG | C64: O/N | E64: Porc. | F64: 0 | G64: 0.00 | I64: 0 | J64: DNC3O | K64: DNC3D | L64: DNC3C | N64: U$S | Q64: AR0140482933 | T64: 0 | U64: 0 | V64: 0 | W64: 0 | Z64: Sin Calificar
A65: 57575 | B65: ON ALBANESI ENERGIA 12 V14/02/26 U$S CG | C65: O/N | E65: Porc. | F65: 0 | G65: 0.00 | I65: 0 | J65: LECDO | Q65: AR0142866786 | T65: 0 | U65: 0 | V65: 0 | W65: 0 | Y65: LECDO | Z65: Sin Calificar
A66: 09306 | B66: LETRAS DEL TESORO CAP $ V30/09/25 | C66: Letr | E66: Porc. | F66: 0 | G66: 0.00 | I66: 0 | J66: S30S5 | P66: 30/09/25 | Q66: AR0145235914 | T66: 0 | U66: 0 | V66: 0 | W66: 0 | Y66: S30S5 | Z66: Sin Calificar
A67: 58535 | B67: ON BANCO INDUSTRIAL CL.1 V.08/09/25 U$S | C67: O/N | E67: Porc. | F67: 0 | G67: 0.00 | I67: 0 | J67: IBC1O | K67: IBC1O | N67: U$S | Q67: AR0146793887 | T67: 0 | U67: 0 | V67: 0 | W67: 0 | Y67: IBC1O | Z67: Sin Calificar
A68: 58361 | B68: ON AEROP ARG 2000 11 V15/12/26 U$S CG | C68: O/N | E68: Porc. | F68: 0 | G68: 0.00 | I68: 0 | J68: AERBO | N68: U$S | Q68: AR0162186347 | T68: 0 | U68: 0 | V68: 0 | W68: 0 | Z68: Sin Calificar
A69: 58525 | B69: ON CIA GEN.COMB. CL.37 V10/03/27 U$S CG | C69: O/N | E69: Porc. | F69: 0 | G69: 0.00 | I69: 0 | J69: CP37 | K69: CP37D | N69: U$S | Q69: AR0172788611 | T69: 0 | U69: 0 | V69: 0 | W69: 0 | X69: AR0172788611 | Z69: Sin Calificar
A70: 57220 | B70: ON PYME PRODUSEM S2 CL2 U$S V30/04/26 CG | C70: O/N | E70: Porc. | F70: 0 | G70: 0.00 | I70: 0 | J70: DF31P | K70: DF31D | L70: DF31C | Q70: AR0178833023 | T70: 0 | U70: 0 | V70: 0 | W70: 0 | Z70: Sin Calificar
A71: 57720 | B71: ON PYME PRODUSEM S2 CL2 U$S V30/04/26 CG | C71: O/N | E71: Porc. | F71: 0 | G71: 0.00 | I71: 0 | J71: PO22P | Q71: AR0178833023 | T71: 0 | U71: 0 | V71: 0 | W71: 0 | X71: AR0178833023 | Y71: PO22P | Z71: Sin Calificar
A72: 57437 | B72: ON ALUAR S.7 V12/10/28 U$S CG | C72: O/N | E72: Porc. | F72: 0 | G72: 0.00 | I72: 0 | J72: LMS7O | K72: LMS7D | L72: LMS7C | M72: LMS7O | N72: U$S | Q72: AR0183513875 | T72: 0 | U72: 0 | V72: 0 | W72: 0 | Y72: LMS7O | Z72: Sin Calificar
A73: 83364 | B73: ON ALUAR S.7 V12/10/28 U$S CG | C73: O/N | E73: Porc. | F73: 0 | G73: 1.00 | I73: 0 | J73: 83364 | N73: DOLAR | Q73: AR0183513875 | T73: 0 | U73: 0 | V73: 0 | W73: 0 | Z73: Sin Calificar
A74: 58340 | B74: ON BANCO COMAFI CL.7 V19/03/25 U$S CG | C74: O/N | E74: Porc. | F74: 0 | G74: 0.00 | I74: 0 | J74: AFC7A | K74: AFC7D | Q74: AR0184512785 | T74: 0 | U74: 0 | V74: 0 | W74: 0 | Y74: AFC7A | Z74: Sin Calificar
A75: 57597 | B75: ON IRSA INVER Y REP C19 V28/02/25 $ CG | C75: O/N | E75: Porc. | F75: 0 | G75: 0.00 | H75: 100 | I75: 0 | J75: IRCKO | Q75: AR0185328686 | T75: 0 | U75: 0 | V75: 0 | W75: 0 | X75: AR0185328686 | Z75: Sin Calificar
A76: 09297 | B76: LETRAS DEL TESORO CAP $ 14/02/25 | C76: Letr | E76: Porc. | F76: 0 | G76: 0.00 | I76: 0 | J76: S14F5 | M76: S2F5X | P76: 14/02/25 | Q76: AR0188958448 | T76: 0 | U76: 0 | V76: 0 | W76: 0 | Y76: S14F5 | Z76: Sin Calificar
A77: 83981 | B77: LETRAS DEL TESORO CAP $ 14/02/25 | C77: Publ | E77: Porc. | F77: 0 | G77: 0.00 | I77: 0 | N77: DOLAR | Q77: AR0188958448 | T77: 0 | U77: 0 | V77: 0 | W77: 0 | X77: AR0188958448 | Z77: Sin Calificar
A78: 57803 | B78: ON IRSA CL.20 6% U$S VTO.10/06/26 CG | C78: O/N | E78: Porc. | F78: 0 | G78: 0.00 | I78: 0 | J78: IRCLO | K78: IRCLD | L78: IRCLC | N78: U$S | Q78: AR0200915251 | T78: 0 | U78: 0 | V78: 0 | W78: 0 | Y78: IRCLO | Z78: Sin Calificar
A79: 57774 | B79: ON YPF CLASE 29 U$S VT28/05/26 C.G | C79: O/N | E79: Porc. | F79: 0 | G79: 0.00 | I79: 0 | J79: YMCVO | K79: YMCVD | L79: YMCVC | M79: YMCVO | N79: U$S | Q79: AR0202080054 | T79: 0 | U79: 0 | V79: 0 | W79: 0 | Y79: YMCVO | Z79: Sin Calificar
A80: 57439 | B80: ON GEN MEDIT Y ROCA CL XXV | C80: O/N | E80: Porc. | F80: 0 | G80: 0.00 | I80: 0 | J80: MRCQO | K80: MRCQD | L80: MRCQC | N80: U$S | Q80: AR0203590796 | T80: 0 | U80: 0 | V80: 0 | W80: 0 | Z80: Sin Calificar
A81: 58119 | B81: VD FF CLUB RIVER PLATE UVA CG | C81: Fide | E81: Porc. | F81: 0 | G81: 0.00 | I81: 0 | J81: CARP | Q81: AR0206289149 | T81: 0 | U81: 0 | V81: 0 | W81: 0 | Z81: Sin Calificar
A82: 57838 | B82: ON CREDICUOTAS CONSUMO 8 V12/06/25 $ CG | C82: O/N | E82: Porc. | F82: 0 | G82: 0.00 | H82: 100 | I82: 0 | J82: DNS8O | Q82: AR0212698713 | T82: 0 | U82: 0 | V82: 0 | W82: 0 | Z82: Sin Calificar
A83: 57817 | B83: ON ALUAR S.9 V13/06/26 U$S CG | C83: O/N | E83: Porc. | F83: 0 | G83: 0.00 | I83: 0 | J83: LMS9O | K83: LMS9D | L83: LMS9C | N83: U$S | Q83: AR0226237573 | T83: 0 | U83: 0 | V83: 0 | W83: 0 | Y83: LMS9O | Z83: Sin Calificar
A84: 08644 | B84: CEDEAR FERRARI NV | C84: Priv | E84: Normal | F84: 0 | G84: 1.00 | I84: 0 | J84: RACE | K84: RACED | L84: RACEC | Q84: AR0227017768 | T84: 0 | U84: 0 | V84: 0 | W84: 0 | Z84: Sin Calificar
A85: 09321 | B85: BONO NACION TASA DUAL15/09/26 $ CG | C85: Publ | E85: Porc. | F85: 0 | G85: 0.00 | I85: 0 | J85: TTS26 | Q85: AR0227219554 | T85: 0 | U85: 0 | V85: 0 | W85: 0 | Y85: TTS26 | Z85: Sin Calificar
A86: 58435 | B86: ON SAN MIGUEL S.12 V06/02/27 U$S CG | C86: O/N | E86: Porc. | F86: 0 | G86: 0.00 | I86: 0 | J86: SNSDO | N86: U$S | Q86: AR0228143829 | T86: 0 | U86: 0 | V86: 0 | W86: 0 | Z86: Sin Calificar
A87: 58256 | B87: ON TELECOM CL.23 28/11/28 U$S CG | C87: O/N | E87: Porc. | F87: 0 | G87: 0.00 | I87: 0 | J87: TLCOO | N87: U$S | Q87: AR0241562484 | T87: 0 | U87: 0 | V87: 0 | W87: 0 | Z87: Sin Calificar
A88: 58483 | B88: ON 360 ENER.SOL. CL.5 V05/09/27 U$S C.G. | C88: O/N | E88: Porc. | F88: 0 | G88: 0.00 | I88: 0 | J88: GYC5O | Q88: AR0253143579 | T88: 0 | U88: 0 | V88: 0 | W88: 0 | Y88: GYC5O | Z88: Sin Calificar
A89: 09293 | B89: LT REP ARGENTINA CAP V11/11/24 $ CG | C89: Letr | E89: Porc. | F89: 0 | G89: 0.00 | I89: 0 | J89: S11N4 | P89: 11/11/24 | Q89: AR0254563239 | T89: 0 | U89: 0 | V89: 0 | W89: 0 | Y89: S11N4 | Z89: Sin Calificar
A90: 65126 | B90: LT REP ARGENTINA CAP V11/11/24 $ CG | C90: Letr | E90: Porc. | F90: 0 | G90: 0.00 | I90: 0 | J90: S11N4 | P90: 11/11/24 | Q90: AR0254563239 | T90: 0 | U90: 0 | V90: 0 | W90: 0 | Z90: Sin Calificar
A91: 08591 | B91: CEDEAR BRASKEM SA | C91: Priv | E91: Normal | F91: 0 | G91: 0.00 | I91: 0 | J91: BAK | Q91: AR0261973801 | T91: 0 | U91: 0 | V91: 0 | W91: 0 | Z91: Sin Calificar
A92: 58557 | B92: ON CREDICUO CONS 12 CL.1 V29/04/26 $ CG | C92: O/N | E92: Porc. | F92: 0 | G92: 0.00 | I92: 0 | J92: ONCC0426 | Q92: AR0268994289 | T92: 0 | U92: 0 | V92: 0 | W92: 0 | Z92: Sin Calificar
A93: 58260 | B93: ON RIZOBACTER S.10 CL.B V28/11/27 U$S CG | C93: O/N | E93: Porc. | F93: 0 | G93: 0.00 | I93: 0 | J93: RZABO | N93: U$S | Q93: AR0272566107 | T93: 0 | U93: 0 | V93: 0 | W93: 0 | Z93: Sin Calificar
A94: 58149 | B94: ON IRSA C22 V23/10/27 | C94: O/N | E94: Porc. | F94: 0 | G94: 0.00 | I94: 0 | J94: IRCNO | Q94: AR0275431465 | T94: 0 | U94: 0 | V94: 0 | W94: 0 | Y94: IRCNO | Z94: Sin Calificar
A95: 09225 | B95: BONOS TESORO CER+4,25 23/05/25 | C95: Publ | E95: Porc. | F95: 0 | G95: 0.00 | I95: 0 | J95: T4X5 | K95: T4X5D | L95: T4X5C | M95: T4X5X | Q95: AR0281825940 | T95: 0 | U95: 0 | V95: 0 | W95: 0 | Y95: T4X5 | Z95: Sin Calificar
A96: 58470 | B96: ON BCO BBVA ARG CL.33 V.27/08/25 U$S CG | C96: O/N | E96: Porc. | F96: 0 | G96: 0.00 | I96: 0 | K96: BFCZD | Q96: AR0283170097 | T96: 0 | U96: 0 | V96: 0 | W96: 0 | Z96: Sin Calificar
A97: 57423 | B97: ON PETRO. ACONCAGUA 17 V30/01/28 U$S CG | C97: O/N | E97: Porc. | F97: 0 | G97: 0.00 | I97: 0 | J97: PECIO | K97: PECIO | N97: U$S | Q97: AR0288436246 | T97: 0 | U97: 0 | V97: 0 | W97: 0 | X97: AR0288436246 | Y97: PECIO | Z97: Sin Calificar
A98: 57723 | B98: ON CAPEX CL.8 U$S V.29/06/26 C.G. | C98: O/N | E98: Porc. | F98: 0 | G98: 0.00 | I98: 0 | J98: CAC8O | K98: CAC8D | L98: CAC8C | N98: U$S | Q98: AR0292006183 | T98: 0 | U98: 0 | V98: 0 | W98: 0 | X98: AR0292006183 | Z98: Sin Calificar
A99: 09327 | B99: LT REP ARG VINC. AL U$S 16/01/26 CG | C99: Letr | E99: Porc. | F99: 0 | G99: 0.00 | I99: 0 | J99: D16E6 | P99: 16/01/26 | Q99: AR0306034593 | T99: 0 | U99: 0 | V99: 0 | W99: 0 | Z99: Sin Calificar
A100: 09295 | B100: LT REP ARGENTINA CAP V30/06/25 $ CG | C100: Letr | E100: Porc. | F100: 0 | G100: 0.00 | I100: 0 | J100: S30J5 | P100: 30/06/25 | Q100: AR0308405304 | T100: 0 | U100: 0 | V100: 0 | W100: 0 | Y100: S30J5 | Z100: Sin Calificar
...

Sheet Cotizacion Dolar Historica
A1: Fecha | B1: Referencia | C1: Moneda
A2: 46021 | B2: 1480.74 | C2: Dolar MEP (local)
A3: 46020 | B3: 1484.35 | C3: Dolar MEP (local)
A4: 46017 | B4: 1486.11 | C4: Dolar MEP (local)
A5: 46016 | B5: 1481.63 | C5: Dolar MEP (local)
A6: 46015 | B6: 1481.63 | C6: Dolar MEP (local)
A7: 46014 | B7: 1479.44 | C7: Dolar MEP (local)
A8: 46013 | B8: 1493.06 | C8: Dolar MEP (local)
A9: 46010 | B9: 1494.62 | C9: Dolar MEP (local)
A10: 46009 | B10: 1498.58 | C10: Dolar MEP (local)
A11: 46008 | B11: 1514.14 | C11: Dolar MEP (local)
A12: 46007 | B12: 1504.3 | C12: Dolar MEP (local)
A13: 46006 | B13: 1492.01 | C13: Dolar MEP (local)
... A3490: 43853 | B3490: 81.64 | C3490: Dolar Cable (exterior)

Sheet PreciosInicialesEspecies
A1: 'ESPECIE' | B1: 'NOMBRE' | C1: 'ORDEN' | D1: 'FEC.ANT.' | E1: 'PCIO.' | F1: 'FECHA' | G1: 'PRECIO' | H1: Tipo Instrumento | I1: Precio Nominal | J1: Precio Nominal USD
A2: 7 | B2: ALUA ALUAR | C2: ALUA | D2: 45656 | E2: 892 | F2: 45659 | G2: 893 | H2: =IF(ISERROR(VLOOKUP(A2,EspeciesVisual!C:R,16,FALSE)),"",VLOOKUP(A2,EspeciesVisual!C:R,16,FALSE)) | I2: =IF(OR(ISNUMBER(SEARCH("obligacion",LOWER(H2))),ISNUMBER(SEARCH("titulo",LOWER(H2))),ISNUMBER(SEARCH("letra",LOWER(H2)))),G2/100,G2) | J2: =I2/1167.806
A3: 19 | B3: AGRO AGROMETAL | C3: AGRO | D3: 45656 | E3: 72.1 | F3: 45659 | G3: 74.3 | H3: =IF(ISERROR(VLOOKUP(A3,EspeciesVisual!C:R,16,FALSE)),"",VLOOKUP(A3,EspeciesVisual!C:R,16,FALSE)) | I3: =IF(OR(ISNUMBER(SEARCH("obligacion",LOWER(H3))),ISNUMBER(SEARCH("titulo",LOWER(H3))),ISNUMBER(SEARCH("letra",LOWER(H3)))),G3/100,G3) | J3: =I3/1167.806
A4: 49 | B4: OEST GRUPO CONCESIONARIO DEL O | C4: OEST | D4: 45656 | E4: 1145 | F4: 45659 | G4: 1130 | H4: =IF(ISERROR(VLOOKUP(A4,EspeciesVisual!C:R,16,FALSE)),"",VLOOKUP(A4,EspeciesVisual!C:R,16,FALSE)) | I4: =IF(OR(ISNUMBER(SEARCH("obligacion",LOWER(H4))),ISNUMBER(SEARCH("titulo",LOWER(H4))),ISNUMBER(SEARCH("letra",LOWER(H4)))),G4/100,G4) | J4: =I4/1167.806
A5: 59 | B5: ARSA ASTARSA | C5: ARSA | E5: 0 | F5: 42762 | G5: 1 | H5: =IF(ISERROR(VLOOKUP(A5,EspeciesVisual!C:R,16,FALSE)),"",VLOOKUP(A5,EspeciesVisual!C:R,16,FALSE)) | I5: =IF(OR(ISNUMBER(SEARCH("obligacion",LOWER(H5))),ISNUMBER(SEARCH("titulo",LOWER(H5))),ISNUMBER(SEARCH("letra",LOWER(H5)))),G5/100,G5) | J5: =I5/1167.806
A6: 66 | B6: AUTOPISTAS DEL SOL | C6: AUSO | D6: 45656 | E6: 3835 | F6: 45659 | G6: 3895 | H6: =IF(ISERROR(VLOOKUP(A6,EspeciesVisual!C:R,16,FALSE)),"",VLOOKUP(A6,EspeciesVisual!C:R,16,FALSE)) | I6: =IF(OR(ISNUMBER(SEARCH("obligacion",LOWER(H6))),ISNUMBER(SEARCH("titulo",LOWER(H6))),ISNUMBER(SEARCH("letra",LOWER(H6)))),G6/100,G6) | J6: =I6/1167.806
A7: 67 | B7: GBAN GAS NATURAL BAN | C7: GBAN | D7: 45656 | E7: 2150 | F7: 45659 | G7: 2200 | H7: =IF(ISERROR(VLOOKUP(A7,EspeciesVisual!C:R,16,FALSE)),"",VLOOKUP(A7,EspeciesVisual!C:R,16,FALSE)) | I7: =IF(OR(ISNUMBER(SEARCH("obligacion",LOWER(H7))),ISNUMBER(SEARCH("titulo",LOWER(H7))),ISNUMBER(SEARCH("letra",LOWER(H7)))),G7/100,G7) | J7: =I7/1167.806
A8: 71 | B8: AZUC AZUCARERA ARGENTINA | C8: AZUC | E8: 0 | F8: 42762 | G8: 1 | H8: =IF(ISERROR(VLOOKUP(A8,EspeciesVisual!C:R,16,FALSE)),"",VLOOKUP(A8,EspeciesVisual!C:R,16,FALSE)) | I8: =IF(OR(ISNUMBER(SEARCH("obligacion",LOWER(H8))),ISNUMBER(SEARCH("titulo",LOWER(H8))),ISNUMBER(SEARCH("letra",LOWER(H8)))),G8/100,G8) | J8: =I8/1167.806
A9: 94 | B9: FRAN BANCO FRANCES | C9: BBAR | D9: 45656 | E9: 7560 | F9: 45659 | G9: 8570 | H9: =IF(ISERROR(VLOOKUP(A9,EspeciesVisual!C:R,16,FALSE)),"",VLOOKUP(A9,EspeciesVisual!C:R,16,FALSE)) | I9: =IF(OR(ISNUMBER(SEARCH("obligacion",LOWER(H9))),ISNUMBER(SEARCH("titulo",LOWER(H9))),ISNUMBER(SEARCH("letra",LOWER(H9)))),G9/100,G9) | J9: =I9/1167.806
A10: 111 | B10: BANCO MACRO S.A. | C10: BMA | D10: 45656 | E10: 11450 | F10: 45659 | G10: 12850 | H10: =IF(ISERROR(VLOOKUP(A10,EspeciesVisual!C:R,16,FALSE)),"",VLOOKUP(A10,EspeciesVisual!C:R,16,FALSE)) | I10: =IF(OR(ISNUMBER(SEARCH("obligacion",LOWER(H10))),ISNUMBER(SEARCH("titulo",LOWER(H10))),ISNUMBER(SEARCH("letra",LOWER(H10)))),G10/100,G10) | J10: =I10/1167.806
A11: 169 | B11: CGPA2 CAMUZZI GAS PAMPEANA | C11: CGPA2 | D11: 45656 | E11: 3880 | F11: 45659 | G11: 3775 | H11: =IF(ISERROR(VLOOKUP(A11,EspeciesVisual!C:R,16,FALSE)),"",VLOOKUP(A11,EspeciesVisual!C:R,16,FALSE)) | I11: =IF(OR(ISNUMBER(SEARCH("obligacion",LOWER(H11))),ISNUMBER(SEARCH("titulo",LOWER(H11))),ISNUMBER(SEARCH("letra",LOWER(H11)))),G11/100,G11) | J11: =I11/1167.806
A12: 204 | B12: CADO CARLOS CASADO | C12: CADO | D12: 45656 | E12: 506 | F12: 45659 | G12: 511 | H12: =IF(ISERROR(VLOOKUP(A12,EspeciesVisual!C:R,16,FALSE)),"",VLOOKUP(A12,EspeciesVisual!C:R,16,FALSE)) | I12: =IF(OR(ISNUMBER(SEARCH("obligacion",LOWER(H12))),ISNUMBER(SEARCH("titulo",LOWER(H12))),ISNUMBER(SEARCH("letra",LOWER(H12)))),G12/100,G12) | J12: =I12/1167.806
A13: 223 | B13: CELU CELULOSA ARGENTINA | C13: CELU | D13: 45656 | E13: 932 | F13: 45659 | G13: 910 | H13: =IF(ISERROR(VLOOKUP(A13,EspeciesVisual!C:R,16,FALSE)),"",VLOOKUP(A13,EspeciesVisual!C:R,16,FALSE)) | I13: =IF(OR(ISNUMBER(SEARCH("obligacion",LOWER(H13))),ISNUMBER(SEARCH("titulo",LOWER(H13))),ISNUMBER(SEARCH("letra",LOWER(H13)))),G13/100,G13) | J13: =I13/1167.806
A14: 247 | B14: COLORIN S.A. (COLO) | C14: COLO | D14: 43656 | E14: 12.5 | F14: 43661 | G14: 12.55 | H14: =IF(ISERROR(VLOOKUP(A14,EspeciesVisual!C:R,16,FALSE)),"",VLOOKUP(A14,EspeciesVisual!C:R,16,FALSE)) | I14: =IF(OR(ISNUMBER(SEARCH("obligacion",LOWER(H14))),ISNUMBER(SEARCH("titulo",LOWER(H14))),ISNUMBER(SEARCH("letra",LOWER(H14)))),G14/100,G14) | J14: =I14/1167.806
A15: 251 | B15: COME COMERCIAL DEL PLATA | C15: COME | D15: 45656 | E15: 248.5 | F15: 45659 | G15: 260.5 | H15: =IF(ISERROR(VLOOKUP(A15,EspeciesVisual!C:R,16,FALSE)),"",VLOOKUP(A15,EspeciesVisual!C:R,16,FALSE)) | I15: =IF(OR(ISNUMBER(SEARCH("obligacion",LOWER(H15))),ISNUMBER(SEARCH("titulo",LOWER(H15))),ISNUMBER(SEARCH("letra",LOWER(H15)))),G15/100,G15) | J15: =I15/1167.806
A16: 274 | B16: CRES CRESUD | C16: CRES | D16: 45656 | E16: 1495 | F16: 45659 | G16: 1560 | H16: =IF(ISERROR(VLOOKUP(A16,EspeciesVisual!C:R,16,FALSE)),"",VLOOKUP(A16,EspeciesVisual!C:R,16,FALSE)) | I16: =IF(OR(ISNUMBER(SEARCH("obligacion",LOWER(H16))),ISNUMBER(SEARCH("titulo",LOWER(H16))),ISNUMBER(SEARCH("letra",LOWER(H16)))),G16/100,G16) | J16: =I16/1167.806
A17: 283 | B17: RIGO CRIST. RIGOLLEAU | C17: RIGO | D17: 45656 | E17: 1040 | F17: 45659 | G17: 1035 | H17: =IF(ISERROR(VLOOKUP(A17,EspeciesVisual!C:R,16,FALSE)),"",VLOOKUP(A17,EspeciesVisual!C:R,16,FALSE)) | I17: =IF(OR(ISNUMBER(SEARCH("obligacion",LOWER(H17))),ISNUMBER(SEARCH("titulo",LOWER(H17))),ISNUMBER(SEARCH("letra",LOWER(H17)))),G17/100,G17) | J17: =I17/1167.806
A18: 307 | B18: DGCU2 DISTRIB. GAS CUYANA | C18: DGCU2 | D18: 45656 | E18: 1890 | F18: 45659 | G18: 1925 | H18: =IF(ISERROR(VLOOKUP(A18,EspeciesVisual!C:R,16,FALSE)),"",VLOOKUP(A18,EspeciesVisual!C:R,16,FALSE)) | I18: =IF(OR(ISNUMBER(SEARCH("obligacion",LOWER(H18))),ISNUMBER(SEARCH("titulo",LOWER(H18))),ISNUMBER(SEARCH("letra",LOWER(H18)))),G18/100,G18) | J18: =I18/1167.806
A19: 322 | B19: CEPU2 CENTRAL PUERTO | C19: CEPU | D19: 45656 | E19: 1770 | F19: 45659 | G19: 1820 | H19: =IF(ISERROR(VLOOKUP(A19,EspeciesVisual!C:R,16,FALSE)),"",VLOOKUP(A19,EspeciesVisual!C:R,16,FALSE)) | I19: =IF(OR(ISNUMBER(SEARCH("obligacion",LOWER(H19))),ISNUMBER(SEARCH("titulo",LOWER(H19))),ISNUMBER(SEARCH("letra",LOWER(H19)))),G19/100,G19) | J19: =I19/1167.806
A20: 336 | B20: DOME DOMEC S.A. | C20: DOME | D20: 45653 | E20: 70.5 | F20: 45659 | G20: 61 | H20: =IF(ISERROR(VLOOKUP(A20,EspeciesVisual!C:R,16,FALSE)),"",VLOOKUP(A20,EspeciesVisual!C:R,16,FALSE)) | I20: =IF(OR(ISNUMBER(SEARCH("obligacion",LOWER(H20))),ISNUMBER(SEARCH("titulo",LOWER(H20))),ISNUMBER(SEARCH("letra",LOWER(H20)))),G20/100,G20) | J20: =I20/1167.806
... A38: 666 | B38: LONG LONGVIE | C38: LONG | D38: 45656 | E38: 36.35 | F38: 45659 | G38: 35.95 | H38: =IF(ISERROR(VLOOKUP(A38,EspeciesVisual!C:R,16,FALSE)),"",VLOOKUP(A38,EspeciesVisual!C:R,16,FALSE)) | I38: =IF(OR(ISNUMBER(SEARCH("obligacion",LOWER(H38))),ISNUMBER(SEARCH("titulo",LOWER(H38))),ISNUMBER(SEARCH("letra",LOWER(H38)))),G38/100,G38) | J38: =I38/1167.806
A39: 706 | B39: PICA NOBLEZA PICCARDO | C39: PICA | E39: 0 | F39: 42762 | G39: 1 | H39: =IF(ISERROR(VLOOKUP(A39,EspeciesVisual!C:R,16,FALSE)),"",VLOOKUP(A39,EspeciesVisual!C:R,16,FALSE)) | I39: =IF(OR(ISNUMBER(SEARCH("obligacion",LOWER(H39))),ISNUMBER(SEARCH("titulo",LOWER(H39))),ISNUMBER(SEARCH("letra",LOWER(H39)))),G39/100,G39) | J39: =I39/1167.806
A40: 710 | B40: YPFD YPF S.A. ESCRITURALES | C40: YPFD | D40: 45656 | E40: 50300 | F40: 45659 | G40: 52400 | H40: =IF(ISERROR(VLOOKUP(A40,EspeciesVisual!C:R,16,FALSE)),"",VLOOKUP(A40,EspeciesVisual!C:R,16,FALSE)) | I40: =IF(OR(ISNUMBER(SEARCH("obligacion",LOWER(H40))),ISNUMBER(SEARCH("titulo",LOWER(H40))),ISNUMBER(SEARCH("letra",LOWER(H40)))),G40/100,G40) | J40: =I40/1167.806
A41: 733 | B41: HARG HOLCIM ARGENTINA SA | C41: HARG | D41: 45656 | E41: 2170 | F41: 45659 | G41: 2230 | H41: =IF(ISERROR(VLOOKUP(A41,EspeciesVisual!C:R,16,FALSE)),"",VLOOKUP(A41,EspeciesVisual!C:R,16,FALSE)) | I41: =IF(OR(ISNUMBER(SEARCH("obligacion",LOWER(H41))),ISNUMBER(SEARCH("titulo",LOWER(H41))),ISNUMBER(SEARCH("letra",LOWER(H41)))),G41/100,G41) | J41: =I41/1167.806
A42: 740 | B42: SEMI MOLINOS J. SEMINO | C42: SEMI | D42: 45656 | E42: 41.25 | F42: 45659 | G42: 41.15 | H42: =IF(ISERROR(VLOOKUP(A42,EspeciesVisual!C:R,16,FALSE)),"",VLOOKUP(A42,EspeciesVisual!C:R,16,FALSE)) | I42: =IF(OR(ISNUMBER(SEARCH("obligacion",LOWER(H42))),ISNUMBER(SEARCH("titulo",LOWER(H42))),ISNUMBER(SEARCH("letra",LOWER(H42)))),G42/100,G42) | J42: =I42/1167.806
A43: 741 | B43: MOLINOS RIO | C43: MOLI5 | D43: 45652 | E43: 4575 | F43: 45659 | G43: 4800 | H43: =IF(ISERROR(VLOOKUP(A43,EspeciesVisual!C:R,16,FALSE)),"",VLOOKUP(A43,EspeciesVisual!C:R,16,FALSE)) | I43: =IF(OR(ISNUMBER(SEARCH("obligacion",LOWER(H43))),ISNUMBER(SEARCH("titulo",LOWER(H43))),ISNUMBER(SEARCH("letra",LOWER(H43)))),G43/100,G43) | J43: =I43/1167.806
A44: 742 | B44: MOLI MOLINOS RIO DE LA PLATA | C44: MOLI | D44: 45656 | E44: 5210 | F44: 45659 | G44: 5280 | H44: =IF(ISERROR(VLOOKUP(A44,EspeciesVisual!C:R,16,FALSE)),"",VLOOKUP(A44,EspeciesVisual!C:R,16,FALSE)) | I44: =IF(OR(ISNUMBER(SEARCH("obligacion",LOWER(H44))),ISNUMBER(SEARCH("titulo",LOWER(H44))),ISNUMBER(SEARCH("letra",LOWER(H44)))),G44/100,G44) | J44: =I44/1167.806
A45: 748 | B45: MORI MORIXE HNOS | C45: MORI | D45: 45656 | E45: 377.5 | F45: 45659 | G45: 384.5 | H45: =IF(ISERROR(VLOOKUP(A45,EspeciesVisual!C:R,16,FALSE)),"",VLOOKUP(A45,EspeciesVisual!C:R,16,FALSE)) | I45: =IF(OR(ISNUMBER(SEARCH("obligacion",LOWER(H45))),ISNUMBER(SEARCH("titulo",LOWER(H45))),ISNUMBER(SEARCH("letra",LOWER(H45)))),G45/100,G45) | J45: =I45/1167.806
A46: 751 | B46: BHIP BANCO HIPOTECARIO | C46: BHIP | D46: 45656 | E46: 571 | F46: 45659 | G46: 602 | H46: =IF(ISERROR(VLOOKUP(A46,EspeciesVisual!C:R,16,FALSE)),"",VLOOKUP(A46,EspeciesVisual!C:R,16,FALSE)) | I46: =IF(OR(ISNUMBER(SEARCH("obligacion",LOWER(H46))),ISNUMBER(SEARCH("titulo",LOWER(H46))),ISNUMBER(SEARCH("letra",LOWER(H46)))),G46/100,G46) | J46: =I46/1167.806
A47: 798 | B47: MIRG MIRGOR | C47: MIRG | D47: 45656 | E47: 26075 | F47: 45659 | G47: 26575 | H47: =IF(ISERROR(VLOOKUP(A47,EspeciesVisual!C:R,16,FALSE)),"",VLOOKUP(A47,EspeciesVisual!C:R,16,FALSE)) | I47: =IF(OR(ISNUMBER(SEARCH("obligacion",LOWER(H47))),ISNUMBER(SEARCH("titulo",LOWER(H47))),ISNUMBER(SEARCH("letra",LOWER(H47)))),G47/100,G47) | J47: =I47/1167.806
A48: 807 | B48: TELECOM ARGENTINA ESCRIT."B" | C48: TECO2 | D48: 45656 | E48: 3070 | F48: 45659 | G48: 3170 | H48: =IF(ISERROR(VLOOKUP(A48,EspeciesVisual!C:R,16,FALSE)),"",VLOOKUP(A48,EspeciesVisual!C:R,16,FALSE)) | I48: =IF(OR(ISNUMBER(SEARCH("obligacion",LOWER(H48))),ISNUMBER(SEARCH("titulo",LOWER(H48))),ISNUMBER(SEARCH("letra",LOWER(H48)))),G48/100,G48) | J48: =I48/1167.806
A49: 810 | B49: PERK PERTRAK ARG. S.A. | C49: PERK | D49: 41912 | E49: 1.25 | F49: 41913 | G49: 1.28 | H49: =IF(ISERROR(VLOOKUP(A49,EspeciesVisual!C:R,16,FALSE)),"",VLOOKUP(A49,EspeciesVisual!C:R,16,FALSE)) | I49: =IF(OR(ISNUMBER(SEARCH("obligacion",LOWER(H49))),ISNUMBER(SEARCH("titulo",LOWER(H49))),ISNUMBER(SEARCH("letra",LOWER(H49)))),G49/100,G49) | J49: =I49/1167.806
A50: 839 | B50: TXAR TERNIUM ARGENTINA S.A. | C50: TXAR | D50: 45656 | E50: 895 | F50: 45659 | G50: 898 | H50: =IF(ISERROR(VLOOKUP(A50,EspeciesVisual!C:R,16,FALSE)),"",VLOOKUP(A50,EspeciesVisual!C:R,16,FALSE)) | I50: =IF(OR(ISNUMBER(SEARCH("obligacion",LOWER(H50))),ISNUMBER(SEARCH("titulo",LOWER(H50))),ISNUMBER(SEARCH("letra",LOWER(H50)))),G50/100,G50) | J50: =I50/1167.806
A51: 849 | B51: TRAN TRANSENER ORS. 1 VOTO | C51: TRAN | D51: 45656 | E51: 2750 | F51: 45659 | G51: 2830 | H51: =IF(ISERROR(VLOOKUP(A51,EspeciesVisual!C:R,16,FALSE)),"",VLOOKUP(A51,EspeciesVisual!C:R,16,FALSE)) | I51: =IF(OR(ISNUMBER(SEARCH("obligacion",LOWER(H51))),ISNUMBER(SEARCH("titulo",LOWER(H51))),ISNUMBER(SEARCH("letra",LOWER(H51)))),G51/100,G51) | J51: =I51/1167.806
... A54: 945 | B54: PSUR PETROLERA DEL CONOSUR 1 | C54: PSUR | D54: 43538 | E54: 3.65 | F54: 43738 | G54: 3.65 | H54: =IF(ISERROR(VLOOKUP(A54,EspeciesVisual!C:R,16,FALSE)),"",VLOOKUP(A54,EspeciesVisual!C:R,16,FALSE)) | I54: =IF(OR(ISNUMBER(SEARCH("obligacion",LOWER(H54))),ISNUMBER(SEARCH("titulo",LOWER(H54))),ISNUMBER(SEARCH("letra",LOWER(H54)))),G54/100,G54) | J54: =I54/1167.806
A55: 1002 | B55: CHEQUES | C55: CPD | E55: 0 | F55: 39426 | G55: 100 | H55: =IF(ISERROR(VLOOKUP(A55,EspeciesVisual!C:R,16,FALSE)),"",VLOOKUP(A55,EspeciesVisual!C:R,16,FALSE)) | I55: =IF(OR(ISNUMBER(SEARCH("obligacion",LOWER(H55))),ISNUMBER(SEARCH("titulo",LOWER(H55))),ISNUMBER(SEARCH("letra",LOWER(H55)))),G55/100,G55) | J55: =I55/1167.806
A56: 1003 | B56: PAGARE | C56: PAGARE | E56: 0 | F56: 44307 | G56: 100 | H56: =IF(ISERROR(VLOOKUP(A56,EspeciesVisual!C:R,16,FALSE)),"",VLOOKUP(A56,EspeciesVisual!C:R,16,FALSE)) | I56: =IF(OR(ISNUMBER(SEARCH("obligacion",LOWER(H56))),ISNUMBER(SEARCH("titulo",LOWER(H56))),ISNUMBER(SEARCH("letra",LOWER(H56)))),G56/100,G56) | J56: =I56/1167.806
A57: 1006 | B57: PAGARE DOLARES | C57: PAGARED | D57: 45656 | E57: 100 | F57: 45659 | G57: 100 | H57: =IF(ISERROR(VLOOKUP(A57,EspeciesVisual!C:R,16,FALSE)),"",VLOOKUP(A57,EspeciesVisual!C:R,16,FALSE)) | I57: =IF(OR(ISNUMBER(SEARCH("obligacion",LOWER(H57))),ISNUMBER(SEARCH("titulo",LOWER(H57))),ISNUMBER(SEARCH("letra",LOWER(H57)))),G57/100,G57) | J57: =I57/1167.806
A58: 1008 | B58: FACTURA DE CREDITO | C58: FCE | D58: 44760 | E58: 100.1 | F58: 44761 | G58: 100.1 | H58: =IF(ISERROR(VLOOKUP(A58,EspeciesVisual!C:R,16,FALSE)),"",VLOOKUP(A58,EspeciesVisual!C:R,16,FALSE)) | I58: =IF(OR(ISNUMBER(SEARCH("obligacion",LOWER(H58))),ISNUMBER(SEARCH("titulo",LOWER(H58))),ISNUMBER(SEARCH("letra",LOWER(H58)))),G58/100,G58) | J58: =I58/1167.806
A59: 1009 | B59: FCE EN USD | C59: FCE | D59: 45656 | E59: 1 | F59: 45659 | G59: 1 | H59: =IF(ISERROR(VLOOKUP(A59,EspeciesVisual!C:R,16,FALSE)),"",VLOOKUP(A59,EspeciesVisual!C:R,16,FALSE)) | I59: =IF(OR(ISNUMBER(SEARCH("obligacion",LOWER(H59))),ISNUMBER(SEARCH("titulo",LOWER(H59))),ISNUMBER(SEARCH("letra",LOWER(H59)))),G59/100,G59) | J59: =I59/1167.806
A60: 1010 | B60: PAGARE A3500 | C60: PAG3500 | D60: 45657 | E60: 103.2 | F60: 45659 | G60: 100 | H60: =IF(ISERROR(VLOOKUP(A60,EspeciesVisual!C:R,16,FALSE)),"",VLOOKUP(A60,EspeciesVisual!C:R,16,FALSE)) | I60: =IF(OR(ISNUMBER(SEARCH("obligacion",LOWER(H60))),ISNUMBER(SEARCH("titulo",LOWER(H60))),ISNUMBER(SEARCH("letra",LOWER(H60)))),G60/100,G60) | J60: =I60/1167.806
A61: 1015 | B61: PAGARE HD | C61: PAGARE HD | E61: 0 | G61: 0 | H61: =IF(ISERROR(VLOOKUP(A61,EspeciesVisual!C:R,16,FALSE)),"",VLOOKUP(A61,EspeciesVisual!C:R,16,FALSE)) | I61: =IF(OR(ISNUMBER(SEARCH("obligacion",LOWER(H61))),ISNUMBER(SEARCH("titulo",LOWER(H61))),ISNUMBER(SEARCH("letra",LOWER(H61)))),G61/100,G61) | J61: =I61/1167.806
A62: 5320 | B62: BONO TESORO NAC. ARS 15.5% VTO | C62: TO26 | D62: 45656 | E62: 84.7 | F62: 45659 | G62: 88 | H62: =IF(ISERROR(VLOOKUP(A62,EspeciesVisual!C:R,16,FALSE)),"",VLOOKUP(A62,EspeciesVisual!C:R,16,FALSE)) | I62: =IF(OR(ISNUMBER(SEARCH("obligacion",LOWER(H62))),ISNUMBER(SEARCH("titulo",LOWER(H62))),ISNUMBER(SEARCH("letra",LOWER(H62)))),G62/100,G62) | J62: =I62/1167.806
A63: 5493 | B63: BONOS TESORO $ AJ. CER 1,50% V | C63: TX24 | D63: 45371 | E63: 1437 | F63: 45372 | G63: 1437 | H63: =IF(ISERROR(VLOOKUP(A63,EspeciesVisual!C:R,16,FALSE)),"",VLOOKUP(A63,EspeciesVisual!C:R,16,FALSE)) | I63: =IF(OR(ISNUMBER(SEARCH("obligacion",LOWER(H63))),ISNUMBER(SEARCH("titulo",LOWER(H63))),ISNUMBER(SEARCH("letra",LOWER(H63)))),G63/100,G63) | J63: =I63/1167.806
A64: 5796 | B64: CHEVRON CORPORATION (CVX) | C64: CVX-US | D64: 45657 | E64: 144.84 | F64: 45659 | G64: 146.71 | H64: =IF(ISERROR(VLOOKUP(A64,EspeciesVisual!C:R,16,FALSE)),"",VLOOKUP(A64,EspeciesVisual!C:R,16,FALSE)) | I64: =IF(OR(ISNUMBER(SEARCH("obligacion",LOWER(H64))),ISNUMBER(SEARCH("titulo",LOWER(H64))),ISNUMBER(SEARCH("letra",LOWER(H64)))),G64/100,G64) | J64: =I64/1167.806
A65: 5821 | B65: CIA SIDERURGICA NACL | C65: SID-US | D65: 45657 | E65: 1.44 | F65: 45659 | G65: 1.42 | H65: =IF(ISERROR(VLOOKUP(A65,EspeciesVisual!C:R,16,FALSE)),"",VLOOKUP(A65,EspeciesVisual!C:R,16,FALSE)) | I65: =IF(OR(ISNUMBER(SEARCH("obligacion",LOWER(H65))),ISNUMBER(SEARCH("titulo",LOWER(H65))),ISNUMBER(SEARCH("letra",LOWER(H65)))),G65/100,G65) | J65: =I65/1167.806
A66: 5858 | B66: VORNADO REALTY TRUST (VNO) | C66: VNO-US | D66: 45657 | E66: 42.04 | F66: 45659 | G66: 42.62 | H66: =IF(ISERROR(VLOOKUP(A66,EspeciesVisual!C:R,16,FALSE)),"",VLOOKUP(A66,EspeciesVisual!C:R,16,FALSE)) | I66: =IF(OR(ISNUMBER(SEARCH("obligacion",LOWER(H66))),ISNUMBER(SEARCH("titulo",LOWER(H66))),ISNUMBER(SEARCH("letra",LOWER(H66)))),G66/100,G66) | J66: =I66/1167.806
A67: 5913 | B67: OCCIDENTAL PETROLEUM CORP. (OX | C67: OXY-US | D67: 45657 | E67: 49.41 | F67: 45659 | G67: 49.81 | H67: =IF(ISERROR(VLOOKUP(A67,EspeciesVisual!C:R,16,FALSE)),"",VLOOKUP(A67,EspeciesVisual!C:R,16,FALSE)) | I67: =IF(OR(ISNUMBER(SEARCH("obligacion",LOWER(H67))),ISNUMBER(SEARCH("titulo",LOWER(H67))),ISNUMBER(SEARCH("letra",LOWER(H67)))),G67/100,G67) | J67: =I67/1167.806
A68: 5921 | B68: BONO USD 2030 LA | C68: AL30 | D68: 45656 | E68: 88050 | F68: 45659 | G68: 88760 | H68: =IF(ISERROR(VLOOKUP(A68,EspeciesVisual!C:R,16,FALSE)),"",VLOOKUP(A68,EspeciesVisual!C:R,16,FALSE)) | I68: =IF(OR(ISNUMBER(SEARCH("obligacion",LOWER(H68))),ISNUMBER(SEARCH("titulo",LOWER(H68))),ISNUMBER(SEARCH("letra",LOWER(H68)))),G68/100,G68) | J68: =I68/1167.806
A69: 5922 | B69: BONO USD 2035 LA | C69: AL35 | D69: 45656 | E69: 81500 | F69: 45659 | G69: 81630 | H69: =IF(ISERROR(VLOOKUP(A69,EspeciesVisual!C:R,16,FALSE)),"",VLOOKUP(A69,EspeciesVisual!C:R,16,FALSE)) | I69: =IF(OR(ISNUMBER(SEARCH("obligacion",LOWER(H69))),ISNUMBER(SEARCH("titulo",LOWER(H69))),ISNUMBER(SEARCH("letra",LOWER(H69)))),G69/100,G69) | J69: =I69/1167.806
A70: 5923 | B70: BONO USD 2038 LA | C70: AE38 | D70: 45656 | E70: 86640 | F70: 45659 | G70: 86500 | H70: =IF(ISERROR(VLOOKUP(A70,EspeciesVisual!C:R,16,FALSE)),"",VLOOKUP(A70,EspeciesVisual!C:R,16,FALSE)) | I70: =IF(OR(ISNUMBER(SEARCH("obligacion",LOWER(H70))),ISNUMBER(SEARCH("titulo",LOWER(H70))),ISNUMBER(SEARCH("letra",LOWER(H70)))),G70/100,G70) | J70: =I70/1167.806
A71: 5924 | B71: BONO USD 2041 LA | C71: AL41 | D71: 45656 | E71: 77500 | F71: 45659 | G71: 77640 | H71: =IF(ISERROR(VLOOKUP(A71,EspeciesVisual!C:R,16,FALSE)),"",VLOOKUP(A71,EspeciesVisual!C:R,16,FALSE)) | I71: =IF(OR(ISNUMBER(SEARCH("obligacion",LOWER(H71))),ISNUMBER(SEARCH("titulo",LOWER(H71))),ISNUMBER(SEARCH("letra",LOWER(H71)))),G71/100,G71) | J71: =I71/1167.806
A72: 5925 | B72: BONCER 2026 2% | C72: TX26 | D72: 45656 | E72: 1678 | F72: 45659 | G72: 1694 | H72: =IF(ISERROR(VLOOKUP(A72,EspeciesVisual!C:R,16,FALSE)),"",VLOOKUP(A72,EspeciesVisual!C:R,16,FALSE)) | I72: =IF(OR(ISNUMBER(SEARCH("obligacion",LOWER(H72))),ISNUMBER(SEARCH("titulo",LOWER(H72))),ISNUMBER(SEARCH("letra",LOWER(H72)))),G72/100,G72) | J72: =I72/1167.806
A73: 5926 | B73: BONCER 2028 2% | C73: TX28 | D73: 45656 | E73: 1581 | F73: 45659 | G73: 1598 | H73: =IF(ISERROR(VLOOKUP(A73,EspeciesVisual!C:R,16,FALSE)),"",VLOOKUP(A73,EspeciesVisual!C:R,16,FALSE)) | I73: =IF(OR(ISNUMBER(SEARCH("obligacion",LOWER(H73))),ISNUMBER(SEARCH("titulo",LOWER(H73))),ISNUMBER(SEARCH("letra",LOWER(H73)))),G73/100,G73) | J73: =I73/1167.806
... A75: 6000 | B75: EUROS | C75: EURO | D75: 45656 | E75: 1 | F75: 45659 | G75: 1 | H75: =IF(ISERROR(VLOOKUP(A75,EspeciesVisual!C:R,16,FALSE)),"",VLOOKUP(A75,EspeciesVisual!C:R,16,FALSE)) | I75: =IF(OR(ISNUMBER(SEARCH("obligacion",LOWER(H75))),ISNUMBER(SEARCH("titulo",LOWER(H75))),ISNUMBER(SEARCH("letra",LOWER(H75)))),G75/100,G75) | J75: =I75/1167.806
A76: 6001 | B76: EURO MONEDA | E76: 0 | G76: 0 | H76: =IF(ISERROR(VLOOKUP(A76,EspeciesVisual!C:R,16,FALSE)),"",VLOOKUP(A76,EspeciesVisual!C:R,16,FALSE)) | I76: =IF(OR(ISNUMBER(SEARCH("obligacion",LOWER(H76))),ISNUMBER(SEARCH("titulo",LOWER(H76))),ISNUMBER(SEARCH("letra",LOWER(H76)))),G76/100,G76) | J76: =I76/1167.806
A77: 6107 | B77: ADR GRUPO FINANCIERO GALICIA | C77: GGAL-US | D77: 45657 | E77: 62.33 | F77: 45659 | G77: 68.76 | H77: =IF(ISERROR(VLOOKUP(A77,EspeciesVisual!C:R,16,FALSE)),"",VLOOKUP(A77,EspeciesVisual!C:R,16,FALSE)) | I77: =IF(OR(ISNUMBER(SEARCH("obligacion",LOWER(H77))),ISNUMBER(SEARCH("titulo",LOWER(H77))),ISNUMBER(SEARCH("letra",LOWER(H77)))),G77/100,G77) | J77: =I77/1167.806
A78: 6472 | B78: ADR PETROLEO BRASILEIRO S.A.(P | C78: PBR-US | D78: 45657 | E78: 12.86 | F78: 45659 | G78: 13.24 | H78: =IF(ISERROR(VLOOKUP(A78,EspeciesVisual!C:R,16,FALSE)),"",VLOOKUP(A78,EspeciesVisual!C:R,16,FALSE)) | I78: =IF(OR(ISNUMBER(SEARCH("obligacion",LOWER(H78))),ISNUMBER(SEARCH("titulo",LOWER(H78))),ISNUMBER(SEARCH("letra",LOWER(H78)))),G78/100,G78) | J78: =I78/1167.806
A79: 6494 | B79: GOLDMAN SACHS GROUP (GS) | C79: GS-US | D79: 45657 | E79: 572.62 | F79: 45659 | G79: 574.97 | H79: =IF(ISERROR(VLOOKUP(A79,EspeciesVisual!C:R,16,FALSE)),"",VLOOKUP(A79,EspeciesVisual!C:R,16,FALSE)) | I79: =IF(OR(ISNUMBER(SEARCH("obligacion",LOWER(H79))),ISNUMBER(SEARCH("titulo",LOWER(H79))),ISNUMBER(SEARCH("letra",LOWER(H79)))),G79/100,G79) | J79: =I79/1167.806
A80: 7000 | B80: DOLARES USA | C80: DOL 7000 | D80: 45656 | E80: 1 | F80: 45659 | G80: 1 | H80: =IF(ISERROR(VLOOKUP(A80,EspeciesVisual!C:R,16,FALSE)),"",VLOOKUP(A80,EspeciesVisual!C:R,16,FALSE)) | I80: =IF(OR(ISNUMBER(SEARCH("obligacion",LOWER(H80))),ISNUMBER(SEARCH("titulo",LOWER(H80))),ISNUMBER(SEARCH("letra",LOWER(H80)))),G80/100,G80) | J80: =I80/1167.806
A81: 7007 | B81: PFIZER (PFE) | C81: PFE-US | D81: 45657 | E81: 26.53 | F81: 45659 | G81: 26.61 | H81: =IF(ISERROR(VLOOKUP(A81,EspeciesVisual!C:R,16,FALSE)),"",VLOOKUP(A81,EspeciesVisual!C:R,16,FALSE)) | I81: =IF(OR(ISNUMBER(SEARCH("obligacion",LOWER(H81))),ISNUMBER(SEARCH("titulo",LOWER(H81))),ISNUMBER(SEARCH("letra",LOWER(H81)))),G81/100,G81) | J81: =I81/1167.806
A82: 7043 | B82: AMAZON (AMZN) | C82: AMZN-US | D82: 45657 | E82: 219.51 | F82: 45659 | G82: 220.225 | H82: =IF(ISERROR(VLOOKUP(A82,EspeciesVisual!C:R,16,FALSE)),"",VLOOKUP(A82,EspeciesVisual!C:R,16,FALSE)) | I82: =IF(OR(ISNUMBER(SEARCH("obligacion",LOWER(H82))),ISNUMBER(SEARCH("titulo",LOWER(H82))),ISNUMBER(SEARCH("letra",LOWER(H82)))),G82/100,G82) | J82: =I82/1167.806
A83: 7044 | B83: NVIDIA CORPORATION | C83: NVDA-US | D83: 45657 | E83: 134.29 | F83: 45659 | G83: 138.31 | H83: =IF(ISERROR(VLOOKUP(A83,EspeciesVisual!C:R,16,FALSE)),"",VLOOKUP(A83,EspeciesVisual!C:R,16,FALSE)) | I83: =IF(OR(ISNUMBER(SEARCH("obligacion",LOWER(H83))),ISNUMBER(SEARCH("titulo",LOWER(H83))),ISNUMBER(SEARCH("letra",LOWER(H83)))),G83/100,G83) | J83: =I83/1167.806
A84: 7074 | B84: MICROSOFT CORP | C84: MSFT-US | D84: 45657 | E84: 421.23 | F84: 45659 | G84: 418.62 | H84: =IF(ISERROR(VLOOKUP(A84,EspeciesVisual!C:R,16,FALSE)),"",VLOOKUP(A84,EspeciesVisual!C:R,16,FALSE)) | I84: =IF(OR(ISNUMBER(SEARCH("obligacion",LOWER(H84))),ISNUMBER(SEARCH("titulo",LOWER(H84))),ISNUMBER(SEARCH("letra",LOWER(H84)))),G84/100,G84) | J84: =I84/1167.806
A85: 7083 | B85: EXXON MOBIL CORP (XOM) | C85: XOM-US | D85: 45657 | E85: 107.57 | F85: 45659 | G85: 107.31 | H85: =IF(ISERROR(VLOOKUP(A85,EspeciesVisual!C:R,16,FALSE)),"",VLOOKUP(A85,EspeciesVisual!C:R,16,FALSE)) | I85: =IF(OR(ISNUMBER(SEARCH("obligacion",LOWER(H85))),ISNUMBER(SEARCH("titulo",LOWER(H85))),ISNUMBER(SEARCH("letra",LOWER(H85)))),G85/100,G85) | J85: =I85/1167.806
A86: 7108 | B86: TRANSPORTADORA GAS DEL SUR (A. | C86: TGS-US | D86: 45657 | E86: 29.27 | F86: 45659 | G86: 32.4 | H86: =IF(ISERROR(VLOOKUP(A86,EspeciesVisual!C:R,16,FALSE)),"",VLOOKUP(A86,EspeciesVisual!C:R,16,FALSE)) | I86: =IF(OR(ISNUMBER(SEARCH("obligacion",LOWER(H86))),ISNUMBER(SEARCH("titulo",LOWER(H86))),ISNUMBER(SEARCH("letra",LOWER(H86)))),G86/100,G86) | J86: =I86/1167.806
A87: 7109 | B87: YPFD ADR | C87: YPF-US | D87: 45657 | E87: 42.51 | F87: 45659 | G87: 44.6 | H87: =IF(ISERROR(VLOOKUP(A87,EspeciesVisual!C:R,16,FALSE)),"",VLOOKUP(A87,EspeciesVisual!C:R,16,FALSE)) | I87: =IF(OR(ISNUMBER(SEARCH("obligacion",LOWER(H87))),ISNUMBER(SEARCH("titulo",LOWER(H87))),ISNUMBER(SEARCH("letra",LOWER(H87)))),G87/100,G87) | J87: =I87/1167.806
A88: 7181 | B88: BANK OF AMERICA S/OFERTA PUBLI | C88: BAC-US | D88: 45657 | E88: 43.95 | F88: 45659 | G88: 44.29 | H88: =IF(ISERROR(VLOOKUP(A88,EspeciesVisual!C:R,16,FALSE)),"",VLOOKUP(A88,EspeciesVisual!C:R,16,FALSE)) | I88: =IF(OR(ISNUMBER(SEARCH("obligacion",LOWER(H88))),ISNUMBER(SEARCH("titulo",LOWER(H88))),ISNUMBER(SEARCH("letra",LOWER(H88)))),G88/100,G88) | J88: =I88/1167.806
A89: 7182 | B89: IMPSAT FIBER NETWORKS | C89: IMPS-US | E89: 0 | G89: 0 | H89: =IF(ISERROR(VLOOKUP(A89,EspeciesVisual!C:R,16,FALSE)),"",VLOOKUP(A89,EspeciesVisual!C:R,16,FALSE)) | I89: =IF(OR(ISNUMBER(SEARCH("obligacion",LOWER(H89))),ISNUMBER(SEARCH("titulo",LOWER(H89))),ISNUMBER(SEARCH("letra",LOWER(H89)))),G89/100,G89) | J89: =I89/1167.806
A90: 7247 | B90: WELLS FARGO & COMPANY (WFC) | C90: WFC-US | D90: 45657 | E90: 70.24 | F90: 45659 | G90: 70.19 | H90: =IF(ISERROR(VLOOKUP(A90,EspeciesVisual!C:R,16,FALSE)),"",VLOOKUP(A90,EspeciesVisual!C:R,16,FALSE)) | I90: =IF(OR(ISNUMBER(SEARCH("obligacion",LOWER(H90))),ISNUMBER(SEARCH("titulo",LOWER(H90))),ISNUMBER(SEARCH("letra",LOWER(H90)))),G90/100,G90) | J90: =I90/1167.806
A91: 7251 | B91: UNITEDHEALTH GROUP INC. (UNH) | C91: UNH-US | E91: 0 | G91: 0 | H91: =IF(ISERROR(VLOOKUP(A91,EspeciesVisual!C:R,16,FALSE)),"",VLOOKUP(A91,EspeciesVisual!C:R,16,FALSE)) | I91: =IF(OR(ISNUMBER(SEARCH("obligacion",LOWER(H91))),ISNUMBER(SEARCH("titulo",LOWER(H91))),ISNUMBER(SEARCH("letra",LOWER(H91)))),G91/100,G91) | J91: =I91/1167.806
A92: 7483 | B92: CEF SELECT AMEX TECH SPDR | C92: XLK-US | D92: 45657 | E92: 232.62 | F92: 45659 | G92: 231.98 | H92: =IF(ISERROR(VLOOKUP(A92,EspeciesVisual!C:R,16,FALSE)),"",VLOOKUP(A92,EspeciesVisual!C:R,16,FALSE)) | I92: =IF(OR(ISNUMBER(SEARCH("obligacion",LOWER(H92))),ISNUMBER(SEARCH("titulo",LOWER(H92))),ISNUMBER(SEARCH("letra",LOWER(H92)))),G92/100,G92) | J92: =I92/1167.806
A93: 7716 | B93: WAL MART STORES INC (WMT) | C93: WMT-US | D93: 45657 | E93: 90.35 | F93: 45659 | G93: 90 | H93: =IF(ISERROR(VLOOKUP(A93,EspeciesVisual!C:R,16,FALSE)),"",VLOOKUP(A93,EspeciesVisual!C:R,16,FALSE)) | I93: =IF(OR(ISNUMBER(SEARCH("obligacion",LOWER(H93))),ISNUMBER(SEARCH("titulo",LOWER(H93))),ISNUMBER(SEARCH("letra",LOWER(H93)))),G93/100,G93) | J93: =I93/1167.806
A94: 7742 | B94: BOEING CO | C94: BA-US | D94: 45657 | E94: 177 | F94: 45659 | G94: 171.87 | H94: =IF(ISERROR(VLOOKUP(A94,EspeciesVisual!C:R,16,FALSE)),"",VLOOKUP(A94,EspeciesVisual!C:R,16,FALSE)) | I94: =IF(OR(ISNUMBER(SEARCH("obligacion",LOWER(H94))),ISNUMBER(SEARCH("titulo",LOWER(H94))),ISNUMBER(SEARCH("letra",LOWER(H94)))),G94/100,G94) | J94: =I94/1167.806
A95: 7747 | B95: S & P 500 DEPOSITARY RECEIPT | C95: SPY-US | D95: 45657 | E95: 586.01 | F95: 45659 | G95: 584.62 | H95: =IF(ISERROR(VLOOKUP(A95,EspeciesVisual!C:R,16,FALSE)),"",VLOOKUP(A95,EspeciesVisual!C:R,16,FALSE)) | I95: =IF(OR(ISNUMBER(SEARCH("obligacion",LOWER(H95))),ISNUMBER(SEARCH("titulo",LOWER(H95))),ISNUMBER(SEARCH("letra",LOWER(H95)))),G95/100,G95) | J95: =I95/1167.806
A96: 7872 | B96: WALT DISNEY CO. | C96: DIS-US | D96: 45657 | E96: 111.35 | F96: 45659 | G96: 110.82 | H96: =IF(ISERROR(VLOOKUP(A96,EspeciesVisual!C:R,16,FALSE)),"",VLOOKUP(A96,EspeciesVisual!C:R,16,FALSE)) | I96: =IF(OR(ISNUMBER(SEARCH("obligacion",LOWER(H96))),ISNUMBER(SEARCH("titulo",LOWER(H96))),ISNUMBER(SEARCH("letra",LOWER(H96)))),G96/100,G96) | J96: =I96/1167.806
A97: 7877 | B97: APPLE COMPUTER INC | C97: AAPL-US | D97: 45657 | E97: 250.44 | F97: 45659 | G97: 243.78 | H97: =IF(ISERROR(VLOOKUP(A97,EspeciesVisual!C:R,16,FALSE)),"",VLOOKUP(A97,EspeciesVisual!C:R,16,FALSE)) | I97: =IF(OR(ISNUMBER(SEARCH("obligacion",LOWER(H97))),ISNUMBER(SEARCH("titulo",LOWER(H97))),ISNUMBER(SEARCH("letra",LOWER(H97)))),G97/100,G97) | J97: =I97/1167.806
A98: 7971 | B98: HOME DEPOT INC.(HD) | C98: HD-US | D98: 45657 | E98: 388.99 | F98: 45659 | G98: 388.46 | H98: =IF(ISERROR(VLOOKUP(A98,EspeciesVisual!C:R,16,FALSE)),"",VLOOKUP(A98,EspeciesVisual!C:R,16,FALSE)) | I98: =IF(OR(ISNUMBER(SEARCH("obligacion",LOWER(H98))),ISNUMBER(SEARCH("titulo",LOWER(H98))),ISNUMBER(SEARCH("letra",LOWER(H98)))),G98/100,G98) | J98: =I98/1167.806
A99: 7974 | B99: AMERICAN EXPRESS COMPANY S/OFE | C99: AXP-US | E99: 0 | G99: 0 | H99: =IF(ISERROR(VLOOKUP(A99,EspeciesVisual!C:R,16,FALSE)),"",VLOOKUP(A99,EspeciesVisual!C:R,16,FALSE)) | I99: =IF(OR(ISNUMBER(SEARCH("obligacion",LOWER(H99))),ISNUMBER(SEARCH("titulo",LOWER(H99))),ISNUMBER(SEARCH("letra",LOWER(H99)))),G99/100,G99) | J99: =I99/1167.806
A100: 8000 | B100: PESOS DISPONIBLE | D100: 43371 | E100: 1 | F100: 43553 | G100: 1 | H100: =IF(ISERROR(VLOOKUP(A100,EspeciesVisual!C:R,16,FALSE)),"",VLOOKUP(A100,EspeciesVisual!C:R,16,FALSE)) | I100: =IF(OR(ISNUMBER(SEARCH("obligacion",LOWER(H100))),ISNUMBER(SEARCH("titulo",LOWER(H100))),ISNUMBER(SEARCH("letra",LOWER(H100)))),G100/100,G100) | J100: =I100/1167.806
A101: 8006 | B101: CEDEAR COCA-COLA COMPANY | C101: KO | D101: 45656 | E101: 14725 | F101: 45659 | G101: 14550 | H101: =IF(ISERROR(VLOOKUP(A101,EspeciesVisual!C:R,16,FALSE)),"",VLOOKUP(A101,EspeciesVisual!C:R,16,FALSE)) | I101: =IF(OR(ISNUMBER(SEARCH("obligacion",LOWER(H101))),ISNUMBER(SEARCH("titulo",LOWER(H101))),ISNUMBER(SEARCH("letra",LOWER(H101)))),G101/100,G101) | J101: =I101/1167.806
A102: 8009 | B102: CEDEAR AMER.EXPR | C102: AXP | D102: 45656 | E102: 23600 | F102: 45659 | G102: 23221.018 | H102: =IF(ISERROR(VLOOKUP(A102,EspeciesVisual!C:R,16,FALSE)),"",VLOOKUP(A102,EspeciesVisual!C:R,16,FALSE)) | I102: =IF(OR(ISNUMBER(SEARCH("obligacion",LOWER(H102))),ISNUMBER(SEARCH("titulo",LOWER(H102))),ISNUMBER(SEARCH("letra",LOWER(H102)))),G102/100,G102) | J102: =I102/1167.806
A103: 8011 | B103: CEDEAR BOEING CO | C103: BA | D103: 45656 | E103: 8740 | F103: 45659 | G103: 8390 | H103: =IF(ISERROR(VLOOKUP(A103,EspeciesVisual!C:R,16,FALSE)),"",VLOOKUP(A103,EspeciesVisual!C:R,16,FALSE)) | I103: =IF(OR(ISNUMBER(SEARCH("obligacion",LOWER(H103))),ISNUMBER(SEARCH("titulo",LOWER(H103))),ISNUMBER(SEARCH("letra",LOWER(H103)))),G103/100,G103) | J103: =I103/1167.806
A104: 8012 | B104: CEDERA CAATERPIL | C104: CAT | D104: 45656 | E104: 21625 | F104: 45659 | G104: 21200 | H104: =IF(ISERROR(VLOOKUP(A104,EspeciesVisual!C:R,16,FALSE)),"",VLOOKUP(A104,EspeciesVisual!C:R,16,FALSE)) | I104: =IF(OR(ISNUMBER(SEARCH("obligacion",LOWER(H104))),ISNUMBER(SEARCH("titulo",LOWER(H104))),ISNUMBER(SEARCH("letra",LOWER(H104)))),G104/100,G104) | J104: =I104/1167.806
A105: 8013 | B105: CEDEAR CHEVRON C | C105: CVX | D105: 45656 | E105: 10650 | F105: 45659 | G105: 10800 | H105: =IF(ISERROR(VLOOKUP(A105,EspeciesVisual!C:R,16,FALSE)),"",VLOOKUP(A105,EspeciesVisual!C:R,16,FALSE)) | I105: =IF(OR(ISNUMBER(SEARCH("obligacion",LOWER(H105))),ISNUMBER(SEARCH("titulo",LOWER(H105))),ISNUMBER(SEARCH("letra",LOWER(H105)))),G105/100,G105) | J105: =I105/1167.806
A106: 8014 | B106: CEDEAR CISCO SYS | C106: CSCO | D106: 45656 | E106: 14050 | F106: 45659 | G106: 13732.46 | H106: =IF(ISERROR(VLOOKUP(A106,EspeciesVisual!C:R,16,FALSE)),"",VLOOKUP(A106,EspeciesVisual!C:R,16,FALSE)) | I106: =IF(OR(ISNUMBER(SEARCH("obligacion",LOWER(H106))),ISNUMBER(SEARCH("titulo",LOWER(H106))),ISNUMBER(SEARCH("letra",LOWER(H106)))),G106/100,G106) | J106: =I106/1167.806
A107: 8017 | B107: CEDEAR DISNEY COMMON STOCK | C107: DISN | D107: 45656 | E107: 10975 | F107: 45659 | G107: 10825 | H107: =IF(ISERROR(VLOOKUP(A107,EspeciesVisual!C:R,16,FALSE)),"",VLOOKUP(A107,EspeciesVisual!C:R,16,FALSE)) | I107: =IF(OR(ISNUMBER(SEARCH("obligacion",LOWER(H107))),ISNUMBER(SEARCH("titulo",LOWER(H107))),ISNUMBER(SEARCH("letra",LOWER(H107)))),G107/100,G107) | J107: =I107/1167.806
A108: 8018 | B108: CEDEAR DE EI DU PONT DE NEMOUR | C108: DD | E108: 0 | G108: 0 | H108: =IF(ISERROR(VLOOKUP(A108,EspeciesVisual!C:R,16,FALSE)),"",VLOOKUP(A108,EspeciesVisual!C:R,16,FALSE)) | I108: =IF(OR(ISNUMBER(SEARCH("obligacion",LOWER(H108))),ISNUMBER(SEARCH("titulo",LOWER(H108))),ISNUMBER(SEARCH("letra",LOWER(H108)))),G108/100,G108) | J108: =I108/1167.806
A109: 8019 | B109: CEDEAR EXXON MOB | C109: XOM | D109: 45656 | E109: 12600 | F109: 45659 | G109: 12650 | H109: =IF(ISERROR(VLOOKUP(A109,EspeciesVisual!C:R,16,FALSE)),"",VLOOKUP(A109,EspeciesVisual!C:R,16,FALSE)) | I109: =IF(OR(ISNUMBER(SEARCH("obligacion",LOWER(H109))),ISNUMBER(SEARCH("titulo",LOWER(H109))),ISNUMBER(SEARCH("letra",LOWER(H109)))),G109/100,G109) | J109: =I109/1167.806
A110: 8020 | B110: CEDEAR GENERAL ELECTRIC | C110: GE | D110: 45656 | E110: 24975 | F110: 45659 | G110: 24750 | H110: =IF(ISERROR(VLOOKUP(A110,EspeciesVisual!C:R,16,FALSE)),"",VLOOKUP(A110,EspeciesVisual!C:R,16,FALSE)) | I110: =IF(OR(ISNUMBER(SEARCH("obligacion",LOWER(H110))),ISNUMBER(SEARCH("titulo",LOWER(H110))),ISNUMBER(SEARCH("letra",LOWER(H110)))),G110/100,G110) | J110: =I110/1167.806
A111: 8023 | B111: HEWLET PACKARD | C111: HPQ | D111: 45656 | E111: 38925 | F111: 45659 | G111: 38200 | H111: =IF(ISERROR(VLOOKUP(A111,EspeciesVisual!C:R,16,FALSE)),"",VLOOKUP(A111,EspeciesVisual!C:R,16,FALSE)) | I111: =IF(OR(ISNUMBER(SEARCH("obligacion",LOWER(H111))),ISNUMBER(SEARCH("titulo",LOWER(H111))),ISNUMBER(SEARCH("letra",LOWER(H111)))),G111/100,G111) | J111: =I111/1167.806
A112: 8024 | B112: CEDEAR IBM CORP. | C112: IBM | D112: 45656 | E112: 17450 | F112: 45659 | G112: 17150 | H112: =IF(ISERROR(VLOOKUP(A112,EspeciesVisual!C:R,16,FALSE)),"",VLOOKUP(A112,EspeciesVisual!C:R,16,FALSE)) | I112: =IF(OR(ISNUMBER(SEARCH("obligacion",LOWER(H112))),ISNUMBER(SEARCH("titulo",LOWER(H112))),ISNUMBER(SEARCH("letra",LOWER(H112)))),G112/100,G112) | J112: =I112/1167.806
A113: 8025 | B113: CEDEAR INTEL | C113: INTC | D113: 45656 | E113: 4720 | F113: 45659 | G113: 4765 | H113: =IF(ISERROR(VLOOKUP(A113,EspeciesVisual!C:R,16,FALSE)),"",VLOOKUP(A113,EspeciesVisual!C:R,16,FALSE)) | I113: =IF(OR(ISNUMBER(SEARCH("obligacion",LOWER(H113))),ISNUMBER(SEARCH("titulo",LOWER(H113))),ISNUMBER(SEARCH("letra",LOWER(H113)))),G113/100,G113) | J113: =I113/1167.806
A114: 8027 | B114: CEDEAR J & J | C114: JNJ | D114: 45656 | E114: 11325 | F114: 45659 | G114: 11325 | H114: =IF(ISERROR(VLOOKUP(A114,EspeciesVisual!C:R,16,FALSE)),"",VLOOKUP(A114,EspeciesVisual!C:R,16,FALSE)) | I114: =IF(OR(ISNUMBER(SEARCH("obligacion",LOWER(H114))),ISNUMBER(SEARCH("titulo",LOWER(H114))),ISNUMBER(SEARCH("letra",LOWER(H114)))),G114/100,G114) | J114: =I114/1167.806
A115: 8028 | B115: CEDEAR JP MORGAN | C115: JPM | D115: 45656 | E115: 19050 | F115: 45659 | G115: 18875 | H115: =IF(ISERROR(VLOOKUP(A115,EspeciesVisual!C:R,16,FALSE)),"",VLOOKUP(A115,EspeciesVisual!C:R,16,FALSE)) | I115: =IF(OR(ISNUMBER(SEARCH("obligacion",LOWER(H115))),ISNUMBER(SEARCH("titulo",LOWER(H115))),ISNUMBER(SEARCH("letra",LOWER(H115)))),G115/100,G115) | J115: =I115/1167.806
A116: 8030 | B116: CEDEAR MCDONALD | C116: MCD | D116: 45656 | E116: 14350 | F116: 45659 | G116: 14350 | H116: =IF(ISERROR(VLOOKUP(A116,EspeciesVisual!C:R,16,FALSE)),"",VLOOKUP(A116,EspeciesVisual!C:R,16,FALSE)) | I116: =IF(OR(ISNUMBER(SEARCH("obligacion",LOWER(H116))),ISNUMBER(SEARCH("titulo",LOWER(H116))),ISNUMBER(SEARCH("letra",LOWER(H116)))),G116/100,G116) | J116: =I116/1167.806
A117: 8031 | B117: CEDEAR MERCK | C117: MRK | D117: 45656 | E117: 23425 | F117: 45659 | G117: 23300 | H117: =IF(ISERROR(VLOOKUP(A117,EspeciesVisual!C:R,16,FALSE)),"",VLOOKUP(A117,EspeciesVisual!C:R,16,FALSE)) | I117: =IF(OR(ISNUMBER(SEARCH("obligacion",LOWER(H117))),ISNUMBER(SEARCH("titulo",LOWER(H117))),ISNUMBER(SEARCH("letra",LOWER(H117)))),G117/100,G117) | J117: =I117/1167.806
A118: 8032 | B118: CEDEAR MICROSOFT | C118: MSFT | D118: 45656 | E118: 16875 | F118: 45659 | G118: 16375 | H118: =IF(ISERROR(VLOOKUP(A118,EspeciesVisual!C:R,16,FALSE)),"",VLOOKUP(A118,EspeciesVisual!C:R,16,FALSE)) | I118: =IF(OR(ISNUMBER(SEARCH("obligacion",LOWER(H118))),ISNUMBER(SEARCH("titulo",LOWER(H118))),ISNUMBER(SEARCH("letra",LOWER(H118)))),G118/100,G118) | J118: =I118/1167.806
A119: 8033 | B119: MINNESOTA CEDEAR | C119: MMM | D119: 45656 | E119: 15425 | F119: 45659 | G119: 15200 | H119: =IF(ISERROR(VLOOKUP(A119,EspeciesVisual!C:R,16,FALSE)),"",VLOOKUP(A119,EspeciesVisual!C:R,16,FALSE)) | I119: =IF(OR(ISNUMBER(SEARCH("obligacion",LOWER(H119))),ISNUMBER(SEARCH("titulo",LOWER(H119))),ISNUMBER(SEARCH("letra",LOWER(H119)))),G119/100,G119) | J119: =I119/1167.806
A120: 8036 | B120: CEDEAR ALTRIA GR | C120: MO | D120: 45656 | E120: 15425 | F120: 45659 | G120: 15475 | H120: =IF(ISERROR(VLOOKUP(A120,EspeciesVisual!C:R,16,FALSE)),"",VLOOKUP(A120,EspeciesVisual!C:R,16,FALSE)) | I120: =IF(OR(ISNUMBER(SEARCH("obligacion",LOWER(H120))),ISNUMBER(SEARCH("titulo",LOWER(H120))),ISNUMBER(SEARCH("letra",LOWER(H120)))),G120/100,G120) | J120: =I120/1167.806
...

Sheet PrecioTenenciasIniciales
A1: Cod.Especie | B1: Ticker | C1: Especie | D1: Cantidad tenencia | E1: Importe invertido | F1: Resultado | G1: Precio tenencia inicial | H1: Ratio CEDEAR | I1: Precio Ajustado
A2: 05921 | B2: BONO | C2: USD 2030 LA | D2: 0 | E2: -357801.88 | F2: 357801.88 | G2: 0 | H2: 1 | I2: 0
A3: 09151 | B3: LETRAS | C3: DESC VTO.31/01/23 | D3: 0 | E3: 3291689.5 | F3: -3291689.5 | G3: 0 | H3: 1 | I3: 0
A4: 09164 | B4: LETRA | C4: A DESC V31/03/23 | D4: 0 | E4: -1220765.7 | F4: 1220765.7 | G4: 0 | H4: 1 | I4: 0
A5: 09234 | B5: BOPREAL | C5: S. 1 A VTO31/10/2 | D5: 613798 | E5: 6.1472671e+08 | F5: 75550525 | G5: 1001.513 | H5: 1 | I5: 1001.513
A6: 65114 | B6: DLR122024 | D6: 0 | E6: 162003.88 | F6: -162003.88 | G6: 0 | H6: 1 | I6: 0
A7: 65116 | B7: DLR012025 | D7: 0 | E7: 113385.07 | F7: -113385.07 | G7: 0 | H7: 1 | I7: 0
A8: 81086 | B8: BONOS | C8: REP. ARG. U$S STEP | D8: 0 | E8: -1428440.7 | F8: 1428440.7 | G8: 0 | H8: 1 | I8: 0
A9: OPERACION | B9: FINANCIERA | D9: 0 | E9: 169347.71 | F9: -169347.71 | G9: 0 | H9: 1 | I9: 0
A10: T | B10: o | C10: t a l e s | D10: 0 | E10: 6.1545612e+08 | F10: 74821107 | G10: 0 | H10: 1 | I10: 0

Sheet RatiosCedearsAcciones
A1: Nombre | B1: Ratio | C1: Key
A2: 3M Company MMM NYSE | B2: 10 | C2: 3M
A3: Abbott Labs ABT NYSE | B3: 4 | C3: ABBOTT
A4: AbbVie Inc. ABBV NYSE | B4: 10 | C4: ABBVIE
A5: Abercrombie & Fitch Co ANF NYSE | B5: 1 | C5: ABERCROMBIE
A6: Accenture ACN NYSE | B6: 75 | C6: ACCENTURE
A7: Adecoagro S.A. ADGO NYSE | B7: 1 | C7: ADECOAGRO
A8: Adidas AG ADS XETRA | B8: 22 | C8: ADIDAS
A9: Adobe Systems Incorporated ADBE NASDAQ | B9: 44 | C9: ADOBE
A10: Adr Jumia Technologies Ag JMIA NYSE | B10: 1 | C10: ADR
A11: Advanced Auto Parts Inc AAP NYSE | B11: 14 | C11: ADVANCED
A12: Aegon N.V. AEG NYSE | B12: 1 | C12: AEGON
A13: Agnico Eagle Mines Limited AEM NYSE | B13: 6 | C13: AGNICO
... A336: Zoom Video Communications Inc. ZM NASDAQ | B336: 47 | C336: ZOOM
