Workbook

Sheet Posicion Inicial Gallo
A1: tipo_especie | B1: Ticker | C1: especie | D1: Codigo especie | E1: Codigo Especie Origen | F1: comentario especies | G1: detalle | H1: custodia | I1: cantidad | J1: precio Tenencia Inicial Pesos | K1: precio Tenencia Inicial USD | L1: Precio de PreciosIniciales | M1: precio costo(en proceso) | N1: Origen precio costo | O1: comentarios precio costo | P1: Precio a Utilizar | Q1: importe_pesos | R1: porc_cartera_pesos | S1: importe_dolares | T1: porc_cartera_dolares | U1: Tipo Instrumento | V1: Precio Nominal
A2: RENTA FIJA EN PESOS | B2: T13F6 | C2: BONO TESORO NACI CAP V.13/02/26 $ CG | D2: 9314 | E2: PreciosInicialesEspecies | H2: CAJA VALORES | I2: 95498084 | J2: 1.0755 | K2: 0.00092095816 | L2: 109.4 | N2: PrecioTenenciasIniciales | P2: 1.04661 | Q2: 1.0270819e+08 | R2: 44.36 | S2: 87949.74 | T2: 44.36 | U2: Títulos Públicos | V2: 1.04661
A3: RENTA FIJA EN PESOS | B3: GNCXO | C3: ON GENNEIA SA REGS 8,75% V.02/09/2027 | D3: 81993 | E3: PreciosInicialesEspecies | H3: CAJA VALORES | I3: 15000 | J3: 753.8 | K3: 0.645484 | L3: 74000 | N3: PrecioTenenciasIniciales | P3: 676.25038 | Q3: 11307000 | R3: 4.88 | S3: 9682.26 | T3: 4.88 | U3: Obligaciones Negociables | V3: 676.25038
A4: RENTA FIJA EN DOLARES | B4: BPOA7 | C4: BOPREAL S. 1 A VTO31/10/27 U$S CG | D4: 9234 | E4: PreciosInicialesEspecies | H4: CAJA VALORES | I4: 208333 | J4: 112460 | K4: 0.96300284 | L4: 112100 | N4: PrecioTenenciasIniciales | P4: 969.12 | Q4: 2.3429129e+08 | R4: 101.2 | S4: 200625.27 | T4: 101.2 | U4: Títulos Públicos | V4: 969.12
A5: RENTA FIJA EN DOLARES | B5: BPY26 | C5: BOPREAL S.3 VTO31/05/26 U$S CG | D5: 9247 | E5: PreciosInicialesEspecies | H5: CAJA VALORES | I5: 10400 | J5: 110900 | K5: 0.94964423 | L5: 109500 | N5: PrecioTenenciasIniciales | P5: 708.51975 | Q5: 11533600 | R5: 4.98 | S5: 9876.3 | T5: 4.98 | U5: Títulos Públicos | V5: 708.51975
A6: RENTA FIJA EN DOLARES | B6: CO26 | C6: TD PUB. PCIA. CORDOBA V.27/10/26 | D6: 32804 | E6: PreciosInicialesEspecies | H6: CAJA VALORES | I6: 9000 | J6: 31990 | K6: 0.27393222 | L6: 30560 | N6: PrecioTenenciasIniciales | P6: 24.918281 | Q6: 2879100 | R6: 1.24 | S6: 2465.39 | T6: 1.24 | U6: Títulos Públicos | V6: 24.918281
A7: RENTA FIJA EN DOLARES | B7: GD30 | C7: BONOS REP. ARG. U$S STEP UP V.09/07/30 | D7: 81086 | E7: PreciosInicialesEspecies | H7: CAJA VALORES | I7: 1500 | J7: 88870 | K7: 0.761 | L7: 89390 | N7: PrecioTenenciasIniciales | P7: 386.61676 | Q7: 1333050 | R7: 0.58 | S7: 1141.5 | T7: 0.58 | U7: Títulos Públicos | V7: 386.61676
A8: RENTA FIJA EN DOLARES | B8: GD35 | C8: BONOS REP. ARG. U$S STEP UP V.09/07/35 | D8: 81088 | E8: PreciosInicialesEspecies | H8: CAJA VALORES | I8: 211200 | J8: 81800 | K8: 0.70045909 | L8: 82400 | N8: PrecioTenenciasIniciales | P8: 566.73652 | Q8: 172761600 | R8: 74.62 | S8: 147936.96 | T8: 74.62 | U8: Títulos Públicos | V8: 566.73652
A9: RENTA FIJA EN DOLARES | B9: TLCMO-A | C9: TELECOM ARGENT 144A 9.5% VTO. 18/07/31 | D9: 83849 | E9: PreciosInicialesEspecies | H9: CAJA VALORES | I9: 10000 | J9: 128910 | K9: 1.103865 | L9: 127400 | N9: PrecioTenenciasIniciales | P9: 1289.1 | Q9: 12891000 | R9: 5.57 | S9: 11038.65 | T9: 5.57 | U9: Obligaciones Negociables | V9: 1289.1
A10: RENTA FIJA EN DOLARES | B10: YM | C10: CXO YPF SOCIEDAD ON 8.75% VTO. 11/09/31 | D10: 83928 | E10: EspeciesGallo | H10: CAJA VALORES | I10: 12140 | J10: 126550 | K10: 1.0836565 | L10: 0 | N10: PrecioTenenciasIniciales | P10: 997.16728 | Q10: 15363170 | R10: 6.64 | S10: 13155.59 | T10: 6.64 | U10: Obligaciones Negociables | V10: 997.16728
A11: CASH | B11: PESOS | C11: PESOS | G11: Cuenta Corriente | I11: -1.0030203e+08 | J11: 1 | K11: 0.00085630694 | L11: 1 | N11: PreciosInicialesEspecies | P11: 1 | Q11: -1.0030203e+08 | R11: -43.32 | S11: -85889.32 | T11: -43.32 | V11: 1
A12: CASH | B12: DOLARES | C12: DOLARES | G12: Cuenta Corriente | I12: -199853.89 | J12: 1167.8055 | K12: 1 | L12: 1167.806 | N12: PreciosInicialesEspecies | P12: 1167.806 | Q12: -2.3339048e+08 | R12: -100.81 | S12: -199853.89 | T12: -100.81 | V12: 1167.806
A13: CASH | B13: DOLAR | C13: DOLAR | G13: Cuenta Corriente | I13: 125.71 | J13: 1148.9303 | K13: 0.98385172 | L13: 1167.806 | N13: PreciosInicialesEspecies | P13: 1167.806 | Q13: 144432.03 | R13: 0.06 | S13: 123.68 | T13: 0.06 | V13: 1167.806

Sheet Posicion Final Gallo
A1: tipo_especie | B1: Ticker | C1: especie | D1: Codigo especie | E1: Codigo Especie Origen | F1: comentario especies | G1: detalle | H1: custodia | I1: cantidad | J1: precio Tenencia Final Pesos | K1: precio Tenencia Final USD | L1: Precio Tenencia Inicial | M1: precio costo(en proceso) | N1: Origen precio costo | O1: comentarios precio costo | P1: Precio a Utilizar | Q1: importe_pesos | R1: porc_cartera_pesos | S1: importe_dolares | T1: porc_cartera_dolares | U1: Tipo Instrumento | V1: Precio Nominal
A2: TITULOS PRIVADOS LOCALES | B2: ALUA | C2: ALUA ALUAR | D2: 7 | E2: PreciosInicialesEspecies | H2: CAJA VALORES | I2: 6150 | J2: 797 | K2: 0.66789919 | L2: 893 | N2: PreciosInicialesEspecies | P2: 893 | Q2: 4901550 | R2: 1.39 | S2: 4107.58 | T2: 1.39 | U2: Acciones | V2: 893
A3: TITULOS PRIVADOS LOCALES | B3: PAMP | C3: PAMPA HOLDING | D3: 457 | E3: PreciosInicialesEspecies | H3: CAJA VALORES | I3: 4350 | J3: 3700 | K3: 3.1006575 | L3: 4385 | N3: PreciosInicialesEspecies | P3: 4385 | Q3: 16095000 | R3: 4.55 | S3: 13487.86 | T3: 4.55 | U3: Acciones | V3: 4385
A4: TITULOS PRIVADOS LOCALES | B4: TGSU2 | C4: TGSU2 TRANSP. GAS DEL SUR | D4: 617 | E4: PreciosInicialesEspecies | H4: CAJA VALORES | I4: 2881 | J4: 6750 | K4: 5.6566053 | L4: 7690 | N4: PreciosInicialesEspecies | P4: 7690 | Q4: 19446750 | R4: 5.5 | S4: 16296.68 | T4: 5.5 | U4: Acciones | V4: 7690
A5: TITULOS PRIVADOS LOCALES | B5: HARG | C5: HARG HOLCIM ARGENTINA SA | D5: 733 | E5: PreciosInicialesEspecies | H5: CAJA VALORES | I5: 625 | J5: 1730 | K5: 1.44976 | L5: 2230 | N5: PreciosInicialesEspecies | P5: 2230 | Q5: 1081250 | R5: 0.31 | S5: 906.1 | T5: 0.31 | U5: Acciones | V5: 2230
A6: TITULOS PRIVADOS LOCALES | B6: TEN | C6: CEDEAR TENARIS S.A. (ADS) | D6: 8524 | E6: PreciosInicialesEspecies | H6: CAJA VALORES | I6: 83 | J6: 40400 | K6: 33.855783 | L6: 44300 | N6: PreciosInicialesEspecies | P6: 44300 | Q6: 3353200 | R6: 0.95 | S6: 2810.03 | T6: 0.95 | U6: Cedears | V6: 44300
A7: TITULOS PRIVADOS LOCALES | B7: LOMA | C7: LOMA NEGRA | D7: 30043 | E7: PreciosInicialesEspecies | H7: CAJA VALORES | I7: 950 | J7: 3045 | K7: 2.5517579 | L7: 2980 | N7: PreciosInicialesEspecies | P7: 2980 | Q7: 2892750 | R7: 0.82 | S7: 2424.17 | T7: 0.82 | U7: Acciones | V7: 2980
A8: RENTA FIJA EN PESOS | B8: VBC10 | C8: ON BCO DE VALORES CI. 1 V.11/03/2027 | D8: 58530 | E8: PreciosInicialesEspecies | H8: CAJA VALORES | I8: 8019 | J8: 1172 | K8: 0.98215364 | L8: 0 | N8: PreciosInicialesEspecies | P8: 0 | Q8: 9398268 | R8: 2.66 | S8: 7875.89 | T8: 2.66 | U8: Obligaciones Negociables | V8: 0
A9: RENTA FIJA EN PESOS | B9: GNCXO | C9: ON GENNEIA SA REGS 8,75% V.02/09/2027 | D9: 81993 | E9: PreciosInicialesEspecies | H9: CAJA VALORES | I9: 15000 | J9: 625 | K9: 0.52376 | L9: 74000 | N9: PreciosInicialesEspecies | P9: 74000 | Q9: 9375000 | R9: 2.65 | S9: 7856.4 | T9: 2.65 | U9: Obligaciones Negociables | V9: 740
A10: RENTA FIJA EN PESOS | B10: MGC90 | C10: ON PAMPA ENERGIA SA REGS 9.5% V08/12/26 | D10: 82445 | E10: PreciosInicialesEspecies | H10: CAJA VALORES | I10: 1333 | J10: 862.5 | K10: 0.7227907 | L10: 83970 | N10: PreciosInicialesEspecies | P10: 83970 | Q10: 1149712.5 | R10: 0.33 | S10: 963.48 | T10: 0.33 | U10: Obligaciones Negociables | V10: 839.7
A11: RENTA FIJA EN PESOS | B11: YMCHO | C11: ON YPF S.A. REGS 4% V.12/02/2026 | D11: 95610 | E11: PreciosInicialesEspecies | H11: CAJA VALORES | I11: 1917 | J11: 283 | K11: 0.23715702 | L11: 46340 | N11: PreciosInicialesEspecies | P11: 46340 | Q11: 542511 | R11: 0.15 | S11: 454.63 | T11: 0.15 | U11: Obligaciones Negociables | V11: 463.4
A12: RENTA FIJA EN DOLARES | B12: AL30 | C12: BONO USD 2030 LA | D12: 5921 | E12: PreciosInicialesEspecies | H12: CAJA VALORES | I12: 31373 | J12: 814.9 | K12: 0.68289899 | L12: 88760 | N12: PreciosInicialesEspecies | P12: 88760 | Q12: 25565858 | R12: 7.23 | S12: 21424.59 | T12: 7.23 | U12: Títulos Públicos | V12: 887.6
A13: RENTA FIJA EN DOLARES | B13: AL35 | C13: BONO USD 2035 LA | D13: 5922 | E13: PreciosInicialesEspecies | H13: CAJA VALORES | I13: 31373 | J13: 823.1 | K13: 0.6897705 | L13: 81630 | N13: PreciosInicialesEspecies | P13: 81630 | Q13: 25823116 | R13: 7.3 | S13: 21640.17 | T13: 7.3 | U13: Títulos Públicos | V13: 816.3
... A21: RENTA FIJA EN DOLARES | B21: YMCHO | C21: YPF SOCIEDAD ON 8.75% VTO. 11/09/31 | D21: 95610 | E21: PreciosInicialesEspecies | H21: CAJA VALORES | I21: 12140 | J21: 1269.9 | K21: 1.064196 | L21: 46340 | N21: PreciosInicialesEspecies | P21: 46340 | Q21: 15416586 | R21: 4.36 | S21: 12919.34 | T21: 4.36 | U21: Obligaciones Negociables | V21: 463.4
A22: CASH | B22: PESOS | C22: PESOS | G22: Cuenta Corriente | I22: 30465.07 | J22: 1 | K22: 0.00083800891 | L22: 1 | N22: PreciosInicialesEspecies | P22: 1 | Q22: 30465.07 | R22: 0.01 | S22: 25.53 | T22: 0.01 | V22: 1
A23: CASH | B23: DOLARES | C23: DOLARES | G23: Cuenta Corriente | I23: 2982.42 | J23: 1193.2953 | K23: 1 | L23: 1167.806 | N23: PreciosInicialesEspecies | P23: 1167.806 | Q23: 3558907.7 | R23: 1.01 | S23: 2982.42 | T23: 1.01 | V23: 1167.806
A24: CASH | B24: DOLAR | C24: DOLAR | G24: Cuenta Corriente | I24: 2531.67 | J24: 1179.6771 | K24: 0.98858856 | L24: 1167.806 | N24: PreciosInicialesEspecies | P24: 1167.806 | Q24: 2986553.1 | R24: 0.84 | S24: 2502.78 | T24: 0.84 | V24: 1167.806

Sheet Boletos
A1: Tipo de Instrumento | B1: Concertación | C1: Liquidación | D1: Nro. Boleto | E1: Moneda | F1: Tipo Operación | G1: Cod.Instrum | H1: Instrumento Crudo | I1: InstrumentoConMoneda | J1: Cantidad | K1: Precio | L1: Tipo Cambio | M1: Bruto | N1: Interés | O1: Gastos | P1: Neto Calculado | Q1: Origen | R1: moneda emision | S1: Auditoría | T1: Precio Nominal
A2: Títulos Públicos | B2: 45681 | D2: 9826 | E2: Pesos | F2: VENTA | G2: 9314 | H2: BONO TESORO NACI CAPV.13/02/26 $ CG | I2: BONO TESORO NACI CAP V.13/02/26 $ CG - Pesos | J2: -95498084 | K2: 109.3 | L2: 1 | M2: -1.0437941e+08 | N2: 0 | O2: 0 | P2: -1.0437941e+08 | Q2: gallo-Renta Fija Pesos | R2: Pesos | S2: Origen: Gallo-Renta Fija Pesos | Fecha: 24/01/25 | Cod: 09314 | Op: VENTA | T2: 1.093
A3: Títulos Públicos | B3: 45681 | D3: 10317 | E3: Dolar MEP | F3: CPRA CABLE | G3: 5921 | H3: BONO USD 2030 LA | I3: BONO REP. ARGENTINA USD STEP UP 2030 - Dolar MEP (local) | J3: 7631 | K3: 65.684 | L3: 1155.75 | M3: 5012.346 | N3: 0 | O3: 0 | P3: 5012.346 | Q3: gallo-Renta Fija Dolares | R3: Dolar MEP (local) | S3: Origen: Gallo-Renta Fija Dolares | Fecha: 24/01/25 | Cod: 05921 | Op: CPRA CABLE | T3: 0.65684
A4: Títulos Públicos | B4: 45681 | D4: 10318 | E4: Dolar MEP | F4: VENTA USD | G4: 5921 | H4: BONO USD 2030 LA | I4: BONO REP. ARGENTINA USD STEP UP 2030 - Dolar MEP (local) | J4: -7631 | K4: 60.935 | L4: 1155.75 | M4: -4649.9499 | N4: 0 | O4: 0 | P4: -4649.9499 | Q4: gallo-Renta Fija Dolares | R4: Dolar MEP (local) | S4: Origen: Gallo-Renta Fija Dolares | Fecha: 24/01/25 | Cod: 05921 | Op: VENTA USD | T4: 0.60935
A5: Títulos Públicos | B5: 45684 | D5: 10328 | E5: Dolar MEP | F5: COMPRA | G5: 81088 | H5: BONOS REP. ARG. U$SSTEP UP V.09/07/35 | I5: BONOS REP. ARG. U$S STEP UP V.09/07/35 - Dolar Cable (exterior) | J5: 2469 | K5: 66.342 | L5: 1162.22 | M5: 1637.984 | N5: 0 | O5: 0 | P5: 1637.984 | Q5: gallo-Renta Fija Dolares | R5: Dolar Cable (exterior) | S5: Origen: Gallo-Renta Fija Dolares | Fecha: 27/01/25 | Cod: 81088 | Op: COMPRA | T5: 0.66342
A6: Títulos Públicos | B6: 45706 | D6: 19864 | E6: Dolar MEP | F6: COMPRA USD | G6: 9234 | H6: BOPREAL S. 1 AVTO31/10/27 U$S CG | I6: BOPREAL S. 1 A VTO31/10/27 U$S CG - Dolar MEP (local) | J6: 40000 | K6: 96.641 | L6: 1203.16 | M6: 38656.4 | N6: 0 | O6: 0 | P6: 38656.4 | Q6: gallo-Renta Fija Dolares | R6: Dolar MEP (local) | S6: Origen: Gallo-Renta Fija Dolares | Fecha: 18/02/25 | Cod: 09234 | Op: COMPRA USD | T6: 0.96641
A7: Títulos Públicos | B7: 45713 | D7: 22758 | E7: Dolar MEP | F7: VENTA USD | G7: 9234 | H7: BOPREAL S. 1 AVTO31/10/27 U$S CG | I7: BOPREAL S. 1 A VTO31/10/27 U$S CG - Dolar MEP (local) | J7: -11513 | K7: 98.178 | L7: 1211.96 | M7: -11303.233 | N7: 0 | O7: 0 | P7: -11303.233 | Q7: gallo-Renta Fija Dolares | R7: Dolar MEP (local) | S7: Origen: Gallo-Renta Fija Dolares | Fecha: 25/02/25 | Cod: 09234 | Op: VENTA USD | T7: 0.98178
A8: Títulos Públicos | B8: 45721 | D8: 24990 | E8: Dolar MEP | F8: COMPRA USD | G8: 9234 | H8: BOPREAL S. 1 AVTO31/10/27 U$S CG | I8: BOPREAL S. 1 A VTO31/10/27 U$S CG - Dolar MEP (local) | J8: 50000 | K8: 97.243 | L8: 1235.31 | M8: 48621.5 | N8: 0 | O8: 0 | P8: 48621.5 | Q8: gallo-Renta Fija Dolares | R8: Dolar MEP (local) | S8: Origen: Gallo-Renta Fija Dolares | Fecha: 05/03/25 | Cod: 09234 | Op: COMPRA USD | T8: 0.97243
A9: Títulos Públicos | B9: 45736 | D9: 32210 | E9: Dolar MEP | F9: VENTA | G9: 9234 | H9: BOPREAL S. 1 AVTO31/10/27 U$S CG | I9: BOPREAL S. 1 A VTO31/10/27 U$S CG - Dolar MEP (local) | J9: -150000 | K9: 98.484 | L9: 1287.59 | M9: -147726 | N9: 0 | O9: 0 | P9: -147726 | Q9: gallo-Renta Fija Dolares | R9: Dolar MEP (local) | S9: Origen: Gallo-Renta Fija Dolares | Fecha: 20/03/25 | Cod: 09234 | Op: VENTA | T9: 0.98484
A10: Títulos Públicos | B10: 45748 | D10: 36434 | E10: Dolar MEP | F10: VENTA USD | G10: 9234 | H10: BOPREAL S. 1 AVTO31/10/27 U$S CG | I10: BOPREAL S. 1 A VTO31/10/27 U$S CG - Dolar MEP (local) | J10: -139860 | K10: 98.453 | L10: 1314.47 | M10: -137696.37 | N10: 0 | O10: 0 | P10: -137696.37 | Q10: gallo-Renta Fija Dolares | R10: Dolar MEP (local) | S10: Origen: Gallo-Renta Fija Dolares | Fecha: 01/04/25 | Cod: 09234 | Op: VENTA USD | T10: 0.98453
A11: Títulos Públicos | B11: 45758 | D11: 41129 | E11: Dolar MEP | F11: COMPRA USD | G11: 9234 | H11: BOPREAL S. 1 AVTO31/10/27 U$S CG | I11: BOPREAL S. 1 A VTO31/10/27 U$S CG - Dolar MEP (local) | J11: 17899 | K11: 97.243 | L11: 1333.33 | M11: 17405.525 | N11: 0 | O11: 0 | P11: 17405.525 | Q11: gallo-Renta Fija Dolares | R11: Dolar MEP (local) | S11: Origen: Gallo-Renta Fija Dolares | Fecha: 11/04/25 | Cod: 09234 | Op: COMPRA USD | T11: 0.97243
A12: Títulos Públicos | B12: 45758 | D12: 41194 | E12: Dolar MEP | F12: COMPRA USD | G12: 9234 | H12: BOPREAL S. 1 AVTO31/10/27 U$S CG | I12: BOPREAL S. 1 A VTO31/10/27 U$S CG - Dolar MEP (local) | J12: 32101 | K12: 97.242 | L12: 1333.33 | M12: 31215.654 | N12: 0 | O12: 0 | P12: 31215.654 | Q12: gallo-Renta Fija Dolares | R12: Dolar MEP (local) | S12: Origen: Gallo-Renta Fija Dolares | Fecha: 11/04/25 | Cod: 09234 | Op: COMPRA USD | T12: 0.97242
A13: Títulos Públicos | B13: 45761 | D13: 42082 | E13: Dolar MEP | F13: VENTA USD | G13: 9234 | H13: BOPREAL S. 1 AVTO31/10/27 U$S CG | I13: BOPREAL S. 1 A VTO31/10/27 U$S CG - Dolar MEP (local) | J13: -23664 | K13: 97.755 | L13: 1253.4 | M13: -23132.743 | N13: 0 | O13: 0 | P13: -23132.743 | Q13: gallo-Renta Fija Dolares | R13: Dolar MEP (local) | S13: Origen: Gallo-Renta Fija Dolares | Fecha: 14/04/25 | Cod: 09234 | Op: VENTA USD | T13: 0.97755
A14: Títulos Públicos | B14: 45768 | D14: 43617 | E14: Dolar MEP | F14: VENTA USD | G14: 9234 | H14: BOPREAL S. 1 AVTO31/10/27 U$S CG | I14: BOPREAL S. 1 A VTO31/10/27 U$S CG - Dolar MEP (local) | J14: -23296 | K14: 98.952 | L14: 1122.08 | M14: -23051.858 | N14: 0 | O14: 0 | P14: -23051.858 | Q14: gallo-Renta Fija Dolares | R14: Dolar MEP (local) | S14: Origen: Gallo-Renta Fija Dolares | Fecha: 21/04/25 | Cod: 09234 | Op: VENTA USD | T14: 0.98952
A15: Títulos Públicos | B15: 45861 | C15: 24/7/2025 | D15: 87737 | E15: Dolar ME | F15: Compra Contado | G15: 5921 | H15: BONO REP. ARGENT | I15: BONO REP. ARGENTINA USD STEP UP 2030 - Dolar MEP (local) | J15: 17044 | K15: 0.5867 | L15: 1264.65 | M15: 99.997148 | N15: 0 | O15: 0 | P15: 99.997148 | Q15: Visual | R15: Dolar MEP (local) | S15: Origen: Visual | Fecha: 23/7/2025 | Cod: 5921 | Op: Compra Contado | T15: 0.005867
A16: Títulos Públicos | B16: 45861 | C16: 24/7/2025 | D16: 87738 | E16: Dolar ME | F16: Compra Contado | G16: 81086 | H16: BONOS REP. ARG. | I16: BONOS REP. ARG. U$S STEP UP V.09/07/30 - Dolar Cable (exterior) | J16: 19884 | K16: 0.6035 | L16: 1264.65 | M16: 119.99994 | N16: 0 | O16: 0 | P16: 119.99994 | Q16: Visual | R16: Dolar Cable (exterior) | S16: Origen: Visual | Fecha: 23/7/2025 | Cod: 81086 | Op: Compra Contado | T16: 0.006035
A17: Títulos Públicos | B17: 45862 | C17: 25/7/2025 | D17: 88405 | E17: Dolar Cabl | F17: Compra Contado | G17: 81086 | H17: BONOS REP. ARG. | I17: BONOS REP. ARG. U$S STEP UP V.09/07/30 - Dolar Cable (exterior) | J17: 11477 | K17: 0.6099 | L17: 1272.91 | M17: 69.998223 | N17: 0 | O17: 0 | P17: 69.998223 | Q17: Visual | R17: Dolar Cable (exterior) | S17: Origen: Visual | Fecha: 24/7/2025 | Cod: 81086 | Op: Compra Contado | T17: 0.006099
A18: Títulos Públicos | B18: 45863 | C18: 28/7/2025 | D18: 88993 | E18: Pesos | F18: Compra Contado | G18: 9235 | H18: BOPREAL S. 1 B VT | I18: BOPREAL S. 1 B VTO31/10/27 U$S CG - Dolar MEP (local) | J18: 10519 | K18: 1277.3276 | L18: 1 | M18: 134362.09 | N18: 0 | O18: 34934.14 | P18: 169296.23 | Q18: Visual | R18: Dolar MEP (local) | S18: Origen: Visual | Fecha: 25/7/2025 | Cod: 9235 | Op: Compra Contado | T18: 12.773276
A19: Títulos Públicos | B19: 45863 | C19: 28/7/2025 | D19: 88994 | E19: Pesos | F19: Venta Contado | G19: 9247 | H19: BOPREAL S.3 VTO3 | I19: BOPREAL S.3 VTO31/05/26 U$S CG - Dolar MEP (local) | J19: -10400 | K19: 1292 | L19: 1 | M19: -134368 | N19: 0 | O19: -34935.68 | P19: -99432.32 | Q19: Visual | R19: Dolar MEP (local) | S19: Origen: Visual | Fecha: 25/7/2025 | Cod: 9247 | Op: Venta Contado | T19: 12.92
A20: Títulos Públicos | B20: 45992 | C20: 1/12/2025 | D20: 160497 | E20: Dolar ME | F20: Venta Contado | G20: 5921 | H20: BONO REP. ARGENT | I20: BONO REP. ARGENTINA USD STEP UP 2030 - Dolar MEP (local) | J20: -5544 | K20: 0.6474 | L20: 1475.23 | M20: -35.891856 | N20: 0 | O20: 8.97 | P20: -44.861856 | Q20: Visual | R20: Dolar MEP (local) | S20: Origen: Visual | Fecha: 1/12/2025 | Cod: 5921 | Op: Venta Contado | T20: 0.006474
A21: Títulos Públicos | B21: 45992 | C21: 1/12/2025 | D21: 160496 | E21: Dolar Cabl | F21: Compra Contado | G21: 5921 | H21: BONO REP. ARGENT | I21: BONO REP. ARGENTINA USD STEP UP 2030 - Dolar MEP (local) | J21: 5544 | K21: 0.6313 | L21: 1475.23 | M21: 34.999272 | N21: 0 | O21: 0 | P21: 34.999272 | Q21: Visual | R21: Dolar MEP (local) | S21: Origen: Visual | Fecha: 1/12/2025 | Cod: 5921 | Op: Compra Contado | T21: 0.006313
A22: Títulos Públicos | B22: 45992 | C22: 2/12/2025 | D22: 160848 | E22: Pesos | F22: Compra Contado | G22: 5922 | H22: BONO REP. ARGENT | I22: BONO REP. ARGENTINA USD STEP UP 2035 - Dolar MEP (local) | J22: 549 | K22: 1092.8 | L22: 1 | M22: 5999.472 | N22: 0 | O22: 1559.86 | P22: 7559.332 | Q22: Visual | R22: Dolar MEP (local) | S22: Origen: Visual | Fecha: 1/12/2025 | Cod: 5922 | Op: Compra Contado | T22: 10.928

Sheet Cauciones Tomadoras
A1: Concertación | B1: Plazo | C1: Liquidación | D1: Operación | E1: Boleto | F1: Contado | G1: Futuro | H1: Tipo de Cambio | I1: Tasa (%) | J1: Interés Bruto | K1: Interés Devengado | L1: Aranceles | M1: Derechos | N1: Costo Financiero | O1: Moneda | P1: Origen | Q1: Auditoría
A2: 45656 | B2: 3 | C2: 45659 | D2: TOM CAU TER | E2: 136345 | F2: -99974060 | G2: -1.0026987e+08 | H2: 1 | J2: -295813.66 | K2: -295813.66 | L2: -32151.54 | M2: 0 | N2: -327965.2 | O2: Pesos | P2: Gallo-Cauciones Pesos | Q2: Origen: Gallo-Cauciones Pesos
A3: 45656 | B3: 3 | C3: 45659 | D3: TOM CAU TER | E3: 136007 | F3: -199825.93 | G3: -199834.14 | H3: 1167.806 | J3: -8.21 | K3: -8.21 | L3: -19.75 | M3: 0 | N3: -27.96 | O3: Dolar MEP | P3: Gallo-Cauciones Dolares | Q3: Origen: Gallo-Cauciones Dolares
A4: 45659 | B4: 1 | C4: 45660 | D4: TOM CAU TER | E4: 421 | F4: -1.0030203e+08 | G4: -1.0039642e+08 | H4: 1 | J4: -94393.82 | K4: -94393.82 | L4: -10730.66 | M4: 0 | N4: -105124.48 | O4: Pesos | P4: Gallo-Cauciones Pesos | Q4: Origen: Gallo-Cauciones Pesos
A5: 45659 | B5: 1 | C5: 45660 | D5: TOM CAU TER | E5: 419 | F5: -199853.89 | G5: -199856.57 | H5: 1167.806 | J5: -2.68 | K5: -2.68 | L5: -6.58 | M5: 0 | N5: -9.26 | O5: Dolar MEP | P5: Gallo-Cauciones Dolares | Q5: Origen: Gallo-Cauciones Dolares
A6: 45660 | B6: 3 | C6: 45663 | D6: TOM CAU TER | E6: 1007 | F6: -1.0040715e+08 | G6: -1.0066958e+08 | H6: 1 | J6: -262434.03 | K6: -262434.03 | L6: -32279.7 | M6: 0 | N6: -294713.73 | O6: Pesos | P6: Gallo-Cauciones Pesos | Q6: Origen: Gallo-Cauciones Pesos
A7: 45660 | B7: 3 | C7: 45663 | D7: TOM CAU TER | E7: 1005 | F7: -199863.15 | G7: -199871.2 | H7: 1167.806 | J7: -8.05 | K7: -8.05 | L7: -19.75 | M7: 0 | N7: -27.8 | O7: Dolar MEP | P7: Gallo-Cauciones Dolares | Q7: Origen: Gallo-Cauciones Dolares
A8: 45663 | B8: 4 | C8: 45667 | D8: TOM CAU TER | E8: 1561 | F8: -1.0070186e+08 | G8: -1.0104364e+08 | H8: 1 | J8: -341779.37 | K8: -341779.37 | L8: -43199.48 | M8: 0 | N8: -384978.85 | O8: Pesos | P8: Gallo-Cauciones Pesos | Q8: Origen: Gallo-Cauciones Pesos
A9: 45663 | B9: 1 | C9: 45664 | D9: TOM CAU TER | E9: 1559 | F9: -199890.95 | G9: -199893.63 | H9: 1167.806 | J9: -2.68 | K9: -2.68 | L9: -6.58 | M9: 0 | N9: -9.26 | O9: Dolar MEP | P9: Gallo-Cauciones Dolares | Q9: Origen: Gallo-Cauciones Dolares
A10: 45664 | B10: 1 | C10: 45665 | D10: TOM CAU TER | E10: 2137 | F10: -199900.21 | G10: -199902.4 | H10: 1167.806 | J10: -2.19 | K10: -2.19 | L10: -6.58 | M10: 0 | N10: -8.77 | O10: Dolar MEP | P10: Gallo-Cauciones Dolares | Q10: Origen: Gallo-Cauciones Dolares
A11: 45665 | B11: 1 | C11: 45666 | D11: TOM CAU TER | E11: 2724 | F11: -199908.98 | G11: -199911.11 | H11: 1167.806 | J11: -2.13 | K11: -2.13 | L11: -6.58 | M11: 0 | N11: -8.71 | O11: Dolar MEP | P11: Gallo-Cauciones Dolares | Q11: Origen: Gallo-Cauciones Dolares
A12: 45666 | B12: 1 | C12: 45667 | D12: TOM CAU TER | E12: 3258 | F12: -199917.69 | G12: -199919.78 | H12: 1167.806 | J12: -2.09 | K12: -2.09 | L12: -6.58 | M12: 0 | N12: -8.67 | O12: Dolar MEP | P12: Gallo-Cauciones Dolares | Q12: Origen: Gallo-Cauciones Dolares
A13: 45667 | B13: 3 | C13: 45670 | D13: TOM CAU TER | E13: 3942 | F13: -1.0108684e+08 | G13: -1.0132613e+08 | H13: 1 | J13: -239285.02 | K13: -239285.02 | L13: -32490.22 | M13: 0 | N13: -271775.24 | O13: Pesos | P13: Gallo-Cauciones Pesos | Q13: Origen: Gallo-Cauciones Pesos
... A57: 45769 | B57: 1 | C57: 45770 | D57: TOM CAU TER | E57: 45476 | F57: -387.81 | G57: -387.83 | H57: 1167.806 | J57: -0.02 | K57: -0.02 | L57: 0 | M57: 0 | N57: -0.02 | O57: Dolar MEP | P57: Gallo-Cauciones Dolares | Q57: Origen: Gallo-Cauciones Dolares

Sheet Cauciones Colocadoras
A1: Concertación | B1: Plazo | C1: Liquidación | D1: Operación | E1: Boleto | F1: Contado | G1: Futuro | H1: Tipo de Cambio | I1: Tasa (%) | J1: Interés Bruto | K1: Interés Devengado | L1: Aranceles | M1: Derechos | N1: Costo Financiero | O1: Moneda | P1: Origen | Q1: Auditoría
A2: 45748 | B2: 2 | C2: 45750 | D2: COL CAU TER | E2: 37507 | F2: 132513.29 | G2: 132557.58 | H2: 1167.806 | J2: 44.29 | K2: 44.29 | L2: 1.61 | M2: 0 | N2: 42.68 | O2: Dolar MEP | P2: Gallo-Cauciones Dolares | Q2: Origen: Gallo-Cauciones Dolares
A3: 45748 | B3: 2 | C3: 45750 | D3: COL CAU TER | E3: 37508 | F3: 5183.43 | G3: 5185.16 | H3: 1167.806 | J3: 1.73 | K3: 1.73 | L3: 0.05 | M3: 0 | N3: 1.68 | O3: Dolar MEP | P3: Gallo-Cauciones Dolares | Q3: Origen: Gallo-Cauciones Dolares

Sheet Rentas y Dividendos Gallo
A1: Tipo de Instrumento | B1: Concertación | C1: Liquidación | D1: Nro. Boleto | E1: Moneda | F1: Tipo Operación | G1: Cod.Instrum | H1: Instrumento Crudo | I1: InstrumentoConMoneda | J1: Cantidad | K1: Precio | L1: Tipo Cambio | M1: Bruto | N1: Interés | O1: Gastos | P1: Costo | Q1: Neto Calculado | R1: Origen | S1: moneda emision | T1: Auditoría
A2: Títulos Públicos | B2: 45667 | D2: 2018 | E2: Dolar MEP | F2: RENTA | G2: 81086 | H2: BONOS REP. ARG. U$SSTEP UP V.09/07/30 | I2: BONOS REP. ARG. U$S STEP UP V.09/07/30 - Dolar Cable (exterior) | J2: 0 | K2: 0 | L2: 1164.01 | M2: 5.4 | N2: 0 | O2: 0.48 | P2: 0 | Q2: -5.88 | R2: Gallo-Renta Fija Dolares | S2: Dolar Cable (exterior) | T2: Origen: Gallo-Renta Fija Dolares | Operación: RENTA
A3: Títulos Públicos | B3: 45667 | D3: 2018 | E3: Dolar MEP | F3: AMORTIZACION | G3: 81086 | H3: BONOS REP. ARG. U$SSTEP UP V.09/07/30 | I3: BONOS REP. ARG. U$S STEP UP V.09/07/30 - Dolar Cable (exterior) | J3: 120 | K3: 1 | L3: 1164.01 | M3: 120 | N3: 0 | O3: 0 | P3: 0.4902 | Q3: -0.4902 | R3: Gallo-Renta Fija Dolares | S3: Dolar Cable (exterior) | T3: Origen: Gallo-Renta Fija Dolares | Operación: AMORTIZACION
A4: Títulos Públicos | B4: 45667 | D4: 1881 | E4: Dolar MEP | F4: RENTA | G4: 81088 | H4: BONOS REP. ARG. U$SSTEP UP V.09/07/35 | I4: BONOS REP. ARG. U$S STEP UP V.09/07/35 - Dolar Cable (exterior) | J4: 0 | K4: 0 | L4: 1164.01 | M4: 3.76 | N4: 0 | O4: 35.4 | P4: 0 | Q4: -39.16 | R4: Gallo-Renta Fija Dolares | S4: Dolar Cable (exterior) | T4: Origen: Gallo-Renta Fija Dolares | Operación: RENTA
A5: Obligaciones Negociables | B5: 45680 | D5: 2595 | E5: Dolar MEP | F5: RENTA | G5: 83849 | H5: TELECOM ARGENT 144A9.5% VTO. 18/07/31 | I5: TELECOM ARGENT 144A 9.5% VTO. 18/07/31 - Dolar Cable (exterior) | J5: 0 | K5: 0 | L5: 1167.35 | M5: 0.4 | N5: 0 | O5: 3.87 | P5: 0 | Q5: -4.27 | R5: Gallo-Renta Fija Dolares | S5: Dolar Cable (exterior) | T5: Origen: Gallo-Renta Fija Dolares | Operación: RENTA
A6: Títulos Públicos | B6: 45684 | D6: 2656 | E6: Dolar MEP | F6: RENTA | G6: 32804 | H6: TD PUB. PCIA. CORDOBAV.27/10/26 | I6: TD PUB.PCIA. CORDOBA 1 V.27/10/26 USD CG - Dolar MEP (local) | J6: 0 | K6: 0 | L6: 1162.22 | M6: 40.07 | N6: 0 | O6: 0.66 | P6: 0 | Q6: -40.73 | R6: Gallo-Renta Fija Dolares | S6: Dolar MEP (local) | T6: Origen: Gallo-Renta Fija Dolares | Operación: RENTA
A7: Títulos Públicos | B7: 45684 | D7: 2656 | E7: Dolar MEP | F7: AMORTIZACION | G7: 32804 | H7: TD PUB. PCIA. CORDOBAV.27/10/26 | I7: TD PUB.PCIA. CORDOBA 1 V.27/10/26 USD CG - Dolar MEP (local) | J7: 281.25 | K7: 1 | L7: 1162.22 | M7: 281.25 | N7: 0 | O7: 0 | P7: 59.0619 | Q7: -59.0619 | R7: Gallo-Renta Fija Dolares | S7: Dolar MEP (local) | T7: Origen: Gallo-Renta Fija Dolares | Operación: AMORTIZACION
A8: Títulos Públicos | B8: 45716 | D8: 3654 | E8: Dolar MEP | F8: RENTA | G8: 9247 | H8: BOPREAL S.3 VTO31/05/26U$S CG | I8: BOPREAL S.3 VTO31/05/26 U$S CG - Dolar MEP (local) | J8: 0 | K8: 0 | L8: 1228.48 | M8: 76.26 | N8: 0 | O8: 0.83 | P8: 0 | Q8: -77.09 | R8: Gallo-Renta Fija Dolares | S8: Dolar MEP (local) | T8: Origen: Gallo-Renta Fija Dolares | Operación: RENTA
A9: Obligaciones Negociables | B9: 45722 | D9: 3852 | E9: Pesos | F9: AMORTIZACION | G9: 81993 | H9: ON GENNEIA SA REGS8,75% V.02/09/2027 | I9: ON GENNEIA SA REGS 8,75% V.02/ - Dolar Cable (exterior) | J9: 1500 | K9: 1 | L9: 1 | M9: 1500 | N9: 0 | O9: 0 | P9: 10145.715 | Q9: -10145.715 | R9: Gallo-Renta Fija Pesos | S9: Dolar Cable (exterior) | T9: Origen: Gallo-Renta Fija Pesos | Operación: AMORTIZACION
A10: Obligaciones Negociables | B10: 45722 | D10: 3943 | E10: Pesos | F10: RENTA | G10: 81993 | H10: ON GENNEIA SA REGS8,75% V.02/09/2027 | I10: ON GENNEIA SA REGS 8,75% V.02/ - Dolar Cable (exterior) | J10: 0 | K10: 0 | L10: 1 | M10: 393.75 | N10: 0 | O10: 0 | P10: 0 | Q10: -393.75 | R10: Gallo-Renta Fija Pesos | S10: Dolar Cable (exterior) | T10: Origen: Gallo-Renta Fija Pesos | Operación: RENTA
A11: Obligaciones Negociables | B11: 45730 | D11: 4250 | E11: Dolar MEP | F11: RENTA | G11: 83928 | H11: YPF SOCIEDAD ON 8.75%VTO. 11/09/31 | I11: YPF SOCIEDAD ON 8.75% VTO. 11/09/31 - Dolar Cable (exterior) | J11: 0 | K11: 0 | L11: 1237.78 | M11: 0.43 | N11: 0 | O11: 4.3 | P11: 0 | Q11: -4.73 | R11: Gallo-Renta Fija Dolares | S11: Dolar Cable (exterior) | T11: Origen: Gallo-Renta Fija Dolares | Operación: RENTA
A12: Títulos Públicos | B12: 45775 | D12: 5771 | E12: Dolar MEP | F12: RENTA | G12: 32804 | H12: TD PUB. PCIA. CORDOBAV.27/10/26 | I12: TD PUB.PCIA. CORDOBA 1 V.27/10/26 USD CG - Dolar MEP (local) | J12: 0 | K12: 0 | L12: 1176.55 | M12: 35.06 | N12: 0 | O12: 0.67 | P12: 0 | Q12: -35.73 | R12: Gallo-Renta Fija Dolares | S12: Dolar MEP (local) | T12: Origen: Gallo-Renta Fija Dolares | Operación: RENTA
A13: Títulos Públicos | B13: 45775 | D13: 5771 | E13: Dolar MEP | F13: AMORTIZACION | G13: 32804 | H13: TD PUB. PCIA. CORDOBAV.27/10/26 | I13: TD PUB.PCIA. CORDOBA 1 V.27/10/26 USD CG - Dolar MEP (local) | J13: 281.25 | K13: 1 | L13: 1176.55 | M13: 281.25 | N13: 0 | O13: 0 | P13: 59.0619 | Q13: -59.0619 | R13: Gallo-Renta Fija Dolares | S13: Dolar MEP (local) | T13: Origen: Gallo-Renta Fija Dolares | Operación: AMORTIZACION
A14: Cedears | B14: 45806 | D14: 7174 | E14: Pesos | F14: DIVIDENDO | G14: 8524 | H14: CEDEAR TENARIS S.A.(ADS) | I14: CEDEAR TENARIS S.A. (ADS) - Pesos | J14: 0 | K14: 0 | L14: 1 | M14: 86.21 | N14: 0 | O14: 0 | P14: 0 | Q14: -86.21 | R14: Gallo-Tit.Privados Exentos | S14: Pesos | T14: Origen: Gallo-Tit.Privados Exentos | Operación: DIVIDENDO
A15: Títulos Públicos | B15: 45810 | C15: 2/6/2025 | D15: 205 | E15: Dolar MEP | F15: RENTA | G15: 9247 | H15: BOPREAL S.3 VTO31/05/26 U$S CG | I15: BOPREAL S.3 VTO31/05/26 U$S CG - Dolar MEP (local) | J15: 0 | K15: 1 | L15: 1183.78 | M15: 77.53 | N15: 0 | O15: 0.47 | P15: 0 | Q15: -78 | R15: Visual-Rentas Dividendos USD | S15: Dolar MEP (local) | T15: Origen: Visual-Rentas Dividendos USD | Cat: Rentas | Op: Renta
A16: Acciones | B16: 45819 | C16: 11/6/2025 | D16: 2623 | E16: Pesos | F16: DIVIDENDO EN EFECTIVO | G16: 617 | H16: TRANSPORTADORA DE GAS DEL SUR ORDS. B 1 V | I16: TRANSPORTADORA DE GAS DEL SUR ORDS. B 1 V - Pesos | J16: 0 | K16: 1 | L16: 1 | M16: 653425.95 | N16: 0 | O16: 2679.07 | P16: 0 | Q16: -656105.02 | R16: Visual-Rentas Dividendos ARS | S16: Pesos | T16: Origen: Visual-Rentas Dividendos ARS | Cat: Dividendos | Op: Dividendo en efectivo
A17: Obligaciones Negociables | B17: 45819 | C17: 11/6/2025 | D17: 2701 | E17: Dolar Cable | F17: RENTA | G17: 82445 | H17: ON PAMPA ENERGIA SA REGS 9.5% | I17: ON PAMPA ENERGIA SA REGS 9.5% - Dolar Cable (exterior) | J17: 0 | K17: 1 | L17: 1186.93 | M17: 126.53 | N17: 0 | O17: 0.77 | P17: 0 | Q17: -127.3 | R17: Visual-Rentas Dividendos USD | S17: Dolar Cable (exterior) | T17: Origen: Visual-Rentas Dividendos USD | Cat: Rentas | Op: Renta
A18: Títulos Públicos | B18: 45848 | C18: 10/7/2025 | D18: 10080 | E18: Dolar MEP | F18: AMORTIZACIÓN | G18: 5927 | H18: BONO REP ARGENTINA USD 1% 2029 | I18: BONO REP ARGENTINA USD 1% 2029 - Dolar MEP (local) | J18: 467.1 | K18: 1 | L18: 1267.87 | M18: 0 | N18: 0 | O18: 0 | P18: 0 | Q18: 467.1 | R18: Visual-Rentas Dividendos USD | S18: Dolar MEP (local) | T18: Origen: Visual-Rentas Dividendos USD | Cat: Rentas | Op: Amortización
A19: Títulos Públicos | B19: 45848 | C19: 10/7/2025 | D19: 10219 | E19: Dolar MEP | F19: RENTA | G19: 5927 | H19: BONO REP ARGENTINA USD 1% 2029 | I19: BONO REP ARGENTINA USD 1% 2029 - Dolar MEP (local) | J19: 0 | K19: 1 | L19: 1267.87 | M19: 20.95 | N19: 0 | O19: 0.06 | P19: 0 | Q19: -21.01 | R19: Visual-Rentas Dividendos USD | S19: Dolar MEP (local) | T19: Origen: Visual-Rentas Dividendos USD | Cat: Rentas | Op: Renta
A20: Títulos Públicos | B20: 45848 | C20: 10/7/2025 | D20: 10668 | E20: Dolar MEP | F20: AMORTIZACIÓN | G20: 5921 | H20: BONO REP. ARGENTINA USD STEP UP 2030 | I20: BONO REP. ARGENTINA USD STEP UP 2030 - Dolar MEP (local) | J20: 2509.84 | K20: 1 | L20: 1267.87 | M20: 0 | N20: 0 | O20: 0 | P20: 0 | Q20: 2509.84 | R20: Visual-Rentas Dividendos USD | S20: Dolar MEP (local) | T20: Origen: Visual-Rentas Dividendos USD | Cat: Rentas | Op: Amortización
A21: Títulos Públicos | B21: 45848 | C21: 10/7/2025 | D21: 10443 | E21: Dolar MEP | F21: RENTA | G21: 5921 | H21: BONO REP. ARGENTINA USD STEP UP 2030 | I21: BONO REP. ARGENTINA USD STEP UP 2030 - Dolar MEP (local) | J21: 0 | K21: 1 | L21: 1267.87 | M21: 103.22 | N21: 0 | O21: 0.31 | P21: 0 | Q21: -103.53 | R21: Visual-Rentas Dividendos USD | S21: Dolar MEP (local) | T21: Origen: Visual-Rentas Dividendos USD | Cat: Rentas | Op: Renta
A22: Títulos Públicos | B22: 45848 | C22: 10/7/2025 | D22: 11314 | E22: Dolar MEP | F22: RENTA | G22: 5922 | H22: BONO REP. ARGENTINA USD STEP UP 2035 | I22: BONO REP. ARGENTINA USD STEP UP 2035 - Dolar MEP (local) | J22: 0 | K22: 1 | L22: 1267.87 | M22: 645.12 | N22: 0 | O22: 1.94 | P22: 0 | Q22: -647.06 | R22: Visual-Rentas Dividendos USD | S22: Dolar MEP (local) | T22: Origen: Visual-Rentas Dividendos USD | Cat: Rentas | Op: Renta
A23: Títulos Públicos | B23: 45848 | C23: 10/7/2025 | D23: 12454 | E23: Dolar Cable | F23: AMORTIZACIÓN | G23: 81086 | H23: BONOS REP. ARG. U$S STEP UP V.09/07/30 | I23: BONOS REP. ARG. U$S STEP UP V.09/07/30 - Dolar Cable (exterior) | J23: 120 | K23: 1 | L23: 1267.87 | M23: 0 | N23: 0 | O23: 0 | P23: 0 | Q23: 120 | R23: Visual-Rentas Dividendos USD | S23: Dolar Cable (exterior) | T23: Origen: Visual-Rentas Dividendos USD | Cat: Rentas | Op: Amortización
A24: Títulos Públicos | B24: 45848 | C24: 10/7/2025 | D24: 12183 | E24: Dolar Cable | F24: RENTA | G24: 81086 | H24: BONOS REP. ARG. U$S STEP UP V.09/07/30 | I24: BONOS REP. ARG. U$S STEP UP V.09/07/30 - Dolar Cable (exterior) | J24: 0 | K24: 1 | L24: 1267.87 | M24: 4.94 | N24: 0 | O24: 0.01 | P24: 0 | Q24: -4.95 | R24: Visual-Rentas Dividendos USD | S24: Dolar Cable (exterior) | T24: Origen: Visual-Rentas Dividendos USD | Cat: Rentas | Op: Renta
A25: Títulos Públicos | B25: 45848 | C25: 10/7/2025 | D25: 12105 | E25: Dolar Cable | F25: RENTA | G25: 81088 | H25: BONOS REP. ARG. U$S STEP UP V.09/07/35 | I25: BONOS REP. ARG. U$S STEP UP V.09/07/35 - Dolar Cable (exterior) | J25: 0 | K25: 1 | L25: 1267.87 | M25: 4393.66 | N25: 0 | O25: 13.26 | P25: 0 | Q25: -4406.92 | R25: Visual-Rentas Dividendos USD | S25: Dolar Cable (exterior) | T25: Origen: Visual-Rentas Dividendos USD | Cat: Rentas | Op: Renta
A26: Obligaciones Negociables | B26: 45863 | C26: 25/7/2025 | D26: 17382 | E26: Dolar Cable | F26: RENTA | G26: 83849 | H26: TELECOM ARGENT 144A 9.5% VTO. 18/07/31 | I26: TELECOM ARGENT 144A 9.5% VTO. 18/07/31 - Dolar Cable (exterior) | J26: 0 | K26: 1 | L26: 1285.98 | M26: 472.13 | N26: 0 | O26: 2.87 | P26: 0 | Q26: -475 | R26: Visual-Rentas Dividendos USD | S26: Dolar Cable (exterior) | T26: Origen: Visual-Rentas Dividendos USD | Cat: Rentas | Op: Renta
... A37: Cedears | B37: 45996 | C37: 5/12/2025 | D37: 58476 | E37: Pesos | F37: DIVIDENDO EN EFECTIVO | G37: 8524 | H37: CEDEAR TENARIS S.A. (ADS) | I37: CEDEAR TENARIS S.A. (ADS) - Pesos | J37: 0 | K37: 1 | L37: 1 | M37: 63609.57 | N37: 0 | O37: 388.51 | P37: 0 | Q37: -63998.08 | R37: Visual-Rentas Dividendos ARS | S37: Pesos | T37: Origen: Visual-Rentas Dividendos ARS | Cat: Dividendos | Op: Dividendo en efectivo

Sheet Resultado Ventas ARS
A1: Origen | B1: Tipo de Instrumento | C1: Instrumento | D1: Cod.Instrum | E1: Concertación | F1: Liquidación | G1: Moneda | H1: Tipo Operación | I1: Cantidad | J1: Precio | K1: Bruto | L1: Interés | M1: Tipo de Cambio | N1: Gastos | O1: IVA | P1: Resultado | Q1: Cantidad Stock Inicial | R1: Precio Stock Inicial | S1: Costo por venta(gallo) | T1: Neto Calculado(visual) | U1: Resultado Calculado(final) | V1: Cantidad de Stock Final | W1: Precio Stock Final | X1: Explicación Q | Y1: Explicación R-U | Z1: chequeado | AA1: Precio Nominal
A2: gallo-Renta Fija Pesos | B2: Títulos Públicos | C2: BONO TESORO NACI CAP V.13/02/26 $ CG - Pesos | D2: 9314 | E2: 45681 | G2: Pesos | H2: VENTA | I2: -95498084 | J2: 109.3 | K2: -1.0437941e+08 | L2: 0 | M2: 1 | N2: 0 | O2: 0 | Q2: 95498084 | R2: 1.04661 | S2: -99949250 | T2: -1.0437941e+08 | U2: 4430156.1 | V2: 0 | W2: 0 | X2: BUSCARV(D2→Posicion Inicial Gallo col V=Precio Nominal, fallback PrecioTenenciasIniciales/PreciosInicialesEspecies) | Y2: R=Precio stock previo | S=-95498084*R2=-95498084*[stock price] | T=K2+L2=-10437940581.199999+0 | U=|T2|-|S2| | Z2: Origen: gallo-Renta Fija Pesos | Cod: 9314 | AA2: 1.093

Sheet Resultado Ventas USD
A1: Origen | B1: Tipo de Instrumento | C1: Instrumento | D1: Cod.Instrum | E1: Concertación | F1: Liquidación | G1: Moneda | H1: Tipo Operación | I1: Cantidad | J1: Precio | K1: Precio Standarizado | L1: Precio Standarizado en USD | M1: Bruto en USD | N1: Interés | O1: Tipo de Cambio | P1: Valor USD Dia | Q1: Gastos | R1: IVA | S1: Resultado | T1: Cantidad Stock Inicial | U1: Precio Stock USD | V1: Costo por venta(gallo) | W1: Neto Calculado(visual) | X1: Resultado Calculado(final) | Y1: Cantidad de Stock Final | Z1: Precio Stock Final | AA1: Explicación T-Z | AB1: Auditoría | AC1: Precio Nominal
A2: gallo-Renta Fija Dolares | B2: Títulos Públicos | C2: BONO REP. ARGENTINA USD STEP UP 2030 - Dolar MEP (local) | D2: 5921 | E2: 45681 | G2: Dolar MEP | H2: CPRA CABLE | I2: 7631 | J2: 65.684 | K2: 65.684 | L2: 65.684 | M2: 5012.346 | N2: 0 | O2: 1 | P2: 1155.75 | Q2: 0 | R2: 0 | T2: 0 | U2: 0.76005775 | V2: 0 | W2: 5012.346 | X2: 0 | Y2: 7631 | Z2: 0.65684 | AA2: T=BUSCARV(D2→Posicion Inicial Gallo col V=Precio Nominal, fallback PrecioTenenciasIniciales/PreciosInicialesEspecies) | U=PrecioPos/P2 | V=7631*U si venta | W=M-Q | X=|W|-|V| | Y=I+T | Z=Promedio | AB2: Origen: gallo-Renta Fija Dolares | Cod: 5921 | K(PrecioStd)=raw | L=K*O | AC2: 0.65684
A3: gallo-Renta Fija Dolares | B3: Títulos Públicos | C3: BONO REP. ARGENTINA USD STEP UP 2030 - Dolar MEP (local) | D3: 5921 | E3: 45681 | G3: Dolar MEP | H3: VENTA USD | I3: -7631 | J3: 60.935 | K3: 60.935 | L3: 60.935 | M3: -4649.9499 | N3: 0 | O3: 1 | P3: 1155.75 | Q3: 0 | R3: 0 | T3: 7631 | U3: 0.65684 | V3: -5012.346 | W3: -4649.9499 | X3: -362.39619 | Y3: 0 | Z3: 0 | AA3: SI D3=D2: Z2, SINO: BUSCARV(col V=Precio Nominal (Posicion Inicial Gallo), fallback PrecioTenenciasIniciales/PreciosInicialesEspecies) | U=PrecioPos/P3 | V=-7631*U si venta | W=M-Q | X=|W|-|V| | Y=I+T | Z=Promedio | AB3: Origen: gallo-Renta Fija Dolares | Cod: 5921 | K(PrecioStd)=raw | L=K*O | AC3: 0.60935
A4: Visual | B4: Títulos Públicos | C4: BONO REP. ARGENTINA USD STEP UP 2030 - Dolar MEP (local) | D4: 5921 | E4: 45861 | F4: 24/7/2025 | G4: Dolar ME | H4: Compra Contado | I4: 17044 | J4: 0.5867 | K4: 58.67 | L4: 58.67 | M4: 9999.7148 | N4: 0 | O4: 1 | P4: 1264.65 | Q4: 0 | R4: 0 | T4: 0 | U4: 0.65684 | V4: 0 | W4: 9999.7148 | X4: 0 | Y4: 17044 | Z4: 0.5867 | AA4: SI D4=D3: Z3, SINO: BUSCARV(col V=Precio Nominal (Posicion Inicial Gallo), fallback PrecioTenenciasIniciales/PreciosInicialesEspecies) | U=PrecioPos/P4 | V=17044*U si venta | W=M-Q | X=|W|-|V| | Y=I+T | Z=Promedio | AB4: Origen: Visual | Cod: 5921 | K(PrecioStd)=x100 | L=K*O | AC4: 0.5867
A5: Visual | B5: Títulos Públicos | C5: BONO REP. ARGENTINA USD STEP UP 2030 - Dolar MEP (local) | D5: 5921 | E5: 45992 | F5: 1/12/2025 | G5: Dolar Cabl | H5: Compra Contado | I5: 5544 | J5: 0.6313 | K5: 63.13 | L5: 63.13 | M5: 3499.9272 | N5: 0 | O5: 1 | P5: 1475.23 | Q5: 0 | R5: 0 | T5: 17044 | U5: 0.5867 | V5: 0 | W5: 3499.9272 | X5: 0 | Y5: 22588 | Z5: 0.59764663 | AA5: SI D5=D4: Z4, SINO: BUSCARV(col V=Precio Nominal (Posicion Inicial Gallo), fallback PrecioTenenciasIniciales/PreciosInicialesEspecies) | U=PrecioPos/P5 | V=5544*U si venta | W=M-Q | X=|W|-|V| | Y=I+T | Z=Promedio | AB5: Origen: Visual | Cod: 5921 | K(PrecioStd)=x100 | L=K*O | AC5: 0.6313
A6: Visual | B6: Títulos Públicos | C6: BONO REP. ARGENTINA USD STEP UP 2030 - Dolar MEP (local) | D6: 5921 | E6: 45992 | F6: 1/12/2025 | G6: Dolar ME | H6: Venta Contado | I6: -5544 | J6: 0.6474 | K6: 64.74 | L6: 64.74 | M6: -3589.1856 | N6: 0 | O6: 1 | P6: 1475.23 | Q6: 0.0897 | R6: 0.01557192 | T6: 22588 | U6: 0.59764663 | V6: -3313.3529 | W6: -3589.2753 | X6: 275.9224 | Y6: 17044 | Z6: 0.59764663 | AA6: SI D6=D5: Z5, SINO: BUSCARV(col V=Precio Nominal (Posicion Inicial Gallo), fallback PrecioTenenciasIniciales/PreciosInicialesEspecies) | U=PrecioPos/P6 | V=-5544*U si venta | W=M-Q | X=|W|-|V| | Y=I+T | Z=Promedio | AB6: Origen: Visual | Cod: 5921 | K(PrecioStd)=x100 | L=K*O | AC6: 0.6474
A7: Visual | B7: Títulos Públicos | C7: BONO REP. ARGENTINA USD STEP UP 2035 - Dolar MEP (local) | D7: 5922 | E7: 45992 | F7: 2/12/2025 | G7: Pesos | H7: Compra Contado | I7: 549 | J7: 1092.8 | K7: 109280 | L7: 74.076585 | M7: 406.68045 | N7: 0 | O7: 0.0006778604 | P7: 1475.23 | Q7: 15.5986 | R7: 2.707917 | T7: 0 | U7: 0.69900309 | V7: 0 | W7: 406.68045 | X7: 0 | Y7: 549 | Z7: 0.74076585 | AA7: SI D7=D6: Z6, SINO: BUSCARV(col V=Precio Nominal (Posicion Inicial Gallo), fallback PrecioTenenciasIniciales/PreciosInicialesEspecies) | U=PrecioPos/P7 | V=549*U si venta | W=M-Q | X=|W|-|V| | Y=I+T | Z=Promedio | AB7: Origen: Visual | Cod: 5922 | K(PrecioStd)=x100 | L=K*O | AC7: 0.74076585
A8: Visual | B8: Títulos Públicos | C8: BONOS REP. ARG. U$S STEP UP V.09/07/30 - Dolar Cable (exterior) | D8: 81086 | E8: 45861 | F8: 24/7/2025 | G8: Dolar ME | H8: Compra Contado | I8: 19884 | J8: 0.6035 | K8: 60.35 | L8: 60.35 | M8: 11999.994 | N8: 0 | O8: 1 | P8: 1264.65 | Q8: 0 | R8: 0 | T8: 1500 | U8: 0.30571048 | V8: 0 | W8: 11999.994 | X8: 0 | Y8: 21384 | Z8: 0.58261129 | AA8: SI D8=D7: Z7, SINO: BUSCARV(col V=Precio Nominal (Posicion Inicial Gallo), fallback PrecioTenenciasIniciales/PreciosInicialesEspecies) | U=PrecioPos/P8 | V=19884*U si venta | W=M-Q | X=|W|-|V| | Y=I+T | Z=Promedio | AB8: Origen: Visual | Cod: 81086 | K(PrecioStd)=x100 | L=K*O | AC8: 0.6035
A9: Visual | B9: Títulos Públicos | C9: BONOS REP. ARG. U$S STEP UP V.09/07/30 - Dolar Cable (exterior) | D9: 81086 | E9: 45862 | F9: 25/7/2025 | G9: Dolar Cabl | H9: Compra Contado | I9: 11477 | J9: 0.6099 | K9: 60.99 | L9: 60.99 | M9: 6999.8223 | N9: 0 | O9: 1 | P9: 1272.91 | Q9: 0 | R9: 0 | T9: 21384 | U9: 0.58261129 | V9: 0 | W9: 6999.8223 | X9: 0 | Y9: 32861 | Z9: 0.59214211 | AA9: SI D9=D8: Z8, SINO: BUSCARV(col V=Precio Nominal (Posicion Inicial Gallo), fallback PrecioTenenciasIniciales/PreciosInicialesEspecies) | U=PrecioPos/P9 | V=11477*U si venta | W=M-Q | X=|W|-|V| | Y=I+T | Z=Promedio | AB9: Origen: Visual | Cod: 81086 | K(PrecioStd)=x100 | L=K*O | AC9: 0.6099
A10: gallo-Renta Fija Dolares | B10: Títulos Públicos | C10: BONOS REP. ARG. U$S STEP UP V.09/07/35 - Dolar Cable (exterior) | D10: 81088 | E10: 45684 | G10: Dolar MEP | H10: COMPRA | I10: 2469 | J10: 66.342 | K10: 66.342 | L10: 66.342 | M10: 1637.984 | N10: 0 | O10: 1 | P10: 1162.22 | Q10: 0 | R10: 0 | T10: 211200 | U10: 0.48763274 | V10: 0 | W10: 1637.984 | X10: 0 | Y10: 213669 | Z10: 0.489664 | AA10: SI D10=D9: Z9, SINO: BUSCARV(col V=Precio Nominal (Posicion Inicial Gallo), fallback PrecioTenenciasIniciales/PreciosInicialesEspecies) | U=PrecioPos/P10 | V=2469*U si venta | W=M-Q | X=|W|-|V| | Y=I+T | Z=Promedio | AB10: Origen: gallo-Renta Fija Dolares | Cod: 81088 | K(PrecioStd)=raw | L=K*O | AC10: 0.66342
A11: gallo-Renta Fija Dolares | B11: Títulos Públicos | C11: BOPREAL S. 1 A VTO31/10/27 U$S CG - Dolar MEP (local) | D11: 9234 | E11: 45706 | G11: Dolar MEP | H11: COMPRA USD | I11: 40000 | J11: 96.641 | K11: 96.641 | L11: 96.641 | M11: 38656.4 | N11: 0 | O11: 1 | P11: 1203.16 | Q11: 0 | R11: 0 | T11: 208333 | U11: 0.80547891 | V11: 0 | W11: 38656.4 | X11: 0 | Y11: 248333 | Z11: 0.83140073 | AA11: SI D11=D10: Z10, SINO: BUSCARV(col V=Precio Nominal (Posicion Inicial Gallo), fallback PrecioTenenciasIniciales/PreciosInicialesEspecies) | U=PrecioPos/P11 | V=40000*U si venta | W=M-Q | X=|W|-|V| | Y=I+T | Z=Promedio | AB11: Origen: gallo-Renta Fija Dolares | Cod: 9234 | K(PrecioStd)=raw | L=K*O | AC11: 0.96641
A12: gallo-Renta Fija Dolares | B12: Títulos Públicos | C12: BOPREAL S. 1 A VTO31/10/27 U$S CG - Dolar MEP (local) | D12: 9234 | E12: 45713 | G12: Dolar MEP | H12: VENTA USD | I12: -11513 | J12: 98.178 | K12: 98.178 | L12: 98.178 | M12: -11303.233 | N12: 0 | O12: 1 | P12: 1211.96 | Q12: 0 | R12: 0 | T12: 248333 | U12: 0.83140073 | V12: -9571.9166 | W12: -11303.233 | X12: 1731.3166 | Y12: 236820 | Z12: 0.83140073 | AA12: SI D12=D11: Z11, SINO: BUSCARV(col V=Precio Nominal (Posicion Inicial Gallo), fallback PrecioTenenciasIniciales/PreciosInicialesEspecies) | U=PrecioPos/P12 | V=-11513*U si venta | W=M-Q | X=|W|-|V| | Y=I+T | Z=Promedio | AB12: Origen: gallo-Renta Fija Dolares | Cod: 9234 | K(PrecioStd)=raw | L=K*O | AC12: 0.98178
A13: gallo-Renta Fija Dolares | B13: Títulos Públicos | C13: BOPREAL S. 1 A VTO31/10/27 U$S CG - Dolar MEP (local) | D13: 9234 | E13: 45721 | G13: Dolar MEP | H13: COMPRA USD | I13: 50000 | J13: 97.243 | K13: 97.243 | L13: 97.243 | M13: 48621.5 | N13: 0 | O13: 1 | P13: 1235.31 | Q13: 0 | R13: 0 | T13: 236820 | U13: 0.83140073 | V13: 0 | W13: 48621.5 | X13: 0 | Y13: 286820 | Z13: 0.85598571 | AA13: SI D13=D12: Z12, SINO: BUSCARV(col V=Precio Nominal (Posicion Inicial Gallo), fallback PrecioTenenciasIniciales/PreciosInicialesEspecies) | U=PrecioPos/P13 | V=50000*U si venta | W=M-Q | X=|W|-|V| | Y=I+T | Z=Promedio | AB13: Origen: gallo-Renta Fija Dolares | Cod: 9234 | K(PrecioStd)=raw | L=K*O | AC13: 0.97243
A14: gallo-Renta Fija Dolares | B14: Títulos Públicos | C14: BOPREAL S. 1 A VTO31/10/27 U$S CG - Dolar MEP (local) | D14: 9234 | E14: 45736 | G14: Dolar MEP | H14: VENTA | I14: -150000 | J14: 98.484 | K14: 98.484 | L14: 98.484 | M14: -147726 | N14: 0 | O14: 1 | P14: 1287.59 | Q14: 0 | R14: 0 | T14: 286820 | U14: 0.85598571 | V14: -128397.86 | W14: -147726 | X14: 19328.144 | Y14: 136820 | Z14: 0.85598571 | AA14: SI D14=D13: Z13, SINO: BUSCARV(col V=Precio Nominal (Posicion Inicial Gallo), fallback PrecioTenenciasIniciales/PreciosInicialesEspecies) | U=PrecioPos/P14 | V=-150000*U si venta | W=M-Q | X=|W|-|V| | Y=I+T | Z=Promedio | AB14: Origen: gallo-Renta Fija Dolares | Cod: 9234 | K(PrecioStd)=raw | L=K*O | AC14: 0.98484
A15: gallo-Renta Fija Dolares | B15: Títulos Públicos | C15: BOPREAL S. 1 A VTO31/10/27 U$S CG - Dolar MEP (local) | D15: 9234 | E15: 45748 | G15: Dolar MEP | H15: VENTA USD | I15: -139860 | J15: 98.453 | K15: 98.453 | L15: 98.453 | M15: -137696.37 | N15: 0 | O15: 1 | P15: 1314.47 | Q15: 0 | R15: 0 | T15: 136820 | U15: 0.85598571 | V15: -119718.16 | W15: -137696.37 | X15: 17978.205 | Y15: -3040 | Z15: 0.85598571 | AA15: SI D15=D14: Z14, SINO: BUSCARV(col V=Precio Nominal (Posicion Inicial Gallo), fallback PrecioTenenciasIniciales/PreciosInicialesEspecies) | U=PrecioPos/P15 | V=-139860*U si venta | W=M-Q | X=|W|-|V| | Y=I+T | Z=Promedio | AB15: Origen: gallo-Renta Fija Dolares | Cod: 9234 | K(PrecioStd)=raw | L=K*O | AC15: 0.98453
A16: gallo-Renta Fija Dolares | B16: Títulos Públicos | C16: BOPREAL S. 1 A VTO31/10/27 U$S CG - Dolar MEP (local) | D16: 9234 | E16: 45758 | G16: Dolar MEP | H16: COMPRA USD | I16: 17899 | J16: 97.243 | K16: 97.243 | L16: 97.243 | M16: 17405.525 | N16: 0 | O16: 1 | P16: 1333.33 | Q16: 0 | R16: 0 | T16: -3040 | U16: 0.85598571 | V16: 0 | W16: 17405.525 | X16: 0 | Y16: 14859 | Z16: 0.99625332 | AA16: SI D16=D15: Z15, SINO: BUSCARV(col V=Precio Nominal (Posicion Inicial Gallo), fallback PrecioTenenciasIniciales/PreciosInicialesEspecies) | U=PrecioPos/P16 | V=17899*U si venta | W=M-Q | X=|W|-|V| | Y=I+T | Z=Promedio | AB16: Origen: gallo-Renta Fija Dolares | Cod: 9234 | K(PrecioStd)=raw | L=K*O | AC16: 0.97243
A17: gallo-Renta Fija Dolares | B17: Títulos Públicos | C17: BOPREAL S. 1 A VTO31/10/27 U$S CG - Dolar MEP (local) | D17: 9234 | E17: 45758 | G17: Dolar MEP | H17: COMPRA USD | I17: 32101 | J17: 97.242 | K17: 97.242 | L17: 97.242 | M17: 31215.654 | N17: 0 | O17: 1 | P17: 1333.33 | Q17: 0 | R17: 0 | T17: 14859 | U17: 0.99625332 | V17: 0 | W17: 31215.654 | X17: 0 | Y17: 46960 | Z17: 0.9799613 | AA17: SI D17=D16: Z16, SINO: BUSCARV(col V=Precio Nominal (Posicion Inicial Gallo), fallback PrecioTenenciasIniciales/PreciosInicialesEspecies) | U=PrecioPos/P17 | V=32101*U si venta | W=M-Q | X=|W|-|V| | Y=I+T | Z=Promedio | AB17: Origen: gallo-Renta Fija Dolares | Cod: 9234 | K(PrecioStd)=raw | L=K*O | AC17: 0.97242
A18: gallo-Renta Fija Dolares | B18: Títulos Públicos | C18: BOPREAL S. 1 A VTO31/10/27 U$S CG - Dolar MEP (local) | D18: 9234 | E18: 45761 | G18: Dolar MEP | H18: VENTA USD | I18: -23664 | J18: 97.755 | K18: 97.755 | L18: 97.755 | M18: -23132.743 | N18: 0 | O18: 1 | P18: 1253.4 | Q18: 0 | R18: 0 | T18: 46960 | U18: 0.9799613 | V18: -23189.804 | W18: -23132.743 | X18: -57.0609 | Y18: 23296 | Z18: 0.9799613 | AA18: SI D18=D17: Z17, SINO: BUSCARV(col V=Precio Nominal (Posicion Inicial Gallo), fallback PrecioTenenciasIniciales/PreciosInicialesEspecies) | U=PrecioPos/P18 | V=-23664*U si venta | W=M-Q | X=|W|-|V| | Y=I+T | Z=Promedio | AB18: Origen: gallo-Renta Fija Dolares | Cod: 9234 | K(PrecioStd)=raw | L=K*O | AC18: 0.97755
A19: gallo-Renta Fija Dolares | B19: Títulos Públicos | C19: BOPREAL S. 1 A VTO31/10/27 U$S CG - Dolar MEP (local) | D19: 9234 | E19: 45768 | G19: Dolar MEP | H19: VENTA USD | I19: -23296 | J19: 98.952 | K19: 98.952 | L19: 98.952 | M19: -23051.858 | N19: 0 | O19: 1 | P19: 1122.08 | Q19: 0 | R19: 0 | T19: 23296 | U19: 0.9799613 | V19: -22829.178 | W19: -23051.858 | X19: 222.67958 | Y19: 0 | Z19: 0 | AA19: SI D19=D18: Z18, SINO: BUSCARV(col V=Precio Nominal (Posicion Inicial Gallo), fallback PrecioTenenciasIniciales/PreciosInicialesEspecies) | U=PrecioPos/P19 | V=-23296*U si venta | W=M-Q | X=|W|-|V| | Y=I+T | Z=Promedio | AB19: Origen: gallo-Renta Fija Dolares | Cod: 9234 | K(PrecioStd)=raw | L=K*O | AC19: 0.98952
A20: Visual | B20: Títulos Públicos | C20: BOPREAL S. 1 B VTO31/10/27 U$S CG - Dolar MEP (local) | D20: 9235 | E20: 45863 | F20: 28/7/2025 | G20: Pesos | H20: Compra Contado | I20: 10519 | J20: 1277.3276 | K20: 127732.76 | L20: 99.327175 | M20: 10448.225 | N20: 0 | O20: 0.00077761707 | P20: 1285.98 | Q20: 349.3414 | R20: 60.645667 | T20: 0 | U20: 0.90691433 | V20: 0 | W20: 10448.225 | X20: 0 | Y20: 10519 | Z20: 0.99327175 | AA20: SI D20=D19: Z19, SINO: BUSCARV(col V=Precio Nominal (Posicion Inicial Gallo), fallback PrecioTenenciasIniciales/PreciosInicialesEspecies) | U=PrecioPos/P20 | V=10519*U si venta | W=M-Q | X=|W|-|V| | Y=I+T | Z=Promedio | AB20: Origen: Visual | Cod: 9235 | K(PrecioStd)=x100 | L=K*O | AC20: 0.99327175
A21: Visual | B21: Títulos Públicos | C21: BOPREAL S.3 VTO31/05/26 U$S CG - Dolar MEP (local) | D21: 9247 | E21: 45863 | F21: 28/7/2025 | G21: Pesos | H21: Venta Contado | I21: -10400 | J21: 1292 | K21: 129200 | L21: 100.46813 | M21: -10448.685 | N21: 0 | O21: 0.00077761707 | P21: 1285.98 | Q21: -349.3568 | R21: 60.64834 | T21: 10400 | U21: 0.55095705 | V21: -5729.9533 | W21: -10099.328 | X21: 4369.3749 | Y21: 0 | Z21: 0 | AA21: SI D21=D20: Z20, SINO: BUSCARV(col V=Precio Nominal (Posicion Inicial Gallo), fallback PrecioTenenciasIniciales/PreciosInicialesEspecies) | U=PrecioPos/P21 | V=-10400*U si venta | W=M-Q | X=|W|-|V| | Y=I+T | Z=Promedio | AB21: Origen: Visual | Cod: 9247 | K(PrecioStd)=x100 | L=K*O | AC21: 1.0046813

Sheet Rentas Dividendos ARS
A1: Instrumento | B1: Cod.Instrum | C1: Categoría | D1: tipo_instrumento | E1: Concertación | F1: Liquidación | G1: Nro. NDC | H1: Tipo Operación | I1: Cantidad | J1: Moneda | K1: Tipo de Cambio | L1: Gastos | M1: Importe | N1: Origen | O1: Importe Original
A2: TRANSPORTADORA DE GAS DEL SUR ORDS. B 1 V | B2: 617 | C2: Dividendos | D2: Acciones | E2: 45819 | F2: 11/6/2025 | G2: 2623 | H2: DIVIDENDO EN EFECTIVO | I2: 0 | J2: Pesos | K2: 1 | L2: 2679.07 | M2: 650746.88 | N2: Visual-Rentas Dividendos ARS | O2: 650746.88
A3: CEDEAR TENARIS S.A.(ADS) | B3: 8524 | C3: Dividendos | D3: Cedears | E3: 45806 | G3: 7174 | H3: DIVIDENDO | I3: 0 | J3: Pesos | K3: 1 | L3: 0 | M3: 86.21 | N3: Gallo-Tit.Privados Exentos | O3: 86.21
A4: CEDEAR TENARIS S.A. (ADS) | B4: 8524 | C4: Dividendos | D4: Cedears | E4: 45996 | F4: 5/12/2025 | G4: 58476 | H4: DIVIDENDO EN EFECTIVO | I4: 0 | J4: Pesos | K4: 1 | L4: 388.51 | M4: 63221.06 | N4: Visual-Rentas Dividendos ARS | O4: 63221.06
A5: ON GENNEIA SA REGS8,75% V.02/09/2027 | B5: 81993 | C5: Rentas | D5: Obligaciones Negociables | E5: 45722 | G5: 3852 | H5: AMORTIZACION | I5: 1500 | J5: Pesos | K5: 1 | L5: 10145.715 | M5: 0 | N5: Gallo-Renta Fija Pesos | ALERTA: MONEDA_EFECTIVA_ARS | O5: 0
A6: ON GENNEIA SA REGS8,75% V.02/09/2027 | B6: 81993 | C6: Rentas | D6: Obligaciones Negociables | E6: 45722 | G6: 3943 | H6: RENTA | I6: 0 | J6: Pesos | K6: 1 | L6: 0 | M6: 393.75 | N6: Gallo-Renta Fija Pesos | ALERTA: MONEDA_EFECTIVA_ARS | O6: 393.75

Sheet Rentas Dividendos USD
A1: Instrumento | B1: Cod.Instrum | C1: Categoría | D1: tipo_instrumento | E1: Concertación | F1: Liquidación | G1: Nro. NDC | H1: Tipo Operación | I1: Cantidad | J1: Moneda | K1: Tipo de Cambio | L1: Gastos | M1: Importe | N1: Origen | O1: Importe Original
A2: BONO REP. ARGENTINA USD STEP UP 2030 | B2: 5921 | C2: Rentas | D2: Títulos Públicos | E2: 45848 | F2: 10/7/2025 | G2: 10668 | H2: AMORTIZACIÓN | I2: 2509.84 | J2: Dolar MEP | K2: 1 | L2: 0 | M2: 0 | N2: Visual-Rentas Dividendos USD | O2: 0
A3: BONO REP. ARGENTINA USD STEP UP 2030 | B3: 5921 | C3: Rentas | D3: Títulos Públicos | E3: 45848 | F3: 10/7/2025 | G3: 10443 | H3: RENTA | I3: 0 | J3: Dolar MEP | K3: 1 | L3: 0.31 | M3: 102.91 | N3: Visual-Rentas Dividendos USD | O3: 102.91
A4: BONO REP. ARGENTINA USD STEP UP 2035 | B4: 5922 | C4: Rentas | D4: Títulos Públicos | E4: 45848 | F4: 10/7/2025 | G4: 11314 | H4: RENTA | I4: 0 | J4: Dolar MEP | K4: 1 | L4: 1.94 | M4: 643.18 | N4: Visual-Rentas Dividendos USD | O4: 643.18
A5: BONO REP ARGENTINA USD 1% 2029 | B5: 5927 | C5: Rentas | D5: Títulos Públicos | E5: 45848 | F5: 10/7/2025 | G5: 10080 | H5: AMORTIZACIÓN | I5: 467.1 | J5: Dolar MEP | K5: 1 | L5: 0 | M5: 0 | N5: Visual-Rentas Dividendos USD | O5: 0
A6: BONO REP ARGENTINA USD 1% 2029 | B6: 5927 | C6: Rentas | D6: Títulos Públicos | E6: 45848 | F6: 10/7/2025 | G6: 10219 | H6: RENTA | I6: 0 | J6: Dolar MEP | K6: 1 | L6: 0.06 | M6: 20.89 | N6: Visual-Rentas Dividendos USD | O6: 20.89
A7: BOPREAL S.3 VTO31/05/26U$S CG | B7: 9247 | C7: Rentas | D7: Títulos Públicos | E7: 45716 | G7: 3654 | H7: RENTA | I7: 0 | J7: Dolar MEP | K7: 1 | L7: 0.83 | M7: 75.43 | N7: Gallo-Renta Fija Dolares | O7: 75.43
A8: BOPREAL S.3 VTO31/05/26 U$S CG | B8: 9247 | C8: Rentas | D8: Títulos Públicos | E8: 45810 | F8: 2/6/2025 | G8: 205 | H8: RENTA | I8: 0 | J8: Dolar MEP | K8: 1 | L8: 0.47 | M8: 77.06 | N8: Visual-Rentas Dividendos USD | O8: 77.06
A9: TD PUB. PCIA. CORDOBAV.27/10/26 | B9: 32804 | C9: Rentas | D9: Títulos Públicos | E9: 45684 | G9: 2656 | H9: RENTA | I9: 0 | J9: Dolar MEP | K9: 1 | L9: 0.66 | M9: 39.41 | N9: Gallo-Renta Fija Dolares | O9: 39.41
A10: TD PUB. PCIA. CORDOBAV.27/10/26 | B10: 32804 | C10: Rentas | D10: Títulos Públicos | E10: 45684 | G10: 2656 | H10: AMORTIZACION | I10: 281.25 | J10: Dolar MEP | K10: 1 | L10: 59.0619 | M10: 0 | N10: Gallo-Renta Fija Dolares | O10: 0
A11: TD PUB. PCIA. CORDOBAV.27/10/26 | B11: 32804 | C11: Rentas | D11: Títulos Públicos | E11: 45775 | G11: 5771 | H11: RENTA | I11: 0 | J11: Dolar MEP | K11: 1 | L11: 0.67 | M11: 34.39 | N11: Gallo-Renta Fija Dolares | O11: 34.39
A12: TD PUB. PCIA. CORDOBAV.27/10/26 | B12: 32804 | C12: Rentas | D12: Títulos Públicos | E12: 45775 | G12: 5771 | H12: AMORTIZACION | I12: 281.25 | J12: Dolar MEP | K12: 1 | L12: 59.0619 | M12: 0 | N12: Gallo-Renta Fija Dolares | O12: 0
A13: TD PUB.PCIA. CORDOBA 1 V.27/10/26 USD CG | B13: 32804 | C13: Rentas | D13: Títulos Públicos | E13: 45866 | F13: 28/7/2025 | G13: 17475 | H13: AMORTIZACIÓN | I13: 545.87 | J13: Dolar MEP | K13: 1 | L13: 0 | M13: 0 | N13: Visual-Rentas Dividendos USD | O13: 0
A14: TD PUB.PCIA. CORDOBA 1 V.27/10/26 USD CG | B14: 32804 | C14: Rentas | D14: Títulos Públicos | E14: 45866 | F14: 28/7/2025 | G14: 17507 | H14: RENTA | I14: 0 | J14: Dolar MEP | K14: 1 | L14: 0.35 | M14: 57.64 | N14: Visual-Rentas Dividendos USD | O14: 57.64
A15: TD PUB.PCIA. CORDOBA 1 V.27/10/26 USD CG | B15: 32804 | C15: Rentas | D15: Títulos Públicos | E15: 45957 | F15: 27/10/2025 | G15: 46291 | H15: RENTA | I15: 0 | J15: Dolar MEP | K15: 1 | L15: 0.29 | M15: 48.03 | N15: Visual-Rentas Dividendos USD | O15: 48.03
A16: TD PUB.PCIA. CORDOBA 1 V.27/10/26 USD CG | B16: 32804 | C16: Rentas | D16: Títulos Públicos | E16: 45957 | F16: 27/10/2025 | G16: 46276 | H16: AMORTIZACIÓN | I16: 545.87 | J16: Dolar MEP | K16: 1 | L16: 0 | M16: 0 | N16: Visual-Rentas Dividendos USD | O16: 0
A17: ON BCO DE VALORES CI. 1 V.11/03/2027 | B17: 58530 | C17: Rentas | D17: Obligaciones Negociables | E17: 45911 | F17: 11/9/2025 | G17: 32213 | H17: RENTA | I17: 0 | J17: Dolar MEP | K17: 1 | L17: 1.82 | M17: 299.54 | N17: Visual-Rentas Dividendos USD | O17: 299.54
A18: BONOS REP. ARG. U$SSTEP UP V.09/07/30 | B18: 81086 | C18: Rentas | D18: Títulos Públicos | E18: 45667 | G18: 2018 | H18: RENTA | I18: 0 | J18: Dolar MEP | K18: 1 | L18: 0.48 | M18: 4.92 | N18: Gallo-Renta Fija Dolares | O18: 4.92
A19: BONOS REP. ARG. U$SSTEP UP V.09/07/30 | B19: 81086 | C19: Rentas | D19: Títulos Públicos | E19: 45667 | G19: 2018 | H19: AMORTIZACION | I19: 120 | J19: Dolar MEP | K19: 1 | L19: 0.4902 | M19: 0 | N19: Gallo-Renta Fija Dolares | O19: 0
A20: BONOS REP. ARG. U$S STEP UP V.09/07/30 | B20: 81086 | C20: Rentas | D20: Títulos Públicos | E20: 45848 | F20: 10/7/2025 | G20: 12454 | H20: AMORTIZACIÓN | I20: 120 | J20: Dolar Cable | K20: 1 | L20: 0 | M20: 0 | N20: Visual-Rentas Dividendos USD | O20: 0
A21: BONOS REP. ARG. U$S STEP UP V.09/07/30 | B21: 81086 | C21: Rentas | D21: Títulos Públicos | E21: 45848 | F21: 10/7/2025 | G21: 12183 | H21: RENTA | I21: 0 | J21: Dolar Cable | K21: 1 | L21: 0.01 | M21: 4.93 | N21: Visual-Rentas Dividendos USD | O21: 4.93
A22: BONOS REP. ARG. U$SSTEP UP V.09/07/35 | B22: 81088 | C22: Rentas | D22: Títulos Públicos | E22: 45667 | G22: 1881 | H22: RENTA | I22: 0 | J22: Dolar MEP | K22: 1 | L22: 35.4 | M22: 31.64 | N22: Gallo-Renta Fija Dolares | O22: -31.64
A23: BONOS REP. ARG. U$S STEP UP V.09/07/35 | B23: 81088 | C23: Rentas | D23: Títulos Públicos | E23: 45848 | F23: 10/7/2025 | G23: 12105 | H23: RENTA | I23: 0 | J23: Dolar Cable | K23: 1 | L23: 13.26 | M23: 4380.4 | N23: Visual-Rentas Dividendos USD | O23: 4380.4
A24: ON GENNEIA SA REGS 8,75% V.02/ | B24: 81993 | C24: Rentas | D24: Obligaciones Negociables | E24: 45903 | F24: 3/9/2025 | G24: 28406 | H24: RENTA | I24: 0 | J24: Dolar Cable | K24: 1 | L24: 1.98 | M24: 324.16 | N24: Visual-Rentas Dividendos USD | O24: 324.16
A25: ON GENNEIA SA REGS 8,75% V.02/ | B25: 81993 | C25: Rentas | D25: Obligaciones Negociables | E25: 45903 | F25: 3/9/2025 | G25: 28387 | H25: AMORTIZACIÓN | I25: 1500 | J25: Dolar Cable | K25: 1 | L25: 0 | M25: 0 | N25: Visual-Rentas Dividendos USD | O25: 0
A26: ON PAMPA ENERGIA SA REGS 9.5% | B26: 82445 | C26: Rentas | D26: Obligaciones Negociables | E26: 45819 | F26: 11/6/2025 | G26: 2701 | H26: RENTA | I26: 0 | J26: Dolar Cable | K26: 1 | L26: 0.77 | M26: 125.76 | N26: Visual-Rentas Dividendos USD | O26: 125.76
A27: TELECOM ARGENT 144A9.5% VTO. 18/07/31 | B27: 83849 | C27: Rentas | D27: Obligaciones Negociables | E27: 45680 | G27: 2595 | H27: RENTA | I27: 0 | J27: Dolar MEP | K27: 1 | L27: 3.87 | M27: 3.47 | N27: Gallo-Renta Fija Dolares | O27: -3.47
A28: TELECOM ARGENT 144A 9.5% VTO. 18/07/31 | B28: 83849 | C28: Rentas | D28: Obligaciones Negociables | E28: 45863 | F28: 25/7/2025 | G28: 17382 | H28: RENTA | I28: 0 | J28: Dolar Cable | K28: 1 | L28: 2.87 | M28: 469.26 | N28: Visual-Rentas Dividendos USD | O28: 469.26
A29: YPF SOCIEDAD ON 8.75%VTO. 11/09/31 | B29: 83928 | C29: Rentas | D29: Obligaciones Negociables | E29: 45730 | G29: 4250 | H29: RENTA | I29: 0 | J29: Dolar MEP | K29: 1 | L29: 4.3 | M29: 3.87 | N29: Gallo-Renta Fija Dolares | O29: -3.87
A30: YPF SOCIEDAD ON 8.75% VTO. 11/09/31 | B30: 83928 | C30: Rentas | D30: Obligaciones Negociables | E30: 45912 | F30: 12/9/2025 | G30: 32485 | H30: RENTA | I30: 0 | J30: Dolar Cable | K30: 1 | L30: 3.21 | M30: 524.7 | N30: Visual-Rentas Dividendos USD | O30: 524.7
A31: ON YPF S.A. REGS 4% V.12/02/2026 | B31: 95610 | C31: Rentas | D31: Obligaciones Negociables | E31: 45882 | F31: 13/8/2025 | G31: 21926 | H31: RENTA | I31: 0 | J31: Dolar Cable | K31: 1 | L31: 0.18 | M31: 29.49 | N31: Visual-Rentas Dividendos USD | O31: 29.49
A32: ON YPF S.A. REGS 4% V.12/02/2026 | B32: 95610 | C32: Rentas | D32: Obligaciones Negociables | E32: 45882 | F32: 13/8/2025 | G32: 21900 | H32: AMORTIZACIÓN | I32: 442.3 | J32: Dolar Cable | K32: 1 | L32: 0 | M32: 0 | N32: Visual-Rentas Dividendos USD | O32: 0

Sheet FCI
A1: Concertación | B1: Liquidación | C1: Moneda | D1: Tipo Operación | E1: Cantidad | F1: Tipo de Cambio | G1: Precio | H1: Bruto | I1: Gastos | J1: IVA | K1: Resultado

Sheet Opciones
A1: Instrumento | B1: Concertación | C1: Liquidación | D1: Moneda | E1: Tipo Operación | F1: Cantidad | G1: Tipo de Cambio | H1: Precio | I1: Bruto | J1: Gastos | K1: IVA | L1: Resultado

Sheet Futuros
A1: Moneda | B1: Instrumento | C1: Tipo de Liquidación | D1: Total

Sheet Pagare_CPD
A1: Instrumento | B1: Concertación | C1: Liquidación | D1: Vencimiento | E1: Tipo Operación | F1: Abreviatura | G1: Moneda | H1: Tipo Cambio | I1: Valor Nominal | J1: Tasa | K1: Valor Final | L1: Gastos | M1: Neto | N1: Origen

Sheet Resumen
A1: Moneda | B1: Ventas | C1: FCI | D1: Opciones | E1: Rentas | F1: Dividendos | G1: Pagare/CPD | H1: Futuros | I1: Cau (Tom) | J1: Cau (Col) | K1: Total
A2: ARS | B2: 4430156.1 | C2: 0 | D2: 0 | E2: 393.75 | F2: 714054.15 | G2: 0 | H2: 0 | I2: -2469126.5 | J2: 0 | K2: 2675477.5
A3: USD | B3: 43486.185 | C3: 0 | D3: 0 | E3: 7301.08 | F3: 0 | G3: 0 | H3: 0 | I3: -1976.48 | J3: 44.36 | K3: 48855.145

Sheet Posicion Titulos
A1: Instrumento | B1: Código | C1: Ticker | D1: Cantidad | E1: Importe | F1: Moneda | G1: Origen
A2: BONO REP ARGENTINA USD 1% 2029 | B2: 5927 | C2: AL29 | D2: 4671 | E2: 4796649.9 | F2: Pesos | G2: Visual-Posicion Titulos
A3: BONO REP. ARGENTINA USD STEP UP 2035 | B3: 5922 | C3: AL35 | D3: 549 | E3: 598410 | F3: Pesos | G3: Visual-Posicion Titulos
A4: TD PUB.PCIA. CORDOBA 1 V.27/10/26 USD CG | B4: 32804 | C4: CO26 | D4: 17468 | E4: 3426348.2 | F4: Pesos | G4: Visual-Posicion Titulos
A5: CEDEAR TENARIS S.A. (ADS) | B5: 8524 | C5: TEN | D5: 83 | E5: 5063000 | F5: Pesos | G5: Visual-Posicion Titulos

Sheet EspeciesVisual
A1: Descripción | B1: Tipo de Especie | C1: Código | D1: Fecha de Emisión | E1: Fecha de Vencimiento | F1: Mercado | G1: Moneda de Emisión | H1: Abreviatura | I1: Lámina Mínima | J1: Moneda (Reuters / Bloomberg) | K1: Código SISCEN | L1: ISIN Code | M1: Moneda (Reuters / Bloomberg) | N1: Moneda de Emisión | O1: Tipo de Instrumento | Q1: InstrumentoConMoneda | R1: Tipo de Especie
G2: Descripción | J2: Símbolo | M2: Descripción | N2: Símbolo
A3: *MAV160601050 | B3: Cheques Diferidos | D3: 31/5/2025 | E3: 31/5/2025 | F3: MAV | G3: Pesos | H3: *MAV160601050 | N3: $ | O3: Especie (CPD/Pagaré/FCE) | Q3: *MAV160601050 - Pesos | R3: Cheques Diferidos
A4: *MAV250700791 | B4: Cheques Diferidos | D4: 31/5/2025 | E4: 31/5/2025 | F4: MAV | G4: Pesos | H4: *MAV250700791 | N4: $ | O4: Especie (CPD/Pagaré/FCE) | Q4: *MAV250700791 - Pesos | R4: Cheques Diferidos
A5: *MAV010800659 | B5: Cheques Diferidos | D5: 31/5/2025 | E5: 31/5/2025 | F5: MAV | G5: Pesos | H5: *MAV010800659 | N5: $ | O5: Especie (CPD/Pagaré/FCE) | Q5: *MAV010800659 - Pesos | R5: Cheques Diferidos
A6: *MAV100700897 | B6: Cheques Diferidos | D6: 31/5/2025 | E6: 31/5/2025 | F6: MAV | G6: Pesos | H6: *MAV100700897 | N6: $ | O6: Especie (CPD/Pagaré/FCE) | Q6: *MAV100700897 - Pesos | R6: Cheques Diferidos
A7: *MAV300700682 | B7: Cheques Diferidos | D7: 31/5/2025 | E7: 31/5/2025 | F7: MAV | G7: Pesos | H7: *MAV300700682 | N7: $ | O7: Especie (CPD/Pagaré/FCE) | Q7: *MAV300700682 - Pesos | R7: Cheques Diferidos
A8: *MAV190600710 | B8: Cheques Diferidos | D8: 31/5/2025 | E8: 31/5/2025 | F8: MAV | G8: Pesos | H8: *MAV190600710 | N8: $ | O8: Especie (CPD/Pagaré/FCE) | Q8: *MAV190600710 - Pesos | R8: Cheques Diferidos
A9: *MAV270600865 | B9: Cheques Diferidos | D9: 31/5/2025 | E9: 31/5/2025 | F9: MAV | G9: Pesos | H9: *MAV270600865 | N9: $ | O9: Especie (CPD/Pagaré/FCE) | Q9: *MAV270600865 - Pesos | R9: Cheques Diferidos
A10: *MAV060700589 | B10: Cheques Diferidos | D10: 31/5/2025 | E10: 31/5/2025 | F10: MAV | G10: Pesos | H10: *MAV060700589 | N10: $ | O10: Especie (CPD/Pagaré/FCE) | Q10: *MAV060700589 - Pesos | R10: Cheques Diferidos
A11: *MAV280600941 | B11: Cheques Diferidos | D11: 31/5/2025 | E11: 31/5/2025 | F11: MAV | G11: Pesos | H11: *MAV280600941 | N11: $ | O11: Especie (CPD/Pagaré/FCE) | Q11: *MAV280600941 - Pesos | R11: Cheques Diferidos
A12: *MAV020700566 | B12: Cheques Diferidos | D12: 31/5/2025 | E12: 31/5/2025 | F12: MAV | G12: Pesos | H12: *MAV020700566 | N12: $ | O12: Especie (CPD/Pagaré/FCE) | Q12: *MAV020700566 - Pesos | R12: Cheques Diferidos
A13: *MAV300601372 | B13: Cheques Diferidos | D13: 31/5/2025 | E13: 31/5/2025 | F13: MAV | G13: Pesos | H13: *MAV300601372 | N13: $ | O13: Especie (CPD/Pagaré/FCE) | Q13: *MAV300601372 - Pesos | R13: Cheques Diferidos
A14: *MAV040600605 | B14: Cheques Diferidos | D14: 31/5/2025 | E14: 31/5/2025 | F14: MAV | G14: Pesos | H14: *MAV040600605 | N14: $ | O14: Especie (CPD/Pagaré/FCE) | Q14: *MAV040600605 - Pesos | R14: Cheques Diferidos
... A224: *MAV170600903 | B224: Cheques Diferidos | D224: 31/5/2025 | E224: 31/5/2025 | F224: MAV | G224: Pesos | H224: *MAV170600903 | N224: $ | O224: Especie (CPD/Pagaré/FCE) | Q224: *MAV170600903 - Pesos | R224: Cheques Diferidos
A225: *MAV200600888 | B225: ECHEQ | D225: 5/6/2025 | E225: 20/6/2025 | F225: BYMA | G225: Pesos | H225: *MAV200600888 | I225: 0.01 | N225: $ | O225: Especie (CPD/Pagaré/FCE) | Q225: *MAV200600888 - Pesos | R225: ECHEQ
A226: *MAV200600883 | B226: ECHEQ | D226: 5/6/2025 | E226: 20/6/2025 | F226: BYMA | G226: Pesos | H226: *MAV200600883 | I226: 0.01 | N226: $ | O226: Especie (CPD/Pagaré/FCE) | Q226: *MAV200600883 - Pesos | R226: ECHEQ
A227: *MAV190600778 | B227: ECHEQ | D227: 5/6/2025 | E227: 19/6/2025 | F227: BYMA | G227: Pesos | H227: *MAV190600778 | I227: 0.01 | N227: $ | O227: Especie (CPD/Pagaré/FCE) | Q227: *MAV190600778 - Pesos | R227: ECHEQ
A228: *MAV230601175 | B228: ECHEQ | D228: 5/6/2025 | E228: 23/6/2025 | F228: BYMA | G228: Pesos | H228: *MAV230601175 | I228: 0.01 | N228: $ | O228: Especie (CPD/Pagaré/FCE) | Q228: *MAV230601175 - Pesos | R228: ECHEQ
A229: *MAV220600711 | B229: ECHEQ | D229: 5/6/2025 | E229: 22/6/2025 | F229: BYMA | G229: Pesos | H229: *MAV220600711 | I229: 0.01 | N229: $ | O229: Especie (CPD/Pagaré/FCE) | Q229: *MAV220600711 - Pesos | R229: ECHEQ
A230: *MAV200600886 | B230: ECHEQ | D230: 5/6/2025 | E230: 20/6/2025 | F230: BYMA | G230: Pesos | H230: *MAV200600886 | I230: 0.01 | N230: $ | O230: Especie (CPD/Pagaré/FCE) | Q230: *MAV200600886 - Pesos | R230: ECHEQ
A231: *MAV200600882 | B231: ECHEQ | D231: 5/6/2025 | E231: 20/6/2025 | F231: BYMA | G231: Pesos | H231: *MAV200600882 | I231: 0.01 | N231: $ | O231: Especie (CPD/Pagaré/FCE) | Q231: *MAV200600882 - Pesos | R231: ECHEQ
A232: *MAV300601575 | B232: ECHEQ | D232: 5/6/2025 | E232: 30/6/2025 | F232: BYMA | G232: Pesos | H232: *MAV300601575 | I232: 0.01 | N232: $ | O232: Especie (CPD/Pagaré/FCE) | Q232: *MAV300601575 - Pesos | R232: ECHEQ
A233: *MAV290600631 | B233: ECHEQ | D233: 5/6/2025 | E233: 29/6/2025 | F233: BYMA | G233: Pesos | H233: *MAV290600631 | I233: 0.01 | N233: $ | O233: Especie (CPD/Pagaré/FCE) | Q233: *MAV290600631 - Pesos | R233: ECHEQ
A234: *MAV240601016 | B234: ECHEQ | D234: 5/6/2025 | E234: 24/6/2025 | F234: BYMA | G234: Pesos | H234: *MAV240601016 | I234: 0.01 | N234: $ | O234: Especie (CPD/Pagaré/FCE) | Q234: *MAV240601016 - Pesos | R234: ECHEQ
A235: *MAV230601173 | B235: ECHEQ | D235: 5/6/2025 | E235: 23/6/2025 | F235: BYMA | G235: Pesos | H235: *MAV230601173 | I235: 0.01 | N235: $ | O235: Especie (CPD/Pagaré/FCE) | Q235: *MAV230601173 - Pesos | R235: ECHEQ
A236: *MAV071001056 | B236: ECHEQ | D236: 16/9/2025 | E236: 9/10/2025 | F236: MAV | G236: Pesos | H236: *MAV071001056 | I236: 0.01 | N236: $ | O236: Especie (CPD/Pagaré/FCE) | Q236: *MAV071001056 - Pesos | R236: ECHEQ
... A914: *BIS301100204 | B914: ECHEQ | D914: 20/8/2025 | E914: 3/12/2025 | F914: MAV | G914: Pesos | H914: *BIS301100204 | I914: 0.01 | N914: $ | O914: Especie (CPD/Pagaré/FCE) | Q914: *BIS301100204 - Pesos | R914: ECHEQ
A915: #UTD190860001 | B915: Pagaré Hard Dolar | E915: 19/8/2026 | F915: BYMA | G915: Dolar MEP (local) | H915: #UTD190860001 | I915: 0.01 | N915: U$D | O915: Especie (CPD/Pagaré/FCE) | Q915: #UTD190860001 - Dolar MEP (local) | R915: Pagaré Hard Dolar
A916: #UTD010860001 | B916: Pagaré Hard Dolar | E916: 1/8/2026 | F916: BYMA | G916: Dolar MEP (local) | H916: #UTD010860001 | I916: 0.01 | N916: U$D | O916: Especie (CPD/Pagaré/FCE) | Q916: #UTD010860001 - Dolar MEP (local) | R916: Pagaré Hard Dolar
A917: *BIN231000052 | B917: ECHEQ | D917: 21/8/2025 | E917: 23/10/2025 | F917: BYMA | G917: Pesos | H917: *BIN231000052 | I917: 0.01 | N917: $ | O917: Especie (CPD/Pagaré/FCE) | Q917: *BIN231000052 - Pesos | R917: ECHEQ
A918: *BIN200900061 | B918: ECHEQ | D918: 21/8/2025 | E918: 20/9/2025 | F918: BYMA | G918: Pesos | H918: *BIN200900061 | I918: 0.01 | N918: $ | O918: Especie (CPD/Pagaré/FCE) | Q918: *BIN200900061 - Pesos | R918: ECHEQ
A919: *MAV300100998 | B919: ECHEQ | D919: 18/11/2025 | E919: 3/2/2026 | F919: MAV | G919: Pesos | H919: *MAV300100998 | I919: 0.01 | N919: $ | O919: Especie (CPD/Pagaré/FCE) | Q919: *MAV300100998 - Pesos | R919: ECHEQ
A920: *MAV300100999 | B920: ECHEQ | D920: 18/11/2025 | E920: 3/2/2026 | F920: MAV | G920: Pesos | H920: *MAV300100999 | I920: 0.01 | N920: $ | O920: Especie (CPD/Pagaré/FCE) | Q920: *MAV300100999 - Pesos | R920: ECHEQ
A921: *MAV300101003 | B921: ECHEQ | D921: 18/11/2025 | E921: 3/2/2026 | F921: MAV | G921: Pesos | H921: *MAV300101003 | I921: 0.01 | N921: $ | O921: Especie (CPD/Pagaré/FCE) | Q921: *MAV300101003 - Pesos | R921: ECHEQ
A922: *MAV300101004 | B922: ECHEQ | D922: 18/11/2025 | E922: 3/2/2026 | F922: MAV | G922: Pesos | H922: *MAV300101004 | I922: 0.01 | N922: $ | O922: Especie (CPD/Pagaré/FCE) | Q922: *MAV300101004 - Pesos | R922: ECHEQ
A923: *MAV020100874 | B923: ECHEQ | D923: 18/11/2025 | E923: 6/1/2026 | F923: MAV | G923: Pesos | H923: *MAV020100874 | I923: 0.01 | N923: $ | O923: Especie (CPD/Pagaré/FCE) | Q923: *MAV020100874 - Pesos | R923: ECHEQ
A924: *MAV020100876 | B924: ECHEQ | D924: 18/11/2025 | E924: 6/1/2026 | F924: MAV | G924: Pesos | H924: *MAV020100876 | I924: 0.01 | N924: $ | O924: Especie (CPD/Pagaré/FCE) | Q924: *MAV020100876 - Pesos | R924: ECHEQ
A925: *MAV230100935 | B925: ECHEQ | D925: 18/11/2025 | E925: 27/1/2026 | F925: MAV | G925: Pesos | H925: *MAV230100935 | I925: 0.01 | N925: $ | O925: Especie (CPD/Pagaré/FCE) | Q925: *MAV230100935 - Pesos | R925: ECHEQ
A926: *MAV301101593 | B926: ECHEQ | D926: 20/11/2025 | E926: 30/11/2025 | F926: BYMA | G926: Pesos | H926: *MAV301101593 | I926: 0.01 | N926: $ | O926: Especie (CPD/Pagaré/FCE) | Q926: *MAV301101593 - Pesos | R926: ECHEQ
A927: *MAV041200881 | B927: ECHEQ | D927: 20/11/2025 | E927: 4/12/2025 | F927: BYMA | G927: Pesos | H927: *MAV041200881 | I927: 0.01 | N927: $ | O927: Especie (CPD/Pagaré/FCE) | Q927: *MAV041200881 - Pesos | R927: ECHEQ
A928: *MAV031200894 | B928: ECHEQ | D928: 20/11/2025 | E928: 3/12/2025 | F928: BYMA | G928: Pesos | H928: *MAV031200894 | I928: 0.01 | N928: $ | O928: Especie (CPD/Pagaré/FCE) | Q928: *MAV031200894 - Pesos | R928: ECHEQ
... A4351: *MOV051100049 | B4351: ECHEQ | D4351: 29/7/2025 | E4351: 10/11/2025 | F4351: MAV | G4351: Pesos | H4351: *MOV051100049 | I4351: 0.01 | N4351: $ | O4351: Especie (CPD/Pagaré/FCE) | Q4351: *MOV051100049 - Pesos | R4351: ECHEQ
A4352: #UMV031150049 | B4352: Pagaré Hard Dolar | E4352: 3/11/2025 | F4352: BYMA | G4352: Dolar MEP (local) | H4352: #UMV031150049 | I4352: 0.01 | N4352: U$D | O4352: Especie (CPD/Pagaré/FCE) | Q4352: #UMV031150049 - Dolar MEP (local) | R4352: Pagaré Hard Dolar
A4353: *BIN010100026 | B4353: ECHEQ | D4353: 11/11/2025 | E4353: 6/1/2026 | F4353: MAV | G4353: Pesos | H4353: *BIN010100026 | I4353: 0.01 | N4353: $ | O4353: Especie (CPD/Pagaré/FCE) | Q4353: *BIN010100026 - Pesos | R4353: ECHEQ
A4354: #MAV111250055 | B4354: Pagare | D4354: 11/11/2025 | E4354: 12/12/2025 | F4354: MAV | G4354: Pesos | H4354: #MAV111250055 | I4354: 0.01 | N4354: $ | O4354: Especie (CPD/Pagaré/FCE) | Q4354: #MAV111250055 - Pesos | R4354: Pagare
A4355: *BIN160100061 | B4355: ECHEQ | D4355: 11/11/2025 | E4355: 16/1/2026 | F4355: BYMA | G4355: Pesos | H4355: *BIN160100061 | I4355: 0.01 | N4355: $ | O4355: Especie (CPD/Pagaré/FCE) | Q4355: *BIN160100061 - Pesos | R4355: ECHEQ
A4356: *TRD121200040 | B4356: ECHEQ | D4356: 12/11/2025 | E4356: 12/12/2025 | F4356: BYMA | G4356: Pesos | H4356: *TRD121200040 | I4356: 0.01 | N4356: $ | O4356: Especie (CPD/Pagaré/FCE) | Q4356: *TRD121200040 - Pesos | R4356: ECHEQ
A4357: *BIN270200037 | B4357: ECHEQ | D4357: 12/11/2025 | E4357: 27/2/2026 | F4357: BYMA | G4357: Pesos | H4357: *BIN270200037 | I4357: 0.01 | N4357: $ | O4357: Especie (CPD/Pagaré/FCE) | Q4357: *BIN270200037 - Pesos | R4357: ECHEQ
A4358: *BIN240200049 | B4358: ECHEQ | D4358: 12/11/2025 | E4358: 24/2/2026 | F4358: BYMA | G4358: Pesos | H4358: *BIN240200049 | I4358: 0.01 | N4358: $ | O4358: Especie (CPD/Pagaré/FCE) | Q4358: *BIN240200049 - Pesos | R4358: ECHEQ
A4359: *MAV130101028 | B4359: ECHEQ | D4359: 12/11/2025 | E4359: 13/1/2026 | F4359: BYMA | G4359: Pesos | H4359: *MAV130101028 | I4359: 0.01 | N4359: $ | O4359: Especie (CPD/Pagaré/FCE) | Q4359: *MAV130101028 - Pesos | R4359: ECHEQ
A4360: *MAV130101027 | B4360: ECHEQ | D4360: 12/11/2025 | E4360: 13/1/2026 | F4360: BYMA | G4360: Pesos | H4360: *MAV130101027 | I4360: 0.01 | N4360: $ | O4360: Especie (CPD/Pagaré/FCE) | Q4360: *MAV130101027 - Pesos | R4360: ECHEQ
A4361: *BIN130200044 | B4361: ECHEQ | D4361: 12/11/2025 | E4361: 13/2/2026 | F4361: BYMA | G4361: Pesos | H4361: *BIN130200044 | I4361: 0.01 | N4361: $ | O4361: Especie (CPD/Pagaré/FCE) | Q4361: *BIN130200044 - Pesos | R4361: ECHEQ
A4362: #UMV231250021 | B4362: Pagare | D4362: 13/11/2025 | E4362: 23/12/2025 | F4362: BYMA | G4362: Dolar MEP (local) | H4362: #UMV231250021 | I4362: 0.01 | N4362: U$D | O4362: Especie (CPD/Pagaré/FCE) | Q4362: #UMV231250021 - Dolar MEP (local) | R4362: Pagare
A4363: *BIN151200149 | B4363: ECHEQ | D4363: 13/11/2025 | E4363: 15/12/2025 | F4363: BYMA | G4363: Pesos | H4363: *BIN151200149 | I4363: 0.01 | N4363: $ | O4363: Especie (CPD/Pagaré/FCE) | Q4363: *BIN151200149 - Pesos | R4363: ECHEQ
A4364: *MAV060200804 | B4364: ECHEQ | D4364: 13/11/2025 | E4364: 10/2/2026 | F4364: MAV | G4364: Pesos | H4364: *MAV060200804 | I4364: 0.01 | N4364: $ | O4364: Especie (CPD/Pagaré/FCE) | Q4364: *MAV060200804 - Pesos | R4364: ECHEQ
... A5042: *BIS301200121 | B5042: ECHEQ | D5042: 9/9/2025 | E5042: 5/1/2026 | F5042: MAV | G5042: Pesos | H5042: *BIS301200121 | I5042: 0.01 | N5042: $ | O5042: Especie (CPD/Pagaré/FCE) | Q5042: *BIS301200121 - Pesos | R5042: ECHEQ
A5043: TRND300900009 | B5043: Cheques Diferidos | E5043: 30/9/2025 | F5043: BYMA | G5043: Pesos | H5043: TRND300900009 | I5043: 0.01 | N5043: $ | O5043: Especie (CPD/Pagaré/FCE) | Q5043: TRND300900009 - Pesos | R5043: Cheques Diferidos
A5044: *MAV200901262 | B5044: ECHEQ | D5044: 10/9/2025 | E5044: 20/9/2025 | F5044: BYMA | G5044: Pesos | H5044: *MAV200901262 | I5044: 0.01 | N5044: $ | O5044: Especie (CPD/Pagaré/FCE) | Q5044: *MAV200901262 - Pesos | R5044: ECHEQ
A5045: *MAV180900981 | B5045: ECHEQ | D5045: 10/9/2025 | E5045: 18/9/2025 | F5045: BYMA | G5045: Pesos | H5045: *MAV180900981 | I5045: 0.01 | N5045: $ | O5045: Especie (CPD/Pagaré/FCE) | Q5045: *MAV180900981 - Pesos | R5045: ECHEQ
A5046: *MAV170900989 | B5046: ECHEQ | D5046: 10/9/2025 | E5046: 17/9/2025 | F5046: BYMA | G5046: Pesos | H5046: *MAV170900989 | I5046: 0.01 | N5046: $ | O5046: Especie (CPD/Pagaré/FCE) | Q5046: *MAV170900989 - Pesos | R5046: ECHEQ
A5047: *CRE151100189 | B5047: ECHEQ | D5047: 10/9/2025 | E5047: 15/11/2025 | F5047: BYMA | G5047: Pesos | H5047: *CRE151100189 | I5047: 0.01 | N5047: $ | O5047: Especie (CPD/Pagaré/FCE) | Q5047: *CRE151100189 - Pesos | R5047: ECHEQ
A5048: *CRE151100188 | B5048: ECHEQ | D5048: 10/9/2025 | E5048: 15/11/2025 | F5048: BYMA | G5048: Pesos | H5048: *CRE151100188 | I5048: 0.01 | N5048: $ | O5048: Especie (CPD/Pagaré/FCE) | Q5048: *CRE151100188 - Pesos | R5048: ECHEQ
A5049: *CRE141100111 | B5049: ECHEQ | D5049: 10/9/2025 | E5049: 14/11/2025 | F5049: BYMA | G5049: Pesos | H5049: *CRE141100111 | I5049: 0.01 | N5049: $ | O5049: Especie (CPD/Pagaré/FCE) | Q5049: *CRE141100111 - Pesos | R5049: ECHEQ
A5050: *CRE141100110 | B5050: ECHEQ | D5050: 10/9/2025 | E5050: 14/11/2025 | F5050: BYMA | G5050: Pesos | H5050: *CRE141100110 | I5050: 0.01 | N5050: $ | O5050: Especie (CPD/Pagaré/FCE) | Q5050: *CRE141100110 - Pesos | R5050: ECHEQ
A5051: *CRE141100108 | B5051: ECHEQ | D5051: 10/9/2025 | E5051: 14/11/2025 | F5051: BYMA | G5051: Pesos | H5051: *CRE141100108 | I5051: 0.01 | N5051: $ | O5051: Especie (CPD/Pagaré/FCE) | Q5051: *CRE141100108 - Pesos | R5051: ECHEQ
A5052: *BIS030200106 | B5052: ECHEQ | D5052: 15/12/2025 | E5052: 3/2/2026 | F5052: MAV | G5052: Pesos | H5052: *BIS030200106 | I5052: 0.01 | N5052: $ | O5052: Especie (CPD/Pagaré/FCE) | Q5052: *BIS030200106 - Pesos | R5052: ECHEQ
A5053: *BIS110400065 | B5053: ECHEQ | D5053: 15/12/2025 | E5053: 11/4/2026 | F5053: MAV | G5053: Pesos | H5053: *BIS110400065 | I5053: 0.01 | N5053: $ | O5053: Especie (CPD/Pagaré/FCE) | Q5053: *BIS110400065 - Pesos | R5053: ECHEQ
A5054: *BIS130200164 | B5054: ECHEQ | D5054: 15/12/2025 | E5054: 13/2/2026 | F5054: MAV | G5054: Pesos | H5054: *BIS130200164 | I5054: 0.01 | N5054: $ | O5054: Especie (CPD/Pagaré/FCE) | Q5054: *BIS130200164 - Pesos | R5054: ECHEQ
A5055: *BIS020300085 | B5055: ECHEQ | D5055: 15/12/2025 | E5055: 2/3/2026 | F5055: MAV | G5055: Pesos | H5055: *BIS020300085 | I5055: 0.01 | N5055: $ | O5055: Especie (CPD/Pagaré/FCE) | Q5055: *BIS020300085 - Pesos | R5055: ECHEQ
... A5449: *MAV101001357 | B5449: ECHEQ | D5449: 3/10/2025 | E5449: 10/10/2025 | F5449: BYMA | G5449: Pesos | H5449: *MAV101001357 | I5449: 0.01 | N5449: $ | O5449: Especie (CPD/Pagaré/FCE) | Q5449: *MAV101001357 - Pesos | R5449: ECHEQ
A5450: TRND091100003 | B5450: Cheques Diferidos | E5450: 9/11/2025 | F5450: MAV | G5450: Pesos | H5450: TRND091100003 | I5450: 0.01 | N5450: $ | O5450: Especie (CPD/Pagaré/FCE) | Q5450: TRND091100003 - Pesos | R5450: Cheques Diferidos
A5451: TRND091200001 | B5451: Cheques Diferidos | E5451: 9/12/2025 | F5451: MAV | G5451: Pesos | H5451: TRND091200001 | I5451: 0.01 | N5451: $ | O5451: Especie (CPD/Pagaré/FCE) | Q5451: TRND091200001 - Pesos | R5451: Cheques Diferidos
A5452: *BIS010300093 | B5452: ECHEQ | D5452: 12/12/2025 | E5452: 1/3/2026 | F5452: MAV | G5452: Pesos | H5452: *BIS010300093 | I5452: 0.01 | N5452: $ | O5452: Especie (CPD/Pagaré/FCE) | Q5452: *BIS010300093 - Pesos | R5452: ECHEQ
A5453: *BIS100100248 | B5453: ECHEQ | D5453: 12/12/2025 | E5453: 10/1/2026 | F5453: MAV | G5453: Pesos | H5453: *BIS100100248 | I5453: 0.01 | N5453: $ | O5453: Especie (CPD/Pagaré/FCE) | Q5453: *BIS100100248 - Pesos | R5453: ECHEQ
A5454: *BIS250100145 | B5454: ECHEQ | D5454: 12/12/2025 | E5454: 25/1/2026 | F5454: MAV | G5454: Pesos | H5454: *BIS250100145 | I5454: 0.01 | N5454: $ | O5454: Especie (CPD/Pagaré/FCE) | Q5454: *BIS250100145 - Pesos | R5454: ECHEQ
A5455: *BIS250200106 | B5455: ECHEQ | D5455: 12/12/2025 | E5455: 25/2/2026 | F5455: MAV | G5455: Pesos | H5455: *BIS250200106 | I5455: 0.01 | N5455: $ | O5455: Especie (CPD/Pagaré/FCE) | Q5455: *BIS250200106 - Pesos | R5455: ECHEQ
A5456: *BIS280200340 | B5456: ECHEQ | D5456: 12/12/2025 | E5456: 28/2/2026 | F5456: MAV | G5456: Pesos | H5456: *BIS280200340 | I5456: 0.01 | N5456: $ | O5456: Especie (CPD/Pagaré/FCE) | Q5456: *BIS280200340 - Pesos | R5456: ECHEQ
A5457: *BIS090200100 | B5457: ECHEQ | D5457: 12/12/2025 | E5457: 9/2/2026 | F5457: MAV | G5457: Pesos | H5457: *BIS090200100 | I5457: 0.01 | N5457: $ | O5457: Especie (CPD/Pagaré/FCE) | Q5457: *BIS090200100 - Pesos | R5457: ECHEQ
A5458: *MAV231201202 | B5458: ECHEQ | D5458: 4/12/2025 | E5458: 23/12/2025 | F5458: MAV | G5458: Pesos | H5458: *MAV231201202 | I5458: 0.01 | N5458: $ | O5458: Especie (CPD/Pagaré/FCE) | Q5458: *MAV231201202 - Pesos | R5458: ECHEQ
A5459: *TRD230400011 | B5459: ECHEQ | D5459: 4/12/2025 | E5459: 23/4/2026 | F5459: MAV | G5459: Pesos | H5459: *TRD230400011 | I5459: 0.01 | N5459: $ | O5459: Especie (CPD/Pagaré/FCE) | Q5459: *TRD230400011 - Pesos | R5459: ECHEQ
A5460: *TRD260400024 | B5460: ECHEQ | D5460: 4/12/2025 | E5460: 26/4/2026 | F5460: MAV | G5460: Pesos | H5460: *TRD260400024 | I5460: 0.01 | N5460: $ | O5460: Especie (CPD/Pagaré/FCE) | Q5460: *TRD260400024 - Pesos | R5460: ECHEQ
A5461: *BIN110300052 | B5461: ECHEQ | D5461: 5/12/2025 | E5461: 11/3/2026 | F5461: BYMA | G5461: Pesos | H5461: *BIN110300052 | I5461: 0.01 | N5461: $ | O5461: Especie (CPD/Pagaré/FCE) | Q5461: *BIN110300052 - Pesos | R5461: ECHEQ
A5462: *MAV151201708 | B5462: ECHEQ | D5462: 5/12/2025 | E5462: 15/12/2025 | F5462: BYMA | G5462: Pesos | H5462: *MAV151201708 | I5462: 0.01 | N5462: $ | O5462: Especie (CPD/Pagaré/FCE) | Q5462: *MAV151201708 - Pesos | R5462: ECHEQ
A5463: *MAV131201162 | B5463: ECHEQ | D5463: 5/12/2025 | E5463: 13/12/2025 | F5463: BYMA | G5463: Pesos | H5463: *MAV131201162 | I5463: 0.01 | N5463: $ | O5463: Especie (CPD/Pagaré/FCE) | Q5463: *MAV131201162 - Pesos | R5463: ECHEQ
... A5602: *AVR111200015 | B5602: ECHEQ | D5602: 4/9/2025 | E5602: 15/12/2025 | F5602: MAV | G5602: Pesos | H5602: *AVR111200015 | I5602: 0.01 | N5602: $ | O5602: Especie (CPD/Pagaré/FCE) | Q5602: *AVR111200015 - Pesos | R5602: ECHEQ
A5603: #UTD200860001 | B5603: Pagaré Hard Dolar | E5603: 20/8/2026 | F5603: BYMA | G5603: Dolar MEP (local) | H5603: #UTD200860001 | I5603: 0.01 | N5603: U$D | O5603: Especie (CPD/Pagaré/FCE) | Q5603: #UTD200860001 - Dolar MEP (local) | R5603: Pagaré Hard Dolar
A5604: *GAR011200287 | B5604: ECHEQ | D5604: 5/9/2025 | E5604: 1/12/2025 | F5604: BYMA | G5604: Pesos | H5604: *GAR011200287 | I5604: 0.01 | N5604: $ | O5604: Especie (CPD/Pagaré/FCE) | Q5604: *GAR011200287 - Pesos | R5604: ECHEQ
A5605: *MAV220901197 | B5605: ECHEQ | D5605: 5/9/2025 | E5605: 22/9/2025 | F5605: BYMA | G5605: Pesos | H5605: *MAV220901197 | I5605: 0.01 | N5605: $ | O5605: Especie (CPD/Pagaré/FCE) | Q5605: *MAV220901197 - Pesos | R5605: ECHEQ
A5606: *MAV210900735 | B5606: ECHEQ | D5606: 5/9/2025 | E5606: 21/9/2025 | F5606: BYMA | G5606: Pesos | H5606: *MAV210900735 | I5606: 0.01 | N5606: $ | O5606: Especie (CPD/Pagaré/FCE) | Q5606: *MAV210900735 - Pesos | R5606: ECHEQ
A5607: *MAV200901234 | B5607: ECHEQ | D5607: 5/9/2025 | E5607: 20/9/2025 | F5607: BYMA | G5607: Pesos | H5607: *MAV200901234 | I5607: 0.01 | N5607: $ | O5607: Especie (CPD/Pagaré/FCE) | Q5607: *MAV200901234 - Pesos | R5607: ECHEQ
A5608: *MAV240900920 | B5608: ECHEQ | D5608: 5/9/2025 | E5608: 24/9/2025 | F5608: BYMA | G5608: Pesos | H5608: *MAV240900920 | I5608: 0.01 | N5608: $ | O5608: Especie (CPD/Pagaré/FCE) | Q5608: *MAV240900920 - Pesos | R5608: ECHEQ
A5609: *MAV230901093 | B5609: ECHEQ | D5609: 5/9/2025 | E5609: 23/9/2025 | F5609: BYMA | G5609: Pesos | H5609: *MAV230901093 | I5609: 0.01 | N5609: $ | O5609: Especie (CPD/Pagaré/FCE) | Q5609: *MAV230901093 - Pesos | R5609: ECHEQ
A5610: *BIN291100072 | B5610: ECHEQ | D5610: 8/9/2025 | E5610: 29/11/2025 | F5610: BYMA | G5610: Pesos | H5610: *BIN291100072 | I5610: 0.01 | N5610: $ | O5610: Especie (CPD/Pagaré/FCE) | Q5610: *BIN291100072 - Pesos | R5610: ECHEQ
A5611: *BIN240900040 | B5611: ECHEQ | D5611: 8/9/2025 | E5611: 24/9/2025 | F5611: BYMA | G5611: Pesos | H5611: *BIN240900040 | I5611: 0.01 | N5611: $ | O5611: Especie (CPD/Pagaré/FCE) | Q5611: *BIN240900040 - Pesos | R5611: ECHEQ
A5612: *MAV161000875 | B5612: ECHEQ | D5612: 12/9/2025 | E5612: 20/10/2025 | F5612: MAV | G5612: Pesos | H5612: *MAV161000875 | I5612: 0.01 | N5612: $ | O5612: Especie (CPD/Pagaré/FCE) | Q5612: *MAV161000875 - Pesos | R5612: ECHEQ
A5613: *MAV141001109 | B5613: ECHEQ | D5613: 12/9/2025 | E5613: 16/10/2025 | F5613: MAV | G5613: Pesos | H5613: *MAV141001109 | I5613: 0.01 | N5613: $ | O5613: Especie (CPD/Pagaré/FCE) | Q5613: *MAV141001109 - Pesos | R5613: ECHEQ
A5614: *MAV061001107 | B5614: ECHEQ | D5614: 12/9/2025 | E5614: 8/10/2025 | F5614: MAV | G5614: Pesos | H5614: *MAV061001107 | I5614: 0.01 | N5614: $ | O5614: Especie (CPD/Pagaré/FCE) | Q5614: *MAV061001107 - Pesos | R5614: ECHEQ
A5615: *MAV201001178 | B5615: ECHEQ | D5615: 12/9/2025 | E5615: 22/10/2025 | F5615: MAV | G5615: Pesos | H5615: *MAV201001178 | I5615: 0.01 | N5615: $ | O5615: Especie (CPD/Pagaré/FCE) | Q5615: *MAV201001178 - Pesos | R5615: ECHEQ
... A7601: *BIS050700049 | B7601: ECHEQ | D7601: 28/5/2025 | E7601: 10/7/2025 | F7601: MAV | G7601: Pesos | H7601: *BIS050700049 | I7601: 1 | N7601: $ | O7601: Especie (CPD/Pagaré/FCE) | Q7601: *BIS050700049 - Pesos | R7601: ECHEQ
...

Sheet EspeciesGallo
A1: 'Codigo' | B1: 'Nombre de la Especie' | C1: 'Tipo' | D1: 'Clase' | E1: 'Precio' | F1: 'Ls' | G1: 'Lam.Min.' | H1: 'V.Res.' | I1: 'Gr' | J1: 'Norm.' | K1: 'Parid' | L1: 'Cable' | M1: 'Block' | N1: 'Mda.' | O1: 'Merc' | P1: 'Vencim' | Q1: 'Isin Code' | R1: 'Emisor' | S1: 'Tipo de Activo' | T1: 'LPA' | U1: 'LOP' | V1: 'LPR' | W1: 'CANT.X LOTE' | X1: 'CUSIP' | Y1: 'OBSERVACIONES' | Z1: 'RIESGO'
A2: 05203 | B2: LETRAS DEL TESORO 182D USD 17/07/2017 | C2: Letr | E2: Porc. | F2: 0 | G2: 0.00 | I2: 0 | J2: L2DL7 | K2: L2L7D | L2: L2L7C | N2: U$S | P2: 17/07/17 | Q2: ARARGE5203E7 | T2: 0 | U2: 0 | V2: 0 | W2: 0 | Y2: L2DL7 | Z2: Sin Calificar
A3: 05227 | B3: LETRAS DEL TESORO U$S VTO.09/02/2018 | C3: Letr | E3: Porc. | F3: 0 | G3: 0.00 | I3: 0 | J3: LTDF8 | K3: LTF8D | L3: LTF8C | N3: U$S | P3: 09/02/18 | Q3: ARARGE5204O4 | T3: 0 | U3: 0 | V3: 0 | W3: 0 | Z3: Sin Calificar
A4: 05228 | B4: LETRAS DEL TESORO U$S VTO.29/06/2018 | C4: Letr | E4: Porc. | F4: 0 | G4: 0.00 | I4: 0 | J4: L2DJ8 | K4: L2J8D | L4: L2J8C | N4: U$S | P4: 29/06/18 | Q4: ARARGE5204P1 | T4: 0 | U4: 0 | V4: 0 | W4: 0 | Z4: Sin Calificar
A5: 05229 | B5: LETRAS DEL TESORO U$S VTO.14/12/2018 | C5: Letr | E5: Porc. | F5: 0 | G5: 0.00 | I5: 0 | J5: LTDD8 | K5: LDD8D | L5: LDD8C | N5: U$S | P5: 14/12/18 | Q5: ARARGE5204Q9 | T5: 0 | U5: 0 | V5: 0 | W5: 0 | Z5: Sin Calificar
A6: 05230 | B6: LETRAS DEL TESORO U$S VTO.13/04/18 | C6: Letr | E6: Porc. | F6: 0 | G6: 0.00 | I6: 0 | J6: L4DA8 | K6: L4D8D | N6: U$S | P6: 13/04/18 | Q6: ARARGE5204S5 | T6: 0 | U6: 0 | V6: 0 | W6: 0 | Z6: Sin Calificar
A7: 53124 | B7: ON.BCO.PCIA.CORDOBA S2 V.18/12/20 | C7: O/N | E7: Porc. | F7: 0 | G7: 0.00 | H7: 100 | I7: 0 | J7: COS2O | Q7: ARBNCO560016 | T7: 0 | U7: 0 | V7: 0 | W7: 0 | Z7: Sin Calificar
A8: 80543 | B8: O.N. CRESUD CL.25 V.11/07/21 U$S CG | C8: O/N | E8: Porc. | F8: 0 | G8: 0.00 | I8: 0 | J8: CSFQO-US | K8: CSFQD | L8: CSFQC | Q8: ARCRES560080 | T8: 0 | U8: 0 | V8: 0 | W8: 0 | Z8: Sin Calificar
A9: 53018 | B9: CPFF CREDICUOTAS CONSUMO 4 $ CG | C9: Fdo. | E9: Porc. | F9: 0 | G9: 0.00 | H9: 100 | I9: 0 | J9: DR04Q | Q9: AREQUI490GX5 | T9: 0 | U9: 0 | V9: 0 | W9: 0 | Z9: Sin Calificar
A10: 31024 | B10: INV.JURAMENTO CLASE B DER.SUSCRIPCION | C10: Priv | E10: Normal | F10: 0 | G10: 0.00 | I10: 0 | J10: INVJX | Q10: ARINJU020043 | T10: 0 | U10: 0 | V10: 0 | W10: 0 | X10: 88031M109 | Z10: Sin Calificar
A11: 96712 | B11: HEPION PHARMACEUTICALS INC. | C11: Priv | E11: Normal | F11: 0 | G11: 0.00 | I11: 0 | J11: HEPA-US | N11: DOLAR | O11: Ext. | Q11: US4268973025 | T11: 0 | U11: 0 | V11: 0 | W11: 0 | X11: 426897302 | Z11: Sin Calificar
A12: 83133 | B12: US TREASURY BILL ZCP V.14/12/23 | C12: Publ | E12: Porc. | F12: 0 | G12: 0.00 | I12: 0 | J12: TB14122023 | N12: DOLAR | O12: Ext. | Q12: US912797FU69 | T12: 0 | U12: 0 | V12: 0 | W12: 0 | Z12: Sin Calificar
A13: 40786 | B13: BONOS C/DESCUENTO EUROS STEP UP V.2033 | C13: Publ | E13: Porc. | F13: 0 | G13: 0.00 | I13: 0 | J13: DICE | K13: DICED | L13: DICEC | Q13: XS0205545840 | T13: 0 | U13: 0 | V13: 0 | W13: 0 | Z13: Sin Calificar
A14: 91598 | B14: BONO PCIA BS AS 09-06-2021 9.95% | C14: Publ | E14: Porc. | F14: 0 | G14: 0.00 | H14: 100 | I14: 0 | J14: PBJ21 | K14: PB21D | L14: PB21C | N14: U$S | Q14: XS1244682487 | T14: 0 | U14: 0 | V14: 0 | W14: 0 | Z14: Sin Calificar
A15: 80554 | B15: NOTA SOCIETE GENERALE 1,253% V.06/07/21 | C15: Priv | E15: Porc. | F15: 0 | G15: 0.00 | I15: 0 | J15: NOSG | N15: U$S | O15: Ext. | Q15: XS1816490467 | T15: 0 | U15: 0 | V15: 0 | W15: 0 | Z15: Sin Calificar
A16: 82808 | B16: ON AGUA Y SANEA 7.9% V.01/05/26 U$S | C16: O/N | E16: Porc. | F16: 0 | G16: 1.00 | I16: 0 | J16: ONAYSA26 | N16: U$S | O16: Usd | Q16: XS2571927768 | T16: 0 | U16: 0 | V16: 0 | W16: 0 | Z16: Sin Calificar
A17: 00795 | B17: PATRICIOS | C17: Priv | D17: ORDS | E17: Normal | F17: 0 | G17: 0.00 | H17: 100 | I17: 0 | Q17: 594918104 | T17: 0 | U17: 0 | V17: 0 | W17: 0 | X17: 594918104 | Z17: Sin Calificar
A18: 06375 | B18: O.N. BANCO HIPOTECARIO | C18: O/N | D18: . | E18: Porc. | F18: 0 | G18: 0.00 | H18: 100 | I18: 0 | J18: OBHX1 | K18: PBHX1 | Q18: 594918104 | T18: 0 | U18: 0 | V18: 0 | W18: 0 | X18: 594918104 | Z18: Sin Calificar
A19: 06376 | B19: 06376 | C19: Priv | D19: . | E19: Normal | F19: 0 | G19: 0.00 | I19: 0 | Q19: 594918104 | T19: 0 | U19: 0 | V19: 0 | W19: 0 | X19: 594918104 | Z19: Sin Calificar
A20: 06383 | B20: 06383 | C20: Priv | D20: . | E20: Normal | F20: 0 | G20: 0.00 | I20: 0 | Q20: 594918104 | T20: 0 | U20: 0 | V20: 0 | W20: 0 | X20: 594918104 | Z20: Sin Calificar
A21: 00762 | B21: NOEL | C21: Priv | D21: ORDS | E21: Normal | F21: 0 | G21: 0.00 | I21: 0 | Q21: 68389X105 | T21: 0 | U21: 0 | V21: 0 | W21: 0 | X21: 68389X105 | Z21: Sin Calificar
A22: 47732 | B22: PROSHARES QQQ TRUST SERIES I | C22: Priv | E22: Normal | F22: 0 | G22: 0.00 | H22: 100 | I22: 0 | J22: QQQ-USA | N22: DOLAR | O22: Ext. | Q22: 73935A104 | T22: 0 | U22: 0 | V22: 0 | W22: 0 | Z22: Sin Calificar
A23: 07719 | B23: SAFE TECHNOLOGIES INTER. INC. | C23: Priv | E23: Normal | F23: 0 | G23: 0.00 | H23: 100 | I23: 0 | J23: SFAD | Q23: 786416107 | T23: 0 | U23: 0 | V23: 0 | W23: 0 | X23: 786416107 | Z23: Sin Calificar
A24: 48877 | B24: SAFE TECHNOLOGIES INC NEW | C24: Priv | E24: Normal | F24: 0 | G24: 0.00 | H24: 100 | I24: 0 | J24: SAFE-US | N24: U$S | O24: Ext. | Q24: 786416107 | T24: 0 | U24: 0 | V24: 0 | W24: 0 | X24: 786416107 | Z24: Sin Calificar
A25: 08570 | B25: CEDEAR ADIDAS AG | C25: Priv | E25: Normal | F25: 0 | G25: 0.00 | I25: 0 | J25: ADS | K25: ADSD | L25: ADSC | N25: DOLAR | Q25: ADSD | T25: 0 | U25: 0 | V25: 0 | W25: 0 | Z25: Sin Calificar
A26: 30015 | B26: BANCO PATAGONIA ACCS. CLASE B | C26: Priv | E26: Normal | F26: 0 | G26: 0.00 | H26: 100 | I26: 0 | J26: BPAT | M26: BPATB | Q26: AMERI013163 | T26: 0 | U26: 0 | V26: 0 | W26: 100 | Z26: Sin Calificar
A27: 57533 | B27: ON PYME CNV ZAFRA SER 1 CL. A V 29/12/25 | C27: O/N | E27: Normal | F27: 0 | G27: 0.00 | I27: 0 | Q27: AR000002607 | T27: 0 | U27: 0 | V27: 0 | W27: 0 | Z27: Moderado
A28: 08648 | B28: CEDEAR DANAHER CORP | C28: Priv | E28: Normal | F28: 0 | G28: 0.00 | I28: 0 | J28: DHR | Q28: AR0002457668 | T28: 0 | U28: 0 | V28: 0 | W28: 0 | X28: AR0002457668 | Z28: Sin Calificar
A29: 57658 | B29: ON MSU ENERGY CL.10 V12/03/26 U$S CG | C29: O/N | E29: Porc. | F29: 0 | G29: 0.00 | I29: 0 | J29: RUCA | K29: RUCAD | Q29: AR0006306242 | T29: 0 | U29: 0 | V29: 0 | W29: 0 | Z29: Sin Calificar
A30: 09260 | B30: LT REP ARGENTINA CAP $ V01/07/24 | C30: Letr | E30: Porc. | F30: 0 | G30: 0.00 | I30: 0 | J30: S01L4 | P30: 01/07/24 | Q30: AR0006731399 | T30: 0 | U30: 0 | V30: 0 | W30: 0 | Z30: Sin Calificar
A31: 58427 | B31: ON BANCO COMAFI CL.9 V30/07/25 U$S CG | C31: O/N | E31: Porc. | F31: 0 | G31: 0.00 | I31: 0 | J31: AFC9O | K31: AFC9D | N31: U$S | Q31: AR0014222183 | T31: 0 | U31: 0 | V31: 0 | W31: 0 | Y31: AFC9O | Z31: Sin Calificar
A32: 09266 | B32: LT REP ARGENTINA CAP V16/08/24 $ CG | C32: Letr | E32: Porc. | F32: 0 | G32: 0.00 | I32: 0 | J32: S16G4 | K32: S2G4D | P32: 16/08/24 | Q32: AR0015187120 | T32: 0 | U32: 0 | V32: 0 | W32: 0 | Y32: S16G4 | Z32: Sin Calificar
A33: 58123 | B33: ON CIA GEN.COMB. CL.36 V10/10/27 U$S CG | C33: O/N | E33: Porc. | F33: 0 | G33: 0.00 | I33: 0 | K33: CP36D | Q33: AR0015464982 | T33: 0 | U33: 0 | V33: 0 | W33: 0 | Z33: Sin Calificar
A34: 58245 | B34: ON YPF ENER.ELEC. C.19 V.22/11/26 U$S CG | C34: O/N | E34: Porc. | F34: 0 | G34: 1.00 | I34: 0 | J34: YFCKO | K34: YFCKO | L34: YFCKO | M34: YFCKO | N34: U$S | Q34: AR0015491712 | R34: YPF ENERGIA ELECTRICA S.A. | T34: 0 | U34: 0 | V34: 0 | W34: 0 | Y34: YFCKO | Z34: Sin Calificar
A35: 58624 | B35: ON ARCOR CL.26 V09/05/27 U$S CG | C35: O/N | E35: Porc. | F35: 0 | G35: 0.00 | I35: 0 | K35: RCCRD | Q35: AR0016944933 | T35: 0 | U35: 0 | V35: 0 | W35: 0 | Z35: Sin Calificar
A36: 09323 | B36: BONO NACION TASA DUAL15/12/26 $ CG | C36: Publ | E36: Porc. | F36: 0 | G36: 0.00 | I36: 0 | J36: TTD26 | Q36: AR0021930364 | T36: 0 | U36: 0 | V36: 0 | W36: 0 | Y36: TTD26 | Z36: Sin Calificar
A37: 57609 | B37: ON P CNV G DEMAGRO S1CB V28/02/26 U$S CG | C37: O/N | E37: Porc. | F37: 0 | G37: 0.00 | I37: 0 | J37: DM1BP | Q37: AR0031436766 | T37: 0 | U37: 0 | V37: 0 | W37: 0 | Z37: Sin Calificar
A38: 08661 | B38: CEDEAR ISHARES TRUST FTSE | C38: Priv | E38: Normal | F38: 0 | G38: 0.00 | I38: 0 | J38: FXI | Q38: AR0033445195 | T38: 0 | U38: 0 | V38: 0 | W38: 0 | Z38: Sin Calificar
A39: 58415 | B39: ON.PLUSPETROL S.A CLASE 1 | C39: O/N | E39: Porc. | F39: 0 | G39: 0.00 | I39: 0 | J39: PLC1O | K39: PLC1O | L39: PLC1O | N39: U$S | Q39: AR0036431960 | T39: 0 | U39: 0 | V39: 0 | W39: 0 | Y39: PLC1O | Z39: Sin Calificar
A40: 58416 | B40: ON.PLUSPETROL S.A CLASE 2 | C40: O/N | E40: Porc. | F40: 0 | G40: 0.00 | I40: 0 | J40: PLC2O | K40: PLC2D | L40: PLC2C | Q40: AR0036431960 | T40: 0 | U40: 0 | V40: 0 | W40: 0 | Y40: PLC2O | Z40: Sin Calificar
A41: 57484 | B41: ON TELECOM CL. 18 V17/11/27 UVA CG | C41: O/N | E41: Porc. | F41: 0 | G41: 0.00 | I41: 0 | J41: TLCJO | Q41: AR0041103448 | T41: 0 | U41: 0 | V41: 0 | W41: 0 | Z41: Sin Calificar
A42: 09281 | B42: LT REP ARGENTINA CAP V13/12/24 $ CG | C42: Letr | E42: Porc. | F42: 0 | G42: 0.00 | I42: 0 | J42: S13D4 | K42: S13DD | L42: S13DC | P42: 13/12/24 | Q42: AR0041901791 | T42: 0 | U42: 0 | V42: 0 | W42: 0 | Y42: S13D4 | Z42: Sin Calificar
A43: 09310 | B43: BONO TESORO NACIONAL V15/12/25 $ CG | C43: Publ | E43: Porc. | F43: 0 | G43: 0.00 | I43: 0 | J43: T15D5 | Q43: AR0057122373 | T43: 0 | U43: 0 | V43: 0 | W43: 0 | Y43: T15D5 | Z43: Sin Calificar
A44: 09311 | B44: BONO TESORO NACION AJ CER V30/5/25 $ CG | C44: Publ | E44: Porc. | F44: 0 | G44: 0.00 | I44: 0 | J44: TZXY5 | M44: TXY5X | Q44: AR0058584431 | T44: 0 | U44: 0 | V44: 0 | W44: 0 | Y44: TZXY5 | Z44: Sin Calificar
A45: 58186 | B45: ON PYME CNV CAIMAN S.2 C.A $ V.30/10/26 | C45: O/N | E45: Porc. | F45: 0 | G45: 0.00 | I45: 0 | N45: U$S | Q45: AR0066632412 | T45: 0 | U45: 0 | V45: 0 | W45: 0 | Z45: Sin Calificar
A46: 57858 | B46: ON RIZOBACTER 9 CL.B U$S V 28/06/26 CG | C46: O/N | E46: Porc. | F46: 0 | G46: 1.00 | I46: 0 | J46: RZ9BO | N46: U$S | Q46: AR0069851811 | T46: 0 | U46: 0 | V46: 0 | W46: 0 | Y46: RZ9BO | Z46: Sin Calificar
A47: 09318 | B47: BONCAP $ 2,15% 30/06/26 | C47: Publ | E47: Porc. | F47: 0 | G47: 0.00 | I47: 0 | J47: T30J6 | Q47: AR0071678673 | T47: 0 | U47: 0 | V47: 0 | W47: 0 | Y47: T30J6 | Z47: Sin Calificar
A48: 58649 | B48: ON CNH IND. CL.9 V.21/05/27 U$S C.G. | C48: O/N | E48: Porc. | F48: 0 | G48: 0.00 | I48: 0 | J48: CIC9O | Q48: AR0073116151 | T48: 0 | U48: 0 | V48: 0 | W48: 0 | Z48: Sin Calificar
A49: 58130 | B49: ON YPF CLASE 33 U$S VTO 10/10/28 C.G | C49: O/N | E49: Porc. | F49: 0 | G49: 0.00 | I49: 0 | J49: YMCZO | K49: YMCZD | L49: YMCZC | Q49: AR0079616063 | T49: 0 | U49: 0 | V49: 0 | W49: 0 | Y49: YMCZO | Z49: Sin Calificar
A50: 58426 | B50: ON LEDESMA CL.15 VTO.04/10/27 U$S CG | C50: O/N | E50: Porc. | F50: 0 | G50: 0.00 | I50: 0 | J50: LDCGO | Q50: AR007977559 | T50: 0 | U50: 0 | V50: 0 | W50: 0 | Y50: LDCGO | Z50: Sin Calificar
A51: 08658 | B51: CEDEAR ETF SPDR GOLD TRUST | C51: Priv | E51: Normal | F51: 0 | G51: 0.00 | I51: 0 | J51: GLD | K51: GLDD | L51: GLDC | Q51: AR0082060689 | T51: 0 | U51: 0 | V51: 0 | W51: 0 | Z51: Sin Calificar
A52: 58338 | B52: ON BANCO HIPOTECARIO CL.8 V20/12/25 $ CG | C52: O/N | E52: Porc. | F52: 0 | G52: 0.00 | I52: 0 | J52: HBC8O | Q52: AR0083266764 | T52: 0 | U52: 0 | V52: 0 | W52: 0 | Z52: Sin Calificar
A53: 58150 | B53: ON IRSA INVYREP C23 V23/10/29 | C53: O/N | E53: Porc. | F53: 0 | G53: 0.00 | I53: 0 | J53: IRCOO | K53: IRCOD | L53: IRCOC | M53: IRCOO | N53: U$S | Q53: AR0084572384 | T53: 0 | U53: 0 | V53: 0 | W53: 0 | Y53: IRCOO | Z53: Sin Calificar
A54: 30061 | B54: DISTRIBUIDORA GAS DEL CENTRO | C54: Priv | E54: Normal | F54: 0 | G54: 0.00 | I54: 0 | J54: DGCE | Q54: AR0097356114 | T54: 0 | U54: 0 | V54: 0 | W54: 0 | Z54: Sin Calificar
A55: 58230 | B55: ON PAN AMERICAN ENER 37 V13/11/28 U$S CG | C55: O/N | E55: Porc. | F55: 0 | G55: 0.00 | I55: 0 | J55: PN37O | K55: PN37D | L55: PN37C | M55: PN37O | Q55: AR0098578880 | T55: 0 | U55: 0 | V55: 0 | W55: 0 | Y55: PN37O | Z55: Sin Calificar
A56: 09251 | B56: LT REP ARGENTINA CAP $ V31/01/25 | C56: Letr | E56: Porc. | F56: 0 | G56: 0.00 | I56: 0 | J56: S31E5 | M56: SE5X | P56: 31/01/25 | Q56: AR0104841496 | T56: 0 | U56: 0 | V56: 0 | W56: 0 | X56: AR0104841496 | Y56: S31E5 | Z56: Sin Calificar
A57: 09305 | B57: LETRAS DEL TESORO CAP $ V31/07/25 | C57: Letr | E57: Porc. | F57: 0 | G57: 0.00 | I57: 0 | J57: S31L5 | M57: SL5X | P57: 31/07/25 | Q57: AR0112750168 | T57: 0 | U57: 0 | V57: 0 | W57: 0 | Y57: S31L5 | Z57: Sin Calificar
A58: 09239 | B58: LT REP ARG AJ CER A DESC V20/05/24 $ CG | C58: Letr | E58: Porc. | F58: 0 | G58: 0.00 | I58: 0 | J58: X20Y4 | P58: 20/05/24 | Q58: AR0125910452 | T58: 0 | U58: 0 | V58: 0 | W58: 0 | Y58: X20Y4 | Z58: Sin Calificar
A59: 57828 | B59: ON YPF ENER.ELEC. C.16 V.13/12/25 U$S CG | C59: O/N | E59: Porc. | F59: 0 | G59: 0.00 | I59: 0 | J59: YFCHO | Q59: AR0128636096 | T59: 0 | U59: 0 | V59: 0 | W59: 0 | Y59: YFCHO | Z59: Sin Calificar
A60: 57855 | B60: ON YPF CLASE 30 U$S VTO 01/07/26 C.G | C60: O/N | E60: Porc. | F60: 0 | G60: 0.00 | I60: 0 | J60: YMCWO | Q60: AR0132676112 | T60: 0 | U60: 0 | V60: 0 | W60: 0 | X60: AR0132676112 | Y60: YMCWO | Z60: Sin Calificar
A61: 08598 | B61: CEDEAR PALANTIR TECHNOLOGIES INC | C61: Priv | E61: Normal | F61: 0 | G61: 0.00 | I61: 0 | J61: PLTR | Q61: AR0132889822 | T61: 0 | U61: 0 | V61: 0 | W61: 0 | Y61: PLTR | Z61: Sin Calificar
A62: 09248 | B62: BONTES $ A DESC AJ CER V15/12/25 | C62: Publ | E62: Porc. | F62: 0 | G62: 0.00 | I62: 0 | J62: TZXD5 | Q62: AR0137939010 | T62: 0 | U62: 0 | V62: 0 | W62: 0 | X62: AR0137939010 | Y62: TZXD5 | Z62: Sin Calificar
A63: 58133 | B63: ON VISTA ENERGY CL.26 V10/10/31 U$S CG | C63: O/N | E63: Porc. | F63: 0 | G63: 0.00 | I63: 0 | J63: VSCRO | K63: VSCRD | L63: VSCRC | N63: DOLAR | Q63: AR0138120560 | T63: 0 | U63: 0 | V63: 0 | W63: 0 | Z63: Sin Calificar
A64: 57646 | B64: ON EDENOR CL.3 V.22/11/26 U$S CG | C64: O/N | E64: Porc. | F64: 0 | G64: 0.00 | I64: 0 | J64: DNC3O | K64: DNC3D | L64: DNC3C | N64: U$S | Q64: AR0140482933 | T64: 0 | U64: 0 | V64: 0 | W64: 0 | Z64: Sin Calificar
A65: 57575 | B65: ON ALBANESI ENERGIA 12 V14/02/26 U$S CG | C65: O/N | E65: Porc. | F65: 0 | G65: 0.00 | I65: 0 | J65: LECDO | Q65: AR0142866786 | T65: 0 | U65: 0 | V65: 0 | W65: 0 | Y65: LECDO | Z65: Sin Calificar
A66: 09306 | B66: LETRAS DEL TESORO CAP $ V30/09/25 | C66: Letr | E66: Porc. | F66: 0 | G66: 0.00 | I66: 0 | J66: S30S5 | P66: 30/09/25 | Q66: AR0145235914 | T66: 0 | U66: 0 | V66: 0 | W66: 0 | Y66: S30S5 | Z66: Sin Calificar
A67: 58535 | B67: ON BANCO INDUSTRIAL CL.1 V.08/09/25 U$S | C67: O/N | E67: Porc. | F67: 0 | G67: 0.00 | I67: 0 | J67: IBC1O | K67: IBC1O | N67: U$S | Q67: AR0146793887 | T67: 0 | U67: 0 | V67: 0 | W67: 0 | Y67: IBC1O | Z67: Sin Calificar
A68: 58361 | B68: ON AEROP ARG 2000 11 V15/12/26 U$S CG | C68: O/N | E68: Porc. | F68: 0 | G68: 0.00 | I68: 0 | J68: AERBO | N68: U$S | Q68: AR0162186347 | T68: 0 | U68: 0 | V68: 0 | W68: 0 | Z68: Sin Calificar
A69: 58525 | B69: ON CIA GEN.COMB. CL.37 V10/03/27 U$S CG | C69: O/N | E69: Porc. | F69: 0 | G69: 0.00 | I69: 0 | J69: CP37 | K69: CP37D | N69: U$S | Q69: AR0172788611 | T69: 0 | U69: 0 | V69: 0 | W69: 0 | X69: AR0172788611 | Z69: Sin Calificar
A70: 57220 | B70: ON PYME PRODUSEM S2 CL2 U$S V30/04/26 CG | C70: O/N | E70: Porc. | F70: 0 | G70: 0.00 | I70: 0 | J70: DF31P | K70: DF31D | L70: DF31C | Q70: AR0178833023 | T70: 0 | U70: 0 | V70: 0 | W70: 0 | Z70: Sin Calificar
A71: 57720 | B71: ON PYME PRODUSEM S2 CL2 U$S V30/04/26 CG | C71: O/N | E71: Porc. | F71: 0 | G71: 0.00 | I71: 0 | J71: PO22P | Q71: AR0178833023 | T71: 0 | U71: 0 | V71: 0 | W71: 0 | X71: AR0178833023 | Y71: PO22P | Z71: Sin Calificar
A72: 57437 | B72: ON ALUAR S.7 V12/10/28 U$S CG | C72: O/N | E72: Porc. | F72: 0 | G72: 0.00 | I72: 0 | J72: LMS7O | K72: LMS7D | L72: LMS7C | M72: LMS7O | N72: U$S | Q72: AR0183513875 | T72: 0 | U72: 0 | V72: 0 | W72: 0 | Y72: LMS7O | Z72: Sin Calificar
A73: 83364 | B73: ON ALUAR S.7 V12/10/28 U$S CG | C73: O/N | E73: Porc. | F73: 0 | G73: 1.00 | I73: 0 | J73: 83364 | N73: DOLAR | Q73: AR0183513875 | T73: 0 | U73: 0 | V73: 0 | W73: 0 | Z73: Sin Calificar
A74: 58340 | B74: ON BANCO COMAFI CL.7 V19/03/25 U$S CG | C74: O/N | E74: Porc. | F74: 0 | G74: 0.00 | I74: 0 | J74: AFC7A | K74: AFC7D | Q74: AR0184512785 | T74: 0 | U74: 0 | V74: 0 | W74: 0 | Y74: AFC7A | Z74: Sin Calificar
A75: 57597 | B75: ON IRSA INVER Y REP C19 V28/02/25 $ CG | C75: O/N | E75: Porc. | F75: 0 | G75: 0.00 | H75: 100 | I75: 0 | J75: IRCKO | Q75: AR0185328686 | T75: 0 | U75: 0 | V75: 0 | W75: 0 | X75: AR0185328686 | Z75: Sin Calificar
A76: 09297 | B76: LETRAS DEL TESORO CAP $ 14/02/25 | C76: Letr | E76: Porc. | F76: 0 | G76: 0.00 | I76: 0 | J76: S14F5 | M76: S2F5X | P76: 14/02/25 | Q76: AR0188958448 | T76: 0 | U76: 0 | V76: 0 | W76: 0 | Y76: S14F5 | Z76: Sin Calificar
A77: 83981 | B77: LETRAS DEL TESORO CAP $ 14/02/25 | C77: Publ | E77: Porc. | F77: 0 | G77: 0.00 | I77: 0 | N77: DOLAR | Q77: AR0188958448 | T77: 0 | U77: 0 | V77: 0 | W77: 0 | X77: AR0188958448 | Z77: Sin Calificar
A78: 57803 | B78: ON IRSA CL.20 6% U$S VTO.10/06/26 CG | C78: O/N | E78: Porc. | F78: 0 | G78: 0.00 | I78: 0 | J78: IRCLO | K78: IRCLD | L78: IRCLC | N78: U$S | Q78: AR0200915251 | T78: 0 | U78: 0 | V78: 0 | W78: 0 | Y78: IRCLO | Z78: Sin Calificar
A79: 57774 | B79: ON YPF CLASE 29 U$S VT28/05/26 C.G | C79: O/N | E79: Porc. | F79: 0 | G79: 0.00 | I79: 0 | J79: YMCVO | K79: YMCVD | L79: YMCVC | M79: YMCVO | N79: U$S | Q79: AR0202080054 | T79: 0 | U79: 0 | V79: 0 | W79: 0 | Y79: YMCVO | Z79: Sin Calificar
A80: 57439 | B80: ON GEN MEDIT Y ROCA CL XXV | C80: O/N | E80: Porc. | F80: 0 | G80: 0.00 | I80: 0 | J80: MRCQO | K80: MRCQD | L80: MRCQC | N80: U$S | Q80: AR0203590796 | T80: 0 | U80: 0 | V80: 0 | W80: 0 | Z80: Sin Calificar
A81: 58119 | B81: VD FF CLUB RIVER PLATE UVA CG | C81: Fide | E81: Porc. | F81: 0 | G81: 0.00 | I81: 0 | J81: CARP | Q81: AR0206289149 | T81: 0 | U81: 0 | V81: 0 | W81: 0 | Z81: Sin Calificar
A82: 57838 | B82: ON CREDICUOTAS CONSUMO 8 V12/06/25 $ CG | C82: O/N | E82: Porc. | F82: 0 | G82: 0.00 | H82: 100 | I82: 0 | J82: DNS8O | Q82: AR0212698713 | T82: 0 | U82: 0 | V82: 0 | W82: 0 | Z82: Sin Calificar
A83: 57817 | B83: ON ALUAR S.9 V13/06/26 U$S CG | C83: O/N | E83: Porc. | F83: 0 | G83: 0.00 | I83: 0 | J83: LMS9O | K83: LMS9D | L83: LMS9C | N83: U$S | Q83: AR0226237573 | T83: 0 | U83: 0 | V83: 0 | W83: 0 | Y83: LMS9O | Z83: Sin Calificar
A84: 08644 | B84: CEDEAR FERRARI NV | C84: Priv | E84: Normal | F84: 0 | G84: 1.00 | I84: 0 | J84: RACE | K84: RACED | L84: RACEC | Q84: AR0227017768 | T84: 0 | U84: 0 | V84: 0 | W84: 0 | Z84: Sin Calificar
A85: 09321 | B85: BONO NACION TASA DUAL15/09/26 $ CG | C85: Publ | E85: Porc. | F85: 0 | G85: 0.00 | I85: 0 | J85: TTS26 | Q85: AR0227219554 | T85: 0 | U85: 0 | V85: 0 | W85: 0 | Y85: TTS26 | Z85: Sin Calificar
A86: 58435 | B86: ON SAN MIGUEL S.12 V06/02/27 U$S CG | C86: O/N | E86: Porc. | F86: 0 | G86: 0.00 | I86: 0 | J86: SNSDO | N86: U$S | Q86: AR0228143829 | T86: 0 | U86: 0 | V86: 0 | W86: 0 | Z86: Sin Calificar
A87: 58256 | B87: ON TELECOM CL.23 28/11/28 U$S CG | C87: O/N | E87: Porc. | F87: 0 | G87: 0.00 | I87: 0 | J87: TLCOO | N87: U$S | Q87: AR0241562484 | T87: 0 | U87: 0 | V87: 0 | W87: 0 | Z87: Sin Calificar
A88: 58483 | B88: ON 360 ENER.SOL. CL.5 V05/09/27 U$S C.G. | C88: O/N | E88: Porc. | F88: 0 | G88: 0.00 | I88: 0 | J88: GYC5O | Q88: AR0253143579 | T88: 0 | U88: 0 | V88: 0 | W88: 0 | Y88: GYC5O | Z88: Sin Calificar
A89: 09293 | B89: LT REP ARGENTINA CAP V11/11/24 $ CG | C89: Letr | E89: Porc. | F89: 0 | G89: 0.00 | I89: 0 | J89: S11N4 | P89: 11/11/24 | Q89: AR0254563239 | T89: 0 | U89: 0 | V89: 0 | W89: 0 | Y89: S11N4 | Z89: Sin Calificar
A90: 65126 | B90: LT REP ARGENTINA CAP V11/11/24 $ CG | C90: Letr | E90: Porc. | F90: 0 | G90: 0.00 | I90: 0 | J90: S11N4 | P90: 11/11/24 | Q90: AR0254563239 | T90: 0 | U90: 0 | V90: 0 | W90: 0 | Z90: Sin Calificar
A91: 08591 | B91: CEDEAR BRASKEM SA | C91: Priv | E91: Normal | F91: 0 | G91: 0.00 | I91: 0 | J91: BAK | Q91: AR0261973801 | T91: 0 | U91: 0 | V91: 0 | W91: 0 | Z91: Sin Calificar
A92: 58557 | B92: ON CREDICUO CONS 12 CL.1 V29/04/26 $ CG | C92: O/N | E92: Porc. | F92: 0 | G92: 0.00 | I92: 0 | J92: ONCC0426 | Q92: AR0268994289 | T92: 0 | U92: 0 | V92: 0 | W92: 0 | Z92: Sin Calificar
A93: 58260 | B93: ON RIZOBACTER S.10 CL.B V28/11/27 U$S CG | C93: O/N | E93: Porc. | F93: 0 | G93: 0.00 | I93: 0 | J93: RZABO | N93: U$S | Q93: AR0272566107 | T93: 0 | U93: 0 | V93: 0 | W93: 0 | Z93: Sin Calificar
A94: 58149 | B94: ON IRSA C22 V23/10/27 | C94: O/N | E94: Porc. | F94: 0 | G94: 0.00 | I94: 0 | J94: IRCNO | Q94: AR0275431465 | T94: 0 | U94: 0 | V94: 0 | W94: 0 | Y94: IRCNO | Z94: Sin Calificar
A95: 09225 | B95: BONOS TESORO CER+4,25 23/05/25 | C95: Publ | E95: Porc. | F95: 0 | G95: 0.00 | I95: 0 | J95: T4X5 | K95: T4X5D | L95: T4X5C | M95: T4X5X | Q95: AR0281825940 | T95: 0 | U95: 0 | V95: 0 | W95: 0 | Y95: T4X5 | Z95: Sin Calificar
A96: 58470 | B96: ON BCO BBVA ARG CL.33 V.27/08/25 U$S CG | C96: O/N | E96: Porc. | F96: 0 | G96: 0.00 | I96: 0 | K96: BFCZD | Q96: AR0283170097 | T96: 0 | U96: 0 | V96: 0 | W96: 0 | Z96: Sin Calificar
A97: 57423 | B97: ON PETRO. ACONCAGUA 17 V30/01/28 U$S CG | C97: O/N | E97: Porc. | F97: 0 | G97: 0.00 | I97: 0 | J97: PECIO | K97: PECIO | N97: U$S | Q97: AR0288436246 | T97: 0 | U97: 0 | V97: 0 | W97: 0 | X97: AR0288436246 | Y97: PECIO | Z97: Sin Calificar
A98: 57723 | B98: ON CAPEX CL.8 U$S V.29/06/26 C.G. | C98: O/N | E98: Porc. | F98: 0 | G98: 0.00 | I98: 0 | J98: CAC8O | K98: CAC8D | L98: CAC8C | N98: U$S | Q98: AR0292006183 | T98: 0 | U98: 0 | V98: 0 | W98: 0 | X98: AR0292006183 | Z98: Sin Calificar
A99: 09327 | B99: LT REP ARG VINC. AL U$S 16/01/26 CG | C99: Letr | E99: Porc. | F99: 0 | G99: 0.00 | I99: 0 | J99: D16E6 | P99: 16/01/26 | Q99: AR0306034593 | T99: 0 | U99: 0 | V99: 0 | W99: 0 | Z99: Sin Calificar
A100: 09295 | B100: LT REP ARGENTINA CAP V30/06/25 $ CG | C100: Letr | E100: Porc. | F100: 0 | G100: 0.00 | I100: 0 | J100: S30J5 | P100: 30/06/25 | Q100: AR0308405304 | T100: 0 | U100: 0 | V100: 0 | W100: 0 | Y100: S30J5 | Z100: Sin Calificar
...

Sheet Cotizacion Dolar Historica
A1: Fecha | B1: Referencia | C1: Moneda
A2: 46021 | B2: 1480.74 | C2: Dolar MEP (local)
A3: 46020 | B3: 1484.35 | C3: Dolar MEP (local)
A4: 46017 | B4: 1486.11 | C4: Dolar MEP (local)
A5: 46016 | B5: 1481.63 | C5: Dolar MEP (local)
A6: 46015 | B6: 1481.63 | C6: Dolar MEP (local)
A7: 46014 | B7: 1479.44 | C7: Dolar MEP (local)
A8: 46013 | B8: 1493.06 | C8: Dolar MEP (local)
A9: 46010 | B9: 1494.62 | C9: Dolar MEP (local)
A10: 46009 | B10: 1498.58 | C10: Dolar MEP (local)
A11: 46008 | B11: 1514.14 | C11: Dolar MEP (local)
A12: 46007 | B12: 1504.3 | C12: Dolar MEP (local)
A13: 46006 | B13: 1492.01 | C13: Dolar MEP (local)
... A3490: 43853 | B3490: 81.64 | C3490: Dolar Cable (exterior)

Sheet PreciosInicialesEspecies
A1: 'ESPECIE' | B1: 'NOMBRE' | C1: 'ORDEN' | D1: 'FEC.ANT.' | E1: 'PCIO.' | F1: 'FECHA' | G1: 'PRECIO' | H1: Tipo Instrumento | I1: Precio Nominal | J1: Precio Nominal USD
A2: 7 | B2: ALUA ALUAR | C2: ALUA | D2: 45656 | E2: 892 | F2: 45659 | G2: 893 | H2: =IF(ISERROR(VLOOKUP(A2,EspeciesVisual!C:R,16,FALSE)),"",VLOOKUP(A2,EspeciesVisual!C:R,16,FALSE)) | I2: =IF(OR(ISNUMBER(SEARCH("obligacion",LOWER(H2))),ISNUMBER(SEARCH("titulo",LOWER(H2))),ISNUMBER(SEARCH("letra",LOWER(H2)))),G2/100,G2) | J2: =I2/1167.806
A3: 19 | B3: AGRO AGROMETAL | C3: AGRO | D3: 45656 | E3: 72.1 | F3: 45659 | G3: 74.3 | H3: =IF(ISERROR(VLOOKUP(A3,EspeciesVisual!C:R,16,FALSE)),"",VLOOKUP(A3,EspeciesVisual!C:R,16,FALSE)) | I3: =IF(OR(ISNUMBER(SEARCH("obligacion",LOWER(H3))),ISNUMBER(SEARCH("titulo",LOWER(H3))),ISNUMBER(SEARCH("letra",LOWER(H3)))),G3/100,G3) | J3: =I3/1167.806
A4: 49 | B4: OEST GRUPO CONCESIONARIO DEL O | C4: OEST | D4: 45656 | E4: 1145 | F4: 45659 | G4: 1130 | H4: =IF(ISERROR(VLOOKUP(A4,EspeciesVisual!C:R,16,FALSE)),"",VLOOKUP(A4,EspeciesVisual!C:R,16,FALSE)) | I4: =IF(OR(ISNUMBER(SEARCH("obligacion",LOWER(H4))),ISNUMBER(SEARCH("titulo",LOWER(H4))),ISNUMBER(SEARCH("letra",LOWER(H4)))),G4/100,G4) | J4: =I4/1167.806
A5: 59 | B5: ARSA ASTARSA | C5: ARSA | E5: 0 | F5: 42762 | G5: 1 | H5: =IF(ISERROR(VLOOKUP(A5,EspeciesVisual!C:R,16,FALSE)),"",VLOOKUP(A5,EspeciesVisual!C:R,16,FALSE)) | I5: =IF(OR(ISNUMBER(SEARCH("obligacion",LOWER(H5))),ISNUMBER(SEARCH("titulo",LOWER(H5))),ISNUMBER(SEARCH("letra",LOWER(H5)))),G5/100,G5) | J5: =I5/1167.806
A6: 66 | B6: AUTOPISTAS DEL SOL | C6: AUSO | D6: 45656 | E6: 3835 | F6: 45659 | G6: 3895 | H6: =IF(ISERROR(VLOOKUP(A6,EspeciesVisual!C:R,16,FALSE)),"",VLOOKUP(A6,EspeciesVisual!C:R,16,FALSE)) | I6: =IF(OR(ISNUMBER(SEARCH("obligacion",LOWER(H6))),ISNUMBER(SEARCH("titulo",LOWER(H6))),ISNUMBER(SEARCH("letra",LOWER(H6)))),G6/100,G6) | J6: =I6/1167.806
A7: 67 | B7: GBAN GAS NATURAL BAN | C7: GBAN | D7: 45656 | E7: 2150 | F7: 45659 | G7: 2200 | H7: =IF(ISERROR(VLOOKUP(A7,EspeciesVisual!C:R,16,FALSE)),"",VLOOKUP(A7,EspeciesVisual!C:R,16,FALSE)) | I7: =IF(OR(ISNUMBER(SEARCH("obligacion",LOWER(H7))),ISNUMBER(SEARCH("titulo",LOWER(H7))),ISNUMBER(SEARCH("letra",LOWER(H7)))),G7/100,G7) | J7: =I7/1167.806
A8: 71 | B8: AZUC AZUCARERA ARGENTINA | C8: AZUC | E8: 0 | F8: 42762 | G8: 1 | H8: =IF(ISERROR(VLOOKUP(A8,EspeciesVisual!C:R,16,FALSE)),"",VLOOKUP(A8,EspeciesVisual!C:R,16,FALSE)) | I8: =IF(OR(ISNUMBER(SEARCH("obligacion",LOWER(H8))),ISNUMBER(SEARCH("titulo",LOWER(H8))),ISNUMBER(SEARCH("letra",LOWER(H8)))),G8/100,G8) | J8: =I8/1167.806
A9: 94 | B9: FRAN BANCO FRANCES | C9: BBAR | D9: 45656 | E9: 7560 | F9: 45659 | G9: 8570 | H9: =IF(ISERROR(VLOOKUP(A9,EspeciesVisual!C:R,16,FALSE)),"",VLOOKUP(A9,EspeciesVisual!C:R,16,FALSE)) | I9: =IF(OR(ISNUMBER(SEARCH("obligacion",LOWER(H9))),ISNUMBER(SEARCH("titulo",LOWER(H9))),ISNUMBER(SEARCH("letra",LOWER(H9)))),G9/100,G9) | J9: =I9/1167.806
A10: 111 | B10: BANCO MACRO S.A. | C10: BMA | D10: 45656 | E10: 11450 | F10: 45659 | G10: 12850 | H10: =IF(ISERROR(VLOOKUP(A10,EspeciesVisual!C:R,16,FALSE)),"",VLOOKUP(A10,EspeciesVisual!C:R,16,FALSE)) | I10: =IF(OR(ISNUMBER(SEARCH("obligacion",LOWER(H10))),ISNUMBER(SEARCH("titulo",LOWER(H10))),ISNUMBER(SEARCH("letra",LOWER(H10)))),G10/100,G10) | J10: =I10/1167.806
A11: 169 | B11: CGPA2 CAMUZZI GAS PAMPEANA | C11: CGPA2 | D11: 45656 | E11: 3880 | F11: 45659 | G11: 3775 | H11: =IF(ISERROR(VLOOKUP(A11,EspeciesVisual!C:R,16,FALSE)),"",VLOOKUP(A11,EspeciesVisual!C:R,16,FALSE)) | I11: =IF(OR(ISNUMBER(SEARCH("obligacion",LOWER(H11))),ISNUMBER(SEARCH("titulo",LOWER(H11))),ISNUMBER(SEARCH("letra",LOWER(H11)))),G11/100,G11) | J11: =I11/1167.806
A12: 204 | B12: CADO CARLOS CASADO | C12: CADO | D12: 45656 | E12: 506 | F12: 45659 | G12: 511 | H12: =IF(ISERROR(VLOOKUP(A12,EspeciesVisual!C:R,16,FALSE)),"",VLOOKUP(A12,EspeciesVisual!C:R,16,FALSE)) | I12: =IF(OR(ISNUMBER(SEARCH("obligacion",LOWER(H12))),ISNUMBER(SEARCH("titulo",LOWER(H12))),ISNUMBER(SEARCH("letra",LOWER(H12)))),G12/100,G12) | J12: =I12/1167.806
A13: 223 | B13: CELU CELULOSA ARGENTINA | C13: CELU | D13: 45656 | E13: 932 | F13: 45659 | G13: 910 | H13: =IF(ISERROR(VLOOKUP(A13,EspeciesVisual!C:R,16,FALSE)),"",VLOOKUP(A13,EspeciesVisual!C:R,16,FALSE)) | I13: =IF(OR(ISNUMBER(SEARCH("obligacion",LOWER(H13))),ISNUMBER(SEARCH("titulo",LOWER(H13))),ISNUMBER(SEARCH("letra",LOWER(H13)))),G13/100,G13) | J13: =I13/1167.806
A14: 247 | B14: COLORIN S.A. (COLO) | C14: COLO | D14: 43656 | E14: 12.5 | F14: 43661 | G14: 12.55 | H14: =IF(ISERROR(VLOOKUP(A14,EspeciesVisual!C:R,16,FALSE)),"",VLOOKUP(A14,EspeciesVisual!C:R,16,FALSE)) | I14: =IF(OR(ISNUMBER(SEARCH("obligacion",LOWER(H14))),ISNUMBER(SEARCH("titulo",LOWER(H14))),ISNUMBER(SEARCH("letra",LOWER(H14)))),G14/100,G14) | J14: =I14/1167.806
A15: 251 | B15: COME COMERCIAL DEL PLATA | C15: COME | D15: 45656 | E15: 248.5 | F15: 45659 | G15: 260.5 | H15: =IF(ISERROR(VLOOKUP(A15,EspeciesVisual!C:R,16,FALSE)),"",VLOOKUP(A15,EspeciesVisual!C:R,16,FALSE)) | I15: =IF(OR(ISNUMBER(SEARCH("obligacion",LOWER(H15))),ISNUMBER(SEARCH("titulo",LOWER(H15))),ISNUMBER(SEARCH("letra",LOWER(H15)))),G15/100,G15) | J15: =I15/1167.806
A16: 274 | B16: CRES CRESUD | C16: CRES | D16: 45656 | E16: 1495 | F16: 45659 | G16: 1560 | H16: =IF(ISERROR(VLOOKUP(A16,EspeciesVisual!C:R,16,FALSE)),"",VLOOKUP(A16,EspeciesVisual!C:R,16,FALSE)) | I16: =IF(OR(ISNUMBER(SEARCH("obligacion",LOWER(H16))),ISNUMBER(SEARCH("titulo",LOWER(H16))),ISNUMBER(SEARCH("letra",LOWER(H16)))),G16/100,G16) | J16: =I16/1167.806
A17: 283 | B17: RIGO CRIST. RIGOLLEAU | C17: RIGO | D17: 45656 | E17: 1040 | F17: 45659 | G17: 1035 | H17: =IF(ISERROR(VLOOKUP(A17,EspeciesVisual!C:R,16,FALSE)),"",VLOOKUP(A17,EspeciesVisual!C:R,16,FALSE)) | I17: =IF(OR(ISNUMBER(SEARCH("obligacion",LOWER(H17))),ISNUMBER(SEARCH("titulo",LOWER(H17))),ISNUMBER(SEARCH("letra",LOWER(H17)))),G17/100,G17) | J17: =I17/1167.806
A18: 307 | B18: DGCU2 DISTRIB. GAS CUYANA | C18: DGCU2 | D18: 45656 | E18: 1890 | F18: 45659 | G18: 1925 | H18: =IF(ISERROR(VLOOKUP(A18,EspeciesVisual!C:R,16,FALSE)),"",VLOOKUP(A18,EspeciesVisual!C:R,16,FALSE)) | I18: =IF(OR(ISNUMBER(SEARCH("obligacion",LOWER(H18))),ISNUMBER(SEARCH("titulo",LOWER(H18))),ISNUMBER(SEARCH("letra",LOWER(H18)))),G18/100,G18) | J18: =I18/1167.806
A19: 322 | B19: CEPU2 CENTRAL PUERTO | C19: CEPU | D19: 45656 | E19: 1770 | F19: 45659 | G19: 1820 | H19: =IF(ISERROR(VLOOKUP(A19,EspeciesVisual!C:R,16,FALSE)),"",VLOOKUP(A19,EspeciesVisual!C:R,16,FALSE)) | I19: =IF(OR(ISNUMBER(SEARCH("obligacion",LOWER(H19))),ISNUMBER(SEARCH("titulo",LOWER(H19))),ISNUMBER(SEARCH("letra",LOWER(H19)))),G19/100,G19) | J19: =I19/1167.806
A20: 336 | B20: DOME DOMEC S.A. | C20: DOME | D20: 45653 | E20: 70.5 | F20: 45659 | G20: 61 | H20: =IF(ISERROR(VLOOKUP(A20,EspeciesVisual!C:R,16,FALSE)),"",VLOOKUP(A20,EspeciesVisual!C:R,16,FALSE)) | I20: =IF(OR(ISNUMBER(SEARCH("obligacion",LOWER(H20))),ISNUMBER(SEARCH("titulo",LOWER(H20))),ISNUMBER(SEARCH("letra",LOWER(H20)))),G20/100,G20) | J20: =I20/1167.806
... A38: 666 | B38: LONG LONGVIE | C38: LONG | D38: 45656 | E38: 36.35 | F38: 45659 | G38: 35.95 | H38: =IF(ISERROR(VLOOKUP(A38,EspeciesVisual!C:R,16,FALSE)),"",VLOOKUP(A38,EspeciesVisual!C:R,16,FALSE)) | I38: =IF(OR(ISNUMBER(SEARCH("obligacion",LOWER(H38))),ISNUMBER(SEARCH("titulo",LOWER(H38))),ISNUMBER(SEARCH("letra",LOWER(H38)))),G38/100,G38) | J38: =I38/1167.806
A39: 706 | B39: PICA NOBLEZA PICCARDO | C39: PICA | E39: 0 | F39: 42762 | G39: 1 | H39: =IF(ISERROR(VLOOKUP(A39,EspeciesVisual!C:R,16,FALSE)),"",VLOOKUP(A39,EspeciesVisual!C:R,16,FALSE)) | I39: =IF(OR(ISNUMBER(SEARCH("obligacion",LOWER(H39))),ISNUMBER(SEARCH("titulo",LOWER(H39))),ISNUMBER(SEARCH("letra",LOWER(H39)))),G39/100,G39) | J39: =I39/1167.806
A40: 710 | B40: YPFD YPF S.A. ESCRITURALES | C40: YPFD | D40: 45656 | E40: 50300 | F40: 45659 | G40: 52400 | H40: =IF(ISERROR(VLOOKUP(A40,EspeciesVisual!C:R,16,FALSE)),"",VLOOKUP(A40,EspeciesVisual!C:R,16,FALSE)) | I40: =IF(OR(ISNUMBER(SEARCH("obligacion",LOWER(H40))),ISNUMBER(SEARCH("titulo",LOWER(H40))),ISNUMBER(SEARCH("letra",LOWER(H40)))),G40/100,G40) | J40: =I40/1167.806
A41: 733 | B41: HARG HOLCIM ARGENTINA SA | C41: HARG | D41: 45656 | E41: 2170 | F41: 45659 | G41: 2230 | H41: =IF(ISERROR(VLOOKUP(A41,EspeciesVisual!C:R,16,FALSE)),"",VLOOKUP(A41,EspeciesVisual!C:R,16,FALSE)) | I41: =IF(OR(ISNUMBER(SEARCH("obligacion",LOWER(H41))),ISNUMBER(SEARCH("titulo",LOWER(H41))),ISNUMBER(SEARCH("letra",LOWER(H41)))),G41/100,G41) | J41: =I41/1167.806
A42: 740 | B42: SEMI MOLINOS J. SEMINO | C42: SEMI | D42: 45656 | E42: 41.25 | F42: 45659 | G42: 41.15 | H42: =IF(ISERROR(VLOOKUP(A42,EspeciesVisual!C:R,16,FALSE)),"",VLOOKUP(A42,EspeciesVisual!C:R,16,FALSE)) | I42: =IF(OR(ISNUMBER(SEARCH("obligacion",LOWER(H42))),ISNUMBER(SEARCH("titulo",LOWER(H42))),ISNUMBER(SEARCH("letra",LOWER(H42)))),G42/100,G42) | J42: =I42/1167.806
A43: 741 | B43: MOLINOS RIO | C43: MOLI5 | D43: 45652 | E43: 4575 | F43: 45659 | G43: 4800 | H43: =IF(ISERROR(VLOOKUP(A43,EspeciesVisual!C:R,16,FALSE)),"",VLOOKUP(A43,EspeciesVisual!C:R,16,FALSE)) | I43: =IF(OR(ISNUMBER(SEARCH("obligacion",LOWER(H43))),ISNUMBER(SEARCH("titulo",LOWER(H43))),ISNUMBER(SEARCH("letra",LOWER(H43)))),G43/100,G43) | J43: =I43/1167.806
A44: 742 | B44: MOLI MOLINOS RIO DE LA PLATA | C44: MOLI | D44: 45656 | E44: 5210 | F44: 45659 | G44: 5280 | H44: =IF(ISERROR(VLOOKUP(A44,EspeciesVisual!C:R,16,FALSE)),"",VLOOKUP(A44,EspeciesVisual!C:R,16,FALSE)) | I44: =IF(OR(ISNUMBER(SEARCH("obligacion",LOWER(H44))),ISNUMBER(SEARCH("titulo",LOWER(H44))),ISNUMBER(SEARCH("letra",LOWER(H44)))),G44/100,G44) | J44: =I44/1167.806
A45: 748 | B45: MORI MORIXE HNOS | C45: MORI | D45: 45656 | E45: 377.5 | F45: 45659 | G45: 384.5 | H45: =IF(ISERROR(VLOOKUP(A45,EspeciesVisual!C:R,16,FALSE)),"",VLOOKUP(A45,EspeciesVisual!C:R,16,FALSE)) | I45: =IF(OR(ISNUMBER(SEARCH("obligacion",LOWER(H45))),ISNUMBER(SEARCH("titulo",LOWER(H45))),ISNUMBER(SEARCH("letra",LOWER(H45)))),G45/100,G45) | J45: =I45/1167.806
A46: 751 | B46: BHIP BANCO HIPOTECARIO | C46: BHIP | D46: 45656 | E46: 571 | F46: 45659 | G46: 602 | H46: =IF(ISERROR(VLOOKUP(A46,EspeciesVisual!C:R,16,FALSE)),"",VLOOKUP(A46,EspeciesVisual!C:R,16,FALSE)) | I46: =IF(OR(ISNUMBER(SEARCH("obligacion",LOWER(H46))),ISNUMBER(SEARCH("titulo",LOWER(H46))),ISNUMBER(SEARCH("letra",LOWER(H46)))),G46/100,G46) | J46: =I46/1167.806
A47: 798 | B47: MIRG MIRGOR | C47: MIRG | D47: 45656 | E47: 26075 | F47: 45659 | G47: 26575 | H47: =IF(ISERROR(VLOOKUP(A47,EspeciesVisual!C:R,16,FALSE)),"",VLOOKUP(A47,EspeciesVisual!C:R,16,FALSE)) | I47: =IF(OR(ISNUMBER(SEARCH("obligacion",LOWER(H47))),ISNUMBER(SEARCH("titulo",LOWER(H47))),ISNUMBER(SEARCH("letra",LOWER(H47)))),G47/100,G47) | J47: =I47/1167.806
A48: 807 | B48: TELECOM ARGENTINA ESCRIT."B" | C48: TECO2 | D48: 45656 | E48: 3070 | F48: 45659 | G48: 3170 | H48: =IF(ISERROR(VLOOKUP(A48,EspeciesVisual!C:R,16,FALSE)),"",VLOOKUP(A48,EspeciesVisual!C:R,16,FALSE)) | I48: =IF(OR(ISNUMBER(SEARCH("obligacion",LOWER(H48))),ISNUMBER(SEARCH("titulo",LOWER(H48))),ISNUMBER(SEARCH("letra",LOWER(H48)))),G48/100,G48) | J48: =I48/1167.806
A49: 810 | B49: PERK PERTRAK ARG. S.A. | C49: PERK | D49: 41912 | E49: 1.25 | F49: 41913 | G49: 1.28 | H49: =IF(ISERROR(VLOOKUP(A49,EspeciesVisual!C:R,16,FALSE)),"",VLOOKUP(A49,EspeciesVisual!C:R,16,FALSE)) | I49: =IF(OR(ISNUMBER(SEARCH("obligacion",LOWER(H49))),ISNUMBER(SEARCH("titulo",LOWER(H49))),ISNUMBER(SEARCH("letra",LOWER(H49)))),G49/100,G49) | J49: =I49/1167.806
A50: 839 | B50: TXAR TERNIUM ARGENTINA S.A. | C50: TXAR | D50: 45656 | E50: 895 | F50: 45659 | G50: 898 | H50: =IF(ISERROR(VLOOKUP(A50,EspeciesVisual!C:R,16,FALSE)),"",VLOOKUP(A50,EspeciesVisual!C:R,16,FALSE)) | I50: =IF(OR(ISNUMBER(SEARCH("obligacion",LOWER(H50))),ISNUMBER(SEARCH("titulo",LOWER(H50))),ISNUMBER(SEARCH("letra",LOWER(H50)))),G50/100,G50) | J50: =I50/1167.806
A51: 849 | B51: TRAN TRANSENER ORS. 1 VOTO | C51: TRAN | D51: 45656 | E51: 2750 | F51: 45659 | G51: 2830 | H51: =IF(ISERROR(VLOOKUP(A51,EspeciesVisual!C:R,16,FALSE)),"",VLOOKUP(A51,EspeciesVisual!C:R,16,FALSE)) | I51: =IF(OR(ISNUMBER(SEARCH("obligacion",LOWER(H51))),ISNUMBER(SEARCH("titulo",LOWER(H51))),ISNUMBER(SEARCH("letra",LOWER(H51)))),G51/100,G51) | J51: =I51/1167.806
... A54: 945 | B54: PSUR PETROLERA DEL CONOSUR 1 | C54: PSUR | D54: 43538 | E54: 3.65 | F54: 43738 | G54: 3.65 | H54: =IF(ISERROR(VLOOKUP(A54,EspeciesVisual!C:R,16,FALSE)),"",VLOOKUP(A54,EspeciesVisual!C:R,16,FALSE)) | I54: =IF(OR(ISNUMBER(SEARCH("obligacion",LOWER(H54))),ISNUMBER(SEARCH("titulo",LOWER(H54))),ISNUMBER(SEARCH("letra",LOWER(H54)))),G54/100,G54) | J54: =I54/1167.806
A55: 1002 | B55: CHEQUES | C55: CPD | E55: 0 | F55: 39426 | G55: 100 | H55: =IF(ISERROR(VLOOKUP(A55,EspeciesVisual!C:R,16,FALSE)),"",VLOOKUP(A55,EspeciesVisual!C:R,16,FALSE)) | I55: =IF(OR(ISNUMBER(SEARCH("obligacion",LOWER(H55))),ISNUMBER(SEARCH("titulo",LOWER(H55))),ISNUMBER(SEARCH("letra",LOWER(H55)))),G55/100,G55) | J55: =I55/1167.806
A56: 1003 | B56: PAGARE | C56: PAGARE | E56: 0 | F56: 44307 | G56: 100 | H56: =IF(ISERROR(VLOOKUP(A56,EspeciesVisual!C:R,16,FALSE)),"",VLOOKUP(A56,EspeciesVisual!C:R,16,FALSE)) | I56: =IF(OR(ISNUMBER(SEARCH("obligacion",LOWER(H56))),ISNUMBER(SEARCH("titulo",LOWER(H56))),ISNUMBER(SEARCH("letra",LOWER(H56)))),G56/100,G56) | J56: =I56/1167.806
A57: 1006 | B57: PAGARE DOLARES | C57: PAGARED | D57: 45656 | E57: 100 | F57: 45659 | G57: 100 | H57: =IF(ISERROR(VLOOKUP(A57,EspeciesVisual!C:R,16,FALSE)),"",VLOOKUP(A57,EspeciesVisual!C:R,16,FALSE)) | I57: =IF(OR(ISNUMBER(SEARCH("obligacion",LOWER(H57))),ISNUMBER(SEARCH("titulo",LOWER(H57))),ISNUMBER(SEARCH("letra",LOWER(H57)))),G57/100,G57) | J57: =I57/1167.806
A58: 1008 | B58: FACTURA DE CREDITO | C58: FCE | D58: 44760 | E58: 100.1 | F58: 44761 | G58: 100.1 | H58: =IF(ISERROR(VLOOKUP(A58,EspeciesVisual!C:R,16,FALSE)),"",VLOOKUP(A58,EspeciesVisual!C:R,16,FALSE)) | I58: =IF(OR(ISNUMBER(SEARCH("obligacion",LOWER(H58))),ISNUMBER(SEARCH("titulo",LOWER(H58))),ISNUMBER(SEARCH("letra",LOWER(H58)))),G58/100,G58) | J58: =I58/1167.806
A59: 1009 | B59: FCE EN USD | C59: FCE | D59: 45656 | E59: 1 | F59: 45659 | G59: 1 | H59: =IF(ISERROR(VLOOKUP(A59,EspeciesVisual!C:R,16,FALSE)),"",VLOOKUP(A59,EspeciesVisual!C:R,16,FALSE)) | I59: =IF(OR(ISNUMBER(SEARCH("obligacion",LOWER(H59))),ISNUMBER(SEARCH("titulo",LOWER(H59))),ISNUMBER(SEARCH("letra",LOWER(H59)))),G59/100,G59) | J59: =I59/1167.806
A60: 1010 | B60: PAGARE A3500 | C60: PAG3500 | D60: 45657 | E60: 103.2 | F60: 45659 | G60: 100 | H60: =IF(ISERROR(VLOOKUP(A60,EspeciesVisual!C:R,16,FALSE)),"",VLOOKUP(A60,EspeciesVisual!C:R,16,FALSE)) | I60: =IF(OR(ISNUMBER(SEARCH("obligacion",LOWER(H60))),ISNUMBER(SEARCH("titulo",LOWER(H60))),ISNUMBER(SEARCH("letra",LOWER(H60)))),G60/100,G60) | J60: =I60/1167.806
A61: 1015 | B61: PAGARE HD | C61: PAGARE HD | E61: 0 | G61: 0 | H61: =IF(ISERROR(VLOOKUP(A61,EspeciesVisual!C:R,16,FALSE)),"",VLOOKUP(A61,EspeciesVisual!C:R,16,FALSE)) | I61: =IF(OR(ISNUMBER(SEARCH("obligacion",LOWER(H61))),ISNUMBER(SEARCH("titulo",LOWER(H61))),ISNUMBER(SEARCH("letra",LOWER(H61)))),G61/100,G61) | J61: =I61/1167.806
A62: 5320 | B62: BONO TESORO NAC. ARS 15.5% VTO | C62: TO26 | D62: 45656 | E62: 84.7 | F62: 45659 | G62: 88 | H62: =IF(ISERROR(VLOOKUP(A62,EspeciesVisual!C:R,16,FALSE)),"",VLOOKUP(A62,EspeciesVisual!C:R,16,FALSE)) | I62: =IF(OR(ISNUMBER(SEARCH("obligacion",LOWER(H62))),ISNUMBER(SEARCH("titulo",LOWER(H62))),ISNUMBER(SEARCH("letra",LOWER(H62)))),G62/100,G62) | J62: =I62/1167.806
A63: 5493 | B63: BONOS TESORO $ AJ. CER 1,50% V | C63: TX24 | D63: 45371 | E63: 1437 | F63: 45372 | G63: 1437 | H63: =IF(ISERROR(VLOOKUP(A63,EspeciesVisual!C:R,16,FALSE)),"",VLOOKUP(A63,EspeciesVisual!C:R,16,FALSE)) | I63: =IF(OR(ISNUMBER(SEARCH("obligacion",LOWER(H63))),ISNUMBER(SEARCH("titulo",LOWER(H63))),ISNUMBER(SEARCH("letra",LOWER(H63)))),G63/100,G63) | J63: =I63/1167.806
A64: 5796 | B64: CHEVRON CORPORATION (CVX) | C64: CVX-US | D64: 45657 | E64: 144.84 | F64: 45659 | G64: 146.71 | H64: =IF(ISERROR(VLOOKUP(A64,EspeciesVisual!C:R,16,FALSE)),"",VLOOKUP(A64,EspeciesVisual!C:R,16,FALSE)) | I64: =IF(OR(ISNUMBER(SEARCH("obligacion",LOWER(H64))),ISNUMBER(SEARCH("titulo",LOWER(H64))),ISNUMBER(SEARCH("letra",LOWER(H64)))),G64/100,G64) | J64: =I64/1167.806
A65: 5821 | B65: CIA SIDERURGICA NACL | C65: SID-US | D65: 45657 | E65: 1.44 | F65: 45659 | G65: 1.42 | H65: =IF(ISERROR(VLOOKUP(A65,EspeciesVisual!C:R,16,FALSE)),"",VLOOKUP(A65,EspeciesVisual!C:R,16,FALSE)) | I65: =IF(OR(ISNUMBER(SEARCH("obligacion",LOWER(H65))),ISNUMBER(SEARCH("titulo",LOWER(H65))),ISNUMBER(SEARCH("letra",LOWER(H65)))),G65/100,G65) | J65: =I65/1167.806
A66: 5858 | B66: VORNADO REALTY TRUST (VNO) | C66: VNO-US | D66: 45657 | E66: 42.04 | F66: 45659 | G66: 42.62 | H66: =IF(ISERROR(VLOOKUP(A66,EspeciesVisual!C:R,16,FALSE)),"",VLOOKUP(A66,EspeciesVisual!C:R,16,FALSE)) | I66: =IF(OR(ISNUMBER(SEARCH("obligacion",LOWER(H66))),ISNUMBER(SEARCH("titulo",LOWER(H66))),ISNUMBER(SEARCH("letra",LOWER(H66)))),G66/100,G66) | J66: =I66/1167.806
A67: 5913 | B67: OCCIDENTAL PETROLEUM CORP. (OX | C67: OXY-US | D67: 45657 | E67: 49.41 | F67: 45659 | G67: 49.81 | H67: =IF(ISERROR(VLOOKUP(A67,EspeciesVisual!C:R,16,FALSE)),"",VLOOKUP(A67,EspeciesVisual!C:R,16,FALSE)) | I67: =IF(OR(ISNUMBER(SEARCH("obligacion",LOWER(H67))),ISNUMBER(SEARCH("titulo",LOWER(H67))),ISNUMBER(SEARCH("letra",LOWER(H67)))),G67/100,G67) | J67: =I67/1167.806
A68: 5921 | B68: BONO USD 2030 LA | C68: AL30 | D68: 45656 | E68: 88050 | F68: 45659 | G68: 88760 | H68: =IF(ISERROR(VLOOKUP(A68,EspeciesVisual!C:R,16,FALSE)),"",VLOOKUP(A68,EspeciesVisual!C:R,16,FALSE)) | I68: =IF(OR(ISNUMBER(SEARCH("obligacion",LOWER(H68))),ISNUMBER(SEARCH("titulo",LOWER(H68))),ISNUMBER(SEARCH("letra",LOWER(H68)))),G68/100,G68) | J68: =I68/1167.806
A69: 5922 | B69: BONO USD 2035 LA | C69: AL35 | D69: 45656 | E69: 81500 | F69: 45659 | G69: 81630 | H69: =IF(ISERROR(VLOOKUP(A69,EspeciesVisual!C:R,16,FALSE)),"",VLOOKUP(A69,EspeciesVisual!C:R,16,FALSE)) | I69: =IF(OR(ISNUMBER(SEARCH("obligacion",LOWER(H69))),ISNUMBER(SEARCH("titulo",LOWER(H69))),ISNUMBER(SEARCH("letra",LOWER(H69)))),G69/100,G69) | J69: =I69/1167.806
A70: 5923 | B70: BONO USD 2038 LA | C70: AE38 | D70: 45656 | E70: 86640 | F70: 45659 | G70: 86500 | H70: =IF(ISERROR(VLOOKUP(A70,EspeciesVisual!C:R,16,FALSE)),"",VLOOKUP(A70,EspeciesVisual!C:R,16,FALSE)) | I70: =IF(OR(ISNUMBER(SEARCH("obligacion",LOWER(H70))),ISNUMBER(SEARCH("titulo",LOWER(H70))),ISNUMBER(SEARCH("letra",LOWER(H70)))),G70/100,G70) | J70: =I70/1167.806
A71: 5924 | B71: BONO USD 2041 LA | C71: AL41 | D71: 45656 | E71: 77500 | F71: 45659 | G71: 77640 | H71: =IF(ISERROR(VLOOKUP(A71,EspeciesVisual!C:R,16,FALSE)),"",VLOOKUP(A71,EspeciesVisual!C:R,16,FALSE)) | I71: =IF(OR(ISNUMBER(SEARCH("obligacion",LOWER(H71))),ISNUMBER(SEARCH("titulo",LOWER(H71))),ISNUMBER(SEARCH("letra",LOWER(H71)))),G71/100,G71) | J71: =I71/1167.806
A72: 5925 | B72: BONCER 2026 2% | C72: TX26 | D72: 45656 | E72: 1678 | F72: 45659 | G72: 1694 | H72: =IF(ISERROR(VLOOKUP(A72,EspeciesVisual!C:R,16,FALSE)),"",VLOOKUP(A72,EspeciesVisual!C:R,16,FALSE)) | I72: =IF(OR(ISNUMBER(SEARCH("obligacion",LOWER(H72))),ISNUMBER(SEARCH("titulo",LOWER(H72))),ISNUMBER(SEARCH("letra",LOWER(H72)))),G72/100,G72) | J72: =I72/1167.806
A73: 5926 | B73: BONCER 2028 2% | C73: TX28 | D73: 45656 | E73: 1581 | F73: 45659 | G73: 1598 | H73: =IF(ISERROR(VLOOKUP(A73,EspeciesVisual!C:R,16,FALSE)),"",VLOOKUP(A73,EspeciesVisual!C:R,16,FALSE)) | I73: =IF(OR(ISNUMBER(SEARCH("obligacion",LOWER(H73))),ISNUMBER(SEARCH("titulo",LOWER(H73))),ISNUMBER(SEARCH("letra",LOWER(H73)))),G73/100,G73) | J73: =I73/1167.806
... A75: 6000 | B75: EUROS | C75: EURO | D75: 45656 | E75: 1 | F75: 45659 | G75: 1 | H75: =IF(ISERROR(VLOOKUP(A75,EspeciesVisual!C:R,16,FALSE)),"",VLOOKUP(A75,EspeciesVisual!C:R,16,FALSE)) | I75: =IF(OR(ISNUMBER(SEARCH("obligacion",LOWER(H75))),ISNUMBER(SEARCH("titulo",LOWER(H75))),ISNUMBER(SEARCH("letra",LOWER(H75)))),G75/100,G75) | J75: =I75/1167.806
A76: 6001 | B76: EURO MONEDA | E76: 0 | G76: 0 | H76: =IF(ISERROR(VLOOKUP(A76,EspeciesVisual!C:R,16,FALSE)),"",VLOOKUP(A76,EspeciesVisual!C:R,16,FALSE)) | I76: =IF(OR(ISNUMBER(SEARCH("obligacion",LOWER(H76))),ISNUMBER(SEARCH("titulo",LOWER(H76))),ISNUMBER(SEARCH("letra",LOWER(H76)))),G76/100,G76) | J76: =I76/1167.806
A77: 6107 | B77: ADR GRUPO FINANCIERO GALICIA | C77: GGAL-US | D77: 45657 | E77: 62.33 | F77: 45659 | G77: 68.76 | H77: =IF(ISERROR(VLOOKUP(A77,EspeciesVisual!C:R,16,FALSE)),"",VLOOKUP(A77,EspeciesVisual!C:R,16,FALSE)) | I77: =IF(OR(ISNUMBER(SEARCH("obligacion",LOWER(H77))),ISNUMBER(SEARCH("titulo",LOWER(H77))),ISNUMBER(SEARCH("letra",LOWER(H77)))),G77/100,G77) | J77: =I77/1167.806
A78: 6472 | B78: ADR PETROLEO BRASILEIRO S.A.(P | C78: PBR-US | D78: 45657 | E78: 12.86 | F78: 45659 | G78: 13.24 | H78: =IF(ISERROR(VLOOKUP(A78,EspeciesVisual!C:R,16,FALSE)),"",VLOOKUP(A78,EspeciesVisual!C:R,16,FALSE)) | I78: =IF(OR(ISNUMBER(SEARCH("obligacion",LOWER(H78))),ISNUMBER(SEARCH("titulo",LOWER(H78))),ISNUMBER(SEARCH("letra",LOWER(H78)))),G78/100,G78) | J78: =I78/1167.806
A79: 6494 | B79: GOLDMAN SACHS GROUP (GS) | C79: GS-US | D79: 45657 | E79: 572.62 | F79: 45659 | G79: 574.97 | H79: =IF(ISERROR(VLOOKUP(A79,EspeciesVisual!C:R,16,FALSE)),"",VLOOKUP(A79,EspeciesVisual!C:R,16,FALSE)) | I79: =IF(OR(ISNUMBER(SEARCH("obligacion",LOWER(H79))),ISNUMBER(SEARCH("titulo",LOWER(H79))),ISNUMBER(SEARCH("letra",LOWER(H79)))),G79/100,G79) | J79: =I79/1167.806
A80: 7000 | B80: DOLARES USA | C80: DOL 7000 | D80: 45656 | E80: 1 | F80: 45659 | G80: 1 | H80: =IF(ISERROR(VLOOKUP(A80,EspeciesVisual!C:R,16,FALSE)),"",VLOOKUP(A80,EspeciesVisual!C:R,16,FALSE)) | I80: =IF(OR(ISNUMBER(SEARCH("obligacion",LOWER(H80))),ISNUMBER(SEARCH("titulo",LOWER(H80))),ISNUMBER(SEARCH("letra",LOWER(H80)))),G80/100,G80) | J80: =I80/1167.806
A81: 7007 | B81: PFIZER (PFE) | C81: PFE-US | D81: 45657 | E81: 26.53 | F81: 45659 | G81: 26.61 | H81: =IF(ISERROR(VLOOKUP(A81,EspeciesVisual!C:R,16,FALSE)),"",VLOOKUP(A81,EspeciesVisual!C:R,16,FALSE)) | I81: =IF(OR(ISNUMBER(SEARCH("obligacion",LOWER(H81))),ISNUMBER(SEARCH("titulo",LOWER(H81))),ISNUMBER(SEARCH("letra",LOWER(H81)))),G81/100,G81) | J81: =I81/1167.806
A82: 7043 | B82: AMAZON (AMZN) | C82: AMZN-US | D82: 45657 | E82: 219.51 | F82: 45659 | G82: 220.225 | H82: =IF(ISERROR(VLOOKUP(A82,EspeciesVisual!C:R,16,FALSE)),"",VLOOKUP(A82,EspeciesVisual!C:R,16,FALSE)) | I82: =IF(OR(ISNUMBER(SEARCH("obligacion",LOWER(H82))),ISNUMBER(SEARCH("titulo",LOWER(H82))),ISNUMBER(SEARCH("letra",LOWER(H82)))),G82/100,G82) | J82: =I82/1167.806
A83: 7044 | B83: NVIDIA CORPORATION | C83: NVDA-US | D83: 45657 | E83: 134.29 | F83: 45659 | G83: 138.31 | H83: =IF(ISERROR(VLOOKUP(A83,EspeciesVisual!C:R,16,FALSE)),"",VLOOKUP(A83,EspeciesVisual!C:R,16,FALSE)) | I83: =IF(OR(ISNUMBER(SEARCH("obligacion",LOWER(H83))),ISNUMBER(SEARCH("titulo",LOWER(H83))),ISNUMBER(SEARCH("letra",LOWER(H83)))),G83/100,G83) | J83: =I83/1167.806
A84: 7074 | B84: MICROSOFT CORP | C84: MSFT-US | D84: 45657 | E84: 421.23 | F84: 45659 | G84: 418.62 | H84: =IF(ISERROR(VLOOKUP(A84,EspeciesVisual!C:R,16,FALSE)),"",VLOOKUP(A84,EspeciesVisual!C:R,16,FALSE)) | I84: =IF(OR(ISNUMBER(SEARCH("obligacion",LOWER(H84))),ISNUMBER(SEARCH("titulo",LOWER(H84))),ISNUMBER(SEARCH("letra",LOWER(H84)))),G84/100,G84) | J84: =I84/1167.806
A85: 7083 | B85: EXXON MOBIL CORP (XOM) | C85: XOM-US | D85: 45657 | E85: 107.57 | F85: 45659 | G85: 107.31 | H85: =IF(ISERROR(VLOOKUP(A85,EspeciesVisual!C:R,16,FALSE)),"",VLOOKUP(A85,EspeciesVisual!C:R,16,FALSE)) | I85: =IF(OR(ISNUMBER(SEARCH("obligacion",LOWER(H85))),ISNUMBER(SEARCH("titulo",LOWER(H85))),ISNUMBER(SEARCH("letra",LOWER(H85)))),G85/100,G85) | J85: =I85/1167.806
A86: 7108 | B86: TRANSPORTADORA GAS DEL SUR (A. | C86: TGS-US | D86: 45657 | E86: 29.27 | F86: 45659 | G86: 32.4 | H86: =IF(ISERROR(VLOOKUP(A86,EspeciesVisual!C:R,16,FALSE)),"",VLOOKUP(A86,EspeciesVisual!C:R,16,FALSE)) | I86: =IF(OR(ISNUMBER(SEARCH("obligacion",LOWER(H86))),ISNUMBER(SEARCH("titulo",LOWER(H86))),ISNUMBER(SEARCH("letra",LOWER(H86)))),G86/100,G86) | J86: =I86/1167.806
A87: 7109 | B87: YPFD ADR | C87: YPF-US | D87: 45657 | E87: 42.51 | F87: 45659 | G87: 44.6 | H87: =IF(ISERROR(VLOOKUP(A87,EspeciesVisual!C:R,16,FALSE)),"",VLOOKUP(A87,EspeciesVisual!C:R,16,FALSE)) | I87: =IF(OR(ISNUMBER(SEARCH("obligacion",LOWER(H87))),ISNUMBER(SEARCH("titulo",LOWER(H87))),ISNUMBER(SEARCH("letra",LOWER(H87)))),G87/100,G87) | J87: =I87/1167.806
A88: 7181 | B88: BANK OF AMERICA S/OFERTA PUBLI | C88: BAC-US | D88: 45657 | E88: 43.95 | F88: 45659 | G88: 44.29 | H88: =IF(ISERROR(VLOOKUP(A88,EspeciesVisual!C:R,16,FALSE)),"",VLOOKUP(A88,EspeciesVisual!C:R,16,FALSE)) | I88: =IF(OR(ISNUMBER(SEARCH("obligacion",LOWER(H88))),ISNUMBER(SEARCH("titulo",LOWER(H88))),ISNUMBER(SEARCH("letra",LOWER(H88)))),G88/100,G88) | J88: =I88/1167.806
A89: 7182 | B89: IMPSAT FIBER NETWORKS | C89: IMPS-US | E89: 0 | G89: 0 | H89: =IF(ISERROR(VLOOKUP(A89,EspeciesVisual!C:R,16,FALSE)),"",VLOOKUP(A89,EspeciesVisual!C:R,16,FALSE)) | I89: =IF(OR(ISNUMBER(SEARCH("obligacion",LOWER(H89))),ISNUMBER(SEARCH("titulo",LOWER(H89))),ISNUMBER(SEARCH("letra",LOWER(H89)))),G89/100,G89) | J89: =I89/1167.806
A90: 7247 | B90: WELLS FARGO & COMPANY (WFC) | C90: WFC-US | D90: 45657 | E90: 70.24 | F90: 45659 | G90: 70.19 | H90: =IF(ISERROR(VLOOKUP(A90,EspeciesVisual!C:R,16,FALSE)),"",VLOOKUP(A90,EspeciesVisual!C:R,16,FALSE)) | I90: =IF(OR(ISNUMBER(SEARCH("obligacion",LOWER(H90))),ISNUMBER(SEARCH("titulo",LOWER(H90))),ISNUMBER(SEARCH("letra",LOWER(H90)))),G90/100,G90) | J90: =I90/1167.806
A91: 7251 | B91: UNITEDHEALTH GROUP INC. (UNH) | C91: UNH-US | E91: 0 | G91: 0 | H91: =IF(ISERROR(VLOOKUP(A91,EspeciesVisual!C:R,16,FALSE)),"",VLOOKUP(A91,EspeciesVisual!C:R,16,FALSE)) | I91: =IF(OR(ISNUMBER(SEARCH("obligacion",LOWER(H91))),ISNUMBER(SEARCH("titulo",LOWER(H91))),ISNUMBER(SEARCH("letra",LOWER(H91)))),G91/100,G91) | J91: =I91/1167.806
A92: 7483 | B92: CEF SELECT AMEX TECH SPDR | C92: XLK-US | D92: 45657 | E92: 232.62 | F92: 45659 | G92: 231.98 | H92: =IF(ISERROR(VLOOKUP(A92,EspeciesVisual!C:R,16,FALSE)),"",VLOOKUP(A92,EspeciesVisual!C:R,16,FALSE)) | I92: =IF(OR(ISNUMBER(SEARCH("obligacion",LOWER(H92))),ISNUMBER(SEARCH("titulo",LOWER(H92))),ISNUMBER(SEARCH("letra",LOWER(H92)))),G92/100,G92) | J92: =I92/1167.806
A93: 7716 | B93: WAL MART STORES INC (WMT) | C93: WMT-US | D93: 45657 | E93: 90.35 | F93: 45659 | G93: 90 | H93: =IF(ISERROR(VLOOKUP(A93,EspeciesVisual!C:R,16,FALSE)),"",VLOOKUP(A93,EspeciesVisual!C:R,16,FALSE)) | I93: =IF(OR(ISNUMBER(SEARCH("obligacion",LOWER(H93))),ISNUMBER(SEARCH("titulo",LOWER(H93))),ISNUMBER(SEARCH("letra",LOWER(H93)))),G93/100,G93) | J93: =I93/1167.806
A94: 7742 | B94: BOEING CO | C94: BA-US | D94: 45657 | E94: 177 | F94: 45659 | G94: 171.87 | H94: =IF(ISERROR(VLOOKUP(A94,EspeciesVisual!C:R,16,FALSE)),"",VLOOKUP(A94,EspeciesVisual!C:R,16,FALSE)) | I94: =IF(OR(ISNUMBER(SEARCH("obligacion",LOWER(H94))),ISNUMBER(SEARCH("titulo",LOWER(H94))),ISNUMBER(SEARCH("letra",LOWER(H94)))),G94/100,G94) | J94: =I94/1167.806
A95: 7747 | B95: S & P 500 DEPOSITARY RECEIPT | C95: SPY-US | D95: 45657 | E95: 586.01 | F95: 45659 | G95: 584.62 | H95: =IF(ISERROR(VLOOKUP(A95,EspeciesVisual!C:R,16,FALSE)),"",VLOOKUP(A95,EspeciesVisual!C:R,16,FALSE)) | I95: =IF(OR(ISNUMBER(SEARCH("obligacion",LOWER(H95))),ISNUMBER(SEARCH("titulo",LOWER(H95))),ISNUMBER(SEARCH("letra",LOWER(H95)))),G95/100,G95) | J95: =I95/1167.806
A96: 7872 | B96: WALT DISNEY CO. | C96: DIS-US | D96: 45657 | E96: 111.35 | F96: 45659 | G96: 110.82 | H96: =IF(ISERROR(VLOOKUP(A96,EspeciesVisual!C:R,16,FALSE)),"",VLOOKUP(A96,EspeciesVisual!C:R,16,FALSE)) | I96: =IF(OR(ISNUMBER(SEARCH("obligacion",LOWER(H96))),ISNUMBER(SEARCH("titulo",LOWER(H96))),ISNUMBER(SEARCH("letra",LOWER(H96)))),G96/100,G96) | J96: =I96/1167.806
A97: 7877 | B97: APPLE COMPUTER INC | C97: AAPL-US | D97: 45657 | E97: 250.44 | F97: 45659 | G97: 243.78 | H97: =IF(ISERROR(VLOOKUP(A97,EspeciesVisual!C:R,16,FALSE)),"",VLOOKUP(A97,EspeciesVisual!C:R,16,FALSE)) | I97: =IF(OR(ISNUMBER(SEARCH("obligacion",LOWER(H97))),ISNUMBER(SEARCH("titulo",LOWER(H97))),ISNUMBER(SEARCH("letra",LOWER(H97)))),G97/100,G97) | J97: =I97/1167.806
A98: 7971 | B98: HOME DEPOT INC.(HD) | C98: HD-US | D98: 45657 | E98: 388.99 | F98: 45659 | G98: 388.46 | H98: =IF(ISERROR(VLOOKUP(A98,EspeciesVisual!C:R,16,FALSE)),"",VLOOKUP(A98,EspeciesVisual!C:R,16,FALSE)) | I98: =IF(OR(ISNUMBER(SEARCH("obligacion",LOWER(H98))),ISNUMBER(SEARCH("titulo",LOWER(H98))),ISNUMBER(SEARCH("letra",LOWER(H98)))),G98/100,G98) | J98: =I98/1167.806
A99: 7974 | B99: AMERICAN EXPRESS COMPANY S/OFE | C99: AXP-US | E99: 0 | G99: 0 | H99: =IF(ISERROR(VLOOKUP(A99,EspeciesVisual!C:R,16,FALSE)),"",VLOOKUP(A99,EspeciesVisual!C:R,16,FALSE)) | I99: =IF(OR(ISNUMBER(SEARCH("obligacion",LOWER(H99))),ISNUMBER(SEARCH("titulo",LOWER(H99))),ISNUMBER(SEARCH("letra",LOWER(H99)))),G99/100,G99) | J99: =I99/1167.806
A100: 8000 | B100: PESOS DISPONIBLE | D100: 43371 | E100: 1 | F100: 43553 | G100: 1 | H100: =IF(ISERROR(VLOOKUP(A100,EspeciesVisual!C:R,16,FALSE)),"",VLOOKUP(A100,EspeciesVisual!C:R,16,FALSE)) | I100: =IF(OR(ISNUMBER(SEARCH("obligacion",LOWER(H100))),ISNUMBER(SEARCH("titulo",LOWER(H100))),ISNUMBER(SEARCH("letra",LOWER(H100)))),G100/100,G100) | J100: =I100/1167.806
A101: 8006 | B101: CEDEAR COCA-COLA COMPANY | C101: KO | D101: 45656 | E101: 14725 | F101: 45659 | G101: 14550 | H101: =IF(ISERROR(VLOOKUP(A101,EspeciesVisual!C:R,16,FALSE)),"",VLOOKUP(A101,EspeciesVisual!C:R,16,FALSE)) | I101: =IF(OR(ISNUMBER(SEARCH("obligacion",LOWER(H101))),ISNUMBER(SEARCH("titulo",LOWER(H101))),ISNUMBER(SEARCH("letra",LOWER(H101)))),G101/100,G101) | J101: =I101/1167.806
A102: 8009 | B102: CEDEAR AMER.EXPR | C102: AXP | D102: 45656 | E102: 23600 | F102: 45659 | G102: 23221.018 | H102: =IF(ISERROR(VLOOKUP(A102,EspeciesVisual!C:R,16,FALSE)),"",VLOOKUP(A102,EspeciesVisual!C:R,16,FALSE)) | I102: =IF(OR(ISNUMBER(SEARCH("obligacion",LOWER(H102))),ISNUMBER(SEARCH("titulo",LOWER(H102))),ISNUMBER(SEARCH("letra",LOWER(H102)))),G102/100,G102) | J102: =I102/1167.806
A103: 8011 | B103: CEDEAR BOEING CO | C103: BA | D103: 45656 | E103: 8740 | F103: 45659 | G103: 8390 | H103: =IF(ISERROR(VLOOKUP(A103,EspeciesVisual!C:R,16,FALSE)),"",VLOOKUP(A103,EspeciesVisual!C:R,16,FALSE)) | I103: =IF(OR(ISNUMBER(SEARCH("obligacion",LOWER(H103))),ISNUMBER(SEARCH("titulo",LOWER(H103))),ISNUMBER(SEARCH("letra",LOWER(H103)))),G103/100,G103) | J103: =I103/1167.806
A104: 8012 | B104: CEDERA CAATERPIL | C104: CAT | D104: 45656 | E104: 21625 | F104: 45659 | G104: 21200 | H104: =IF(ISERROR(VLOOKUP(A104,EspeciesVisual!C:R,16,FALSE)),"",VLOOKUP(A104,EspeciesVisual!C:R,16,FALSE)) | I104: =IF(OR(ISNUMBER(SEARCH("obligacion",LOWER(H104))),ISNUMBER(SEARCH("titulo",LOWER(H104))),ISNUMBER(SEARCH("letra",LOWER(H104)))),G104/100,G104) | J104: =I104/1167.806
A105: 8013 | B105: CEDEAR CHEVRON C | C105: CVX | D105: 45656 | E105: 10650 | F105: 45659 | G105: 10800 | H105: =IF(ISERROR(VLOOKUP(A105,EspeciesVisual!C:R,16,FALSE)),"",VLOOKUP(A105,EspeciesVisual!C:R,16,FALSE)) | I105: =IF(OR(ISNUMBER(SEARCH("obligacion",LOWER(H105))),ISNUMBER(SEARCH("titulo",LOWER(H105))),ISNUMBER(SEARCH("letra",LOWER(H105)))),G105/100,G105) | J105: =I105/1167.806
A106: 8014 | B106: CEDEAR CISCO SYS | C106: CSCO | D106: 45656 | E106: 14050 | F106: 45659 | G106: 13732.46 | H106: =IF(ISERROR(VLOOKUP(A106,EspeciesVisual!C:R,16,FALSE)),"",VLOOKUP(A106,EspeciesVisual!C:R,16,FALSE)) | I106: =IF(OR(ISNUMBER(SEARCH("obligacion",LOWER(H106))),ISNUMBER(SEARCH("titulo",LOWER(H106))),ISNUMBER(SEARCH("letra",LOWER(H106)))),G106/100,G106) | J106: =I106/1167.806
A107: 8017 | B107: CEDEAR DISNEY COMMON STOCK | C107: DISN | D107: 45656 | E107: 10975 | F107: 45659 | G107: 10825 | H107: =IF(ISERROR(VLOOKUP(A107,EspeciesVisual!C:R,16,FALSE)),"",VLOOKUP(A107,EspeciesVisual!C:R,16,FALSE)) | I107: =IF(OR(ISNUMBER(SEARCH("obligacion",LOWER(H107))),ISNUMBER(SEARCH("titulo",LOWER(H107))),ISNUMBER(SEARCH("letra",LOWER(H107)))),G107/100,G107) | J107: =I107/1167.806
A108: 8018 | B108: CEDEAR DE EI DU PONT DE NEMOUR | C108: DD | E108: 0 | G108: 0 | H108: =IF(ISERROR(VLOOKUP(A108,EspeciesVisual!C:R,16,FALSE)),"",VLOOKUP(A108,EspeciesVisual!C:R,16,FALSE)) | I108: =IF(OR(ISNUMBER(SEARCH("obligacion",LOWER(H108))),ISNUMBER(SEARCH("titulo",LOWER(H108))),ISNUMBER(SEARCH("letra",LOWER(H108)))),G108/100,G108) | J108: =I108/1167.806
A109: 8019 | B109: CEDEAR EXXON MOB | C109: XOM | D109: 45656 | E109: 12600 | F109: 45659 | G109: 12650 | H109: =IF(ISERROR(VLOOKUP(A109,EspeciesVisual!C:R,16,FALSE)),"",VLOOKUP(A109,EspeciesVisual!C:R,16,FALSE)) | I109: =IF(OR(ISNUMBER(SEARCH("obligacion",LOWER(H109))),ISNUMBER(SEARCH("titulo",LOWER(H109))),ISNUMBER(SEARCH("letra",LOWER(H109)))),G109/100,G109) | J109: =I109/1167.806
A110: 8020 | B110: CEDEAR GENERAL ELECTRIC | C110: GE | D110: 45656 | E110: 24975 | F110: 45659 | G110: 24750 | H110: =IF(ISERROR(VLOOKUP(A110,EspeciesVisual!C:R,16,FALSE)),"",VLOOKUP(A110,EspeciesVisual!C:R,16,FALSE)) | I110: =IF(OR(ISNUMBER(SEARCH("obligacion",LOWER(H110))),ISNUMBER(SEARCH("titulo",LOWER(H110))),ISNUMBER(SEARCH("letra",LOWER(H110)))),G110/100,G110) | J110: =I110/1167.806
A111: 8023 | B111: HEWLET PACKARD | C111: HPQ | D111: 45656 | E111: 38925 | F111: 45659 | G111: 38200 | H111: =IF(ISERROR(VLOOKUP(A111,EspeciesVisual!C:R,16,FALSE)),"",VLOOKUP(A111,EspeciesVisual!C:R,16,FALSE)) | I111: =IF(OR(ISNUMBER(SEARCH("obligacion",LOWER(H111))),ISNUMBER(SEARCH("titulo",LOWER(H111))),ISNUMBER(SEARCH("letra",LOWER(H111)))),G111/100,G111) | J111: =I111/1167.806
A112: 8024 | B112: CEDEAR IBM CORP. | C112: IBM | D112: 45656 | E112: 17450 | F112: 45659 | G112: 17150 | H112: =IF(ISERROR(VLOOKUP(A112,EspeciesVisual!C:R,16,FALSE)),"",VLOOKUP(A112,EspeciesVisual!C:R,16,FALSE)) | I112: =IF(OR(ISNUMBER(SEARCH("obligacion",LOWER(H112))),ISNUMBER(SEARCH("titulo",LOWER(H112))),ISNUMBER(SEARCH("letra",LOWER(H112)))),G112/100,G112) | J112: =I112/1167.806
A113: 8025 | B113: CEDEAR INTEL | C113: INTC | D113: 45656 | E113: 4720 | F113: 45659 | G113: 4765 | H113: =IF(ISERROR(VLOOKUP(A113,EspeciesVisual!C:R,16,FALSE)),"",VLOOKUP(A113,EspeciesVisual!C:R,16,FALSE)) | I113: =IF(OR(ISNUMBER(SEARCH("obligacion",LOWER(H113))),ISNUMBER(SEARCH("titulo",LOWER(H113))),ISNUMBER(SEARCH("letra",LOWER(H113)))),G113/100,G113) | J113: =I113/1167.806
A114: 8027 | B114: CEDEAR J & J | C114: JNJ | D114: 45656 | E114: 11325 | F114: 45659 | G114: 11325 | H114: =IF(ISERROR(VLOOKUP(A114,EspeciesVisual!C:R,16,FALSE)),"",VLOOKUP(A114,EspeciesVisual!C:R,16,FALSE)) | I114: =IF(OR(ISNUMBER(SEARCH("obligacion",LOWER(H114))),ISNUMBER(SEARCH("titulo",LOWER(H114))),ISNUMBER(SEARCH("letra",LOWER(H114)))),G114/100,G114) | J114: =I114/1167.806
A115: 8028 | B115: CEDEAR JP MORGAN | C115: JPM | D115: 45656 | E115: 19050 | F115: 45659 | G115: 18875 | H115: =IF(ISERROR(VLOOKUP(A115,EspeciesVisual!C:R,16,FALSE)),"",VLOOKUP(A115,EspeciesVisual!C:R,16,FALSE)) | I115: =IF(OR(ISNUMBER(SEARCH("obligacion",LOWER(H115))),ISNUMBER(SEARCH("titulo",LOWER(H115))),ISNUMBER(SEARCH("letra",LOWER(H115)))),G115/100,G115) | J115: =I115/1167.806
A116: 8030 | B116: CEDEAR MCDONALD | C116: MCD | D116: 45656 | E116: 14350 | F116: 45659 | G116: 14350 | H116: =IF(ISERROR(VLOOKUP(A116,EspeciesVisual!C:R,16,FALSE)),"",VLOOKUP(A116,EspeciesVisual!C:R,16,FALSE)) | I116: =IF(OR(ISNUMBER(SEARCH("obligacion",LOWER(H116))),ISNUMBER(SEARCH("titulo",LOWER(H116))),ISNUMBER(SEARCH("letra",LOWER(H116)))),G116/100,G116) | J116: =I116/1167.806
A117: 8031 | B117: CEDEAR MERCK | C117: MRK | D117: 45656 | E117: 23425 | F117: 45659 | G117: 23300 | H117: =IF(ISERROR(VLOOKUP(A117,EspeciesVisual!C:R,16,FALSE)),"",VLOOKUP(A117,EspeciesVisual!C:R,16,FALSE)) | I117: =IF(OR(ISNUMBER(SEARCH("obligacion",LOWER(H117))),ISNUMBER(SEARCH("titulo",LOWER(H117))),ISNUMBER(SEARCH("letra",LOWER(H117)))),G117/100,G117) | J117: =I117/1167.806
A118: 8032 | B118: CEDEAR MICROSOFT | C118: MSFT | D118: 45656 | E118: 16875 | F118: 45659 | G118: 16375 | H118: =IF(ISERROR(VLOOKUP(A118,EspeciesVisual!C:R,16,FALSE)),"",VLOOKUP(A118,EspeciesVisual!C:R,16,FALSE)) | I118: =IF(OR(ISNUMBER(SEARCH("obligacion",LOWER(H118))),ISNUMBER(SEARCH("titulo",LOWER(H118))),ISNUMBER(SEARCH("letra",LOWER(H118)))),G118/100,G118) | J118: =I118/1167.806
A119: 8033 | B119: MINNESOTA CEDEAR | C119: MMM | D119: 45656 | E119: 15425 | F119: 45659 | G119: 15200 | H119: =IF(ISERROR(VLOOKUP(A119,EspeciesVisual!C:R,16,FALSE)),"",VLOOKUP(A119,EspeciesVisual!C:R,16,FALSE)) | I119: =IF(OR(ISNUMBER(SEARCH("obligacion",LOWER(H119))),ISNUMBER(SEARCH("titulo",LOWER(H119))),ISNUMBER(SEARCH("letra",LOWER(H119)))),G119/100,G119) | J119: =I119/1167.806
A120: 8036 | B120: CEDEAR ALTRIA GR | C120: MO | D120: 45656 | E120: 15425 | F120: 45659 | G120: 15475 | H120: =IF(ISERROR(VLOOKUP(A120,EspeciesVisual!C:R,16,FALSE)),"",VLOOKUP(A120,EspeciesVisual!C:R,16,FALSE)) | I120: =IF(OR(ISNUMBER(SEARCH("obligacion",LOWER(H120))),ISNUMBER(SEARCH("titulo",LOWER(H120))),ISNUMBER(SEARCH("letra",LOWER(H120)))),G120/100,G120) | J120: =I120/1167.806
...

Sheet PrecioTenenciasIniciales
A1: Cod.Especie | B1: Ticker | C1: Especie | D1: Cantidad tenencia | E1: Importe invertido | F1: Resultado | G1: Precio tenencia inicial | H1: Ratio CEDEAR | I1: Precio Ajustado
A2: 05248 | B2: LETRA | C2: DEL TESORO VTO. 11/ | D2: 0 | E2: 2094505.3 | F2: -2094505.3 | G2: 0 | H2: 1 | I2: 0
A3: 05436 | B3: BONAR | C3: U$S 7% 2017 (AA17) | D3: 0 | E3: 7955.9 | F3: -7955.9 | G3: 0 | H3: 1 | I3: 0
A4: 05458 | B4: BONO | C4: REP ARG VTO. 07/05/2 | D4: 0 | E4: 3604283.5 | F4: -3604283.5 | G4: 0 | H4: 1 | I4: 0
A5: 05468 | B5: BONO | C5: NAC ARG USD 8% BONAR | D5: 0 | E5: 2147312.3 | F5: -2147312.3 | G5: 0 | H5: 1 | I5: 0
A6: 05921 | B6: BONO | C6: USD 2030 LA | D6: 0 | E6: -60773709 | F6: 60773709 | G6: 0 | H6: 1 | I6: 0
A7: 05922 | B7: BONO | C7: USD 2035 LA | D7: 0 | E7: -49030517 | F7: 49030517 | G7: 0 | H7: 1 | I7: 0
A8: 05927 | B8: BONO | C8: USD 2029 1% LA | D8: 0 | E8: -10102656 | F8: 10102656 | G8: 0 | H8: 1 | I8: 0
A9: 09206 | B9: LT | C9: REP ARG A DESC. VTO31/ | D9: 0 | E9: -45413.38 | F9: 45413.38 | G9: 0 | H9: 1 | I9: 0
A10: 09234 | B10: BOPREAL | C10: S. 1 A VTO31/10/2 | D10: 208333 | E10: 2.0189968e+08 | F10: 32391615 | G10: 969.12 | H10: 1 | I10: 969.12
A11: 09247 | B11: BOPREAL | C11: S.3 VTO31/05/26 U | D11: 10400 | E11: 7368605.4 | F11: 4164994.6 | G11: 708.51975 | H11: 1 | I11: 708.51975
A12: 09251 | B12: LT | C12: REP ARGENTINA CAP $ V3 | D12: 0 | E12: -3969344.3 | F12: 3969344.3 | G12: 0 | H12: 1 | I12: 0
A13: 09256 | B13: LT | C13: REP ARGENTINA CAP $ V3 | D13: 0 | E13: -5368217.1 | F13: 5368217.1 | G13: 0 | H13: 1 | I13: 0
... A26: 91870 | B26: ON | C26: YPF CLASE 39 8,50% U$S | D26: 0 | E26: 12789762 | F26: -12789762 | G26: 0 | H26: 1 | I26: 0
A27: OPERACION | B27: FINANCIERA | D27: 0 | E27: 10113363 | F27: -10113363 | G27: 0 | H27: 1 | I27: 0
A28: T | B28: o | C28: t a l e s | D28: 0 | E28: 3.5303465e+08 | F28: 2.1203335e+08 | G28: 0 | H28: 1 | I28: 0

Sheet RatiosCedearsAcciones
A1: Nombre | B1: Ratio | C1: Key
A2: 3M Company MMM NYSE | B2: 10 | C2: 3M
A3: Abbott Labs ABT NYSE | B3: 4 | C3: ABBOTT
A4: AbbVie Inc. ABBV NYSE | B4: 10 | C4: ABBVIE
A5: Abercrombie & Fitch Co ANF NYSE | B5: 1 | C5: ABERCROMBIE
A6: Accenture ACN NYSE | B6: 75 | C6: ACCENTURE
A7: Adecoagro S.A. ADGO NYSE | B7: 1 | C7: ADECOAGRO
A8: Adidas AG ADS XETRA | B8: 22 | C8: ADIDAS
A9: Adobe Systems Incorporated ADBE NASDAQ | B9: 44 | C9: ADOBE
A10: Adr Jumia Technologies Ag JMIA NYSE | B10: 1 | C10: ADR
A11: Advanced Auto Parts Inc AAP NYSE | B11: 14 | C11: ADVANCED
A12: Aegon N.V. AEG NYSE | B12: 1 | C12: AEGON
A13: Agnico Eagle Mines Limited AEM NYSE | B13: 6 | C13: AGNICO
... A336: Zoom Video Communications Inc. ZM NASDAQ | B336: 47 | C336: ZOOM
